Workbook

Sheet Folha de Pagamento
B1: Folha de Pagamento | G1: CNPJ da empresa: Referência da Folha de Pagamento: Quantidade de horas mensais usada: Data de Construção:
A3: Cod. | B3: Cod. contrato funcionário | C3: Cargo atual | D3: Novo Cargo | E3: Senioridade | F3: Nível Organizacional | G3: Área | H3: Departamento | I3: Carga Horária | J3: Salários | K3: Tipo de Contratação | L3: CBO | M3: Gênero | N3: Data de Admissão | O3: Unidade | P3: Observações
A4: 1 | B4: 1362 | C4: ALMOXARIFE | E4: Não trabalhamos senioridade | F4: Operacional | G4: Edificação | I4: 220 | J4: 3683 | K4: CLT | L4: 818631 | M4: Masculino | N4: 45871
A5: 1 | B5: 1957 | C5: ALMOXARIFE | E5: Não trabalhamos senioridade | F5: Operacional | G5: Edificação | I5: 220 | J5: 3683 | K5: CLT | L5: 818631 | M5: Feminino | N5: 45870
A6: 2 | B6: 1964 | C6: ANALISTA DE COMPRAS | E6: Não trabalhamos senioridade | F6: Operacional | G6: Suprimentos | I6: 220 | J6: 3780 | K6: CLT | L6: 599850 | M6: Masculino | N6: 45872
A7: 3 | B7: 1910 | C7: ANALISTA DE CRIAÇAO | E7: Não trabalhamos senioridade | F7: Operacional | G7: Marketing | I7: 220 | J7: 5429 | K7: CLT | L7: 1423-35 | M7: Masculino | N7: 45873
A8: 4 | B8: PJ1 | C8: ANALISTA DE INOVAÇÃO | E8: Não trabalhamos senioridade | F8: Tático | G8: Inovação | I8: 220 | J8: =10000/1.37 -> 7299.2701 | K8: PJ | M8: Masculino | N8: 45874
A9: 5 | B9: 1373 | C9: ANALISTA DE MANUTENÇÃO II | E9: Pleno | F9: Operacional | G9: Edificação | I9: 220 | J9: 4550 | K9: CLT | L9: 5143-25 | M9: Masculino | N9: 45875
A10: 6 | B10: 139 | C10: ANALISTA DE MARKETING l | E10: Não trabalhamos senioridade | F10: Operacional | G10: Marketing | I10: 220 | J10: 4025.88 | K10: CLT | L10: 1423-35 | M10: Feminino | N10: 45876
A11: 7 | B11: 1962 | C11: ANALISTA DE PÓS VENDAS II | E11: Pleno | F11: Operacional | G11: Pós Vendas | I11: 220 | J11: 4550 | K11: CLT | L11: 226938 | M11: Masculino | N11: 45877
A12: 8 | B12: 187 | C12: ANALISTA DE URBANISMO | E12: Não trabalhamos senioridade | F12: Operacional | G12: Urbanismo | I12: 220 | J12: 5830 | K12: CLT | L12: 446083 | M12: Feminino | N12: 45878
A13: 9 | B13: 1868 | C13: ANALISTA FINANCEIRO COMERCIAL III | E13: Sênior | F13: Operacional | G13: Financeiro | I13: 220 | J13: 5213 | K13: CLT | L13: 226938 | M13: Feminino | N13: 45879
A14: 10 | B14: 176 | C14: ANALISTA FINANCEIRO DE CAPTAÇÃO DE RECURSOS III | E14: Sênior | F14: Operacional | G14: Financeiro | I14: 220 | J14: 5213 | K14: CLT | L14: 2525-45 | M14: Feminino | N14: 45880
A15: 11 | B15: 1927 | C15: ANALISTA FINANCEIRO I | E15: Júnior | F15: Operacional | G15: Financeiro | I15: 220 | J15: 3993 | K15: CLT | L15: 226938 | M15: Feminino | N15: 45881
A16: 12 | B16: 164 | C16: ASSISTENTE ADM DE LEGALIZAÇÃO III | E16: Sênior | F16: Operacional | G16: Legalização | I16: 220 | J16: 3652 | K16: CLT | L16: 807461 | M16: Feminino | N16: 45882
A17: 13 | B17: 1892 | C17: ASSISTENTE ADMINISTRATIVO lll | E17: Sênior | F17: Operacional | G17: Administrativo | I17: 220 | J17: 3439.7 | K17: CLT | L17: 807461 | M17: Feminino | N17: 45883
A18: 14 | B18: 1940 | C18: ASSISTENTE DE CONTROLADORIA III | E18: Sênior | F18: Operacional | G18: Controladoria | I18: 220 | J18: 3652 | K18: CLT | L18: 807461 | M18: Feminino | N18: 45884
A19: 15 | B19: 1963 | C19: ASSISTENTE DE ENGENHARIA lll | E19: Sênior | F19: Operacional | G19: Edificação | I19: 220 | J19: 3652 | K19: CLT | L19: 446083 | M19: Feminino | N19: 45885
A20: 16 | B20: 190 | C20: ASSISTENTE DE MARKETING | E20: Não trabalhamos senioridade | F20: Operacional | G20: Marketing | I20: 220 | J20: 2919 | K20: CLT | L20: 807461 | M20: Feminino | N20: 45886
A21: 17 | B21: 189 | C21: ASSISTENTE DE RECURSOS HUMANOS | E21: Não trabalhamos senioridade | F21: Operacional | G21: DHO | I21: 220 | J21: 2919 | K21: CLT | L21: 807461 | M21: Feminino | N21: 45887
A22: 18 | B22: 1656 | C22: ASSISTENTE DE TI | E22: Não trabalhamos senioridade | F22: Operacional | G22: Tecnologia da Informação | I22: 220 | J22: 2919 | K22: CLT | L22: 464864 | M22: Masculino | N22: 45888
A23: 19 | B23: 192 | C23: ASSISTENTE FINANCEIRO CONTAS A PAGAR | E23: Não trabalhamos senioridade | F23: Operacional | G23: Financeiro | I23: 220 | J23: 2919 | K23: CLT | L23: 815131 | M23: Masculino | N23: 45889
A24: 19 | B24: 193 | C24: ASSISTENTE FINANCEIRO CONTAS A PAGAR | E24: Não trabalhamos senioridade | F24: Operacional | G24: Financeiro | I24: 220 | J24: 2919 | K24: CLT | L24: 815131 | M24: Masculino | N24: 45890
A25: 19 | B25: 1941 | C25: ASSISTENTE FINANCEIRO CONTAS A PAGAR III | E25: Não trabalhamos senioridade | F25: Operacional | G25: Financeiro | I25: 220 | J25: 3652 | K25: CLT | L25: 815131 | M25: Masculino | N25: 45891
A26: 20 | B26: 1961 | C26: AUXILIAR ADMINISTRATIVO | E26: Não trabalhamos senioridade | F26: Operacional | G26: Administrativo | I26: 220 | J26: 2254 | K26: CLT | L26: 807308 | M26: Feminino | N26: 45892
... A29: 23 | B29: 191 | C29: AUXILIAR DE ENGENHARIA | E29: Não trabalhamos senioridade | F29: Operacional | G29: Urbanismo | I29: 220 | J29: 2560 | K29: CLT | L29: 446083 | M29: Masculino | N29: 45895
A30: 24 | B30: PJ2 | C30: CONTROLER JURÍDICO | E30: Não trabalhamos senioridade | F30: Tático | G30: Administrativo | I30: 220 | J30: =11339/1.37 -> 8276.6423 | K30: PJ | M30: Feminino | N30: 45896
A31: 25 | B31: PJ3 | C31: CONTROLLER GERAL | E31: Não trabalhamos senioridade | F31: Tático | G31: Controladoria | I31: 220 | J31: =16000/1.37 -> 11678.832 | K31: PJ | M31: Feminino | N31: 45897
A32: 26 | B32: PJ4 | C32: CONTROLLER TÉCNICO | E32: Não trabalhamos senioridade | F32: Tático | G32: Controladoria | I32: 220 | J32: =12663.6/1.37 -> 9243.5037 | K32: PJ | M32: Masculino | N32: 45898
A33: 27 | B33: 1959 | C33: COORDENADOR DE DHO | E33: Não trabalhamos senioridade | F33: Tático | G33: DHO | I33: 220 | J33: 7420 | K33: CLT | L33: 1422-05 | M33: Feminino | N33: 45899
A34: 28 | B34: 151 | C34: COORDENADOR DE LEGAIZAÇÃO ll | E34: Pleno | F34: Tático | G34: Legalização | I34: 220 | J34: 8647 | K34: CLT | L34: 840698 | M34: Masculino | N34: 45900
A35: 29 | B35: 1911 | C35: COORDENADOR DE MARKETING II | E35: Pleno | F35: Tático | G35: Marketing | I35: 220 | J35: 8647 | K35: CLT | L35: 1423-15 | M35: Feminino | N35: 45870
A36: 30 | B36: 1452 | C36: COORDENADOR DE OBRAS | E36: Não trabalhamos senioridade | F36: Operacional | G36: Edificação | I36: 220 | J36: 8714 | K36: CLT | L36: 1413-05 | M36: Masculino | N36: 45871
A37: 31 | B37: PJ5 | C37: COORDENADOR DE SUPRIMENTOS | E37: Não trabalhamos senioridade | F37: Tático | G37: Suprimentos | I37: 220 | J37: =16000/1.51 -> 10596.026 | K37: PJ | M37: Feminino | N37: 45872
A38: 32 | B38: PJ6 | C38: COORDENADOR FINANCEIRO | E38: Não trabalhamos senioridade | F38: Tático | G38: Financeiro | I38: 220 | J38: =12000/1.51 -> 7947.0199 | K38: PJ | M38: Masculino | N38: 45873
A39: 33 | B39: PJ7 | C39: DIRETOR | E39: Não trabalhamos senioridade | F39: Estratégico | G39: Comercial | I39: 220 | J39: =58000/1.04 -> 55769.231 | K39: PJ | M39: Masculino | N39: 45874
A40: 34 | B40: 132 | C40: ENCARREGADO DE OBRAS | E40: Não trabalhamos senioridade | F40: Operacional | G40: Urbanismo | I40: 220 | J40: 8461 | K40: CLT | L40: 1900113 | M40: Masculino | N40: 45875
A41: 34 | B41: 182 | C41: ENCARREGADO DE OBRAS | E41: Não trabalhamos senioridade | F41: Operacional | G41: Urbanismo | I41: 220 | J41: 11540 | K41: CLT | L41: 1900113 | M41: Masculino | N41: 45876
A42: 35 | B42: 1351 | C42: ENCARREGADO OBRAS/MANUTENCAO | E42: Não trabalhamos senioridade | F42: Operacional | G42: Edificação | I42: 220 | J42: 8714 | K42: CLT | L42: 5143-25 | M42: Masculino
A43: 36 | B43: PJ8 | C43: ENGENHEIRO JUNIOR DE URBANISMO | E43: Júnior | F43: Operacional | G43: Urbanismo | I43: 220 | J43: =8390/1.49 -> 5630.8725 | K43: PJ | M43: Masculino
A44: 37 | B44: PJ9 | C44: ENGENHEIRO SÊNIOR | E44: Sênior | F44: Tático | G44: Edificação | I44: 220 | J44: =19000/1.32 -> 14393.939 | K44: PJ | M44: Feminino
A45: 38 | B45: E01 | C45: ESTAGIARIO (A) | E45: Não trabalhamos senioridade | F45: Operacional | G45: Novos Negócios | I45: 150 | J45: 1521 | K45: Estagiário | L45: 446083 | M45: Feminino
A46: 39 | B46: E03 | C46: ESTAGIÁRIO(A) ADM | E46: Não trabalhamos senioridade | F46: Operacional | G46: Administrativo | I46: 150 | J46: 1521 | K46: Estagiário | L46: 807308 | M46: Masculino
A47: 40 | B47: E04 | C47: ESTAGIARIO(A) ENG. CIVIL | E47: Não trabalhamos senioridade | F47: Operacional | G47: Urbanismo | I47: 150 | J47: 1521 | K47: Estagiário | M47: Feminino
A48: 41 | B48: 1940 | C48: ESTAGIÁRIO(A) RH/DP | E48: Não trabalhamos senioridade | F48: Operacional | G48: DHO | I48: 100 | J48: 1014 | K48: Estagiário | L48: 807308 | M48: Feminino
A49: 42 | B49: PJ10 | C49: GERENTE ADMINISTRATIVA | E49: Não trabalhamos senioridade | F49: Tático | G49: Administrativo | I49: 220 | J49: =16160/1.32 -> 12242.424 | K49: PJ | M49: Feminino
A50: 43 | B50: PJ11 | C50: GERENTE COMERCIAL | E50: Não trabalhamos senioridade | F50: Tático | G50: Comercial | I50: 220 | J50: =15960/1.32 -> 12090.909 | K50: PJ | M50: Masculino
A51: 44 | B51: PJ12 | C51: GERENTE DE EDIFICAÇÕES | E51: Não trabalhamos senioridade | F51: Tático | G51: Edificação | I51: 220 | J51: =39740/1.32 -> 30106.061 | K51: PJ | M51: Masculino
A52: 45 | B52: PJ13 | C52: GERENTE DE HOUSE | E52: Não trabalhamos senioridade | F52: Tático | G52: Comercial | I52: 220 | J52: =5125 -> 5125 | K52: PJ | M52: Feminino
A53: 46 | B53: PJ14 | C53: GERENTE DE IMOBILIÁRIAS EXTERNAS | E53: Não trabalhamos senioridade | F53: Tático | G53: Comercial | I53: 220 | J53: =5266 -> 5266 | K53: PJ | M53: Masculino
A54: 46 | B54: PJ15 | C54: GERENTE DE IMOBILIÁRIAS EXTERNAS | E54: Não trabalhamos senioridade | F54: Tático | G54: Comercial | I54: 220 | J54: =5795 -> 5795 | K54: PJ | M54: Masculino
A55: 47 | B55: PJ16 | C55: GERENTE DE INCORPORAÇÃO | E55: Não trabalhamos senioridade | F55: Tático | G55: Incorporação | I55: 220 | J55: =18540/1.32 -> 14045.455 | K55: PJ | M55: Feminino
A56: 48 | B56: PJ17 | C56: GERENTE DE PARCERIAS | E56: Não trabalhamos senioridade | F56: Tático | G56: Comercial | I56: 220 | J56: =5640 -> 5640 | K56: PJ | M56: Feminino
A57: 48 | B57: PJ18 | C57: GERENTE DE PARCERIAS | E57: Não trabalhamos senioridade | F57: Tático | G57: Comercial | I57: 220 | J57: =5050 -> 5050 | K57: PJ | M57: Feminino
A58: 49 | B58: PJ19 | C58: GERENTE DE PARCERIAS EXTERNAS | E58: Não trabalhamos senioridade | F58: Tático | G58: Comercial | I58: 220 | J58: =5000 -> 5000 | K58: PJ | M58: Masculino
A59: 50 | B59: PJ20 | C59: GERENTE DE URBANISMO | E59: Não trabalhamos senioridade | F59: Tático | G59: Urbanismo | I59: 220 | J59: =37000/1.32 -> 28030.303 | K59: PJ | M59: Masculino
A60: 51 | B60: PJ21 | C60: SUPERVISOR DE NOVOS NEGÓCIOS | E60: Não trabalhamos senioridade | F60: Tático | G60: Novos Negócios | I60: 220 | J60: =12000/1.37 -> 8759.1241 | K60: PJ | M60: Masculino
A61: 52 | B61: 186 | C61: SUPERVISOR(A) FINANCEIRO I | E61: Júnior | F61: Operacional | G61: Financeiro | I61: 220 | J61: 5955.08 | K61: CLT | L61: 4102-35 | M61: Feminino
A62: 53 | B62: PJ22 | C62: TECNICO ANALISTA DE CUSTOS | E62: Não trabalhamos senioridade | F62: Operacional | G62: Edificação | I62: 220 | J62: =10430/1.49 -> 7000 | K62: PJ | M62: Masculino
A63: 54 | B63: 1871 | C63: TECNOLOGO EM CONSTRUÇÃO DE EDIFICIOS | E63: Não trabalhamos senioridade | F63: Operacional | G63: Edificação | I63: 220 | J63: 8585 | K63: CLT | L63: 2142-80 | M63: Masculino
A271: 158
A272: 125
A273: 152
A274: 152
A275: 152
A276: 152
A277: 152
A278: 152
A279: 153
A280: 154
A281: 154
A282: 154
... A311: 156

Sheet Jobmatch
A1: Jobmatch
A3: Cod. | B3: Cargos Empresa | C3: Área | D3: Departamento | E3: Nível Organizacional | F3: Cod. Pesquisa | G3: Cargos Pesquisa | H3: Senioridade | I3: Observações | J3: Tipo de Contrato | K3: Pesquisa | L3: Pesquisas
A4: 1 | B4: =VLOOKUP(A4,'Folha de Pagamento'!A:C,3,0) -> ALMOXARIFE | C4: =VLOOKUP(A4,'Folha de Pagamento'!A:G,7,0) -> Edificação | D4: 8 - ADM PROJETOS | E4: =VLOOKUP(A4,'Folha de Pagamento'!A:F,6,0) -> Operacional | F4: 203 | G4: Almoxarife | H4: Indiferente | L4: Construção | M4: TI | O4: Geral
A5: 2 | B5: =VLOOKUP(A5,'Folha de Pagamento'!A:C,3,0) -> ANALISTA DE COMPRAS | C5: =VLOOKUP(A5,'Folha de Pagamento'!A:G,7,0) -> Suprimentos | D5: 9 - ADM PROJETOS | E5: =VLOOKUP(A5,'Folha de Pagamento'!A:F,6,0) -> Operacional | F5: 136 | G5: Analista de Compras | H5: Pleno | L5: Construção | M5: TI | N5: Industria | O5: Geral
A6: 3 | B6: =VLOOKUP(A6,'Folha de Pagamento'!A:C,3,0) -> ANALISTA DE CRIAÇAO | C6: =VLOOKUP(A6,'Folha de Pagamento'!A:G,7,0) -> Marketing | D6: 10 - ADM PROJETOS | E6: =VLOOKUP(A6,'Folha de Pagamento'!A:F,6,0) -> Operacional | F6: 45 | G6: Analista de Criação | H6: Indiferente | L6: Construção | O6: Geral
A7: 4 | B7: =VLOOKUP(A7,'Folha de Pagamento'!A:C,3,0) -> ANALISTA DE INOVAÇÃO | C7: =VLOOKUP(A7,'Folha de Pagamento'!A:G,7,0) -> Inovação | D7: 11 - ADM PROJETOS | E7: =VLOOKUP(A7,'Folha de Pagamento'!A:F,6,0) -> Tático | F7: 437 | G7: Analista de Inovação | H7: Indiferente
A8: 5 | B8: =VLOOKUP(A8,'Folha de Pagamento'!A:C,3,0) -> ANALISTA DE MANUTENÇÃO II | C8: =VLOOKUP(A8,'Folha de Pagamento'!A:G,7,0) -> Edificação | D8: 12 - ADM PROJETOS | E8: =VLOOKUP(A8,'Folha de Pagamento'!A:F,6,0) -> Operacional | F8: 820 | G8: Encarregado de Manutenção | H8: Indiferente | L8: Construção | M8: TI | O8: Geral
A9: 6 | B9: =VLOOKUP(A9,'Folha de Pagamento'!A:C,3,0) -> ANALISTA DE MARKETING l | C9: =VLOOKUP(A9,'Folha de Pagamento'!A:G,7,0) -> Marketing | D9: 13 - ADM PROJETOS | E9: =VLOOKUP(A9,'Folha de Pagamento'!A:F,6,0) -> Operacional | F9: 42 | G9: Analista de Marketing | H9: Júnior | O9: Geral
A10: 7 | B10: =VLOOKUP(A10,'Folha de Pagamento'!A:C,3,0) -> ANALISTA DE PÓS VENDAS II | C10: =VLOOKUP(A10,'Folha de Pagamento'!A:G,7,0) -> Pós Vendas | D10: 14 - ADM PROJETOS | E10: =VLOOKUP(A10,'Folha de Pagamento'!A:F,6,0) -> Operacional | F10: 19 | G10: Analista Comercial | H10: Pleno | O10: Geral
A11: 8 | B11: =VLOOKUP(A11,'Folha de Pagamento'!A:C,3,0) -> ANALISTA DE URBANISMO | C11: =VLOOKUP(A11,'Folha de Pagamento'!A:G,7,0) -> Urbanismo | D11: 15 - ADM PROJETOS | E11: =VLOOKUP(A11,'Folha de Pagamento'!A:F,6,0) -> Operacional | F11: 1199 | G11: Analista de Urbanismo | H11: Indiferente | L11: Construção | M11: TI | N11: Industria | O11: Geral
A12: 9 | B12: =VLOOKUP(A12,'Folha de Pagamento'!A:C,3,0) -> ANALISTA FINANCEIRO COMERCIAL III | C12: =VLOOKUP(A12,'Folha de Pagamento'!A:G,7,0) -> Financeiro | D12: 16 - ADM PROJETOS | E12: =VLOOKUP(A12,'Folha de Pagamento'!A:F,6,0) -> Operacional | F12: 16 | G12: Analista Financeiro | H12: Sênior | L12: Construção | M12: TI | O12: Geral
A13: 10 | B13: =VLOOKUP(A13,'Folha de Pagamento'!A:C,3,0) -> ANALISTA FINANCEIRO DE CAPTAÇÃO DE RECURSOS III | C13: =VLOOKUP(A13,'Folha de Pagamento'!A:G,7,0) -> Financeiro | D13: 17 - ADM PROJETOS | E13: =VLOOKUP(A13,'Folha de Pagamento'!A:F,6,0) -> Operacional | F13: 16 | G13: Analista Financeiro | H13: Sênior | L13: Construção | M13: TI | N13: Industria | O13: Geral
A14: 11 | B14: =VLOOKUP(A14,'Folha de Pagamento'!A:C,3,0) -> ANALISTA FINANCEIRO I | C14: =VLOOKUP(A14,'Folha de Pagamento'!A:G,7,0) -> Financeiro | D14: 18 - ADM PROJETOS | E14: =VLOOKUP(A14,'Folha de Pagamento'!A:F,6,0) -> Operacional | F14: 16 | G14: Analista Financeiro | H14: Júnior | L14: Construção | M14: TI | N14: Industria | O14: Geral
A15: 12 | B15: =VLOOKUP(A15,'Folha de Pagamento'!A:C,3,0) -> ASSISTENTE ADM DE LEGALIZAÇÃO III | C15: =VLOOKUP(A15,'Folha de Pagamento'!A:G,7,0) -> Legalização | D15: 19 - ADM PROJETOS | E15: =VLOOKUP(A15,'Folha de Pagamento'!A:F,6,0) -> Operacional | F15: 1201 | G15: Assistente de Legalização | H15: Indiferente
A16: 13 | B16: =VLOOKUP(A16,'Folha de Pagamento'!A:C,3,0) -> ASSISTENTE ADMINISTRATIVO lll | C16: =VLOOKUP(A16,'Folha de Pagamento'!A:G,7,0) -> Administrativo | D16: 20 - ADM PROJETOS | E16: =VLOOKUP(A16,'Folha de Pagamento'!A:F,6,0) -> Operacional | F16: 59 | G16: Assistente Administrativo | H16: Indiferente | O16: Geral
A17: 14 | B17: =VLOOKUP(A17,'Folha de Pagamento'!A:C,3,0) -> ASSISTENTE DE CONTROLADORIA III | C17: =VLOOKUP(A17,'Folha de Pagamento'!A:G,7,0) -> Controladoria | D17: 21 - ADM PROJETOS | E17: =VLOOKUP(A17,'Folha de Pagamento'!A:F,6,0) -> Operacional | F17: 150 | G17: Assistente de Controladoria | H17: Indiferente
A18: 15 | B18: =VLOOKUP(A18,'Folha de Pagamento'!A:C,3,0) -> ASSISTENTE DE ENGENHARIA lll | C18: =VLOOKUP(A18,'Folha de Pagamento'!A:G,7,0) -> Edificação | D18: 22 - ADM PROJETOS | E18: =VLOOKUP(A18,'Folha de Pagamento'!A:F,6,0) -> Operacional | F18: 531 | G18: Assistente de Engenharia | H18: Indiferente | O18: Geral
A19: 16 | B19: =VLOOKUP(A19,'Folha de Pagamento'!A:C,3,0) -> ASSISTENTE DE MARKETING | C19: =VLOOKUP(A19,'Folha de Pagamento'!A:G,7,0) -> Marketing | D19: 23 - ADM PROJETOS | E19: =VLOOKUP(A19,'Folha de Pagamento'!A:F,6,0) -> Operacional | F19: 71 | G19: Assistente de Marketing | H19: Indiferente | L19: Construção | M19: TI | O19: Geral
A20: 17 | B20: =VLOOKUP(A20,'Folha de Pagamento'!A:C,3,0) -> ASSISTENTE DE RECURSOS HUMANOS | C20: =VLOOKUP(A20,'Folha de Pagamento'!A:G,7,0) -> DHO | D20: 24 - ADM PROJETOS | E20: =VLOOKUP(A20,'Folha de Pagamento'!A:F,6,0) -> Operacional | F20: 77 | G20: Assistente de Recursos Humanos | H20: Indiferente | L20: Construção | M20: TI | N20: Industria | O20: Geral
A21: 18 | B21: =VLOOKUP(A21,'Folha de Pagamento'!A:C,3,0) -> ASSISTENTE DE TI | C21: =VLOOKUP(A21,'Folha de Pagamento'!A:G,7,0) -> Tecnologia da Informação | D21: 25 - ADM PROJETOS | E21: =VLOOKUP(A21,'Folha de Pagamento'!A:F,6,0) -> Operacional | F21: 31 | G21: Assistente de Tecnologia da Informação | H21: Indiferente | L21: Construção | O21: Geral
A22: 19 | B22: =VLOOKUP(A22,'Folha de Pagamento'!A:C,3,0) -> ASSISTENTE FINANCEIRO CONTAS A PAGAR | C22: =VLOOKUP(A22,'Folha de Pagamento'!A:G,7,0) -> Financeiro | D22: 26 - ADM PROJETOS | E22: =VLOOKUP(A22,'Folha de Pagamento'!A:F,6,0) -> Operacional | F22: 79 | G22: Assistente Financeiro | H22: Indiferente | L22: Construção | M22: TI | O22: Geral
A23: 20 | B23: =VLOOKUP(A23,'Folha de Pagamento'!A:C,3,0) -> AUXILIAR ADMINISTRATIVO | C23: =VLOOKUP(A23,'Folha de Pagamento'!A:G,7,0) -> Administrativo | D23: 27 - ADM PROJETOS | E23: =VLOOKUP(A23,'Folha de Pagamento'!A:F,6,0) -> Operacional | F23: 83 | G23: Auxiliar Administrativo | H23: Indiferente | L23: Construção | O23: Geral
A24: 21 | B24: =VLOOKUP(A24,'Folha de Pagamento'!A:C,3,0) -> AUXILIAR ADMINISTRATIVO III | C24: =VLOOKUP(A24,'Folha de Pagamento'!A:G,7,0) -> Administrativo | D24: 28 - ADM PROJETOS | E24: =VLOOKUP(A24,'Folha de Pagamento'!A:F,6,0) -> Operacional | F24: 83 | G24: Auxiliar Administrativo | H24: Indiferente | M24: TI | O24: Geral
A25: 22 | B25: =VLOOKUP(A25,'Folha de Pagamento'!A:C,3,0) -> AUXILIAR DE ATENDIMENTO II | C25: =VLOOKUP(A25,'Folha de Pagamento'!A:G,7,0) -> Recepção | D25: 29 - ADM PROJETOS | E25: =VLOOKUP(A25,'Folha de Pagamento'!A:F,6,0) -> Operacional | F25: 318 | G25: Auxiliar de Atendimento | H25: Indiferente | L25: Construção | M25: TI | O25: Geral
A26: 23 | B26: =VLOOKUP(A26,'Folha de Pagamento'!A:C,3,0) -> AUXILIAR DE ENGENHARIA | C26: =VLOOKUP(A26,'Folha de Pagamento'!A:G,7,0) -> Urbanismo | D26: 30 - ADM PROJETOS | E26: =VLOOKUP(A26,'Folha de Pagamento'!A:F,6,0) -> Operacional | F26: 207 | G26: Auxiliar de Engenharia | H26: Indiferente | M26: TI | O26: Geral
A27: 24 | B27: =VLOOKUP(A27,'Folha de Pagamento'!A:C,3,0) -> CONTROLER JURÍDICO | C27: =VLOOKUP(A27,'Folha de Pagamento'!A:G,7,0) -> Administrativo | D27: 31 - ADM PROJETOS | E27: =VLOOKUP(A27,'Folha de Pagamento'!A:F,6,0) -> Tático | F27: 9 | G27: Advogado | H27: Sênior | M27: TI | O27: Geral
A28: 25 | B28: =VLOOKUP(A28,'Folha de Pagamento'!A:C,3,0) -> CONTROLLER GERAL | C28: =VLOOKUP(A28,'Folha de Pagamento'!A:G,7,0) -> Controladoria | D28: 32 - ADM PROJETOS | E28: =VLOOKUP(A28,'Folha de Pagamento'!A:F,6,0) -> Tático | F28: 95 | G28: Controller | H28: Indiferente | M28: TI | N28: Industria | O28: Geral
A29: 26 | B29: =VLOOKUP(A29,'Folha de Pagamento'!A:C,3,0) -> CONTROLLER TÉCNICO | C29: =VLOOKUP(A29,'Folha de Pagamento'!A:G,7,0) -> Controladoria | D29: 33 - ADM PROJETOS | E29: =VLOOKUP(A29,'Folha de Pagamento'!A:F,6,0) -> Tático | F29: 26 | G29: Analista de Controladoria | H29: Especialista | M29: TI | O29: Geral
A30: 27 | B30: =VLOOKUP(A30,'Folha de Pagamento'!A:C,3,0) -> COORDENADOR DE DHO | C30: =VLOOKUP(A30,'Folha de Pagamento'!A:G,7,0) -> DHO | D30: 34 - ADM PROJETOS | E30: =VLOOKUP(A30,'Folha de Pagamento'!A:F,6,0) -> Tático | F30: 121 | G30: Coordenador de Recursos Humanos | H30: Indiferente | L30: Construção | M30: TI | N30: Industria | O30: Geral
A31: 28 | B31: =VLOOKUP(A31,'Folha de Pagamento'!A:C,3,0) -> COORDENADOR DE LEGAIZAÇÃO ll | C31: =VLOOKUP(A31,'Folha de Pagamento'!A:G,7,0) -> Legalização | D31: 35 - ADM PROJETOS | E31: =VLOOKUP(A31,'Folha de Pagamento'!A:F,6,0) -> Tático | F31: 1203 | G31: Coordenador de Legalização | H31: Indiferente | L31: Construção | M31: TI | N31: Industria | O31: Geral
A32: 29 | B32: =VLOOKUP(A32,'Folha de Pagamento'!A:C,3,0) -> COORDENADOR DE MARKETING II | C32: =VLOOKUP(A32,'Folha de Pagamento'!A:G,7,0) -> Marketing | D32: 36 - ADM PROJETOS | E32: =VLOOKUP(A32,'Folha de Pagamento'!A:F,6,0) -> Tático | F32: 56 | G32: Coordenador de Marketing | H32: Indiferente | L32: Construção | M32: TI | N32: Industria | O32: Geral
A33: 30 | B33: =VLOOKUP(A33,'Folha de Pagamento'!A:C,3,0) -> COORDENADOR DE OBRAS | C33: =VLOOKUP(A33,'Folha de Pagamento'!A:G,7,0) -> Edificação | D33: 37 - ADM PROJETOS | E33: Tático | F33: 209 | G33: Coordenador de Obras | H33: Indiferente | L33: Construção | M33: TI | N33: Industria | O33: Geral
A34: 31 | B34: =VLOOKUP(A34,'Folha de Pagamento'!A:C,3,0) -> COORDENADOR DE SUPRIMENTOS | C34: =VLOOKUP(A34,'Folha de Pagamento'!A:G,7,0) -> Suprimentos | D34: 38 - ADM PROJETOS | E34: =VLOOKUP(A34,'Folha de Pagamento'!A:F,6,0) -> Tático | F34: 137 | G34: Coordenador de Compras | H34: Indiferente | L34: Construção | M34: TI | O34: Geral
A35: 32 | B35: =VLOOKUP(A35,'Folha de Pagamento'!A:C,3,0) -> COORDENADOR FINANCEIRO | C35: =VLOOKUP(A35,'Folha de Pagamento'!A:G,7,0) -> Financeiro | D35: 39 - ADM PROJETOS | E35: =VLOOKUP(A35,'Folha de Pagamento'!A:F,6,0) -> Tático | F35: 122 | G35: Coordenador Financeiro | H35: Indiferente | L35: Construção | M35: TI | O35: Geral
A36: 33 | B36: =VLOOKUP(A36,'Folha de Pagamento'!A:C,3,0) -> DIRETOR | C36: =VLOOKUP(A36,'Folha de Pagamento'!A:G,7,0) -> Comercial | D36: 40 - ADM PROJETOS | E36: =VLOOKUP(A36,'Folha de Pagamento'!A:F,6,0) -> Estratégico | F36: 456 | G36: CEO | H36: Indiferente | L36: Construção | M36: TI | N36: Industria | O36: Geral
A37: 34 | B37: =VLOOKUP(A37,'Folha de Pagamento'!A:C,3,0) -> ENCARREGADO DE OBRAS | C37: =VLOOKUP(A37,'Folha de Pagamento'!A:G,7,0) -> Urbanismo | D37: 41 - ADM PROJETOS | E37: =VLOOKUP(A37,'Folha de Pagamento'!A:F,6,0) -> Operacional | F37: 470 | G37: Mestre de Obras | H37: Indiferente | L37: Construção | M37: TI | O37: Geral
A38: 35 | B38: =VLOOKUP(A38,'Folha de Pagamento'!A:C,3,0) -> ENCARREGADO OBRAS/MANUTENCAO | C38: =VLOOKUP(A38,'Folha de Pagamento'!A:G,7,0) -> Edificação | D38: 42 - ADM PROJETOS | E38: =VLOOKUP(A38,'Folha de Pagamento'!A:F,6,0) -> Operacional | F38: 470 | G38: Mestre de Obras | H38: Indiferente
A39: 36 | B39: =VLOOKUP(A39,'Folha de Pagamento'!A:C,3,0) -> ENGENHEIRO JUNIOR DE URBANISMO | C39: =VLOOKUP(A39,'Folha de Pagamento'!A:G,7,0) -> Urbanismo | D39: 43 - ADM PROJETOS | E39: =VLOOKUP(A39,'Folha de Pagamento'!A:F,6,0) -> Operacional | F39: 212 | G39: Engenheiro de Urbanismo | H39: Indiferente | L39: Construção | M39: TI | O39: Geral
A40: 37 | B40: =VLOOKUP(A40,'Folha de Pagamento'!A:C,3,0) -> ENGENHEIRO SÊNIOR | C40: =VLOOKUP(A40,'Folha de Pagamento'!A:G,7,0) -> Edificação | D40: 44 - ADM PROJETOS | E40: =VLOOKUP(A40,'Folha de Pagamento'!A:F,6,0) -> Tático | F40: 212 | G40: Engenheiro de Urbanismo | H40: Indiferente | L40: Construção | O40: Geral
A41: 38 | B41: =VLOOKUP(A41,'Folha de Pagamento'!A:C,3,0) -> ESTAGIARIO (A) | C41: =VLOOKUP(A41,'Folha de Pagamento'!A:G,7,0) -> Novos Negócios | D41: 45 - ADM PROJETOS | E41: =VLOOKUP(A41,'Folha de Pagamento'!A:F,6,0) -> Operacional | F41: 338 | G41: Estagiário Administrativo | H41: Indiferente | L41: Construção | M41: TI | N41: Industria | O41: Geral
A42: 39 | B42: =VLOOKUP(A42,'Folha de Pagamento'!A:C,3,0) -> ESTAGIÁRIO(A) ADM | C42: =VLOOKUP(A42,'Folha de Pagamento'!A:G,7,0) -> Administrativo | D42: 46 - ADM PROJETOS | E42: =VLOOKUP(A42,'Folha de Pagamento'!A:F,6,0) -> Operacional | F42: 338 | G42: Estagiário Administrativo | H42: Indiferente | L42: Construção | M42: TI | N42: Industria | O42: Geral
A43: 40 | B43: =VLOOKUP(A43,'Folha de Pagamento'!A:C,3,0) -> ESTAGIARIO(A) ENG. CIVIL | C43: =VLOOKUP(A43,'Folha de Pagamento'!A:G,7,0) -> Urbanismo | D43: 47 - ADM PROJETOS | E43: =VLOOKUP(A43,'Folha de Pagamento'!A:F,6,0) -> Operacional | F43: 1204 | G43: Estagiário de Engenharia Civil | H43: Indiferente | O43: Geral
A44: 41 | B44: =VLOOKUP(A44,'Folha de Pagamento'!A:C,3,0) -> ESTAGIÁRIO(A) RH/DP | C44: =VLOOKUP(A44,'Folha de Pagamento'!A:G,7,0) -> DHO | D44: 48 - ADM PROJETOS | E44: =VLOOKUP(A44,'Folha de Pagamento'!A:F,6,0) -> Operacional | F44: 338 | G44: Estagiário Administrativo | H44: Indiferente | L44: Construção | M44: TI | O44: Geral
A45: 42 | B45: =VLOOKUP(A45,'Folha de Pagamento'!A:C,3,0) -> GERENTE ADMINISTRATIVA | C45: =VLOOKUP(A45,'Folha de Pagamento'!A:G,7,0) -> Administrativo | D45: 49 - ADM PROJETOS | E45: =VLOOKUP(A45,'Folha de Pagamento'!A:F,6,0) -> Tático | F45: 106 | G45: Gerente Administrativo | H45: Indiferente
A46: 43 | B46: =VLOOKUP(A46,'Folha de Pagamento'!A:C,3,0) -> GERENTE COMERCIAL | C46: =VLOOKUP(A46,'Folha de Pagamento'!A:G,7,0) -> Comercial | D46: 50 - ADM PROJETOS | E46: =VLOOKUP(A46,'Folha de Pagamento'!A:F,6,0) -> Tático | F46: 107 | G46: Gerente Comercial | H46: Indiferente | L46: Construção | M46: TI | O46: Geral
A47: 44 | B47: =VLOOKUP(A47,'Folha de Pagamento'!A:C,3,0) -> GERENTE DE EDIFICAÇÕES | C47: =VLOOKUP(A47,'Folha de Pagamento'!A:G,7,0) -> Edificação | D47: 51 - ADM PROJETOS | E47: =VLOOKUP(A47,'Folha de Pagamento'!A:F,6,0) -> Tático | F47: 311 | G47: Gerente de Operações | H47: Indiferente | N47: Industria | O47: Geral
A48: 45 | B48: =VLOOKUP(A48,'Folha de Pagamento'!A:C,3,0) -> GERENTE DE HOUSE | C48: =VLOOKUP(A48,'Folha de Pagamento'!A:G,7,0) -> Comercial | D48: 52 - ADM PROJETOS | E48: =VLOOKUP(A48,'Folha de Pagamento'!A:F,6,0) -> Tático | F48: 107 | G48: Gerente Comercial | H48: Indiferente
A49: 46 | B49: =VLOOKUP(A49,'Folha de Pagamento'!A:C,3,0) -> GERENTE DE IMOBILIÁRIAS EXTERNAS | C49: =VLOOKUP(A49,'Folha de Pagamento'!A:G,7,0) -> Comercial | D49: 53 - ADM PROJETOS | E49: =VLOOKUP(A49,'Folha de Pagamento'!A:F,6,0) -> Tático | F49: 1205 | G49: Gerente de Imobiliárias | H49: Indiferente | L49: Construção | O49: Geral
A50: 47 | B50: =VLOOKUP(A50,'Folha de Pagamento'!A:C,3,0) -> GERENTE DE INCORPORAÇÃO | C50: =VLOOKUP(A50,'Folha de Pagamento'!A:G,7,0) -> Incorporação | D50: 54 - ADM PROJETOS | E50: =VLOOKUP(A50,'Folha de Pagamento'!A:F,6,0) -> Tático | F50: 548 | G50: Gerente de Incorporação | H50: Indiferente | L50: Construção | M50: TI | N50: Industria | O50: Geral
A51: 48 | B51: =VLOOKUP(A51,'Folha de Pagamento'!A:C,3,0) -> GERENTE DE PARCERIAS | C51: =VLOOKUP(A51,'Folha de Pagamento'!A:G,7,0) -> Comercial | D51: 55 - ADM PROJETOS | E51: =VLOOKUP(A51,'Folha de Pagamento'!A:F,6,0) -> Tático | F51: 408 | G51: Gerente de Relacionamento | H51: Indiferente
A52: 49 | B52: =VLOOKUP(A52,'Folha de Pagamento'!A:C,3,0) -> GERENTE DE PARCERIAS EXTERNAS | C52: =VLOOKUP(A52,'Folha de Pagamento'!A:G,7,0) -> Comercial | D52: 56 - ADM PROJETOS | E52: =VLOOKUP(A52,'Folha de Pagamento'!A:F,6,0) -> Tático | F52: 408 | G52: Gerente de Relacionamento | H52: Indiferente | L52: Construção | M52: TI | N52: Industria | O52: Geral
A53: 50 | B53: =VLOOKUP(A53,'Folha de Pagamento'!A:C,3,0) -> GERENTE DE URBANISMO | C53: =VLOOKUP(A53,'Folha de Pagamento'!A:G,7,0) -> Urbanismo | D53: 57 - ADM PROJETOS | E53: =VLOOKUP(A53,'Folha de Pagamento'!A:F,6,0) -> Tático | F53: 311 | G53: Gerente de Operações | H53: Indiferente | L53: Construção | M53: TI | N53: Industria | O53: Geral
A54: 51 | B54: =VLOOKUP(A54,'Folha de Pagamento'!A:C,3,0) -> SUPERVISOR DE NOVOS NEGÓCIOS | C54: =VLOOKUP(A54,'Folha de Pagamento'!A:G,7,0) -> Novos Negócios | D54: 58 - ADM PROJETOS | E54: =VLOOKUP(A54,'Folha de Pagamento'!A:F,6,0) -> Tático | F54: 583 | G54: Supervisor de Negócios | H54: Indiferente | L54: Construção | M54: TI | N54: Industria | O54: Geral
A55: 52 | B55: =VLOOKUP(A55,'Folha de Pagamento'!A:C,3,0) -> SUPERVISOR(A) FINANCEIRO I | C55: =VLOOKUP(A55,'Folha de Pagamento'!A:G,7,0) -> Financeiro | D55: 59 - ADM PROJETOS | E55: =VLOOKUP(A55,'Folha de Pagamento'!A:F,6,0) -> Operacional | F55: 469 | G55: Supervisor Financeiro | H55: Júnior | L55: Construção | O55: Geral
A56: 53 | B56: =VLOOKUP(A56,'Folha de Pagamento'!A:C,3,0) -> TECNICO ANALISTA DE CUSTOS | C56: =VLOOKUP(A56,'Folha de Pagamento'!A:G,7,0) -> Edificação | D56: 60 - ADM PROJETOS | E56: =VLOOKUP(A56,'Folha de Pagamento'!A:F,6,0) -> Operacional | F56: 876 | G56: Analista de Custos | H56: Indiferente | O56: Geral
A57: 54 | B57: =VLOOKUP(A57,'Folha de Pagamento'!A:C,3,0) -> TECNOLOGO EM CONSTRUÇÃO DE EDIFICIOS | C57: =VLOOKUP(A57,'Folha de Pagamento'!A:G,7,0) -> Edificação | D57: 61 - ADM PROJETOS | E57: =VLOOKUP(A57,'Folha de Pagamento'!A:F,6,0) -> Operacional | F57: 269 | G57: Técnico em Edificações | H57: Indiferente | L57: Construção | M57: TI | N57: Industria | O57: Geral

Sheet Cálculos Comparativos
J1: DADOS PARA COMPARAÇÃO | O1: ='Informações Relevantes Cenário'!A1 -> Cenário 01: Pesquisas Consolidadas - Nacional | U1: ="% Distância da "&'Painel Geral'!B5 -> % Distância da Mediana | V1: Posicionamento
A3: Cod. | B3: Cargos Empresa | C3: Média Empresa | D3: Cod. Área | E3: Diretoria | F3: Novo Cargo | H3: Centro de Custo | I3: Nível Organizacional | J3: Cod. Pesquisa | K3: Cargos Pesquisa | L3: Senioridade | M3: Código+Senioridade | N3: Número de Colaboradores | O3: Menor Salário | P3: 1º Quartil | Q3: Média | R3: Mediana | S3: 3º Quartil | T3: Maior Salário | U3: C-01 | V3: C-01 (Posicionamento)
A4: 13 | B4: =VLOOKUP(A4,Jobmatch!A:G,2,0) -> ASSISTENTE ADMINISTRATIVO lll | C4: =IFERROR(AVERAGEIF('Folha de Pagamento'!A:A,A4,'Folha de Pagamento'!J:J),"") -> 3439.7 | D4: 1 | E4: =VLOOKUP(A4,Jobmatch!A:H,3,0) -> Administrativo | F4: Assistente Administrativo | G4: =VLOOKUP(F4,'Página24'!A:A,1,0) -> Assistente Administrativo | H4: =VLOOKUP(A4,Jobmatch!A:I,4,0) -> 20 - ADM PROJETOS | I4: =VLOOKUP(A4,Jobmatch!A:I,5,0) -> Operacional | J4: =VLOOKUP(A4,Jobmatch!A:I,6,0) -> 59 | K4: =VLOOKUP(A4,Jobmatch!A:I,7,0) -> Assistente Administrativo | L4: =VLOOKUP(A4,Jobmatch!A:I,8,0) -> Indiferente | M4: =J4&L4 -> 59Indiferente | N4: =COUNTIF('Folha de Pagamento'!A:A,A4) -> 1 | O4: =IFERROR(VLOOKUP(M4,'C-01'!$D:$L,4,0),"") -> 2076.09 | P4: =IFERROR(VLOOKUP(M4,'C-01'!$D:$L,5,0),"") -> 2329.53 | Q4: =IFERROR(VLOOKUP(M4,'C-01'!$D:$L,6,0),"") -> 2673.92 | R4: =IFERROR(VLOOKUP(M4,'C-01'!$D:$L,7,0),"") -> 2630.61 | S4: =IFERROR(VLOOKUP(M4,'C-01'!$D:$L,8,0),"") -> 2914.75 | T4: =IFERROR(VLOOKUP(M4,'C-01'!$D:$L,9,0),"") -> 3662.52 | U4: =IFS('Painel Geral'!$B$5="Mediana",IFERROR(IF(OR(C4="",R4=0,R4=""),"",($C4/$R4)),""),'Painel Geral'!$B$5="Menor Salário",IFERROR(IF(OR(C4="",R4=0,R4=""),"",($C4/$O4)),""),'Painel Geral'!$B$5="1º Quartil",IFERROR(IF(OR(C4="",R4=0,R4=""),"",($C4/$P4)),""), 'Painel Geral'!$B$5="Média",IFERROR(IF(OR(C4="",R4=0,R4=""),"",($C4/$Q4)),""),'Painel Geral'!$B$5="3º Quartil",IFERROR(IF(OR(C4="",R4=0,R4=""),"",($C4/$S4)),""),'Painel Geral'!$B$5="Maior Salário",IFERROR(IF(OR(C4="",R4=0,R4=""),"",($C4/$T4)),"")) -> 1.3075674 | V4: =IFS(OR(O4="",O4=0,C4="", C4=0),"",U4<=80%,"Muito Defasado",U4<=90%,"Defasado",U4<=100%,"Na Média",U4<=110%,"Competitivo",U4<=120%,"Muito Competitivo",U4>120%,"Agressivo") -> Agressivo
A5: 20 | B5: =VLOOKUP(A5,Jobmatch!A:G,2,0) -> AUXILIAR ADMINISTRATIVO | C5: =IFERROR(AVERAGEIF('Folha de Pagamento'!A:A,A5,'Folha de Pagamento'!J:J),"") -> 2254 | D5: 1 | E5: =VLOOKUP(A5,Jobmatch!A:H,3,0) -> Administrativo | F5: Auxiliar Administrativo | G5: =VLOOKUP(F5,'Página24'!A:A,1,0) -> Auxiliar Administrativo | H5: =VLOOKUP(A5,Jobmatch!A:I,4,0) -> 27 - ADM PROJETOS | I5: =VLOOKUP(A5,Jobmatch!A:I,5,0) -> Operacional | J5: =VLOOKUP(A5,Jobmatch!A:I,6,0) -> 83 | K5: =VLOOKUP(A5,Jobmatch!A:I,7,0) -> Auxiliar Administrativo | L5: =VLOOKUP(A5,Jobmatch!A:I,8,0) -> Indiferente | M5: =J5&L5 -> 83Indiferente | N5: =COUNTIF('Folha de Pagamento'!A:A,A5) -> 1 | O5: =IFERROR(VLOOKUP(M5,'C-01'!$D:$L,4,0),"") -> 1771.74 | P5: =IFERROR(VLOOKUP(M5,'C-01'!$D:$L,5,0),"") -> 2128.74 | Q5: =IFERROR(VLOOKUP(M5,'C-01'!$D:$L,6,0),"") -> 2292.87 | R5: =IFERROR(VLOOKUP(M5,'C-01'!$D:$L,7,0),"") -> 2309.71 | S5: =IFERROR(VLOOKUP(M5,'C-01'!$D:$L,8,0),"") -> 2375.14 | T5: =IFERROR(VLOOKUP(M5,'C-01'!$D:$L,9,0),"") -> 3073.32 | U5: =IFS('Painel Geral'!$B$5="Mediana",IFERROR(IF(OR(C5="",R5=0,R5=""),"",($C5/$R5)),""),'Painel Geral'!$B$5="Menor Salário",IFERROR(IF(OR(C5="",R5=0,R5=""),"",($C5/$O5)),""),'Painel Geral'!$B$5="1º Quartil",IFERROR(IF(OR(C5="",R5=0,R5=""),"",($C5/$P5)),""), 'Painel Geral'!$B$5="Média",IFERROR(IF(OR(C5="",R5=0,R5=""),"",($C5/$Q5)),""),'Painel Geral'!$B$5="3º Quartil",IFERROR(IF(OR(C5="",R5=0,R5=""),"",($C5/$S5)),""),'Painel Geral'!$B$5="Maior Salário",IFERROR(IF(OR(C5="",R5=0,R5=""),"",($C5/$T5)),"")) -> 0.97588009 | V5: =IFS(OR(O5="",O5=0,C5="", C5=0),"",U5<=80%,"Muito Defasado",U5<=90%,"Defasado",U5<=100%,"Na Média",U5<=110%,"Competitivo",U5<=120%,"Muito Competitivo",U5>120%,"Agressivo") -> Na Média
A6: 21 | B6: =VLOOKUP(A6,Jobmatch!A:G,2,0) -> AUXILIAR ADMINISTRATIVO III | C6: =IFERROR(AVERAGEIF('Folha de Pagamento'!A:A,A6,'Folha de Pagamento'!J:J),"") -> 2739.04 | D6: 1 | E6: =VLOOKUP(A6,Jobmatch!A:H,3,0) -> Administrativo | F6: Auxiliar Administrativo | G6: =VLOOKUP(F6,'Página24'!A:A,1,0) -> Auxiliar Administrativo | H6: =VLOOKUP(A6,Jobmatch!A:I,4,0) -> 28 - ADM PROJETOS | I6: =VLOOKUP(A6,Jobmatch!A:I,5,0) -> Operacional | J6: =VLOOKUP(A6,Jobmatch!A:I,6,0) -> 83 | K6: =VLOOKUP(A6,Jobmatch!A:I,7,0) -> Auxiliar Administrativo | L6: =VLOOKUP(A6,Jobmatch!A:I,8,0) -> Indiferente | M6: =J6&L6 -> 83Indiferente | N6: =COUNTIF('Folha de Pagamento'!A:A,A6) -> 1 | O6: =IFERROR(VLOOKUP(M6,'C-01'!$D:$L,4,0),"") -> 1771.74 | P6: =IFERROR(VLOOKUP(M6,'C-01'!$D:$L,5,0),"") -> 2128.74 | Q6: =IFERROR(VLOOKUP(M6,'C-01'!$D:$L,6,0),"") -> 2292.87 | R6: =IFERROR(VLOOKUP(M6,'C-01'!$D:$L,7,0),"") -> 2309.71 | S6: =IFERROR(VLOOKUP(M6,'C-01'!$D:$L,8,0),"") -> 2375.14 | T6: =IFERROR(VLOOKUP(M6,'C-01'!$D:$L,9,0),"") -> 3073.32 | U6: =IFS('Painel Geral'!$B$5="Mediana",IFERROR(IF(OR(C6="",R6=0,R6=""),"",($C6/$R6)),""),'Painel Geral'!$B$5="Menor Salário",IFERROR(IF(OR(C6="",R6=0,R6=""),"",($C6/$O6)),""),'Painel Geral'!$B$5="1º Quartil",IFERROR(IF(OR(C6="",R6=0,R6=""),"",($C6/$P6)),""), 'Painel Geral'!$B$5="Média",IFERROR(IF(OR(C6="",R6=0,R6=""),"",($C6/$Q6)),""),'Painel Geral'!$B$5="3º Quartil",IFERROR(IF(OR(C6="",R6=0,R6=""),"",($C6/$S6)),""),'Painel Geral'!$B$5="Maior Salário",IFERROR(IF(OR(C6="",R6=0,R6=""),"",($C6/$T6)),"")) -> 1.1858805 | V6: =IFS(OR(O6="",O6=0,C6="", C6=0),"",U6<=80%,"Muito Defasado",U6<=90%,"Defasado",U6<=100%,"Na Média",U6<=110%,"Competitivo",U6<=120%,"Muito Competitivo",U6>120%,"Agressivo") -> Muito Competitivo
A7: 24 | B7: =VLOOKUP(A7,Jobmatch!A:G,2,0) -> CONTROLER JURÍDICO | C7: =IFERROR(AVERAGEIF('Folha de Pagamento'!A:A,A7,'Folha de Pagamento'!J:J),"") -> 8276.6423 | D7: 1 | E7: =VLOOKUP(A7,Jobmatch!A:H,3,0) -> Administrativo | F7: Controller Jurídico | G7: =VLOOKUP(F7,'Página24'!A:A,1,0) -> #N/A | H7: =VLOOKUP(A7,Jobmatch!A:I,4,0) -> 31 - ADM PROJETOS | I7: =VLOOKUP(A7,Jobmatch!A:I,5,0) -> Tático | J7: =VLOOKUP(A7,Jobmatch!A:I,6,0) -> 9 | K7: =VLOOKUP(A7,Jobmatch!A:I,7,0) -> Advogado | L7: =VLOOKUP(A7,Jobmatch!A:I,8,0) -> Sênior | M7: =J7&L7 -> 9Sênior | N7: =COUNTIF('Folha de Pagamento'!A:A,A7) -> 1 | O7: =IFERROR(VLOOKUP(M7,'C-01'!$D:$L,4,0),"") -> 0 | P7: =IFERROR(VLOOKUP(M7,'C-01'!$D:$L,5,0),"") -> 0 | Q7: =IFERROR(VLOOKUP(M7,'C-01'!$D:$L,6,0),"") -> 0 | R7: =IFERROR(VLOOKUP(M7,'C-01'!$D:$L,7,0),"") -> 0 | S7: =IFERROR(VLOOKUP(M7,'C-01'!$D:$L,8,0),"") -> 0 | T7: =IFERROR(VLOOKUP(M7,'C-01'!$D:$L,9,0),"") -> 0 | U7: =IFS('Painel Geral'!$B$5="Mediana",IFERROR(IF(OR(C7="",R7=0,R7=""),"",($C7/$R7)),""),'Painel Geral'!$B$5="Menor Salário",IFERROR(IF(OR(C7="",R7=0,R7=""),"",($C7/$O7)),""),'Painel Geral'!$B$5="1º Quartil",IFERROR(IF(OR(C7="",R7=0,R7=""),"",($C7/$P7)),""), 'Painel Geral'!$B$5="Média",IFERROR(IF(OR(C7="",R7=0,R7=""),"",($C7/$Q7)),""),'Painel Geral'!$B$5="3º Quartil",IFERROR(IF(OR(C7="",R7=0,R7=""),"",($C7/$S7)),""),'Painel Geral'!$B$5="Maior Salário",IFERROR(IF(OR(C7="",R7=0,R7=""),"",($C7/$T7)),"")) | V7: =IFS(OR(O7="",O7=0,C7="", C7=0),"",U7<=80%,"Muito Defasado",U7<=90%,"Defasado",U7<=100%,"Na Média",U7<=110%,"Competitivo",U7<=120%,"Muito Competitivo",U7>120%,"Agressivo")
A8: 39 | B8: =VLOOKUP(A8,Jobmatch!A:G,2,0) -> ESTAGIÁRIO(A) ADM | C8: =IFERROR(AVERAGEIF('Folha de Pagamento'!A:A,A8,'Folha de Pagamento'!J:J),"") -> 1521 | D8: 1 | E8: =VLOOKUP(A8,Jobmatch!A:H,3,0) -> Administrativo | F8: Estagiário Administrativo | G8: =VLOOKUP(F8,'Página24'!A:A,1,0) -> #N/A | H8: =VLOOKUP(A8,Jobmatch!A:I,4,0) -> 46 - ADM PROJETOS | I8: =VLOOKUP(A8,Jobmatch!A:I,5,0) -> Operacional | J8: =VLOOKUP(A8,Jobmatch!A:I,6,0) -> 338 | K8: =VLOOKUP(A8,Jobmatch!A:I,7,0) -> Estagiário Administrativo | L8: =VLOOKUP(A8,Jobmatch!A:I,8,0) -> Indiferente | M8: =J8&L8 -> 338Indiferente | N8: =COUNTIF('Folha de Pagamento'!A:A,A8) -> 1 | O8: =IFERROR(VLOOKUP(M8,'C-01'!$D:$L,4,0),"") -> 1558.5273 | P8: =IFERROR(VLOOKUP(M8,'C-01'!$D:$L,5,0),"") -> 1615.0841 | Q8: =IFERROR(VLOOKUP(M8,'C-01'!$D:$L,6,0),"") -> 1753.3432 | R8: =IFERROR(VLOOKUP(M8,'C-01'!$D:$L,7,0),"") -> 1721.9182 | S8: =IFERROR(VLOOKUP(M8,'C-01'!$D:$L,8,0),"") -> 1860.1773 | T8: =IFERROR(VLOOKUP(M8,'C-01'!$D:$L,9,0),"") -> 2011.0023 | U8: =IFS('Painel Geral'!$B$5="Mediana",IFERROR(IF(OR(C8="",R8=0,R8=""),"",($C8/$R8)),""),'Painel Geral'!$B$5="Menor Salário",IFERROR(IF(OR(C8="",R8=0,R8=""),"",($C8/$O8)),""),'Painel Geral'!$B$5="1º Quartil",IFERROR(IF(OR(C8="",R8=0,R8=""),"",($C8/$P8)),""), 'Painel Geral'!$B$5="Média",IFERROR(IF(OR(C8="",R8=0,R8=""),"",($C8/$Q8)),""),'Painel Geral'!$B$5="3º Quartil",IFERROR(IF(OR(C8="",R8=0,R8=""),"",($C8/$S8)),""),'Painel Geral'!$B$5="Maior Salário",IFERROR(IF(OR(C8="",R8=0,R8=""),"",($C8/$T8)),"")) -> 0.88331723 | V8: =IFS(OR(O8="",O8=0,C8="", C8=0),"",U8<=80%,"Muito Defasado",U8<=90%,"Defasado",U8<=100%,"Na Média",U8<=110%,"Competitivo",U8<=120%,"Muito Competitivo",U8>120%,"Agressivo") -> Defasado
A9: 42 | B9: =VLOOKUP(A9,Jobmatch!A:G,2,0) -> GERENTE ADMINISTRATIVA | C9: =IFERROR(AVERAGEIF('Folha de Pagamento'!A:A,A9,'Folha de Pagamento'!J:J),"") -> 12242.424 | D9: 1 | E9: =VLOOKUP(A9,Jobmatch!A:H,3,0) -> Administrativo | F9: Gerente Administrativa | G9: =VLOOKUP(F9,'Página24'!A:A,1,0) -> Gerente Administrativa | H9: =VLOOKUP(A9,Jobmatch!A:I,4,0) -> 49 - ADM PROJETOS | I9: =VLOOKUP(A9,Jobmatch!A:I,5,0) -> Tático | J9: =VLOOKUP(A9,Jobmatch!A:I,6,0) -> 106 | K9: =VLOOKUP(A9,Jobmatch!A:I,7,0) -> Gerente Administrativo | L9: =VLOOKUP(A9,Jobmatch!A:I,8,0) -> Indiferente | M9: =J9&L9 -> 106Indiferente | N9: =COUNTIF('Folha de Pagamento'!A:A,A9) -> 2 | O9: =IFERROR(VLOOKUP(M9,'C-01'!$D:$L,4,0),"") -> 5281.61 | P9: =IFERROR(VLOOKUP(M9,'C-01'!$D:$L,5,0),"") -> 6616.13 | Q9: =IFERROR(VLOOKUP(M9,'C-01'!$D:$L,6,0),"") -> 9881.52 | R9: =IFERROR(VLOOKUP(M9,'C-01'!$D:$L,7,0),"") -> 10052.23 | S9: =IFERROR(VLOOKUP(M9,'C-01'!$D:$L,8,0),"") -> 12479.94 | T9: =IFERROR(VLOOKUP(M9,'C-01'!$D:$L,9,0),"") -> 15257.82 | U9: =IFS('Painel Geral'!$B$5="Mediana",IFERROR(IF(OR(C9="",R9=0,R9=""),"",($C9/$R9)),""),'Painel Geral'!$B$5="Menor Salário",IFERROR(IF(OR(C9="",R9=0,R9=""),"",($C9/$O9)),""),'Painel Geral'!$B$5="1º Quartil",IFERROR(IF(OR(C9="",R9=0,R9=""),"",($C9/$P9)),""), 'Painel Geral'!$B$5="Média",IFERROR(IF(OR(C9="",R9=0,R9=""),"",($C9/$Q9)),""),'Painel Geral'!$B$5="3º Quartil",IFERROR(IF(OR(C9="",R9=0,R9=""),"",($C9/$S9)),""),'Painel Geral'!$B$5="Maior Salário",IFERROR(IF(OR(C9="",R9=0,R9=""),"",($C9/$T9)),"")) -> 1.2178814 | V9: =IFS(OR(O9="",O9=0,C9="", C9=0),"",U9<=80%,"Muito Defasado",U9<=90%,"Defasado",U9<=100%,"Na Média",U9<=110%,"Competitivo",U9<=120%,"Muito Competitivo",U9>120%,"Agressivo") -> Agressivo
A10: 33 | B10: =VLOOKUP(A10,Jobmatch!A:G,2,0) -> DIRETOR | C10: =IFERROR(AVERAGEIF('Folha de Pagamento'!A:A,A10,'Folha de Pagamento'!J:J),"") -> 55769.231 | D10: 2 | E10: =VLOOKUP(A10,Jobmatch!A:H,3,0) -> Comercial | F10: Diretor | G10: =VLOOKUP(F10,'Página24'!A:A,1,0) -> Diretor | H10: =VLOOKUP(A10,Jobmatch!A:I,4,0) -> 40 - ADM PROJETOS | I10: =VLOOKUP(A10,Jobmatch!A:I,5,0) -> Estratégico | J10: =VLOOKUP(A10,Jobmatch!A:I,6,0) -> 456 | K10: =VLOOKUP(A10,Jobmatch!A:I,7,0) -> CEO | L10: =VLOOKUP(A10,Jobmatch!A:I,8,0) -> Indiferente | M10: =J10&L10 -> 456Indiferente | N10: =COUNTIF('Folha de Pagamento'!A:A,A10) -> 1 | O10: =IFERROR(VLOOKUP(M10,'C-01'!$D:$L,4,0),"") -> 18287.31 | P10: =IFERROR(VLOOKUP(M10,'C-01'!$D:$L,5,0),"") -> 24816.78 | Q10: =IFERROR(VLOOKUP(M10,'C-01'!$D:$L,6,0),"") -> 32648.36 | R10: =IFERROR(VLOOKUP(M10,'C-01'!$D:$L,7,0),"") -> 29147.75 | S10: =IFERROR(VLOOKUP(M10,'C-01'!$D:$L,8,0),"") -> 37122.89 | T10: =IFERROR(VLOOKUP(M10,'C-01'!$D:$L,9,0),"") -> 55429.54 | U10: =IFS('Painel Geral'!$B$5="Mediana",IFERROR(IF(OR(C10="",R10=0,R10=""),"",($C10/$R10)),""),'Painel Geral'!$B$5="Menor Salário",IFERROR(IF(OR(C10="",R10=0,R10=""),"",($C10/$O10)),""),'Painel Geral'!$B$5="1º Quartil",IFERROR(IF(OR(C10="",R10=0,R10=""),"",($C10/$P10)),""), 'Painel Geral'!$B$5="Média",IFERROR(IF(OR(C10="",R10=0,R10=""),"",($C10/$Q10)),""),'Painel Geral'!$B$5="3º Quartil",IFERROR(IF(OR(C10="",R10=0,R10=""),"",($C10/$S10)),""),'Painel Geral'!$B$5="Maior Salário",IFERROR(IF(OR(C10="",R10=0,R10=""),"",($C10/$T10)),"")) -> 1.9133288 | V10: =IFS(OR(O10="",O10=0,C10="", C10=0),"",U10<=80%,"Muito Defasado",U10<=90%,"Defasado",U10<=100%,"Na Média",U10<=110%,"Competitivo",U10<=120%,"Muito Competitivo",U10>120%,"Agressivo") -> Agressivo
A11: 43 | B11: =VLOOKUP(A11,Jobmatch!A:G,2,0) -> GERENTE COMERCIAL | C11: =IFERROR(AVERAGEIF('Folha de Pagamento'!A:A,A11,'Folha de Pagamento'!J:J),"") -> 12090.909 | D11: 2 | E11: =VLOOKUP(A11,Jobmatch!A:H,3,0) -> Comercial | F11: Gerente Comercial | G11: =VLOOKUP(F11,'Página24'!A:A,1,0) -> Gerente Comercial | H11: =VLOOKUP(A11,Jobmatch!A:I,4,0) -> 50 - ADM PROJETOS | I11: =VLOOKUP(A11,Jobmatch!A:I,5,0) -> Tático | J11: =VLOOKUP(A11,Jobmatch!A:I,6,0) -> 107 | K11: =VLOOKUP(A11,Jobmatch!A:I,7,0) -> Gerente Comercial | L11: =VLOOKUP(A11,Jobmatch!A:I,8,0) -> Indiferente | M11: =J11&L11 -> 107Indiferente | N11: =COUNTIF('Folha de Pagamento'!A:A,A11) -> 4 | O11: =IFERROR(VLOOKUP(M11,'C-01'!$D:$L,4,0),"") -> 5570.67 | P11: =IFERROR(VLOOKUP(M11,'C-01'!$D:$L,5,0),"") -> 9778.91 | Q11: =IFERROR(VLOOKUP(M11,'C-01'!$D:$L,6,0),"") -> 12281.04 | R11: =IFERROR(VLOOKUP(M11,'C-01'!$D:$L,7,0),"") -> 12107.57 | S11: =IFERROR(VLOOKUP(M11,'C-01'!$D:$L,8,0),"") -> 15321.87 | T11: =IFERROR(VLOOKUP(M11,'C-01'!$D:$L,9,0),"") -> 19289.48 | U11: =IFS('Painel Geral'!$B$5="Mediana",IFERROR(IF(OR(C11="",R11=0,R11=""),"",($C11/$R11)),""),'Painel Geral'!$B$5="Menor Salário",IFERROR(IF(OR(C11="",R11=0,R11=""),"",($C11/$O11)),""),'Painel Geral'!$B$5="1º Quartil",IFERROR(IF(OR(C11="",R11=0,R11=""),"",($C11/$P11)),""), 'Painel Geral'!$B$5="Média",IFERROR(IF(OR(C11="",R11=0,R11=""),"",($C11/$Q11)),""),'Painel Geral'!$B$5="3º Quartil",IFERROR(IF(OR(C11="",R11=0,R11=""),"",($C11/$S11)),""),'Painel Geral'!$B$5="Maior Salário",IFERROR(IF(OR(C11="",R11=0,R11=""),"",($C11/$T11)),"")) -> 0.99862393 | V11: =IFS(OR(O11="",O11=0,C11="", C11=0),"",U11<=80%,"Muito Defasado",U11<=90%,"Defasado",U11<=100%,"Na Média",U11<=110%,"Competitivo",U11<=120%,"Muito Competitivo",U11>120%,"Agressivo") -> Na Média
A12: 45 | B12: =VLOOKUP(A12,Jobmatch!A:G,2,0) -> GERENTE DE HOUSE | C12: =IFERROR(AVERAGEIF('Folha de Pagamento'!A:A,A12,'Folha de Pagamento'!J:J),"") -> 5125 | D12: 2 | E12: =VLOOKUP(A12,Jobmatch!A:H,3,0) -> Comercial | F12: Gerente House | G12: =VLOOKUP(F12,'Página24'!A:A,1,0) -> Gerente House | H12: =VLOOKUP(A12,Jobmatch!A:I,4,0) -> 52 - ADM PROJETOS | I12: =VLOOKUP(A12,Jobmatch!A:I,5,0) -> Tático | J12: =VLOOKUP(A12,Jobmatch!A:I,6,0) -> 107 | K12: =VLOOKUP(A12,Jobmatch!A:I,7,0) -> Gerente Comercial | L12: =VLOOKUP(A12,Jobmatch!A:I,8,0) -> Indiferente | M12: =J12&L12 -> 107Indiferente | N12: =COUNTIF('Folha de Pagamento'!A:A,A12) -> 1 | O12: =IFERROR(VLOOKUP(M12,'C-01'!$D:$L,4,0),"") -> 5570.67 | P12: =IFERROR(VLOOKUP(M12,'C-01'!$D:$L,5,0),"") -> 9778.91 | Q12: =IFERROR(VLOOKUP(M12,'C-01'!$D:$L,6,0),"") -> 12281.04 | R12: =IFERROR(VLOOKUP(M12,'C-01'!$D:$L,7,0),"") -> 12107.57 | S12: =IFERROR(VLOOKUP(M12,'C-01'!$D:$L,8,0),"") -> 15321.87 | T12: =IFERROR(VLOOKUP(M12,'C-01'!$D:$L,9,0),"") -> 19289.48 | U12: =IFS('Painel Geral'!$B$5="Mediana",IFERROR(IF(OR(C12="",R12=0,R12=""),"",($C12/$R12)),""),'Painel Geral'!$B$5="Menor Salário",IFERROR(IF(OR(C12="",R12=0,R12=""),"",($C12/$O12)),""),'Painel Geral'!$B$5="1º Quartil",IFERROR(IF(OR(C12="",R12=0,R12=""),"",($C12/$P12)),""), 'Painel Geral'!$B$5="Média",IFERROR(IF(OR(C12="",R12=0,R12=""),"",($C12/$Q12)),""),'Painel Geral'!$B$5="3º Quartil",IFERROR(IF(OR(C12="",R12=0,R12=""),"",($C12/$S12)),""),'Painel Geral'!$B$5="Maior Salário",IFERROR(IF(OR(C12="",R12=0,R12=""),"",($C12/$T12)),"")) -> 0.4232889 | V12: =IFS(OR(O12="",O12=0,C12="", C12=0),"",U12<=80%,"Muito Defasado",U12<=90%,"Defasado",U12<=100%,"Na Média",U12<=110%,"Competitivo",U12<=120%,"Muito Competitivo",U12>120%,"Agressivo") -> Muito Defasado
A13: 46 | B13: =VLOOKUP(A13,Jobmatch!A:G,2,0) -> GERENTE DE IMOBILIÁRIAS EXTERNAS | C13: =IFERROR(AVERAGEIF('Folha de Pagamento'!A:A,A13,'Folha de Pagamento'!J:J),"") -> 5530.5 | D13: 2 | E13: =VLOOKUP(A13,Jobmatch!A:H,3,0) -> Comercial | F13: Gerente Imobiliárias Externas | G13: =VLOOKUP(F13,'Página24'!A:A,1,0) -> #N/A | H13: =VLOOKUP(A13,Jobmatch!A:I,4,0) -> 53 - ADM PROJETOS | I13: =VLOOKUP(A13,Jobmatch!A:I,5,0) -> Tático | J13: =VLOOKUP(A13,Jobmatch!A:I,6,0) -> 1205 | K13: =VLOOKUP(A13,Jobmatch!A:I,7,0) -> Gerente de Imobiliárias | L13: =VLOOKUP(A13,Jobmatch!A:I,8,0) -> Indiferente | M13: =J13&L13 -> 1205Indiferente | N13: =COUNTIF('Folha de Pagamento'!A:A,A13) -> 2 | O13: =IFERROR(VLOOKUP(M13,'C-01'!$D:$L,4,0),"") -> 0 | P13: =IFERROR(VLOOKUP(M13,'C-01'!$D:$L,5,0),"") -> 0 | Q13: =IFERROR(VLOOKUP(M13,'C-01'!$D:$L,6,0),"") -> 0 | R13: =IFERROR(VLOOKUP(M13,'C-01'!$D:$L,7,0),"") -> 0 | S13: =IFERROR(VLOOKUP(M13,'C-01'!$D:$L,8,0),"") -> 0 | T13: =IFERROR(VLOOKUP(M13,'C-01'!$D:$L,9,0),"") -> 0 | U13: =IFS('Painel Geral'!$B$5="Mediana",IFERROR(IF(OR(C13="",R13=0,R13=""),"",($C13/$R13)),""),'Painel Geral'!$B$5="Menor Salário",IFERROR(IF(OR(C13="",R13=0,R13=""),"",($C13/$O13)),""),'Painel Geral'!$B$5="1º Quartil",IFERROR(IF(OR(C13="",R13=0,R13=""),"",($C13/$P13)),""), 'Painel Geral'!$B$5="Média",IFERROR(IF(OR(C13="",R13=0,R13=""),"",($C13/$Q13)),""),'Painel Geral'!$B$5="3º Quartil",IFERROR(IF(OR(C13="",R13=0,R13=""),"",($C13/$S13)),""),'Painel Geral'!$B$5="Maior Salário",IFERROR(IF(OR(C13="",R13=0,R13=""),"",($C13/$T13)),"")) | V13: =IFS(OR(O13="",O13=0,C13="", C13=0),"",U13<=80%,"Muito Defasado",U13<=90%,"Defasado",U13<=100%,"Na Média",U13<=110%,"Competitivo",U13<=120%,"Muito Competitivo",U13>120%,"Agressivo")
A14: 48 | B14: =VLOOKUP(A14,Jobmatch!A:G,2,0) -> GERENTE DE PARCERIAS | C14: =IFERROR(AVERAGEIF('Folha de Pagamento'!A:A,A14,'Folha de Pagamento'!J:J),"") -> 5345 | D14: 2 | E14: =VLOOKUP(A14,Jobmatch!A:H,3,0) -> Comercial | F14: Gerente Parcerias | G14: =VLOOKUP(F14,'Página24'!A:A,1,0) -> Gerente Parcerias | H14: =VLOOKUP(A14,Jobmatch!A:I,4,0) -> 55 - ADM PROJETOS | I14: =VLOOKUP(A14,Jobmatch!A:I,5,0) -> Tático | J14: =VLOOKUP(A14,Jobmatch!A:I,6,0) -> 408 | K14: =VLOOKUP(A14,Jobmatch!A:I,7,0) -> Gerente de Relacionamento | L14: =VLOOKUP(A14,Jobmatch!A:I,8,0) -> Indiferente | M14: =J14&L14 -> 408Indiferente | N14: =COUNTIF('Folha de Pagamento'!A:A,A14) -> 2 | O14: =IFERROR(VLOOKUP(M14,'C-01'!$D:$L,4,0),"") -> 5772.56 | P14: =IFERROR(VLOOKUP(M14,'C-01'!$D:$L,5,0),"") -> 7608.96 | Q14: =IFERROR(VLOOKUP(M14,'C-01'!$D:$L,6,0),"") -> 10973.95 | R14: =IFERROR(VLOOKUP(M14,'C-01'!$D:$L,7,0),"") -> 10996.97 | S14: =IFERROR(VLOOKUP(M14,'C-01'!$D:$L,8,0),"") -> 14004.27 | T14: =IFERROR(VLOOKUP(M14,'C-01'!$D:$L,9,0),"") -> 16628.86 | U14: =IFS('Painel Geral'!$B$5="Mediana",IFERROR(IF(OR(C14="",R14=0,R14=""),"",($C14/$R14)),""),'Painel Geral'!$B$5="Menor Salário",IFERROR(IF(OR(C14="",R14=0,R14=""),"",($C14/$O14)),""),'Painel Geral'!$B$5="1º Quartil",IFERROR(IF(OR(C14="",R14=0,R14=""),"",($C14/$P14)),""), 'Painel Geral'!$B$5="Média",IFERROR(IF(OR(C14="",R14=0,R14=""),"",($C14/$Q14)),""),'Painel Geral'!$B$5="3º Quartil",IFERROR(IF(OR(C14="",R14=0,R14=""),"",($C14/$S14)),""),'Painel Geral'!$B$5="Maior Salário",IFERROR(IF(OR(C14="",R14=0,R14=""),"",($C14/$T14)),"")) -> 0.48604297 | V14: =IFS(OR(O14="",O14=0,C14="", C14=0),"",U14<=80%,"Muito Defasado",U14<=90%,"Defasado",U14<=100%,"Na Média",U14<=110%,"Competitivo",U14<=120%,"Muito Competitivo",U14>120%,"Agressivo") -> Muito Defasado
A15: 49 | B15: =VLOOKUP(A15,Jobmatch!A:G,2,0) -> GERENTE DE PARCERIAS EXTERNAS | C15: =IFERROR(AVERAGEIF('Folha de Pagamento'!A:A,A15,'Folha de Pagamento'!J:J),"") -> 5000 | D15: 2 | E15: =VLOOKUP(A15,Jobmatch!A:H,3,0) -> Comercial | F15: Gerente Parcerias Externas | G15: =VLOOKUP(F15,'Página24'!A:A,1,0) -> Gerente Parcerias Externas | H15: =VLOOKUP(A15,Jobmatch!A:I,4,0) -> 56 - ADM PROJETOS | I15: =VLOOKUP(A15,Jobmatch!A:I,5,0) -> Tático | J15: =VLOOKUP(A15,Jobmatch!A:I,6,0) -> 408 | K15: =VLOOKUP(A15,Jobmatch!A:I,7,0) -> Gerente de Relacionamento | L15: =VLOOKUP(A15,Jobmatch!A:I,8,0) -> Indiferente | M15: =J15&L15 -> 408Indiferente | N15: =COUNTIF('Folha de Pagamento'!A:A,A15) -> 2 | O15: =IFERROR(VLOOKUP(M15,'C-01'!$D:$L,4,0),"") -> 5772.56 | P15: =IFERROR(VLOOKUP(M15,'C-01'!$D:$L,5,0),"") -> 7608.96 | Q15: =IFERROR(VLOOKUP(M15,'C-01'!$D:$L,6,0),"") -> 10973.95 | R15: =IFERROR(VLOOKUP(M15,'C-01'!$D:$L,7,0),"") -> 10996.97 | S15: =IFERROR(VLOOKUP(M15,'C-01'!$D:$L,8,0),"") -> 14004.27 | T15: =IFERROR(VLOOKUP(M15,'C-01'!$D:$L,9,0),"") -> 16628.86 | U15: =IFS('Painel Geral'!$B$5="Mediana",IFERROR(IF(OR(C15="",R15=0,R15=""),"",($C15/$R15)),""),'Painel Geral'!$B$5="Menor Salário",IFERROR(IF(OR(C15="",R15=0,R15=""),"",($C15/$O15)),""),'Painel Geral'!$B$5="1º Quartil",IFERROR(IF(OR(C15="",R15=0,R15=""),"",($C15/$P15)),""), 'Painel Geral'!$B$5="Média",IFERROR(IF(OR(C15="",R15=0,R15=""),"",($C15/$Q15)),""),'Painel Geral'!$B$5="3º Quartil",IFERROR(IF(OR(C15="",R15=0,R15=""),"",($C15/$S15)),""),'Painel Geral'!$B$5="Maior Salário",IFERROR(IF(OR(C15="",R15=0,R15=""),"",($C15/$T15)),"")) -> 0.4546707 | V15: =IFS(OR(O15="",O15=0,C15="", C15=0),"",U15<=80%,"Muito Defasado",U15<=90%,"Defasado",U15<=100%,"Na Média",U15<=110%,"Competitivo",U15<=120%,"Muito Competitivo",U15>120%,"Agressivo") -> Muito Defasado
... A57: 50 | B57: =VLOOKUP(A57,Jobmatch!A:G,2,0) -> GERENTE DE URBANISMO | C57: =IFERROR(AVERAGEIF('Folha de Pagamento'!A:A,A57,'Folha de Pagamento'!J:J),"") -> 28030.303 | D57: 10 | E57: =VLOOKUP(A57,Jobmatch!A:H,3,0) -> Urbanismo | F57: Gerente Urbanismo | G57: =VLOOKUP(F57,'Página24'!A:A,1,0) -> Gerente Urbanismo | H57: =VLOOKUP(A57,Jobmatch!A:I,4,0) -> 57 - ADM PROJETOS | I57: =VLOOKUP(A57,Jobmatch!A:I,5,0) -> Tático | J57: =VLOOKUP(A57,Jobmatch!A:I,6,0) -> 311 | K57: =VLOOKUP(A57,Jobmatch!A:I,7,0) -> Gerente de Operações | L57: =VLOOKUP(A57,Jobmatch!A:I,8,0) -> Indiferente | M57: =J57&L57 -> 311Indiferente | N57: =COUNTIF('Folha de Pagamento'!A:A,A57) -> 2 | O57: =IFERROR(VLOOKUP(M57,'C-01'!$D:$L,4,0),"") -> 7331.45 | P57: =IFERROR(VLOOKUP(M57,'C-01'!$D:$L,5,0),"") -> 10114.75 | Q57: =IFERROR(VLOOKUP(M57,'C-01'!$D:$L,6,0),"") -> 12711.42 | R57: =IFERROR(VLOOKUP(M57,'C-01'!$D:$L,7,0),"") -> 12517.82 | S57: =IFERROR(VLOOKUP(M57,'C-01'!$D:$L,8,0),"") -> 14749 | T57: =IFERROR(VLOOKUP(M57,'C-01'!$D:$L,9,0),"") -> 19098.65 | U57: =IFS('Painel Geral'!$B$5="Mediana",IFERROR(IF(OR(C57="",R57=0,R57=""),"",($C57/$R57)),""),'Painel Geral'!$B$5="Menor Salário",IFERROR(IF(OR(C57="",R57=0,R57=""),"",($C57/$O57)),""),'Painel Geral'!$B$5="1º Quartil",IFERROR(IF(OR(C57="",R57=0,R57=""),"",($C57/$P57)),""), 'Painel Geral'!$B$5="Média",IFERROR(IF(OR(C57="",R57=0,R57=""),"",($C57/$Q57)),""),'Painel Geral'!$B$5="3º Quartil",IFERROR(IF(OR(C57="",R57=0,R57=""),"",($C57/$S57)),""),'Painel Geral'!$B$5="Maior Salário",IFERROR(IF(OR(C57="",R57=0,R57=""),"",($C57/$T57)),"")) -> 2.239232 | V57: =IFS(OR(O57="",O57=0,C57="", C57=0),"",U57<=80%,"Muito Defasado",U57<=90%,"Defasado",U57<=100%,"Na Média",U57<=110%,"Competitivo",U57<=120%,"Muito Competitivo",U57>120%,"Agressivo") -> Agressivo

Sheet Página24
A1: Auxiliar Administrativo
A2: Auxiliar Administrativo
A3: Assistente Administrativo
A4: Gerente Administrativa
A5: Assistente Controladoria
A6: Controller Técnico
A7: Controller Geral
A8: Gerente Parcerias
A9: Gerente Parcerias Externas
A10: Gerente Comercial
A11: Gerente House
A12: Diretor
... A44: Gerente Urbanismo

Sheet Tabela 7
I1: DADOS PARA COMPARAÇÃO | O1: ='Informações Relevantes Cenário'!A1 -> Cenário 01: Pesquisas Consolidadas - Nacional | T1: ="% Distância da "&'Painel Geral'!B5 -> % Distância da Mediana | U1: Posicionamento
A3: Cod. | B3: Cargos Empresa | C3: Média Empresa | D3: Cod. Área | E3: Diretoria | F3: Novo Cargo | G3: Centro de Custo | H3: Nível Organizacional | I3: Cod. Pesquisa | J3: Cargos Pesquisa | K3: Senioridade | L3: Código+Senioridade | M3: Número de Colaboradores | O3: 1º Quartil | P3: Média | Q3: Mediana | R3: 3º Quartil | S3: Maior Salário | T3: C-01 | U3: C-01 (Posicionamento)
A4: 22 | B4: =VLOOKUP(A4,Jobmatch!A:G,2,0) -> AUXILIAR DE ATENDIMENTO II | C4: =IFERROR(AVERAGEIF('Folha de Pagamento'!A:A,A4,'Folha de Pagamento'!J:J),"") -> 2560 | D4: 1 | E4: =VLOOKUP(A4,Jobmatch!A:H,3,0) -> Recepção | F4: Auxiliar Atendimento | G4: =VLOOKUP(A4,Jobmatch!A:I,4,0) -> 29 - ADM PROJETOS | H4: =VLOOKUP(A4,Jobmatch!A:I,5,0) -> Operacional | I4: =VLOOKUP(A4,Jobmatch!A:I,6,0) -> 318 | J4: =VLOOKUP(A4,Jobmatch!A:I,7,0) -> Auxiliar de Atendimento | K4: =VLOOKUP(A4,Jobmatch!A:I,8,0) -> Indiferente | L4: =I4&K4 -> 318Indiferente | M4: =COUNTIF('Folha de Pagamento'!A:A,A4) -> 1 | N4: 10 | O4: =IFERROR(VLOOKUP(L4,'C-01'!$D:$L,5,0),"") -> 1778.55 | P4: =IFERROR(VLOOKUP(L4,'C-01'!$D:$L,6,0),"") -> 2041.06 | Q4: =IFERROR(VLOOKUP(L4,'C-01'!$D:$L,7,0),"") -> 2052.94 | R4: =IFERROR(VLOOKUP(L4,'C-01'!$D:$L,8,0),"") -> 2169.15 | S4: =IFERROR(VLOOKUP(L4,'C-01'!$D:$L,9,0),"") -> 2574.08 | T4: =IFS('Painel Geral'!$B$5="Mediana",IFERROR(IF(OR(C4="",Q4=0,Q4=""),"",($C4/$Q4)),""),'Painel Geral'!$B$5="Menor Salário",IFERROR(IF(OR(C4="",Q4=0,Q4=""),"",($C4/$N4)),""),'Painel Geral'!$B$5="1º Quartil",IFERROR(IF(OR(C4="",Q4=0,Q4=""),"",($C4/$O4)),""), 'Painel Geral'!$B$5="Média",IFERROR(IF(OR(C4="",Q4=0,Q4=""),"",($C4/$P4)),""),'Painel Geral'!$B$5="3º Quartil",IFERROR(IF(OR(C4="",Q4=0,Q4=""),"",($C4/$R4)),""),'Painel Geral'!$B$5="Maior Salário",IFERROR(IF(OR(C4="",Q4=0,Q4=""),"",($C4/$S4)),"")) -> 1.2469921 | U4: =IFS(OR(N4="",N4=0,C4="", C4=0),"",T4<=80%,"Muito Defasado",T4<=90%,"Defasado",T4<=100%,"Na Média",T4<=110%,"Competitivo",T4<=120%,"Muito Competitivo",T4>120%,"Agressivo") -> Agressivo | V4: =Z29*1.2 -> 2176.3124 | W4: =V4*1.2 -> 2611.5749 | X4: =W4*1.2 -> 3133.8899 | Y4: =X4*1.2 -> 3760.6679 | Z4: =Y4*1.2 -> 4512.8014 | AA4: =Z4*1.2 -> 5415.3617 | AB4: =AA4*1.2 -> 6498.4341 | AC4: =AB4*1.2 -> 7798.1209 | AD4: =AC4*1.2 -> 9357.7451 | ... AJ4: =AI4*1.2 -> 27942.077
A5: 20 | B5: =VLOOKUP(A5,Jobmatch!A:G,2,0) -> AUXILIAR ADMINISTRATIVO | C5: =IFERROR(AVERAGEIF('Folha de Pagamento'!A:A,A5,'Folha de Pagamento'!J:J),"") -> 2254 | D5: 1 | E5: =VLOOKUP(A5,Jobmatch!A:H,3,0) -> Administrativo | F5: Auxiliar Administrativo | G5: =VLOOKUP(A5,Jobmatch!A:I,4,0) -> 27 - ADM PROJETOS | H5: =VLOOKUP(A5,Jobmatch!A:I,5,0) -> Operacional | I5: =VLOOKUP(A5,Jobmatch!A:I,6,0) -> 83 | J5: =VLOOKUP(A5,Jobmatch!A:I,7,0) -> Auxiliar Administrativo | K5: =VLOOKUP(A5,Jobmatch!A:I,8,0) -> Indiferente | L5: =I5&K5 -> 83Indiferente | M5: =COUNTIF('Folha de Pagamento'!A:A,A5) -> 1 | N5: 10 | O5: =IFERROR(VLOOKUP(L5,'C-01'!$D:$L,5,0),"") -> 2128.74 | P5: =IFERROR(VLOOKUP(L5,'C-01'!$D:$L,6,0),"") -> 2292.87 | Q5: =IFERROR(VLOOKUP(L5,'C-01'!$D:$L,7,0),"") -> 2309.71 | R5: =IFERROR(VLOOKUP(L5,'C-01'!$D:$L,8,0),"") -> 2375.14 | S5: =IFERROR(VLOOKUP(L5,'C-01'!$D:$L,9,0),"") -> 3073.32 | T5: =IFS('Painel Geral'!$B$5="Mediana",IFERROR(IF(OR(C5="",Q5=0,Q5=""),"",($C5/$Q5)),""),'Painel Geral'!$B$5="Menor Salário",IFERROR(IF(OR(C5="",Q5=0,Q5=""),"",($C5/$N5)),""),'Painel Geral'!$B$5="1º Quartil",IFERROR(IF(OR(C5="",Q5=0,Q5=""),"",($C5/$O5)),""), 'Painel Geral'!$B$5="Média",IFERROR(IF(OR(C5="",Q5=0,Q5=""),"",($C5/$P5)),""),'Painel Geral'!$B$5="3º Quartil",IFERROR(IF(OR(C5="",Q5=0,Q5=""),"",($C5/$R5)),""),'Painel Geral'!$B$5="Maior Salário",IFERROR(IF(OR(C5="",Q5=0,Q5=""),"",($C5/$S5)),"")) -> 0.97588009 | U5: =IFS(OR(N5="",N5=0,C5="", C5=0),"",T5<=80%,"Muito Defasado",T5<=90%,"Defasado",T5<=100%,"Na Média",T5<=110%,"Competitivo",T5<=120%,"Muito Competitivo",T5>120%,"Agressivo") -> Na Média | V5: 10 | W5: 11 | X5: 12 | Y5: 13 | Z5: 14 | AA5: 15 | AB5: 16 | AC5: 17 | AD5: 18 | AE5: 19 | AF5: 20 | AG5: 21 | AH5: 22 | AI5: 23 | AJ5: 24
A6: 21 | B6: =VLOOKUP(A6,Jobmatch!A:G,2,0) -> AUXILIAR ADMINISTRATIVO III | C6: =IFERROR(AVERAGEIF('Folha de Pagamento'!A:A,A6,'Folha de Pagamento'!J:J),"") -> 2739.04 | D6: 1 | E6: =VLOOKUP(A6,Jobmatch!A:H,3,0) -> Administrativo | F6: Auxiliar Administrativo | G6: =VLOOKUP(A6,Jobmatch!A:I,4,0) -> 28 - ADM PROJETOS | H6: =VLOOKUP(A6,Jobmatch!A:I,5,0) -> Operacional | I6: =VLOOKUP(A6,Jobmatch!A:I,6,0) -> 83 | J6: =VLOOKUP(A6,Jobmatch!A:I,7,0) -> Auxiliar Administrativo | K6: =VLOOKUP(A6,Jobmatch!A:I,8,0) -> Indiferente | L6: =I6&K6 -> 83Indiferente | M6: =COUNTIF('Folha de Pagamento'!A:A,A6) -> 1 | N6: 10 | O6: =IFERROR(VLOOKUP(L6,'C-01'!$D:$L,5,0),"") -> 2128.74 | P6: =IFERROR(VLOOKUP(L6,'C-01'!$D:$L,6,0),"") -> 2292.87 | Q6: =IFERROR(VLOOKUP(L6,'C-01'!$D:$L,7,0),"") -> 2309.71 | R6: =IFERROR(VLOOKUP(L6,'C-01'!$D:$L,8,0),"") -> 2375.14 | S6: =IFERROR(VLOOKUP(L6,'C-01'!$D:$L,9,0),"") -> 3073.32 | T6: =IFS('Painel Geral'!$B$5="Mediana",IFERROR(IF(OR(C6="",Q6=0,Q6=""),"",($C6/$Q6)),""),'Painel Geral'!$B$5="Menor Salário",IFERROR(IF(OR(C6="",Q6=0,Q6=""),"",($C6/$N6)),""),'Painel Geral'!$B$5="1º Quartil",IFERROR(IF(OR(C6="",Q6=0,Q6=""),"",($C6/$O6)),""), 'Painel Geral'!$B$5="Média",IFERROR(IF(OR(C6="",Q6=0,Q6=""),"",($C6/$P6)),""),'Painel Geral'!$B$5="3º Quartil",IFERROR(IF(OR(C6="",Q6=0,Q6=""),"",($C6/$R6)),""),'Painel Geral'!$B$5="Maior Salário",IFERROR(IF(OR(C6="",Q6=0,Q6=""),"",($C6/$S6)),"")) -> 1.1858805 | U6: =IFS(OR(N6="",N6=0,C6="", C6=0),"",T6<=80%,"Muito Defasado",T6<=90%,"Defasado",T6<=100%,"Na Média",T6<=110%,"Competitivo",T6<=120%,"Muito Competitivo",T6>120%,"Agressivo") -> Muito Competitivo
A7: 18 | B7: =VLOOKUP(A7,Jobmatch!A:G,2,0) -> ASSISTENTE DE TI | C7: =IFERROR(AVERAGEIF('Folha de Pagamento'!A:A,A7,'Folha de Pagamento'!J:J),"") -> 2919 | D7: 1 | E7: =VLOOKUP(A7,Jobmatch!A:H,3,0) -> Tecnologia da Informação | F7: Assistente TI | G7: =VLOOKUP(A7,Jobmatch!A:I,4,0) -> 25 - ADM PROJETOS | H7: =VLOOKUP(A7,Jobmatch!A:I,5,0) -> Operacional | I7: =VLOOKUP(A7,Jobmatch!A:I,6,0) -> 31 | J7: =VLOOKUP(A7,Jobmatch!A:I,7,0) -> Assistente de Tecnologia da Informação | K7: =VLOOKUP(A7,Jobmatch!A:I,8,0) -> Indiferente | L7: =I7&K7 -> 31Indiferente | M7: =COUNTIF('Folha de Pagamento'!A:A,A7) -> 2 | N7: 10 | O7: =IFERROR(VLOOKUP(L7,'C-01'!$D:$L,5,0),"") -> 2066.4 | P7: =IFERROR(VLOOKUP(L7,'C-01'!$D:$L,6,0),"") -> 2589.89 | Q7: =IFERROR(VLOOKUP(L7,'C-01'!$D:$L,7,0),"") -> 2413.7 | R7: =IFERROR(VLOOKUP(L7,'C-01'!$D:$L,8,0),"") -> 3121.21 | S7: =IFERROR(VLOOKUP(L7,'C-01'!$D:$L,9,0),"") -> 3521.6 | T7: =IFS('Painel Geral'!$B$5="Mediana",IFERROR(IF(OR(C7="",Q7=0,Q7=""),"",($C7/$Q7)),""),'Painel Geral'!$B$5="Menor Salário",IFERROR(IF(OR(C7="",Q7=0,Q7=""),"",($C7/$N7)),""),'Painel Geral'!$B$5="1º Quartil",IFERROR(IF(OR(C7="",Q7=0,Q7=""),"",($C7/$O7)),""), 'Painel Geral'!$B$5="Média",IFERROR(IF(OR(C7="",Q7=0,Q7=""),"",($C7/$P7)),""),'Painel Geral'!$B$5="3º Quartil",IFERROR(IF(OR(C7="",Q7=0,Q7=""),"",($C7/$R7)),""),'Painel Geral'!$B$5="Maior Salário",IFERROR(IF(OR(C7="",Q7=0,Q7=""),"",($C7/$S7)),"")) -> 1.2093466 | U7: =IFS(OR(N7="",N7=0,C7="", C7=0),"",T7<=80%,"Muito Defasado",T7<=90%,"Defasado",T7<=100%,"Na Média",T7<=110%,"Competitivo",T7<=120%,"Muito Competitivo",T7>120%,"Agressivo") -> Agressivo
A8: 13 | B8: =VLOOKUP(A8,Jobmatch!A:G,2,0) -> ASSISTENTE ADMINISTRATIVO lll | C8: =IFERROR(AVERAGEIF('Folha de Pagamento'!A:A,A8,'Folha de Pagamento'!J:J),"") -> 3439.7 | D8: 1 | E8: =VLOOKUP(A8,Jobmatch!A:H,3,0) -> Administrativo | F8: Assistente Administrativo | G8: =VLOOKUP(A8,Jobmatch!A:I,4,0) -> 20 - ADM PROJETOS | H8: =VLOOKUP(A8,Jobmatch!A:I,5,0) -> Operacional | I8: =VLOOKUP(A8,Jobmatch!A:I,6,0) -> 59 | J8: =VLOOKUP(A8,Jobmatch!A:I,7,0) -> Assistente Administrativo | K8: =VLOOKUP(A8,Jobmatch!A:I,8,0) -> Indiferente | L8: =I8&K8 -> 59Indiferente | M8: =COUNTIF('Folha de Pagamento'!A:A,A8) -> 1 | N8: 10 | O8: =IFERROR(VLOOKUP(L8,'C-01'!$D:$L,5,0),"") -> 2329.53 | P8: =IFERROR(VLOOKUP(L8,'C-01'!$D:$L,6,0),"") -> 2673.92 | Q8: =IFERROR(VLOOKUP(L8,'C-01'!$D:$L,7,0),"") -> 2630.61 | R8: =IFERROR(VLOOKUP(L8,'C-01'!$D:$L,8,0),"") -> 2914.75 | S8: =IFERROR(VLOOKUP(L8,'C-01'!$D:$L,9,0),"") -> 3662.52 | T8: =IFS('Painel Geral'!$B$5="Mediana",IFERROR(IF(OR(C8="",Q8=0,Q8=""),"",($C8/$Q8)),""),'Painel Geral'!$B$5="Menor Salário",IFERROR(IF(OR(C8="",Q8=0,Q8=""),"",($C8/$N8)),""),'Painel Geral'!$B$5="1º Quartil",IFERROR(IF(OR(C8="",Q8=0,Q8=""),"",($C8/$O8)),""), 'Painel Geral'!$B$5="Média",IFERROR(IF(OR(C8="",Q8=0,Q8=""),"",($C8/$P8)),""),'Painel Geral'!$B$5="3º Quartil",IFERROR(IF(OR(C8="",Q8=0,Q8=""),"",($C8/$R8)),""),'Painel Geral'!$B$5="Maior Salário",IFERROR(IF(OR(C8="",Q8=0,Q8=""),"",($C8/$S8)),"")) -> 1.3075674 | U8: =IFS(OR(N8="",N8=0,C8="", C8=0),"",T8<=80%,"Muito Defasado",T8<=90%,"Defasado",T8<=100%,"Na Média",T8<=110%,"Competitivo",T8<=120%,"Muito Competitivo",T8>120%,"Agressivo") -> Agressivo
A9: 19 | B9: =VLOOKUP(A9,Jobmatch!A:G,2,0) -> ASSISTENTE FINANCEIRO CONTAS A PAGAR | C9: =IFERROR(AVERAGEIF('Folha de Pagamento'!A:A,A9,'Folha de Pagamento'!J:J),"") -> 3163.3333 | D9: 6 | E9: =VLOOKUP(A9,Jobmatch!A:H,3,0) -> Financeiro | F9: Assistente Financeiro Contas a Pagar | G9: =VLOOKUP(A9,Jobmatch!A:I,4,0) -> 26 - ADM PROJETOS | H9: =VLOOKUP(A9,Jobmatch!A:I,5,0) -> Operacional | I9: =VLOOKUP(A9,Jobmatch!A:I,6,0) -> 79 | J9: =VLOOKUP(A9,Jobmatch!A:I,7,0) -> Assistente Financeiro | K9: =VLOOKUP(A9,Jobmatch!A:I,8,0) -> Indiferente | L9: =I9&K9 -> 79Indiferente | M9: =COUNTIF('Folha de Pagamento'!A:A,A9) -> 3 | N9: 10 | O9: =IFERROR(VLOOKUP(L9,'C-01'!$D:$L,5,0),"") -> 2560.05 | P9: =IFERROR(VLOOKUP(L9,'C-01'!$D:$L,6,0),"") -> 2799.02 | Q9: =IFERROR(VLOOKUP(L9,'C-01'!$D:$L,7,0),"") -> 2658.89 | R9: =IFERROR(VLOOKUP(L9,'C-01'!$D:$L,8,0),"") -> 2935.06 | S9: =IFERROR(VLOOKUP(L9,'C-01'!$D:$L,9,0),"") -> 3630.87 | T9: =IFS('Painel Geral'!$B$5="Mediana",IFERROR(IF(OR(C9="",Q9=0,Q9=""),"",($C9/$Q9)),""),'Painel Geral'!$B$5="Menor Salário",IFERROR(IF(OR(C9="",Q9=0,Q9=""),"",($C9/$N9)),""),'Painel Geral'!$B$5="1º Quartil",IFERROR(IF(OR(C9="",Q9=0,Q9=""),"",($C9/$O9)),""), 'Painel Geral'!$B$5="Média",IFERROR(IF(OR(C9="",Q9=0,Q9=""),"",($C9/$P9)),""),'Painel Geral'!$B$5="3º Quartil",IFERROR(IF(OR(C9="",Q9=0,Q9=""),"",($C9/$R9)),""),'Painel Geral'!$B$5="Maior Salário",IFERROR(IF(OR(C9="",Q9=0,Q9=""),"",($C9/$S9)),"")) -> 1.1897195 | U9: =IFS(OR(N9="",N9=0,C9="", C9=0),"",T9<=80%,"Muito Defasado",T9<=90%,"Defasado",T9<=100%,"Na Média",T9<=110%,"Competitivo",T9<=120%,"Muito Competitivo",T9>120%,"Agressivo") -> Muito Competitivo
A10: 23 | B10: =VLOOKUP(A10,Jobmatch!A:G,2,0) -> AUXILIAR DE ENGENHARIA | C10: =IFERROR(AVERAGEIF('Folha de Pagamento'!A:A,A10,'Folha de Pagamento'!J:J),"") -> 2560 | D10: 10 | E10: =VLOOKUP(A10,Jobmatch!A:H,3,0) -> Urbanismo | F10: Auxiliar Engenharia | G10: =VLOOKUP(A10,Jobmatch!A:I,4,0) -> 30 - ADM PROJETOS | H10: =VLOOKUP(A10,Jobmatch!A:I,5,0) -> Operacional | I10: =VLOOKUP(A10,Jobmatch!A:I,6,0) -> 207 | J10: =VLOOKUP(A10,Jobmatch!A:I,7,0) -> Auxiliar de Engenharia | K10: =VLOOKUP(A10,Jobmatch!A:I,8,0) -> Indiferente | L10: =I10&K10 -> 207Indiferente | M10: =COUNTIF('Folha de Pagamento'!A:A,A10) -> 1 | N10: 11 | O10: =IFERROR(VLOOKUP(L10,'C-01'!$D:$L,5,0),"") -> 2644.47 | P10: =IFERROR(VLOOKUP(L10,'C-01'!$D:$L,6,0),"") -> 2819.08 | Q10: =IFERROR(VLOOKUP(L10,'C-01'!$D:$L,7,0),"") -> 2714.85 | R10: =IFERROR(VLOOKUP(L10,'C-01'!$D:$L,8,0),"") -> 2941.58 | S10: =IFERROR(VLOOKUP(L10,'C-01'!$D:$L,9,0),"") -> 3168.31 | T10: =IFS('Painel Geral'!$B$5="Mediana",IFERROR(IF(OR(C10="",Q10=0,Q10=""),"",($C10/$Q10)),""),'Painel Geral'!$B$5="Menor Salário",IFERROR(IF(OR(C10="",Q10=0,Q10=""),"",($C10/$N10)),""),'Painel Geral'!$B$5="1º Quartil",IFERROR(IF(OR(C10="",Q10=0,Q10=""),"",($C10/$O10)),""), 'Painel Geral'!$B$5="Média",IFERROR(IF(OR(C10="",Q10=0,Q10=""),"",($C10/$P10)),""),'Painel Geral'!$B$5="3º Quartil",IFERROR(IF(OR(C10="",Q10=0,Q10=""),"",($C10/$R10)),""),'Painel Geral'!$B$5="Maior Salário",IFERROR(IF(OR(C10="",Q10=0,Q10=""),"",($C10/$S10)),"")) -> 0.94296186 | U10: =IFS(OR(N10="",N10=0,C10="", C10=0),"",T10<=80%,"Muito Defasado",T10<=90%,"Defasado",T10<=100%,"Na Média",T10<=110%,"Competitivo",T10<=120%,"Muito Competitivo",T10>120%,"Agressivo") -> Na Média
A11: 14 | B11: =VLOOKUP(A11,Jobmatch!A:G,2,0) -> ASSISTENTE DE CONTROLADORIA III | C11: =IFERROR(AVERAGEIF('Folha de Pagamento'!A:A,A11,'Folha de Pagamento'!J:J),"") -> 3652 | D11: 3 | E11: =VLOOKUP(A11,Jobmatch!A:H,3,0) -> Controladoria | F11: Assistente Controladoria | G11: =VLOOKUP(A11,Jobmatch!A:I,4,0) -> 21 - ADM PROJETOS | H11: =VLOOKUP(A11,Jobmatch!A:I,5,0) -> Operacional | I11: =VLOOKUP(A11,Jobmatch!A:I,6,0) -> 150 | J11: =VLOOKUP(A11,Jobmatch!A:I,7,0) -> Assistente de Controladoria | K11: =VLOOKUP(A11,Jobmatch!A:I,8,0) -> Indiferente | L11: =I11&K11 -> 150Indiferente | M11: =COUNTIF('Folha de Pagamento'!A:A,A11) -> 1 | N11: 11 | O11: =IFERROR(VLOOKUP(L11,'C-01'!$D:$L,5,0),"") -> 2640.81 | P11: =IFERROR(VLOOKUP(L11,'C-01'!$D:$L,6,0),"") -> 2821.08 | Q11: =IFERROR(VLOOKUP(L11,'C-01'!$D:$L,7,0),"") -> 2766.4 | R11: =IFERROR(VLOOKUP(L11,'C-01'!$D:$L,8,0),"") -> 3222.24 | S11: =IFERROR(VLOOKUP(L11,'C-01'!$D:$L,9,0),"") -> 3327.42 | T11: =IFS('Painel Geral'!$B$5="Mediana",IFERROR(IF(OR(C11="",Q11=0,Q11=""),"",($C11/$Q11)),""),'Painel Geral'!$B$5="Menor Salário",IFERROR(IF(OR(C11="",Q11=0,Q11=""),"",($C11/$N11)),""),'Painel Geral'!$B$5="1º Quartil",IFERROR(IF(OR(C11="",Q11=0,Q11=""),"",($C11/$O11)),""), 'Painel Geral'!$B$5="Média",IFERROR(IF(OR(C11="",Q11=0,Q11=""),"",($C11/$P11)),""),'Painel Geral'!$B$5="3º Quartil",IFERROR(IF(OR(C11="",Q11=0,Q11=""),"",($C11/$R11)),""),'Painel Geral'!$B$5="Maior Salário",IFERROR(IF(OR(C11="",Q11=0,Q11=""),"",($C11/$S11)),"")) -> 1.3201272 | U11: =IFS(OR(N11="",N11=0,C11="", C11=0),"",T11<=80%,"Muito Defasado",T11<=90%,"Defasado",T11<=100%,"Na Média",T11<=110%,"Competitivo",T11<=120%,"Muito Competitivo",T11>120%,"Agressivo") -> Agressivo
A12: 16 | B12: =VLOOKUP(A12,Jobmatch!A:G,2,0) -> ASSISTENTE DE MARKETING | C12: =IFERROR(AVERAGEIF('Folha de Pagamento'!A:A,A12,'Folha de Pagamento'!J:J),"") -> 2919 | D12: 8 | E12: =VLOOKUP(A12,Jobmatch!A:H,3,0) -> Marketing | F12: Assistente Marketing | G12: =VLOOKUP(A12,Jobmatch!A:I,4,0) -> 23 - ADM PROJETOS | H12: =VLOOKUP(A12,Jobmatch!A:I,5,0) -> Operacional | I12: =VLOOKUP(A12,Jobmatch!A:I,6,0) -> 71 | J12: =VLOOKUP(A12,Jobmatch!A:I,7,0) -> Assistente de Marketing | K12: =VLOOKUP(A12,Jobmatch!A:I,8,0) -> Indiferente | L12: =I12&K12 -> 71Indiferente | M12: =COUNTIF('Folha de Pagamento'!A:A,A12) -> 1 | N12: 11 | O12: =IFERROR(VLOOKUP(L12,'C-01'!$D:$L,5,0),"") -> 2720.21 | P12: =IFERROR(VLOOKUP(L12,'C-01'!$D:$L,6,0),"") -> 3016.74 | Q12: =IFERROR(VLOOKUP(L12,'C-01'!$D:$L,7,0),"") -> 2882.27 | R12: =IFERROR(VLOOKUP(L12,'C-01'!$D:$L,8,0),"") -> 3152.81 | S12: =IFERROR(VLOOKUP(L12,'C-01'!$D:$L,9,0),"") -> 4078.78 | T12: =IFS('Painel Geral'!$B$5="Mediana",IFERROR(IF(OR(C12="",Q12=0,Q12=""),"",($C12/$Q12)),""),'Painel Geral'!$B$5="Menor Salário",IFERROR(IF(OR(C12="",Q12=0,Q12=""),"",($C12/$N12)),""),'Painel Geral'!$B$5="1º Quartil",IFERROR(IF(OR(C12="",Q12=0,Q12=""),"",($C12/$O12)),""), 'Painel Geral'!$B$5="Média",IFERROR(IF(OR(C12="",Q12=0,Q12=""),"",($C12/$P12)),""),'Painel Geral'!$B$5="3º Quartil",IFERROR(IF(OR(C12="",Q12=0,Q12=""),"",($C12/$R12)),""),'Painel Geral'!$B$5="Maior Salário",IFERROR(IF(OR(C12="",Q12=0,Q12=""),"",($C12/$S12)),"")) -> 1.0127434 | U12: =IFS(OR(N12="",N12=0,C12="", C12=0),"",T12<=80%,"Muito Defasado",T12<=90%,"Defasado",T12<=100%,"Na Média",T12<=110%,"Competitivo",T12<=120%,"Muito Competitivo",T12>120%,"Agressivo") -> Competitivo
A13: 17 | B13: =VLOOKUP(A13,Jobmatch!A:G,2,0) -> ASSISTENTE DE RECURSOS HUMANOS | C13: =IFERROR(AVERAGEIF('Folha de Pagamento'!A:A,A13,'Folha de Pagamento'!J:J),"") -> 2919 | D13: 4 | E13: =VLOOKUP(A13,Jobmatch!A:H,3,0) -> DHO | F13: Assistente Recursos Humanos | G13: =VLOOKUP(A13,Jobmatch!A:I,4,0) -> 24 - ADM PROJETOS | H13: =VLOOKUP(A13,Jobmatch!A:I,5,0) -> Operacional | I13: =VLOOKUP(A13,Jobmatch!A:I,6,0) -> 77 | J13: =VLOOKUP(A13,Jobmatch!A:I,7,0) -> Assistente de Recursos Humanos | K13: =VLOOKUP(A13,Jobmatch!A:I,8,0) -> Indiferente | L13: =I13&K13 -> 77Indiferente | M13: =COUNTIF('Folha de Pagamento'!A:A,A13) -> 1 | N13: 12 | O13: =IFERROR(VLOOKUP(L13,'C-01'!$D:$L,5,0),"") -> 2619.08 | P13: =IFERROR(VLOOKUP(L13,'C-01'!$D:$L,6,0),"") -> 3097.88 | Q13: =IFERROR(VLOOKUP(L13,'C-01'!$D:$L,7,0),"") -> 3080.23 | R13: =IFERROR(VLOOKUP(L13,'C-01'!$D:$L,8,0),"") -> 3491.33 | S13: =IFERROR(VLOOKUP(L13,'C-01'!$D:$L,9,0),"") -> 4078.78 | T13: =IFS('Painel Geral'!$B$5="Mediana",IFERROR(IF(OR(C13="",Q13=0,Q13=""),"",($C13/$Q13)),""),'Painel Geral'!$B$5="Menor Salário",IFERROR(IF(OR(C13="",Q13=0,Q13=""),"",($C13/$N13)),""),'Painel Geral'!$B$5="1º Quartil",IFERROR(IF(OR(C13="",Q13=0,Q13=""),"",($C13/$O13)),""), 'Painel Geral'!$B$5="Média",IFERROR(IF(OR(C13="",Q13=0,Q13=""),"",($C13/$P13)),""),'Painel Geral'!$B$5="3º Quartil",IFERROR(IF(OR(C13="",Q13=0,Q13=""),"",($C13/$R13)),""),'Painel Geral'!$B$5="Maior Salário",IFERROR(IF(OR(C13="",Q13=0,Q13=""),"",($C13/$S13)),"")) -> 0.94765651 | U13: =IFS(OR(N13="",N13=0,C13="", C13=0),"",T13<=80%,"Muito Defasado",T13<=90%,"Defasado",T13<=100%,"Na Média",T13<=110%,"Competitivo",T13<=120%,"Muito Competitivo",T13>120%,"Agressivo") -> Na Média
A14: 1 | B14: =VLOOKUP(A14,Jobmatch!A:G,2,0) -> ALMOXARIFE | C14: =IFERROR(AVERAGEIF('Folha de Pagamento'!A:A,A14,'Folha de Pagamento'!J:J),"") -> 3683 | D14: 5 | E14: =VLOOKUP(A14,Jobmatch!A:H,3,0) -> Edificação | F14: Almoxarife | G14: =VLOOKUP(A14,Jobmatch!A:I,4,0) -> 8 - ADM PROJETOS | H14: =VLOOKUP(A14,Jobmatch!A:I,5,0) -> Operacional | I14: =VLOOKUP(A14,Jobmatch!A:I,6,0) -> 203 | J14: =VLOOKUP(A14,Jobmatch!A:I,7,0) -> Almoxarife | K14: =VLOOKUP(A14,Jobmatch!A:I,8,0) -> Indiferente | L14: =I14&K14 -> 203Indiferente | M14: =COUNTIF('Folha de Pagamento'!A:A,A14) -> 2 | N14: 12 | O14: =IFERROR(VLOOKUP(L14,'C-01'!$D:$L,5,0),"") -> 3088.9 | P14: =IFERROR(VLOOKUP(L14,'C-01'!$D:$L,6,0),"") -> 3397.38 | Q14: =IFERROR(VLOOKUP(L14,'C-01'!$D:$L,7,0),"") -> 3088.9 | R14: =IFERROR(VLOOKUP(L14,'C-01'!$D:$L,8,0),"") -> 3703.26 | S14: =IFERROR(VLOOKUP(L14,'C-01'!$D:$L,9,0),"") -> 4425.21 | T14: =IFS('Painel Geral'!$B$5="Mediana",IFERROR(IF(OR(C14="",Q14=0,Q14=""),"",($C14/$Q14)),""),'Painel Geral'!$B$5="Menor Salário",IFERROR(IF(OR(C14="",Q14=0,Q14=""),"",($C14/$N14)),""),'Painel Geral'!$B$5="1º Quartil",IFERROR(IF(OR(C14="",Q14=0,Q14=""),"",($C14/$O14)),""), 'Painel Geral'!$B$5="Média",IFERROR(IF(OR(C14="",Q14=0,Q14=""),"",($C14/$P14)),""),'Painel Geral'!$B$5="3º Quartil",IFERROR(IF(OR(C14="",Q14=0,Q14=""),"",($C14/$R14)),""),'Painel Geral'!$B$5="Maior Salário",IFERROR(IF(OR(C14="",Q14=0,Q14=""),"",($C14/$S14)),"")) -> 1.1923338 | U14: =IFS(OR(N14="",N14=0,C14="", C14=0),"",T14<=80%,"Muito Defasado",T14<=90%,"Defasado",T14<=100%,"Na Média",T14<=110%,"Competitivo",T14<=120%,"Muito Competitivo",T14>120%,"Agressivo") -> Muito Competitivo
A15: 12 | B15: =VLOOKUP(A15,Jobmatch!A:G,2,0) -> ASSISTENTE ADM DE LEGALIZAÇÃO III | C15: =IFERROR(AVERAGEIF('Folha de Pagamento'!A:A,A15,'Folha de Pagamento'!J:J),"") -> 3652 | D15: 7 | E15: =VLOOKUP(A15,Jobmatch!A:H,3,0) -> Legalização | F15: Assistente Adm Legalização Sr | G15: =VLOOKUP(A15,Jobmatch!A:I,4,0) -> 19 - ADM PROJETOS | H15: =VLOOKUP(A15,Jobmatch!A:I,5,0) -> Operacional | I15: =VLOOKUP(A15,Jobmatch!A:I,6,0) -> 1201 | J15: =VLOOKUP(A15,Jobmatch!A:I,7,0) -> Assistente de Legalização | K15: =VLOOKUP(A15,Jobmatch!A:I,8,0) -> Indiferente | L15: =I15&K15 -> 1201Indiferente | M15: =COUNTIF('Folha de Pagamento'!A:A,A15) -> 2 | N15: 12 | O15: =IFERROR(VLOOKUP(L15,'C-01'!$D:$L,5,0),"") -> 2803.34 | P15: =IFERROR(VLOOKUP(L15,'C-01'!$D:$L,6,0),"") -> 3092.92 | Q15: =IFERROR(VLOOKUP(L15,'C-01'!$D:$L,7,0),"") -> 3092.92 | R15: =IFERROR(VLOOKUP(L15,'C-01'!$D:$L,8,0),"") -> 3382.51 | S15: =IFERROR(VLOOKUP(L15,'C-01'!$D:$L,9,0),"") -> 3672.09 | T15: =IFS('Painel Geral'!$B$5="Mediana",IFERROR(IF(OR(C15="",Q15=0,Q15=""),"",($C15/$Q15)),""),'Painel Geral'!$B$5="Menor Salário",IFERROR(IF(OR(C15="",Q15=0,Q15=""),"",($C15/$N15)),""),'Painel Geral'!$B$5="1º Quartil",IFERROR(IF(OR(C15="",Q15=0,Q15=""),"",($C15/$O15)),""), 'Painel Geral'!$B$5="Média",IFERROR(IF(OR(C15="",Q15=0,Q15=""),"",($C15/$P15)),""),'Painel Geral'!$B$5="3º Quartil",IFERROR(IF(OR(C15="",Q15=0,Q15=""),"",($C15/$R15)),""),'Painel Geral'!$B$5="Maior Salário",IFERROR(IF(OR(C15="",Q15=0,Q15=""),"",($C15/$S15)),"")) -> 1.1807612 | U15: =IFS(OR(N15="",N15=0,C15="", C15=0),"",T15<=80%,"Muito Defasado",T15<=90%,"Defasado",T15<=100%,"Na Média",T15<=110%,"Competitivo",T15<=120%,"Muito Competitivo",T15>120%,"Agressivo") -> Muito Competitivo | AP15: 0.03
A16: 11 | B16: =VLOOKUP(A16,Jobmatch!A:G,2,0) -> ANALISTA FINANCEIRO I | C16: =IFERROR(AVERAGEIF('Folha de Pagamento'!A:A,A16,'Folha de Pagamento'!J:J),"") -> 3993 | D16: 6 | E16: =VLOOKUP(A16,Jobmatch!A:H,3,0) -> Financeiro | F16: Analista Financeiro Jr | G16: =VLOOKUP(A16,Jobmatch!A:I,4,0) -> 18 - ADM PROJETOS | H16: =VLOOKUP(A16,Jobmatch!A:I,5,0) -> Operacional | I16: =VLOOKUP(A16,Jobmatch!A:I,6,0) -> 16 | J16: =VLOOKUP(A16,Jobmatch!A:I,7,0) -> Analista Financeiro | K16: =VLOOKUP(A16,Jobmatch!A:I,8,0) -> Júnior | L16: =I16&K16 -> 16Júnior | M16: =COUNTIF('Folha de Pagamento'!A:A,A16) -> 1 | N16: 12 | O16: =IFERROR(VLOOKUP(L16,'C-01'!$D:$L,5,0),"") -> 3176.35 | P16: =IFERROR(VLOOKUP(L16,'C-01'!$D:$L,6,0),"") -> 3539.11 | Q16: =IFERROR(VLOOKUP(L16,'C-01'!$D:$L,7,0),"") -> 3493.97 | R16: =IFERROR(VLOOKUP(L16,'C-01'!$D:$L,8,0),"") -> 3798.49 | S16: =IFERROR(VLOOKUP(L16,'C-01'!$D:$L,9,0),"") -> 4392.23 | T16: =IFS('Painel Geral'!$B$5="Mediana",IFERROR(IF(OR(C16="",Q16=0,Q16=""),"",($C16/$Q16)),""),'Painel Geral'!$B$5="Menor Salário",IFERROR(IF(OR(C16="",Q16=0,Q16=""),"",($C16/$N16)),""),'Painel Geral'!$B$5="1º Quartil",IFERROR(IF(OR(C16="",Q16=0,Q16=""),"",($C16/$O16)),""), 'Painel Geral'!$B$5="Média",IFERROR(IF(OR(C16="",Q16=0,Q16=""),"",($C16/$P16)),""),'Painel Geral'!$B$5="3º Quartil",IFERROR(IF(OR(C16="",Q16=0,Q16=""),"",($C16/$R16)),""),'Painel Geral'!$B$5="Maior Salário",IFERROR(IF(OR(C16="",Q16=0,Q16=""),"",($C16/$S16)),"")) -> 1.1428261 | U16: =IFS(OR(N16="",N16=0,C16="", C16=0),"",T16<=80%,"Muito Defasado",T16<=90%,"Defasado",T16<=100%,"Na Média",T16<=110%,"Competitivo",T16<=120%,"Muito Competitivo",T16>120%,"Agressivo") -> Muito Competitivo
A17: 6 | B17: =VLOOKUP(A17,Jobmatch!A:G,2,0) -> ANALISTA DE MARKETING l | C17: =IFERROR(AVERAGEIF('Folha de Pagamento'!A:A,A17,'Folha de Pagamento'!J:J),"") -> 4025.88 | D17: 8 | E17: =VLOOKUP(A17,Jobmatch!A:H,3,0) -> Marketing | F17: Analista Marketing Jr | G17: =VLOOKUP(A17,Jobmatch!A:I,4,0) -> 13 - ADM PROJETOS | H17: =VLOOKUP(A17,Jobmatch!A:I,5,0) -> Operacional | I17: =VLOOKUP(A17,Jobmatch!A:I,6,0) -> 42 | J17: =VLOOKUP(A17,Jobmatch!A:I,7,0) -> Analista de Marketing | K17: =VLOOKUP(A17,Jobmatch!A:I,8,0) -> Júnior | L17: =I17&K17 -> 42Júnior | M17: =COUNTIF('Folha de Pagamento'!A:A,A17) -> 1 | N17: 12 | O17: =IFERROR(VLOOKUP(L17,'C-01'!$D:$L,5,0),"") -> 3503.85 | P17: =IFERROR(VLOOKUP(L17,'C-01'!$D:$L,6,0),"") -> 3792.81 | Q17: =IFERROR(VLOOKUP(L17,'C-01'!$D:$L,7,0),"") -> 3674.96 | R17: =IFERROR(VLOOKUP(L17,'C-01'!$D:$L,8,0),"") -> 3977.13 | S17: =IFERROR(VLOOKUP(L17,'C-01'!$D:$L,9,0),"") -> 5225.68 | T17: =IFS('Painel Geral'!$B$5="Mediana",IFERROR(IF(OR(C17="",Q17=0,Q17=""),"",($C17/$Q17)),""),'Painel Geral'!$B$5="Menor Salário",IFERROR(IF(OR(C17="",Q17=0,Q17=""),"",($C17/$N17)),""),'Painel Geral'!$B$5="1º Quartil",IFERROR(IF(OR(C17="",Q17=0,Q17=""),"",($C17/$O17)),""), 'Painel Geral'!$B$5="Média",IFERROR(IF(OR(C17="",Q17=0,Q17=""),"",($C17/$P17)),""),'Painel Geral'!$B$5="3º Quartil",IFERROR(IF(OR(C17="",Q17=0,Q17=""),"",($C17/$R17)),""),'Painel Geral'!$B$5="Maior Salário",IFERROR(IF(OR(C17="",Q17=0,Q17=""),"",($C17/$S17)),"")) -> 1.0954895 | U17: =IFS(OR(N17="",N17=0,C17="", C17=0),"",T17<=80%,"Muito Defasado",T17<=90%,"Defasado",T17<=100%,"Na Média",T17<=110%,"Competitivo",T17<=120%,"Muito Competitivo",T17>120%,"Agressivo") -> Competitivo
A18: 15 | B18: =VLOOKUP(A18,Jobmatch!A:G,2,0) -> ASSISTENTE DE ENGENHARIA lll | C18: =IFERROR(AVERAGEIF('Folha de Pagamento'!A:A,A18,'Folha de Pagamento'!J:J),"") -> 3652 | D18: 5 | E18: =VLOOKUP(A18,Jobmatch!A:H,3,0) -> Edificação | F18: Assistente Engenharia | G18: =VLOOKUP(A18,Jobmatch!A:I,4,0) -> 22 - ADM PROJETOS | H18: =VLOOKUP(A18,Jobmatch!A:I,5,0) -> Operacional | I18: =VLOOKUP(A18,Jobmatch!A:I,6,0) -> 531 | J18: =VLOOKUP(A18,Jobmatch!A:I,7,0) -> Assistente de Engenharia | K18: =VLOOKUP(A18,Jobmatch!A:I,8,0) -> Indiferente | L18: =I18&K18 -> 531Indiferente | M18: =COUNTIF('Folha de Pagamento'!A:A,A18) -> 1 | N18: 13 | O18: =IFERROR(VLOOKUP(L18,'C-01'!$D:$L,5,0),"") -> 3945.44 | P18: =IFERROR(VLOOKUP(L18,'C-01'!$D:$L,6,0),"") -> 4031.84 | Q18: =IFERROR(VLOOKUP(L18,'C-01'!$D:$L,7,0),"") -> 3945.44 | R18: =IFERROR(VLOOKUP(L18,'C-01'!$D:$L,8,0),"") -> 3945.44 | S18: =IFERROR(VLOOKUP(L18,'C-01'!$D:$L,9,0),"") -> 5084.96 | T18: =IFS('Painel Geral'!$B$5="Mediana",IFERROR(IF(OR(C18="",Q18=0,Q18=""),"",($C18/$Q18)),""),'Painel Geral'!$B$5="Menor Salário",IFERROR(IF(OR(C18="",Q18=0,Q18=""),"",($C18/$N18)),""),'Painel Geral'!$B$5="1º Quartil",IFERROR(IF(OR(C18="",Q18=0,Q18=""),"",($C18/$O18)),""), 'Painel Geral'!$B$5="Média",IFERROR(IF(OR(C18="",Q18=0,Q18=""),"",($C18/$P18)),""),'Painel Geral'!$B$5="3º Quartil",IFERROR(IF(OR(C18="",Q18=0,Q18=""),"",($C18/$R18)),""),'Painel Geral'!$B$5="Maior Salário",IFERROR(IF(OR(C18="",Q18=0,Q18=""),"",($C18/$S18)),"")) -> 0.92562553 | U18: =IFS(OR(N18="",N18=0,C18="", C18=0),"",T18<=80%,"Muito Defasado",T18<=90%,"Defasado",T18<=100%,"Na Média",T18<=110%,"Competitivo",T18<=120%,"Muito Competitivo",T18>120%,"Agressivo") -> Na Média | AK18: 1799 | AL18: =AK18*AN27 -> 1813.5937
A19: 54 | B19: =VLOOKUP(A19,Jobmatch!A:G,2,0) -> TECNOLOGO EM CONSTRUÇÃO DE EDIFICIOS | C19: =IFERROR(AVERAGEIF('Folha de Pagamento'!A:A,A19,'Folha de Pagamento'!J:J),"") -> 8585 | D19: 5 | E19: =VLOOKUP(A19,Jobmatch!A:H,3,0) -> Edificação | F19: Tecnólogo Construção Edifícios | G19: =VLOOKUP(A19,Jobmatch!A:I,4,0) -> 61 - ADM PROJETOS | H19: =VLOOKUP(A19,Jobmatch!A:I,5,0) -> Operacional | I19: =VLOOKUP(A19,Jobmatch!A:I,6,0) -> 269 | J19: =VLOOKUP(A19,Jobmatch!A:I,7,0) -> Técnico em Edificações | K19: =VLOOKUP(A19,Jobmatch!A:I,8,0) -> Indiferente | L19: =I19&K19 -> 269Indiferente | M19: =COUNTIF('Folha de Pagamento'!A:A,A19) -> 1 | N19: 13 | O19: =IFERROR(VLOOKUP(L19,'C-01'!$D:$L,5,0),"") -> 3732.17 | P19: =IFERROR(VLOOKUP(L19,'C-01'!$D:$L,6,0),"") -> 4583.42 | Q19: =IFERROR(VLOOKUP(L19,'C-01'!$D:$L,7,0),"") -> 4022.01 | R19: =IFERROR(VLOOKUP(L19,'C-01'!$D:$L,8,0),"") -> 4417.17 | S19: =IFERROR(VLOOKUP(L19,'C-01'!$D:$L,9,0),"") -> 9075.39 | T19: =IFS('Painel Geral'!$B$5="Mediana",IFERROR(IF(OR(C19="",Q19=0,Q19=""),"",($C19/$Q19)),""),'Painel Geral'!$B$5="Menor Salário",IFERROR(IF(OR(C19="",Q19=0,Q19=""),"",($C19/$N19)),""),'Painel Geral'!$B$5="1º Quartil",IFERROR(IF(OR(C19="",Q19=0,Q19=""),"",($C19/$O19)),""), 'Painel Geral'!$B$5="Média",IFERROR(IF(OR(C19="",Q19=0,Q19=""),"",($C19/$P19)),""),'Painel Geral'!$B$5="3º Quartil",IFERROR(IF(OR(C19="",Q19=0,Q19=""),"",($C19/$R19)),""),'Painel Geral'!$B$5="Maior Salário",IFERROR(IF(OR(C19="",Q19=0,Q19=""),"",($C19/$S19)),"")) -> 2.1345049 | U19: =IFS(OR(N19="",N19=0,C19="", C19=0),"",T19<=80%,"Muito Defasado",T19<=90%,"Defasado",T19<=100%,"Na Média",T19<=110%,"Competitivo",T19<=120%,"Muito Competitivo",T19>120%,"Agressivo") -> Agressivo | AK19: 45778
A20: 3 | B20: =VLOOKUP(A20,Jobmatch!A:G,2,0) -> ANALISTA DE CRIAÇAO | C20: =IFERROR(AVERAGEIF('Folha de Pagamento'!A:A,A20,'Folha de Pagamento'!J:J),"") -> 5429 | D20: 8 | E20: =VLOOKUP(A20,Jobmatch!A:H,3,0) -> Marketing | F20: Analista Criação | G20: =VLOOKUP(A20,Jobmatch!A:I,4,0) -> 10 - ADM PROJETOS | H20: =VLOOKUP(A20,Jobmatch!A:I,5,0) -> Operacional | I20: =VLOOKUP(A20,Jobmatch!A:I,6,0) -> 45 | J20: =VLOOKUP(A20,Jobmatch!A:I,7,0) -> Analista de Criação | K20: =VLOOKUP(A20,Jobmatch!A:I,8,0) -> Indiferente | L20: =I20&K20 -> 45Indiferente | M20: =COUNTIF('Folha de Pagamento'!A:A,A20) -> 1 | N20: 13 | O20: =IFERROR(VLOOKUP(L20,'C-01'!$D:$L,5,0),"") -> 3527.33 | P20: =IFERROR(VLOOKUP(L20,'C-01'!$D:$L,6,0),"") -> 4325.16 | Q20: =IFERROR(VLOOKUP(L20,'C-01'!$D:$L,7,0),"") -> 4325.72 | R20: =IFERROR(VLOOKUP(L20,'C-01'!$D:$L,8,0),"") -> 4988.66 | S20: =IFERROR(VLOOKUP(L20,'C-01'!$D:$L,9,0),"") -> 6418.74 | T20: =IFS('Painel Geral'!$B$5="Mediana",IFERROR(IF(OR(C20="",Q20=0,Q20=""),"",($C20/$Q20)),""),'Painel Geral'!$B$5="Menor Salário",IFERROR(IF(OR(C20="",Q20=0,Q20=""),"",($C20/$N20)),""),'Painel Geral'!$B$5="1º Quartil",IFERROR(IF(OR(C20="",Q20=0,Q20=""),"",($C20/$O20)),""), 'Painel Geral'!$B$5="Média",IFERROR(IF(OR(C20="",Q20=0,Q20=""),"",($C20/$P20)),""),'Painel Geral'!$B$5="3º Quartil",IFERROR(IF(OR(C20="",Q20=0,Q20=""),"",($C20/$R20)),""),'Painel Geral'!$B$5="Maior Salário",IFERROR(IF(OR(C20="",Q20=0,Q20=""),"",($C20/$S20)),"")) -> 1.2550512 | U20: =IFS(OR(N20="",N20=0,C20="", C20=0),"",T20<=80%,"Muito Defasado",T20<=90%,"Defasado",T20<=100%,"Na Média",T20<=110%,"Competitivo",T20<=120%,"Muito Competitivo",T20>120%,"Agressivo") -> Agressivo | AK20: 0.23 | AL20: =1+(AK20/100) -> 1.0023 | AM20: =AL20 -> 1.0023
A21: 4 | B21: =VLOOKUP(A21,Jobmatch!A:G,2,0) -> ANALISTA DE INOVAÇÃO | C21: =IFERROR(AVERAGEIF('Folha de Pagamento'!A:A,A21,'Folha de Pagamento'!J:J),"") -> 7299.2701 | D21: 7 | E21: =VLOOKUP(A21,Jobmatch!A:H,3,0) -> Inovação | F21: Analista Inovação | G21: =VLOOKUP(A21,Jobmatch!A:I,4,0) -> 11 - ADM PROJETOS | H21: =VLOOKUP(A21,Jobmatch!A:I,5,0) -> Tático | I21: =VLOOKUP(A21,Jobmatch!A:I,6,0) -> 437 | J21: =VLOOKUP(A21,Jobmatch!A:I,7,0) -> Analista de Inovação | K21: =VLOOKUP(A21,Jobmatch!A:I,8,0) -> Indiferente | L21: =I21&K21 -> 437Indiferente | M21: =COUNTIF('Folha de Pagamento'!A:A,A21) -> 1 | N21: 14 | O21: =IFERROR(VLOOKUP(L21,'C-01'!$D:$L,5,0),"") -> 5268.47 | P21: =IFERROR(VLOOKUP(L21,'C-01'!$D:$L,6,0),"") -> 5831.57 | Q21: =IFERROR(VLOOKUP(L21,'C-01'!$D:$L,7,0),"") -> 5268.47 | R21: =IFERROR(VLOOKUP(L21,'C-01'!$D:$L,8,0),"") -> 6822.26 | S21: =IFERROR(VLOOKUP(L21,'C-01'!$D:$L,9,0),"") -> 7760.14 | T21: =IFS('Painel Geral'!$B$5="Mediana",IFERROR(IF(OR(C21="",Q21=0,Q21=""),"",($C21/$Q21)),""),'Painel Geral'!$B$5="Menor Salário",IFERROR(IF(OR(C21="",Q21=0,Q21=""),"",($C21/$N21)),""),'Painel Geral'!$B$5="1º Quartil",IFERROR(IF(OR(C21="",Q21=0,Q21=""),"",($C21/$O21)),""), 'Painel Geral'!$B$5="Média",IFERROR(IF(OR(C21="",Q21=0,Q21=""),"",($C21/$P21)),""),'Painel Geral'!$B$5="3º Quartil",IFERROR(IF(OR(C21="",Q21=0,Q21=""),"",($C21/$R21)),""),'Painel Geral'!$B$5="Maior Salário",IFERROR(IF(OR(C21="",Q21=0,Q21=""),"",($C21/$S21)),"")) -> 1.385463 | U21: =IFS(OR(N21="",N21=0,C21="", C21=0),"",T21<=80%,"Muito Defasado",T21<=90%,"Defasado",T21<=100%,"Na Média",T21<=110%,"Competitivo",T21<=120%,"Muito Competitivo",T21>120%,"Agressivo") -> Agressivo | AK21: 0.21 | AL21: =1+(AK21/100) -> 1.0021 | AM21: =AM20*AL21 -> 1.0044048
A22: 2 | B22: =VLOOKUP(A22,Jobmatch!A:G,2,0) -> ANALISTA DE COMPRAS | C22: =IFERROR(AVERAGEIF('Folha de Pagamento'!A:A,A22,'Folha de Pagamento'!J:J),"") -> 3780 | D22: 1 | E22: =VLOOKUP(A22,Jobmatch!A:H,3,0) -> Suprimentos | F22: Analista Compras | G22: =VLOOKUP(A22,Jobmatch!A:I,4,0) -> 9 - ADM PROJETOS | H22: =VLOOKUP(A22,Jobmatch!A:I,5,0) -> Operacional | I22: =VLOOKUP(A22,Jobmatch!A:I,6,0) -> 136 | J22: =VLOOKUP(A22,Jobmatch!A:I,7,0) -> Analista de Compras | K22: =VLOOKUP(A22,Jobmatch!A:I,8,0) -> Pleno | L22: =I22&K22 -> 136Pleno | M22: =COUNTIF('Folha de Pagamento'!A:A,A22) -> 1 | N22: 15 | O22: =IFERROR(VLOOKUP(L22,'C-01'!$D:$L,5,0),"") -> 4524.76 | P22: =IFERROR(VLOOKUP(L22,'C-01'!$D:$L,6,0),"") -> 6002.23 | Q22: =IFERROR(VLOOKUP(L22,'C-01'!$D:$L,7,0),"") -> 5275.87 | R22: =IFERROR(VLOOKUP(L22,'C-01'!$D:$L,8,0),"") -> 7842.89 | S22: =IFERROR(VLOOKUP(L22,'C-01'!$D:$L,9,0),"") -> 7842.89 | T22: =IFS('Painel Geral'!$B$5="Mediana",IFERROR(IF(OR(C22="",Q22=0,Q22=""),"",($C22/$Q22)),""),'Painel Geral'!$B$5="Menor Salário",IFERROR(IF(OR(C22="",Q22=0,Q22=""),"",($C22/$N22)),""),'Painel Geral'!$B$5="1º Quartil",IFERROR(IF(OR(C22="",Q22=0,Q22=""),"",($C22/$O22)),""), 'Painel Geral'!$B$5="Média",IFERROR(IF(OR(C22="",Q22=0,Q22=""),"",($C22/$P22)),""),'Painel Geral'!$B$5="3º Quartil",IFERROR(IF(OR(C22="",Q22=0,Q22=""),"",($C22/$R22)),""),'Painel Geral'!$B$5="Maior Salário",IFERROR(IF(OR(C22="",Q22=0,Q22=""),"",($C22/$S22)),"")) -> 0.71646951 | U22: =IFS(OR(N22="",N22=0,C22="", C22=0),"",T22<=80%,"Muito Defasado",T22<=90%,"Defasado",T22<=100%,"Na Média",T22<=110%,"Competitivo",T22<=120%,"Muito Competitivo",T22>120%,"Agressivo") -> Muito Defasado | AK22: -0.21 | AL22: =1+(AK22/100) -> 0.9979 | AM22: =AM21*AL22 -> 1.0022956
A23: 7 | B23: =VLOOKUP(A23,Jobmatch!A:G,2,0) -> ANALISTA DE PÓS VENDAS II | C23: =IFERROR(AVERAGEIF('Folha de Pagamento'!A:A,A23,'Folha de Pagamento'!J:J),"") -> 4550 | D23: 9 | E23: =VLOOKUP(A23,Jobmatch!A:H,3,0) -> Pós Vendas | F23: Analista Pós-Vendas Pl | G23: =VLOOKUP(A23,Jobmatch!A:I,4,0) -> 14 - ADM PROJETOS | H23: =VLOOKUP(A23,Jobmatch!A:I,5,0) -> Operacional | I23: =VLOOKUP(A23,Jobmatch!A:I,6,0) -> 19 | J23: =VLOOKUP(A23,Jobmatch!A:I,7,0) -> Analista Comercial | K23: =VLOOKUP(A23,Jobmatch!A:I,8,0) -> Pleno | L23: =I23&K23 -> 19Pleno | M23: =COUNTIF('Folha de Pagamento'!A:A,A23) -> 1 | N23: 15 | O23: =IFERROR(VLOOKUP(L23,'C-01'!$D:$L,5,0),"") -> 4898.28 | P23: =IFERROR(VLOOKUP(L23,'C-01'!$D:$L,6,0),"") -> 5747.37 | Q23: =IFERROR(VLOOKUP(L23,'C-01'!$D:$L,7,0),"") -> 5320.06 | R23: =IFERROR(VLOOKUP(L23,'C-01'!$D:$L,8,0),"") -> 6382.81 | S23: =IFERROR(VLOOKUP(L23,'C-01'!$D:$L,9,0),"") -> 7445.55 | T23: =IFS('Painel Geral'!$B$5="Mediana",IFERROR(IF(OR(C23="",Q23=0,Q23=""),"",($C23/$Q23)),""),'Painel Geral'!$B$5="Menor Salário",IFERROR(IF(OR(C23="",Q23=0,Q23=""),"",($C23/$N23)),""),'Painel Geral'!$B$5="1º Quartil",IFERROR(IF(OR(C23="",Q23=0,Q23=""),"",($C23/$O23)),""), 'Painel Geral'!$B$5="Média",IFERROR(IF(OR(C23="",Q23=0,Q23=""),"",($C23/$P23)),""),'Painel Geral'!$B$5="3º Quartil",IFERROR(IF(OR(C23="",Q23=0,Q23=""),"",($C23/$R23)),""),'Painel Geral'!$B$5="Maior Salário",IFERROR(IF(OR(C23="",Q23=0,Q23=""),"",($C23/$S23)),"")) -> 0.85525351 | U23: =IFS(OR(N23="",N23=0,C23="", C23=0),"",T23<=80%,"Muito Defasado",T23<=90%,"Defasado",T23<=100%,"Na Média",T23<=110%,"Competitivo",T23<=120%,"Muito Competitivo",T23>120%,"Agressivo") -> Defasado | AK23: 0.52 | AL23: =1+(AK23/100) -> 1.0052 | AM23: =AM22*AL23 -> 1.0075075
A24: 9 | B24: =VLOOKUP(A24,Jobmatch!A:G,2,0) -> ANALISTA FINANCEIRO COMERCIAL III | C24: =IFERROR(AVERAGEIF('Folha de Pagamento'!A:A,A24,'Folha de Pagamento'!J:J),"") -> 5213 | D24: 6 | E24: =VLOOKUP(A24,Jobmatch!A:H,3,0) -> Financeiro | F24: Analista Financeiro Comercial Sr | G24: =VLOOKUP(A24,Jobmatch!A:I,4,0) -> 16 - ADM PROJETOS | H24: =VLOOKUP(A24,Jobmatch!A:I,5,0) -> Operacional | I24: =VLOOKUP(A24,Jobmatch!A:I,6,0) -> 16 | J24: =VLOOKUP(A24,Jobmatch!A:I,7,0) -> Analista Financeiro | K24: =VLOOKUP(A24,Jobmatch!A:I,8,0) -> Sênior | L24: =I24&K24 -> 16Sênior | M24: =COUNTIF('Folha de Pagamento'!A:A,A24) -> 1 | N24: 15 | O24: =IFERROR(VLOOKUP(L24,'C-01'!$D:$L,5,0),"") -> 5489.27 | P24: =IFERROR(VLOOKUP(L24,'C-01'!$D:$L,6,0),"") -> 6172.24 | Q24: =IFERROR(VLOOKUP(L24,'C-01'!$D:$L,7,0),"") -> 5910.71 | R24: =IFERROR(VLOOKUP(L24,'C-01'!$D:$L,8,0),"") -> 6737.39 | S24: =IFERROR(VLOOKUP(L24,'C-01'!$D:$L,9,0),"") -> 8185.08 | T24: =IFS('Painel Geral'!$B$5="Mediana",IFERROR(IF(OR(C24="",Q24=0,Q24=""),"",($C24/$Q24)),""),'Painel Geral'!$B$5="Menor Salário",IFERROR(IF(OR(C24="",Q24=0,Q24=""),"",($C24/$N24)),""),'Painel Geral'!$B$5="1º Quartil",IFERROR(IF(OR(C24="",Q24=0,Q24=""),"",($C24/$O24)),""), 'Painel Geral'!$B$5="Média",IFERROR(IF(OR(C24="",Q24=0,Q24=""),"",($C24/$P24)),""),'Painel Geral'!$B$5="3º Quartil",IFERROR(IF(OR(C24="",Q24=0,Q24=""),"",($C24/$R24)),""),'Painel Geral'!$B$5="Maior Salário",IFERROR(IF(OR(C24="",Q24=0,Q24=""),"",($C24/$S24)),"")) -> 0.88195834 | U24: =IFS(OR(N24="",N24=0,C24="", C24=0),"",T24<=80%,"Muito Defasado",T24<=90%,"Defasado",T24<=100%,"Na Média",T24<=110%,"Competitivo",T24<=120%,"Muito Competitivo",T24>120%,"Agressivo") -> Defasado | AK24: 0.03 | AL24: =1+(AK24/100) -> 1.0003 | AM24: =AM23*AL24 -> 1.0078098
A25: 10 | B25: =VLOOKUP(A25,Jobmatch!A:G,2,0) -> ANALISTA FINANCEIRO DE CAPTAÇÃO DE RECURSOS III | C25: =IFERROR(AVERAGEIF('Folha de Pagamento'!A:A,A25,'Folha de Pagamento'!J:J),"") -> 5213 | D25: 6 | E25: =VLOOKUP(A25,Jobmatch!A:H,3,0) -> Financeiro | F25: Analista Financeiro Captação Recursos Sr | G25: =VLOOKUP(A25,Jobmatch!A:I,4,0) -> 17 - ADM PROJETOS | H25: =VLOOKUP(A25,Jobmatch!A:I,5,0) -> Operacional | I25: =VLOOKUP(A25,Jobmatch!A:I,6,0) -> 16 | J25: =VLOOKUP(A25,Jobmatch!A:I,7,0) -> Analista Financeiro | K25: =VLOOKUP(A25,Jobmatch!A:I,8,0) -> Sênior | L25: =I25&K25 -> 16Sênior | M25: =COUNTIF('Folha de Pagamento'!A:A,A25) -> 1 | N25: 15 | O25: =IFERROR(VLOOKUP(L25,'C-01'!$D:$L,5,0),"") -> 5489.27 | P25: =IFERROR(VLOOKUP(L25,'C-01'!$D:$L,6,0),"") -> 6172.24 | Q25: =IFERROR(VLOOKUP(L25,'C-01'!$D:$L,7,0),"") -> 5910.71 | R25: =IFERROR(VLOOKUP(L25,'C-01'!$D:$L,8,0),"") -> 6737.39 | S25: =IFERROR(VLOOKUP(L25,'C-01'!$D:$L,9,0),"") -> 8185.08 | T25: =IFS('Painel Geral'!$B$5="Mediana",IFERROR(IF(OR(C25="",Q25=0,Q25=""),"",($C25/$Q25)),""),'Painel Geral'!$B$5="Menor Salário",IFERROR(IF(OR(C25="",Q25=0,Q25=""),"",($C25/$N25)),""),'Painel Geral'!$B$5="1º Quartil",IFERROR(IF(OR(C25="",Q25=0,Q25=""),"",($C25/$O25)),""), 'Painel Geral'!$B$5="Média",IFERROR(IF(OR(C25="",Q25=0,Q25=""),"",($C25/$P25)),""),'Painel Geral'!$B$5="3º Quartil",IFERROR(IF(OR(C25="",Q25=0,Q25=""),"",($C25/$R25)),""),'Painel Geral'!$B$5="Maior Salário",IFERROR(IF(OR(C25="",Q25=0,Q25=""),"",($C25/$S25)),"")) -> 0.88195834 | U25: =IFS(OR(N25="",N25=0,C25="", C25=0),"",T25<=80%,"Muito Defasado",T25<=90%,"Defasado",T25<=100%,"Na Média",T25<=110%,"Competitivo",T25<=120%,"Muito Competitivo",T25>120%,"Agressivo") -> Defasado | AK25: 0.03 | AL25: =1+(AK25/100) -> 1.0003 | AM25: =AM24*AL25 -> 1.0081121
A26: 53 | B26: =VLOOKUP(A26,Jobmatch!A:G,2,0) -> TECNICO ANALISTA DE CUSTOS | C26: =IFERROR(AVERAGEIF('Folha de Pagamento'!A:A,A26,'Folha de Pagamento'!J:J),"") -> 7000 | D26: 5 | E26: =VLOOKUP(A26,Jobmatch!A:H,3,0) -> Edificação | F26: Técnico Analista Custos | G26: =VLOOKUP(A26,Jobmatch!A:I,4,0) -> 60 - ADM PROJETOS | H26: =VLOOKUP(A26,Jobmatch!A:I,5,0) -> Operacional | I26: =VLOOKUP(A26,Jobmatch!A:I,6,0) -> 876 | J26: =VLOOKUP(A26,Jobmatch!A:I,7,0) -> Analista de Custos | K26: =VLOOKUP(A26,Jobmatch!A:I,8,0) -> Indiferente | L26: =I26&K26 -> 876Indiferente | M26: =COUNTIF('Folha de Pagamento'!A:A,A26) -> 3 | N26: 17 | O26: =IFERROR(VLOOKUP(L26,'C-01'!$D:$L,5,0),"") -> 6868.23 | P26: =IFERROR(VLOOKUP(L26,'C-01'!$D:$L,6,0),"") -> 7611.25 | Q26: =IFERROR(VLOOKUP(L26,'C-01'!$D:$L,7,0),"") -> 7320.76 | R26: =IFERROR(VLOOKUP(L26,'C-01'!$D:$L,8,0),"") -> 8153.71 | S26: =IFERROR(VLOOKUP(L26,'C-01'!$D:$L,9,0),"") -> 9161.15 | T26: =IFS('Painel Geral'!$B$5="Mediana",IFERROR(IF(OR(C26="",Q26=0,Q26=""),"",($C26/$Q26)),""),'Painel Geral'!$B$5="Menor Salário",IFERROR(IF(OR(C26="",Q26=0,Q26=""),"",($C26/$N26)),""),'Painel Geral'!$B$5="1º Quartil",IFERROR(IF(OR(C26="",Q26=0,Q26=""),"",($C26/$O26)),""), 'Painel Geral'!$B$5="Média",IFERROR(IF(OR(C26="",Q26=0,Q26=""),"",($C26/$P26)),""),'Painel Geral'!$B$5="3º Quartil",IFERROR(IF(OR(C26="",Q26=0,Q26=""),"",($C26/$R26)),""),'Painel Geral'!$B$5="Maior Salário",IFERROR(IF(OR(C26="",Q26=0,Q26=""),"",($C26/$S26)),"")) -> 0.95618488 | U26: =IFS(OR(N26="",N26=0,C26="", C26=0),"",T26<=80%,"Muito Defasado",T26<=90%,"Defasado",T26<=100%,"Na Média",T26<=110%,"Competitivo",T26<=120%,"Muito Competitivo",T26>120%,"Agressivo") -> Na Média
A27: 35 | B27: =VLOOKUP(A27,Jobmatch!A:G,2,0) -> ENCARREGADO OBRAS/MANUTENCAO | C27: =IFERROR(AVERAGEIF('Folha de Pagamento'!A:A,A27,'Folha de Pagamento'!J:J),"") -> 8714 | D27: 5 | E27: =VLOOKUP(A27,Jobmatch!A:H,3,0) -> Edificação | F27: Encarregado Obras / Manutenção | G27: =VLOOKUP(A27,Jobmatch!A:I,4,0) -> 42 - ADM PROJETOS | H27: =VLOOKUP(A27,Jobmatch!A:I,5,0) -> Operacional | I27: =VLOOKUP(A27,Jobmatch!A:I,6,0) -> 470 | J27: =VLOOKUP(A27,Jobmatch!A:I,7,0) -> Mestre de Obras | K27: =VLOOKUP(A27,Jobmatch!A:I,8,0) -> Indiferente | L27: =I27&K27 -> 470Indiferente | M27: =COUNTIF('Folha de Pagamento'!A:A,A27) -> 1 | N27: 17 | O27: =IFERROR(VLOOKUP(L27,'C-01'!$D:$L,5,0),"") -> 5530.26 | P27: =IFERROR(VLOOKUP(L27,'C-01'!$D:$L,6,0),"") -> 7689.13 | Q27: =IFERROR(VLOOKUP(L27,'C-01'!$D:$L,7,0),"") -> 7460.82 | R27: =IFERROR(VLOOKUP(L27,'C-01'!$D:$L,8,0),"") -> 9785.54 | S27: =IFERROR(VLOOKUP(L27,'C-01'!$D:$L,9,0),"") -> 11138.95 | T27: =IFS('Painel Geral'!$B$5="Mediana",IFERROR(IF(OR(C27="",Q27=0,Q27=""),"",($C27/$Q27)),""),'Painel Geral'!$B$5="Menor Salário",IFERROR(IF(OR(C27="",Q27=0,Q27=""),"",($C27/$N27)),""),'Painel Geral'!$B$5="1º Quartil",IFERROR(IF(OR(C27="",Q27=0,Q27=""),"",($C27/$O27)),""), 'Painel Geral'!$B$5="Média",IFERROR(IF(OR(C27="",Q27=0,Q27=""),"",($C27/$P27)),""),'Painel Geral'!$B$5="3º Quartil",IFERROR(IF(OR(C27="",Q27=0,Q27=""),"",($C27/$R27)),""),'Painel Geral'!$B$5="Maior Salário",IFERROR(IF(OR(C27="",Q27=0,Q27=""),"",($C27/$S27)),"")) -> 1.1679681 | U27: =IFS(OR(N27="",N27=0,C27="", C27=0),"",T27<=80%,"Muito Defasado",T27<=90%,"Defasado",T27<=100%,"Na Média",T27<=110%,"Competitivo",T27<=120%,"Muito Competitivo",T27>120%,"Agressivo") -> Muito Competitivo | AN27: =AM25 -> 1.0081121
A28: 34 | B28: =VLOOKUP(A28,Jobmatch!A:G,2,0) -> ENCARREGADO DE OBRAS | C28: =IFERROR(AVERAGEIF('Folha de Pagamento'!A:A,A28,'Folha de Pagamento'!J:J),"") -> 10000.5 | D28: 10 | E28: =VLOOKUP(A28,Jobmatch!A:H,3,0) -> Urbanismo | F28: Encarregado Obras | G28: =VLOOKUP(A28,Jobmatch!A:I,4,0) -> 41 - ADM PROJETOS | H28: =VLOOKUP(A28,Jobmatch!A:I,5,0) -> Operacional | I28: =VLOOKUP(A28,Jobmatch!A:I,6,0) -> 470 | J28: =VLOOKUP(A28,Jobmatch!A:I,7,0) -> Mestre de Obras | K28: =VLOOKUP(A28,Jobmatch!A:I,8,0) -> Indiferente | L28: =I28&K28 -> 470Indiferente | M28: =COUNTIF('Folha de Pagamento'!A:A,A28) -> 2 | N28: 17 | O28: =IFERROR(VLOOKUP(L28,'C-01'!$D:$L,5,0),"") -> 5530.26 | P28: =IFERROR(VLOOKUP(L28,'C-01'!$D:$L,6,0),"") -> 7689.13 | Q28: =IFERROR(VLOOKUP(L28,'C-01'!$D:$L,7,0),"") -> 7460.82 | R28: =IFERROR(VLOOKUP(L28,'C-01'!$D:$L,8,0),"") -> 9785.54 | S28: =IFERROR(VLOOKUP(L28,'C-01'!$D:$L,9,0),"") -> 11138.95 | T28: =IFS('Painel Geral'!$B$5="Mediana",IFERROR(IF(OR(C28="",Q28=0,Q28=""),"",($C28/$Q28)),""),'Painel Geral'!$B$5="Menor Salário",IFERROR(IF(OR(C28="",Q28=0,Q28=""),"",($C28/$N28)),""),'Painel Geral'!$B$5="1º Quartil",IFERROR(IF(OR(C28="",Q28=0,Q28=""),"",($C28/$O28)),""), 'Painel Geral'!$B$5="Média",IFERROR(IF(OR(C28="",Q28=0,Q28=""),"",($C28/$P28)),""),'Painel Geral'!$B$5="3º Quartil",IFERROR(IF(OR(C28="",Q28=0,Q28=""),"",($C28/$R28)),""),'Painel Geral'!$B$5="Maior Salário",IFERROR(IF(OR(C28="",Q28=0,Q28=""),"",($C28/$S28)),"")) -> 1.3404023 | U28: =IFS(OR(N28="",N28=0,C28="", C28=0),"",T28<=80%,"Muito Defasado",T28<=90%,"Defasado",T28<=100%,"Na Média",T28<=110%,"Competitivo",T28<=120%,"Muito Competitivo",T28>120%,"Agressivo") -> Agressivo
A29: 32 | B29: =VLOOKUP(A29,Jobmatch!A:G,2,0) -> COORDENADOR FINANCEIRO | C29: =IFERROR(AVERAGEIF('Folha de Pagamento'!A:A,A29,'Folha de Pagamento'!J:J),"") -> 7947.0199 | D29: 6 | E29: =VLOOKUP(A29,Jobmatch!A:H,3,0) -> Financeiro | F29: Coordenador Financeiro | G29: =VLOOKUP(A29,Jobmatch!A:I,4,0) -> 39 - ADM PROJETOS | H29: =VLOOKUP(A29,Jobmatch!A:I,5,0) -> Tático | I29: =VLOOKUP(A29,Jobmatch!A:I,6,0) -> 122 | J29: =VLOOKUP(A29,Jobmatch!A:I,7,0) -> Coordenador Financeiro | K29: =VLOOKUP(A29,Jobmatch!A:I,8,0) -> Indiferente | L29: =I29&K29 -> 122Indiferente | M29: =COUNTIF('Folha de Pagamento'!A:A,A29) -> 1 | N29: 17 | O29: =IFERROR(VLOOKUP(L29,'C-01'!$D:$L,5,0),"") -> 6325.01 | P29: =IFERROR(VLOOKUP(L29,'C-01'!$D:$L,6,0),"") -> 7452.59 | Q29: =IFERROR(VLOOKUP(L29,'C-01'!$D:$L,7,0),"") -> 7558.57 | R29: =IFERROR(VLOOKUP(L29,'C-01'!$D:$L,8,0),"") -> 8691.7 | S29: =IFERROR(VLOOKUP(L29,'C-01'!$D:$L,9,0),"") -> 9982.25 | T29: =IFS('Painel Geral'!$B$5="Mediana",IFERROR(IF(OR(C29="",Q29=0,Q29=""),"",($C29/$Q29)),""),'Painel Geral'!$B$5="Menor Salário",IFERROR(IF(OR(C29="",Q29=0,Q29=""),"",($C29/$N29)),""),'Painel Geral'!$B$5="1º Quartil",IFERROR(IF(OR(C29="",Q29=0,Q29=""),"",($C29/$O29)),""), 'Painel Geral'!$B$5="Média",IFERROR(IF(OR(C29="",Q29=0,Q29=""),"",($C29/$P29)),""),'Painel Geral'!$B$5="3º Quartil",IFERROR(IF(OR(C29="",Q29=0,Q29=""),"",($C29/$R29)),""),'Painel Geral'!$B$5="Maior Salário",IFERROR(IF(OR(C29="",Q29=0,Q29=""),"",($C29/$S29)),"")) -> 1.051392 | U29: =IFS(OR(N29="",N29=0,C29="", C29=0),"",T29<=80%,"Muito Defasado",T29<=90%,"Defasado",T29<=100%,"Na Média",T29<=110%,"Competitivo",T29<=120%,"Muito Competitivo",T29>120%,"Agressivo") -> Competitivo | Y29: 1799 | Z29: =Y29*AN27 -> 1813.5937
A30: 8 | B30: =VLOOKUP(A30,Jobmatch!A:G,2,0) -> ANALISTA DE URBANISMO | C30: =IFERROR(AVERAGEIF('Folha de Pagamento'!A:A,A30,'Folha de Pagamento'!J:J),"") -> 5830 | D30: 10 | E30: =VLOOKUP(A30,Jobmatch!A:H,3,0) -> Urbanismo | F30: Analista Urbanismo | G30: =VLOOKUP(A30,Jobmatch!A:I,4,0) -> 15 - ADM PROJETOS | H30: =VLOOKUP(A30,Jobmatch!A:I,5,0) -> Operacional | I30: =VLOOKUP(A30,Jobmatch!A:I,6,0) -> 1199 | J30: =VLOOKUP(A30,Jobmatch!A:I,7,0) -> Analista de Urbanismo | K30: =VLOOKUP(A30,Jobmatch!A:I,8,0) -> Indiferente | L30: =I30&K30 -> 1199Indiferente | M30: =COUNTIF('Folha de Pagamento'!A:A,A30) -> 1 | N30: 17 | O30: =IFERROR(VLOOKUP(L30,'C-01'!$D:$L,5,0),"") -> 6091.54 | P30: =IFERROR(VLOOKUP(L30,'C-01'!$D:$L,6,0),"") -> 7637.46 | Q30: =IFERROR(VLOOKUP(L30,'C-01'!$D:$L,7,0),"") -> 7848.45 | R30: =IFERROR(VLOOKUP(L30,'C-01'!$D:$L,8,0),"") -> 9161.15 | S30: =IFERROR(VLOOKUP(L30,'C-01'!$D:$L,9,0),"") -> 9161.15 | T30: =IFS('Painel Geral'!$B$5="Mediana",IFERROR(IF(OR(C30="",Q30=0,Q30=""),"",($C30/$Q30)),""),'Painel Geral'!$B$5="Menor Salário",IFERROR(IF(OR(C30="",Q30=0,Q30=""),"",($C30/$N30)),""),'Painel Geral'!$B$5="1º Quartil",IFERROR(IF(OR(C30="",Q30=0,Q30=""),"",($C30/$O30)),""), 'Painel Geral'!$B$5="Média",IFERROR(IF(OR(C30="",Q30=0,Q30=""),"",($C30/$P30)),""),'Painel Geral'!$B$5="3º Quartil",IFERROR(IF(OR(C30="",Q30=0,Q30=""),"",($C30/$R30)),""),'Painel Geral'!$B$5="Maior Salário",IFERROR(IF(OR(C30="",Q30=0,Q30=""),"",($C30/$S30)),"")) -> 0.74282183 | U30: =IFS(OR(N30="",N30=0,C30="", C30=0),"",T30<=80%,"Muito Defasado",T30<=90%,"Defasado",T30<=100%,"Na Média",T30<=110%,"Competitivo",T30<=120%,"Muito Competitivo",T30>120%,"Agressivo") -> Muito Defasado | Y30: 0.8 | Z30: grade | AA30: 1 | AB30: %
A31: 29 | B31: =VLOOKUP(A31,Jobmatch!A:G,2,0) -> COORDENADOR DE MARKETING II | C31: =IFERROR(AVERAGEIF('Folha de Pagamento'!A:A,A31,'Folha de Pagamento'!J:J),"") -> 8647 | D31: 8 | E31: =VLOOKUP(A31,Jobmatch!A:H,3,0) -> Marketing | F31: Coordenador Marketing | G31: =VLOOKUP(A31,Jobmatch!A:I,4,0) -> 36 - ADM PROJETOS | H31: =VLOOKUP(A31,Jobmatch!A:I,5,0) -> Tático | I31: =VLOOKUP(A31,Jobmatch!A:I,6,0) -> 56 | J31: =VLOOKUP(A31,Jobmatch!A:I,7,0) -> Coordenador de Marketing | K31: =VLOOKUP(A31,Jobmatch!A:I,8,0) -> Indiferente | L31: =I31&K31 -> 56Indiferente | M31: =COUNTIF('Folha de Pagamento'!A:A,A31) -> 1 | N31: 17 | O31: =IFERROR(VLOOKUP(L31,'C-01'!$D:$L,5,0),"") -> 7141.59 | P31: =IFERROR(VLOOKUP(L31,'C-01'!$D:$L,6,0),"") -> 7927.07 | Q31: =IFERROR(VLOOKUP(L31,'C-01'!$D:$L,7,0),"") -> 7958.59 | R31: =IFERROR(VLOOKUP(L31,'C-01'!$D:$L,8,0),"") -> 8825.19 | S31: =IFERROR(VLOOKUP(L31,'C-01'!$D:$L,9,0),"") -> 10531.61 | T31: =IFS('Painel Geral'!$B$5="Mediana",IFERROR(IF(OR(C31="",Q31=0,Q31=""),"",($C31/$Q31)),""),'Painel Geral'!$B$5="Menor Salário",IFERROR(IF(OR(C31="",Q31=0,Q31=""),"",($C31/$N31)),""),'Painel Geral'!$B$5="1º Quartil",IFERROR(IF(OR(C31="",Q31=0,Q31=""),"",($C31/$O31)),""), 'Painel Geral'!$B$5="Média",IFERROR(IF(OR(C31="",Q31=0,Q31=""),"",($C31/$P31)),""),'Painel Geral'!$B$5="3º Quartil",IFERROR(IF(OR(C31="",Q31=0,Q31=""),"",($C31/$R31)),""),'Painel Geral'!$B$5="Maior Salário",IFERROR(IF(OR(C31="",Q31=0,Q31=""),"",($C31/$S31)),"")) -> 1.086499 | U31: =IFS(OR(N31="",N31=0,C31="", C31=0),"",T31<=80%,"Muito Defasado",T31<=90%,"Defasado",T31<=100%,"Na Média",T31<=110%,"Competitivo",T31<=120%,"Muito Competitivo",T31>120%,"Agressivo") -> Competitivo | Y31: =AA31*0.8 -> 1867.2 | Z31: 10 | AA31: =-4466+1611*Z31-155*Z31*Z31+6.19*Z31*Z31*Z31 -> 2334 | AN31: =AN29/AN27 -> 0
A32: 28 | B32: =VLOOKUP(A32,Jobmatch!A:G,2,0) -> COORDENADOR DE LEGAIZAÇÃO ll | C32: =IFERROR(AVERAGEIF('Folha de Pagamento'!A:A,A32,'Folha de Pagamento'!J:J),"") -> 8647 | D32: 7 | E32: =VLOOKUP(A32,Jobmatch!A:H,3,0) -> Legalização | F32: Coordenador Legalização Pl | G32: =VLOOKUP(A32,Jobmatch!A:I,4,0) -> 35 - ADM PROJETOS | H32: =VLOOKUP(A32,Jobmatch!A:I,5,0) -> Tático | I32: =VLOOKUP(A32,Jobmatch!A:I,6,0) -> 1203 | J32: =VLOOKUP(A32,Jobmatch!A:I,7,0) -> Coordenador de Legalização | K32: =VLOOKUP(A32,Jobmatch!A:I,8,0) -> Indiferente | L32: =I32&K32 -> 1203Indiferente | M32: =COUNTIF('Folha de Pagamento'!A:A,A32) -> 1 | N32: 17 | O32: =IFERROR(VLOOKUP(L32,'C-01'!$D:$L,5,0),"") -> 8783.31 | P32: =IFERROR(VLOOKUP(L32,'C-01'!$D:$L,6,0),"") -> 8872.04 | Q32: =IFERROR(VLOOKUP(L32,'C-01'!$D:$L,7,0),"") -> 8872.04 | R32: =IFERROR(VLOOKUP(L32,'C-01'!$D:$L,8,0),"") -> 8960.78 | S32: =IFERROR(VLOOKUP(L32,'C-01'!$D:$L,9,0),"") -> 9049.51 | T32: =IFS('Painel Geral'!$B$5="Mediana",IFERROR(IF(OR(C32="",Q32=0,Q32=""),"",($C32/$Q32)),""),'Painel Geral'!$B$5="Menor Salário",IFERROR(IF(OR(C32="",Q32=0,Q32=""),"",($C32/$N32)),""),'Painel Geral'!$B$5="1º Quartil",IFERROR(IF(OR(C32="",Q32=0,Q32=""),"",($C32/$O32)),""), 'Painel Geral'!$B$5="Média",IFERROR(IF(OR(C32="",Q32=0,Q32=""),"",($C32/$P32)),""),'Painel Geral'!$B$5="3º Quartil",IFERROR(IF(OR(C32="",Q32=0,Q32=""),"",($C32/$R32)),""),'Painel Geral'!$B$5="Maior Salário",IFERROR(IF(OR(C32="",Q32=0,Q32=""),"",($C32/$S32)),"")) -> 0.97463492 | U32: =IFS(OR(N32="",N32=0,C32="", C32=0),"",T32<=80%,"Muito Defasado",T32<=90%,"Defasado",T32<=100%,"Na Média",T32<=110%,"Competitivo",T32<=120%,"Muito Competitivo",T32>120%,"Agressivo") -> Na Média | Z32: 11 | AA32: =-4466+1611*Z32-155*Z32*Z32+6.19*Z32*Z32*Z32 -> 2738.89 | AB32: =(AA32-AA31)/AA31 -> 0.17347472
A33: 42 | B33: =VLOOKUP(A33,Jobmatch!A:G,2,0) -> GERENTE ADMINISTRATIVA | C33: =IFERROR(AVERAGEIF('Folha de Pagamento'!A:A,A33,'Folha de Pagamento'!J:J),"") -> 12242.424 | D33: 1 | E33: =VLOOKUP(A33,Jobmatch!A:H,3,0) -> Administrativo | F33: Gerente Administrativa | G33: =VLOOKUP(A33,Jobmatch!A:I,4,0) -> 49 - ADM PROJETOS | H33: =VLOOKUP(A33,Jobmatch!A:I,5,0) -> Tático | I33: =VLOOKUP(A33,Jobmatch!A:I,6,0) -> 106 | J33: =VLOOKUP(A33,Jobmatch!A:I,7,0) -> Gerente Administrativo | K33: =VLOOKUP(A33,Jobmatch!A:I,8,0) -> Indiferente | L33: =I33&K33 -> 106Indiferente | M33: =COUNTIF('Folha de Pagamento'!A:A,A33) -> 2 | N33: 17 | O33: =IFERROR(VLOOKUP(L33,'C-01'!$D:$L,5,0),"") -> 6616.13 | P33: =IFERROR(VLOOKUP(L33,'C-01'!$D:$L,6,0),"") -> 9881.52 | Q33: =IFERROR(VLOOKUP(L33,'C-01'!$D:$L,7,0),"") -> 10052.23 | R33: =IFERROR(VLOOKUP(L33,'C-01'!$D:$L,8,0),"") -> 12479.94 | S33: =IFERROR(VLOOKUP(L33,'C-01'!$D:$L,9,0),"") -> 15257.82 | T33: =IFS('Painel Geral'!$B$5="Mediana",IFERROR(IF(OR(C33="",Q33=0,Q33=""),"",($C33/$Q33)),""),'Painel Geral'!$B$5="Menor Salário",IFERROR(IF(OR(C33="",Q33=0,Q33=""),"",($C33/$N33)),""),'Painel Geral'!$B$5="1º Quartil",IFERROR(IF(OR(C33="",Q33=0,Q33=""),"",($C33/$O33)),""), 'Painel Geral'!$B$5="Média",IFERROR(IF(OR(C33="",Q33=0,Q33=""),"",($C33/$P33)),""),'Painel Geral'!$B$5="3º Quartil",IFERROR(IF(OR(C33="",Q33=0,Q33=""),"",($C33/$R33)),""),'Painel Geral'!$B$5="Maior Salário",IFERROR(IF(OR(C33="",Q33=0,Q33=""),"",($C33/$S33)),"")) -> 1.2178814 | U33: =IFS(OR(N33="",N33=0,C33="", C33=0),"",T33<=80%,"Muito Defasado",T33<=90%,"Defasado",T33<=100%,"Na Média",T33<=110%,"Competitivo",T33<=120%,"Muito Competitivo",T33>120%,"Agressivo") -> Agressivo | Z33: 12 | AA33: =-4466+1611*Z33-155*Z33*Z33+6.19*Z33*Z33*Z33 -> 3242.32 | AB33: =(AA33-AA32)/AA32 -> 0.18380804
A34: 48 | B34: =VLOOKUP(A34,Jobmatch!A:G,2,0) -> GERENTE DE PARCERIAS | C34: =IFERROR(AVERAGEIF('Folha de Pagamento'!A:A,A34,'Folha de Pagamento'!J:J),"") -> 5345 | D34: 2 | E34: =VLOOKUP(A34,Jobmatch!A:H,3,0) -> Comercial | F34: Gerente Parcerias | G34: =VLOOKUP(A34,Jobmatch!A:I,4,0) -> 55 - ADM PROJETOS | H34: =VLOOKUP(A34,Jobmatch!A:I,5,0) -> Tático | I34: =VLOOKUP(A34,Jobmatch!A:I,6,0) -> 408 | J34: =VLOOKUP(A34,Jobmatch!A:I,7,0) -> Gerente de Relacionamento | K34: =VLOOKUP(A34,Jobmatch!A:I,8,0) -> Indiferente | L34: =I34&K34 -> 408Indiferente | M34: =COUNTIF('Folha de Pagamento'!A:A,A34) -> 2 | N34: 18 | O34: =IFERROR(VLOOKUP(L34,'C-01'!$D:$L,5,0),"") -> 7608.96 | P34: =IFERROR(VLOOKUP(L34,'C-01'!$D:$L,6,0),"") -> 10973.95 | Q34: =IFERROR(VLOOKUP(L34,'C-01'!$D:$L,7,0),"") -> 10996.97 | R34: =IFERROR(VLOOKUP(L34,'C-01'!$D:$L,8,0),"") -> 14004.27 | S34: =IFERROR(VLOOKUP(L34,'C-01'!$D:$L,9,0),"") -> 16628.86 | T34: =IFS('Painel Geral'!$B$5="Mediana",IFERROR(IF(OR(C34="",Q34=0,Q34=""),"",($C34/$Q34)),""),'Painel Geral'!$B$5="Menor Salário",IFERROR(IF(OR(C34="",Q34=0,Q34=""),"",($C34/$N34)),""),'Painel Geral'!$B$5="1º Quartil",IFERROR(IF(OR(C34="",Q34=0,Q34=""),"",($C34/$O34)),""), 'Painel Geral'!$B$5="Média",IFERROR(IF(OR(C34="",Q34=0,Q34=""),"",($C34/$P34)),""),'Painel Geral'!$B$5="3º Quartil",IFERROR(IF(OR(C34="",Q34=0,Q34=""),"",($C34/$R34)),""),'Painel Geral'!$B$5="Maior Salário",IFERROR(IF(OR(C34="",Q34=0,Q34=""),"",($C34/$S34)),"")) -> 0.48604297 | U34: =IFS(OR(N34="",N34=0,C34="", C34=0),"",T34<=80%,"Muito Defasado",T34<=90%,"Defasado",T34<=100%,"Na Média",T34<=110%,"Competitivo",T34<=120%,"Muito Competitivo",T34>120%,"Agressivo") -> Muito Defasado | Z34: 13 | AA34: =-4466+1611*Z34-155*Z34*Z34+6.19*Z34*Z34*Z34 -> 3881.43 | AB34: =(AA34-AA33)/AA33 -> 0.19711503
A35: 49 | B35: =VLOOKUP(A35,Jobmatch!A:G,2,0) -> GERENTE DE PARCERIAS EXTERNAS | C35: =IFERROR(AVERAGEIF('Folha de Pagamento'!A:A,A35,'Folha de Pagamento'!J:J),"") -> 5000 | D35: 2 | E35: =VLOOKUP(A35,Jobmatch!A:H,3,0) -> Comercial | F35: Gerente Parcerias Externas | G35: =VLOOKUP(A35,Jobmatch!A:I,4,0) -> 56 - ADM PROJETOS | H35: =VLOOKUP(A35,Jobmatch!A:I,5,0) -> Tático | I35: =VLOOKUP(A35,Jobmatch!A:I,6,0) -> 408 | J35: =VLOOKUP(A35,Jobmatch!A:I,7,0) -> Gerente de Relacionamento | K35: =VLOOKUP(A35,Jobmatch!A:I,8,0) -> Indiferente | L35: =I35&K35 -> 408Indiferente | M35: =COUNTIF('Folha de Pagamento'!A:A,A35) -> 2 | N35: 18 | O35: =IFERROR(VLOOKUP(L35,'C-01'!$D:$L,5,0),"") -> 7608.96 | P35: =IFERROR(VLOOKUP(L35,'C-01'!$D:$L,6,0),"") -> 10973.95 | Q35: =IFERROR(VLOOKUP(L35,'C-01'!$D:$L,7,0),"") -> 10996.97 | R35: =IFERROR(VLOOKUP(L35,'C-01'!$D:$L,8,0),"") -> 14004.27 | S35: =IFERROR(VLOOKUP(L35,'C-01'!$D:$L,9,0),"") -> 16628.86 | T35: =IFS('Painel Geral'!$B$5="Mediana",IFERROR(IF(OR(C35="",Q35=0,Q35=""),"",($C35/$Q35)),""),'Painel Geral'!$B$5="Menor Salário",IFERROR(IF(OR(C35="",Q35=0,Q35=""),"",($C35/$N35)),""),'Painel Geral'!$B$5="1º Quartil",IFERROR(IF(OR(C35="",Q35=0,Q35=""),"",($C35/$O35)),""), 'Painel Geral'!$B$5="Média",IFERROR(IF(OR(C35="",Q35=0,Q35=""),"",($C35/$P35)),""),'Painel Geral'!$B$5="3º Quartil",IFERROR(IF(OR(C35="",Q35=0,Q35=""),"",($C35/$R35)),""),'Painel Geral'!$B$5="Maior Salário",IFERROR(IF(OR(C35="",Q35=0,Q35=""),"",($C35/$S35)),"")) -> 0.4546707 | U35: =IFS(OR(N35="",N35=0,C35="", C35=0),"",T35<=80%,"Muito Defasado",T35<=90%,"Defasado",T35<=100%,"Na Média",T35<=110%,"Competitivo",T35<=120%,"Muito Competitivo",T35>120%,"Agressivo") -> Muito Defasado | Z35: 14 | AA35: =-4466+1611*Z35-155*Z35*Z35+6.19*Z35*Z35*Z35 -> 4693.36 | AB35: =(AA35-AA34)/AA34 -> 0.20918321
A36: 31 | B36: =VLOOKUP(A36,Jobmatch!A:G,2,0) -> COORDENADOR DE SUPRIMENTOS | C36: =IFERROR(AVERAGEIF('Folha de Pagamento'!A:A,A36,'Folha de Pagamento'!J:J),"") -> 10596.026 | D36: 1 | E36: =VLOOKUP(A36,Jobmatch!A:H,3,0) -> Suprimentos | F36: Coordenador Suprimentos | G36: =VLOOKUP(A36,Jobmatch!A:I,4,0) -> 38 - ADM PROJETOS | H36: =VLOOKUP(A36,Jobmatch!A:I,5,0) -> Tático | I36: =VLOOKUP(A36,Jobmatch!A:I,6,0) -> 137 | J36: =VLOOKUP(A36,Jobmatch!A:I,7,0) -> Coordenador de Compras | K36: =VLOOKUP(A36,Jobmatch!A:I,8,0) -> Indiferente | L36: =I36&K36 -> 137Indiferente | M36: =COUNTIF('Folha de Pagamento'!A:A,A36) -> 1 | N36: 18 | O36: =IFERROR(VLOOKUP(L36,'C-01'!$D:$L,5,0),"") -> 10557.77 | P36: =IFERROR(VLOOKUP(L36,'C-01'!$D:$L,6,0),"") -> 13345.69 | Q36: =IFERROR(VLOOKUP(L36,'C-01'!$D:$L,7,0),"") -> 11060.52 | R36: =IFERROR(VLOOKUP(L36,'C-01'!$D:$L,8,0),"") -> 14991.02 | S36: =IFERROR(VLOOKUP(L36,'C-01'!$D:$L,9,0),"") -> 18921.53 | T36: =IFS('Painel Geral'!$B$5="Mediana",IFERROR(IF(OR(C36="",Q36=0,Q36=""),"",($C36/$Q36)),""),'Painel Geral'!$B$5="Menor Salário",IFERROR(IF(OR(C36="",Q36=0,Q36=""),"",($C36/$N36)),""),'Painel Geral'!$B$5="1º Quartil",IFERROR(IF(OR(C36="",Q36=0,Q36=""),"",($C36/$O36)),""), 'Painel Geral'!$B$5="Média",IFERROR(IF(OR(C36="",Q36=0,Q36=""),"",($C36/$P36)),""),'Painel Geral'!$B$5="3º Quartil",IFERROR(IF(OR(C36="",Q36=0,Q36=""),"",($C36/$R36)),""),'Painel Geral'!$B$5="Maior Salário",IFERROR(IF(OR(C36="",Q36=0,Q36=""),"",($C36/$S36)),"")) -> 0.95800437 | U36: =IFS(OR(N36="",N36=0,C36="", C36=0),"",T36<=80%,"Muito Defasado",T36<=90%,"Defasado",T36<=100%,"Na Média",T36<=110%,"Competitivo",T36<=120%,"Muito Competitivo",T36>120%,"Agressivo") -> Na Média | Z36: 15 | AA36: =-4466+1611*Z36-155*Z36*Z36+6.19*Z36*Z36*Z36 -> 5715.25 | AB36: =(AA36-AA35)/AA35 -> 0.21773101
A37: 43 | B37: =VLOOKUP(A37,Jobmatch!A:G,2,0) -> GERENTE COMERCIAL | C37: =IFERROR(AVERAGEIF('Folha de Pagamento'!A:A,A37,'Folha de Pagamento'!J:J),"") -> 12090.909 | D37: 2 | E37: =VLOOKUP(A37,Jobmatch!A:H,3,0) -> Comercial | F37: Gerente Comercial | G37: =VLOOKUP(A37,Jobmatch!A:I,4,0) -> 50 - ADM PROJETOS | H37: =VLOOKUP(A37,Jobmatch!A:I,5,0) -> Tático | I37: =VLOOKUP(A37,Jobmatch!A:I,6,0) -> 107 | J37: =VLOOKUP(A37,Jobmatch!A:I,7,0) -> Gerente Comercial | K37: =VLOOKUP(A37,Jobmatch!A:I,8,0) -> Indiferente | L37: =I37&K37 -> 107Indiferente | M37: =COUNTIF('Folha de Pagamento'!A:A,A37) -> 4 | N37: 18 | O37: =IFERROR(VLOOKUP(L37,'C-01'!$D:$L,5,0),"") -> 9778.91 | P37: =IFERROR(VLOOKUP(L37,'C-01'!$D:$L,6,0),"") -> 12281.04 | Q37: =IFERROR(VLOOKUP(L37,'C-01'!$D:$L,7,0),"") -> 12107.57 | R37: =IFERROR(VLOOKUP(L37,'C-01'!$D:$L,8,0),"") -> 15321.87 | S37: =IFERROR(VLOOKUP(L37,'C-01'!$D:$L,9,0),"") -> 19289.48 | T37: =IFS('Painel Geral'!$B$5="Mediana",IFERROR(IF(OR(C37="",Q37=0,Q37=""),"",($C37/$Q37)),""),'Painel Geral'!$B$5="Menor Salário",IFERROR(IF(OR(C37="",Q37=0,Q37=""),"",($C37/$N37)),""),'Painel Geral'!$B$5="1º Quartil",IFERROR(IF(OR(C37="",Q37=0,Q37=""),"",($C37/$O37)),""), 'Painel Geral'!$B$5="Média",IFERROR(IF(OR(C37="",Q37=0,Q37=""),"",($C37/$P37)),""),'Painel Geral'!$B$5="3º Quartil",IFERROR(IF(OR(C37="",Q37=0,Q37=""),"",($C37/$R37)),""),'Painel Geral'!$B$5="Maior Salário",IFERROR(IF(OR(C37="",Q37=0,Q37=""),"",($C37/$S37)),"")) -> 0.99862393 | U37: =IFS(OR(N37="",N37=0,C37="", C37=0),"",T37<=80%,"Muito Defasado",T37<=90%,"Defasado",T37<=100%,"Na Média",T37<=110%,"Competitivo",T37<=120%,"Muito Competitivo",T37>120%,"Agressivo") -> Na Média | Z37: 16 | AA37: =-4466+1611*Z37-155*Z37*Z37+6.19*Z37*Z37*Z37 -> 6984.24 | AB37: =(AA37-AA36)/AA36 -> 0.22203578
A38: 45 | B38: =VLOOKUP(A38,Jobmatch!A:G,2,0) -> GERENTE DE HOUSE | C38: =IFERROR(AVERAGEIF('Folha de Pagamento'!A:A,A38,'Folha de Pagamento'!J:J),"") -> 5125 | D38: 2 | E38: =VLOOKUP(A38,Jobmatch!A:H,3,0) -> Comercial | F38: Gerente House | G38: =VLOOKUP(A38,Jobmatch!A:I,4,0) -> 52 - ADM PROJETOS | H38: =VLOOKUP(A38,Jobmatch!A:I,5,0) -> Tático | I38: =VLOOKUP(A38,Jobmatch!A:I,6,0) -> 107 | J38: =VLOOKUP(A38,Jobmatch!A:I,7,0) -> Gerente Comercial | K38: =VLOOKUP(A38,Jobmatch!A:I,8,0) -> Indiferente | L38: =I38&K38 -> 107Indiferente | M38: =COUNTIF('Folha de Pagamento'!A:A,A38) -> 1 | N38: 18 | O38: =IFERROR(VLOOKUP(L38,'C-01'!$D:$L,5,0),"") -> 9778.91 | P38: =IFERROR(VLOOKUP(L38,'C-01'!$D:$L,6,0),"") -> 12281.04 | Q38: =IFERROR(VLOOKUP(L38,'C-01'!$D:$L,7,0),"") -> 12107.57 | R38: =IFERROR(VLOOKUP(L38,'C-01'!$D:$L,8,0),"") -> 15321.87 | S38: =IFERROR(VLOOKUP(L38,'C-01'!$D:$L,9,0),"") -> 19289.48 | T38: =IFS('Painel Geral'!$B$5="Mediana",IFERROR(IF(OR(C38="",Q38=0,Q38=""),"",($C38/$Q38)),""),'Painel Geral'!$B$5="Menor Salário",IFERROR(IF(OR(C38="",Q38=0,Q38=""),"",($C38/$N38)),""),'Painel Geral'!$B$5="1º Quartil",IFERROR(IF(OR(C38="",Q38=0,Q38=""),"",($C38/$O38)),""), 'Painel Geral'!$B$5="Média",IFERROR(IF(OR(C38="",Q38=0,Q38=""),"",($C38/$P38)),""),'Painel Geral'!$B$5="3º Quartil",IFERROR(IF(OR(C38="",Q38=0,Q38=""),"",($C38/$R38)),""),'Painel Geral'!$B$5="Maior Salário",IFERROR(IF(OR(C38="",Q38=0,Q38=""),"",($C38/$S38)),"")) -> 0.4232889 | U38: =IFS(OR(N38="",N38=0,C38="", C38=0),"",T38<=80%,"Muito Defasado",T38<=90%,"Defasado",T38<=100%,"Na Média",T38<=110%,"Competitivo",T38<=120%,"Muito Competitivo",T38>120%,"Agressivo") -> Muito Defasado | Z38: 17 | AA38: =-4466+1611*Z38-155*Z38*Z38+6.19*Z38*Z38*Z38 -> 8537.47 | AB38: =(AA38-AA37)/AA37 -> 0.2223907
A39: 44 | B39: =VLOOKUP(A39,Jobmatch!A:G,2,0) -> GERENTE DE EDIFICAÇÕES | C39: =IFERROR(AVERAGEIF('Folha de Pagamento'!A:A,A39,'Folha de Pagamento'!J:J),"") -> 30106.061 | D39: 5 | E39: =VLOOKUP(A39,Jobmatch!A:H,3,0) -> Edificação | F39: Gerente Edificações | G39: =VLOOKUP(A39,Jobmatch!A:I,4,0) -> 51 - ADM PROJETOS | H39: =VLOOKUP(A39,Jobmatch!A:I,5,0) -> Tático | I39: =VLOOKUP(A39,Jobmatch!A:I,6,0) -> 311 | J39: =VLOOKUP(A39,Jobmatch!A:I,7,0) -> Gerente de Operações | K39: =VLOOKUP(A39,Jobmatch!A:I,8,0) -> Indiferente | L39: =I39&K39 -> 311Indiferente | M39: =COUNTIF('Folha de Pagamento'!A:A,A39) -> 1 | N39: 19 | O39: =IFERROR(VLOOKUP(L39,'C-01'!$D:$L,5,0),"") -> 10114.75 | P39: =IFERROR(VLOOKUP(L39,'C-01'!$D:$L,6,0),"") -> 12711.42 | Q39: =IFERROR(VLOOKUP(L39,'C-01'!$D:$L,7,0),"") -> 12517.82 | R39: =IFERROR(VLOOKUP(L39,'C-01'!$D:$L,8,0),"") -> 14749 | S39: =IFERROR(VLOOKUP(L39,'C-01'!$D:$L,9,0),"") -> 19098.65 | T39: =IFS('Painel Geral'!$B$5="Mediana",IFERROR(IF(OR(C39="",Q39=0,Q39=""),"",($C39/$Q39)),""),'Painel Geral'!$B$5="Menor Salário",IFERROR(IF(OR(C39="",Q39=0,Q39=""),"",($C39/$N39)),""),'Painel Geral'!$B$5="1º Quartil",IFERROR(IF(OR(C39="",Q39=0,Q39=""),"",($C39/$O39)),""), 'Painel Geral'!$B$5="Média",IFERROR(IF(OR(C39="",Q39=0,Q39=""),"",($C39/$P39)),""),'Painel Geral'!$B$5="3º Quartil",IFERROR(IF(OR(C39="",Q39=0,Q39=""),"",($C39/$R39)),""),'Painel Geral'!$B$5="Maior Salário",IFERROR(IF(OR(C39="",Q39=0,Q39=""),"",($C39/$S39)),"")) -> 2.4050562 | U39: =IFS(OR(N39="",N39=0,C39="", C39=0),"",T39<=80%,"Muito Defasado",T39<=90%,"Defasado",T39<=100%,"Na Média",T39<=110%,"Competitivo",T39<=120%,"Muito Competitivo",T39>120%,"Agressivo") -> Agressivo | Z39: 18 | AA39: =-4466+1611*Z39-155*Z39*Z39+6.19*Z39*Z39*Z39 -> 10412.08 | AB39: =(AA39-AA38)/AA38 -> 0.21957442
A40: 50 | B40: =VLOOKUP(A40,Jobmatch!A:G,2,0) -> GERENTE DE URBANISMO | C40: =IFERROR(AVERAGEIF('Folha de Pagamento'!A:A,A40,'Folha de Pagamento'!J:J),"") -> 28030.303 | D40: 10 | E40: =VLOOKUP(A40,Jobmatch!A:H,3,0) -> Urbanismo | F40: Gerente Urbanismo | G40: =VLOOKUP(A40,Jobmatch!A:I,4,0) -> 57 - ADM PROJETOS | H40: =VLOOKUP(A40,Jobmatch!A:I,5,0) -> Tático | I40: =VLOOKUP(A40,Jobmatch!A:I,6,0) -> 311 | J40: =VLOOKUP(A40,Jobmatch!A:I,7,0) -> Gerente de Operações | K40: =VLOOKUP(A40,Jobmatch!A:I,8,0) -> Indiferente | L40: =I40&K40 -> 311Indiferente | M40: =COUNTIF('Folha de Pagamento'!A:A,A40) -> 2 | N40: 19 | O40: =IFERROR(VLOOKUP(L40,'C-01'!$D:$L,5,0),"") -> 10114.75 | P40: =IFERROR(VLOOKUP(L40,'C-01'!$D:$L,6,0),"") -> 12711.42 | Q40: =IFERROR(VLOOKUP(L40,'C-01'!$D:$L,7,0),"") -> 12517.82 | R40: =IFERROR(VLOOKUP(L40,'C-01'!$D:$L,8,0),"") -> 14749 | S40: =IFERROR(VLOOKUP(L40,'C-01'!$D:$L,9,0),"") -> 19098.65 | T40: =IFS('Painel Geral'!$B$5="Mediana",IFERROR(IF(OR(C40="",Q40=0,Q40=""),"",($C40/$Q40)),""),'Painel Geral'!$B$5="Menor Salário",IFERROR(IF(OR(C40="",Q40=0,Q40=""),"",($C40/$N40)),""),'Painel Geral'!$B$5="1º Quartil",IFERROR(IF(OR(C40="",Q40=0,Q40=""),"",($C40/$O40)),""), 'Painel Geral'!$B$5="Média",IFERROR(IF(OR(C40="",Q40=0,Q40=""),"",($C40/$P40)),""),'Painel Geral'!$B$5="3º Quartil",IFERROR(IF(OR(C40="",Q40=0,Q40=""),"",($C40/$R40)),""),'Painel Geral'!$B$5="Maior Salário",IFERROR(IF(OR(C40="",Q40=0,Q40=""),"",($C40/$S40)),"")) -> 2.239232 | U40: =IFS(OR(N40="",N40=0,C40="", C40=0),"",T40<=80%,"Muito Defasado",T40<=90%,"Defasado",T40<=100%,"Na Média",T40<=110%,"Competitivo",T40<=120%,"Muito Competitivo",T40>120%,"Agressivo") -> Agressivo | Z40: 19 | AA40: =-4466+1611*Z40-155*Z40*Z40+6.19*Z40*Z40*Z40 -> 12645.21 | AB40: =(AA40-AA39)/AA39 -> 0.21447492
A41: 27 | B41: =VLOOKUP(A41,Jobmatch!A:G,2,0) -> COORDENADOR DE DHO | C41: =IFERROR(AVERAGEIF('Folha de Pagamento'!A:A,A41,'Folha de Pagamento'!J:J),"") -> 7420 | D41: 4 | E41: =VLOOKUP(A41,Jobmatch!A:H,3,0) -> DHO | F41: Coordenador DHO | G41: =VLOOKUP(A41,Jobmatch!A:I,4,0) -> 34 - ADM PROJETOS | H41: =VLOOKUP(A41,Jobmatch!A:I,5,0) -> Tático | I41: =VLOOKUP(A41,Jobmatch!A:I,6,0) -> 121 | J41: =VLOOKUP(A41,Jobmatch!A:I,7,0) -> Coordenador de Recursos Humanos | K41: =VLOOKUP(A41,Jobmatch!A:I,8,0) -> Indiferente | L41: =I41&K41 -> 121Indiferente | M41: =COUNTIF('Folha de Pagamento'!A:A,A41) -> 1 | N41: 19 | O41: =IFERROR(VLOOKUP(L41,'C-01'!$D:$L,5,0),"") -> 10014.8 | P41: =IFERROR(VLOOKUP(L41,'C-01'!$D:$L,6,0),"") -> 11303.85 | Q41: =IFERROR(VLOOKUP(L41,'C-01'!$D:$L,7,0),"") -> 12568.77 | R41: =IFERROR(VLOOKUP(L41,'C-01'!$D:$L,8,0),"") -> 13225.36 | S41: =IFERROR(VLOOKUP(L41,'C-01'!$D:$L,9,0),"") -> 13881.95 | T41: =IFS('Painel Geral'!$B$5="Mediana",IFERROR(IF(OR(C41="",Q41=0,Q41=""),"",($C41/$Q41)),""),'Painel Geral'!$B$5="Menor Salário",IFERROR(IF(OR(C41="",Q41=0,Q41=""),"",($C41/$N41)),""),'Painel Geral'!$B$5="1º Quartil",IFERROR(IF(OR(C41="",Q41=0,Q41=""),"",($C41/$O41)),""), 'Painel Geral'!$B$5="Média",IFERROR(IF(OR(C41="",Q41=0,Q41=""),"",($C41/$P41)),""),'Painel Geral'!$B$5="3º Quartil",IFERROR(IF(OR(C41="",Q41=0,Q41=""),"",($C41/$R41)),""),'Painel Geral'!$B$5="Maior Salário",IFERROR(IF(OR(C41="",Q41=0,Q41=""),"",($C41/$S41)),"")) -> 0.59035212 | U41: =IFS(OR(N41="",N41=0,C41="", C41=0),"",T41<=80%,"Muito Defasado",T41<=90%,"Defasado",T41<=100%,"Na Média",T41<=110%,"Competitivo",T41<=120%,"Muito Competitivo",T41>120%,"Agressivo") -> Muito Defasado | Z41: 20 | AA41: =-4466+1611*Z41-155*Z41*Z41+6.19*Z41*Z41*Z41 -> 15274 | AB41: =(AA41-AA40)/AA40 -> 0.2078882
A42: 26 | B42: =VLOOKUP(A42,Jobmatch!A:G,2,0) -> CONTROLLER TÉCNICO | C42: =IFERROR(AVERAGEIF('Folha de Pagamento'!A:A,A42,'Folha de Pagamento'!J:J),"") -> 9243.5037 | D42: 3 | E42: =VLOOKUP(A42,Jobmatch!A:H,3,0) -> Controladoria | F42: Controller Técnico | G42: =VLOOKUP(A42,Jobmatch!A:I,4,0) -> 33 - ADM PROJETOS | H42: =VLOOKUP(A42,Jobmatch!A:I,5,0) -> Tático | I42: =VLOOKUP(A42,Jobmatch!A:I,6,0) -> 26 | J42: =VLOOKUP(A42,Jobmatch!A:I,7,0) -> Analista de Controladoria | K42: =VLOOKUP(A42,Jobmatch!A:I,8,0) -> Especialista | L42: =I42&K42 -> 26Especialista | M42: =COUNTIF('Folha de Pagamento'!A:A,A42) -> 1 | N42: 19 | O42: =IFERROR(VLOOKUP(L42,'C-01'!$D:$L,5,0),"") -> 10665.2 | P42: =IFERROR(VLOOKUP(L42,'C-01'!$D:$L,6,0),"") -> 12572.61 | Q42: =IFERROR(VLOOKUP(L42,'C-01'!$D:$L,7,0),"") -> 13758.75 | R42: =IFERROR(VLOOKUP(L42,'C-01'!$D:$L,8,0),"") -> 15666.17 | S42: =IFERROR(VLOOKUP(L42,'C-01'!$D:$L,9,0),"") -> 15995.86 | T42: =IFS('Painel Geral'!$B$5="Mediana",IFERROR(IF(OR(C42="",Q42=0,Q42=""),"",($C42/$Q42)),""),'Painel Geral'!$B$5="Menor Salário",IFERROR(IF(OR(C42="",Q42=0,Q42=""),"",($C42/$N42)),""),'Painel Geral'!$B$5="1º Quartil",IFERROR(IF(OR(C42="",Q42=0,Q42=""),"",($C42/$O42)),""), 'Painel Geral'!$B$5="Média",IFERROR(IF(OR(C42="",Q42=0,Q42=""),"",($C42/$P42)),""),'Painel Geral'!$B$5="3º Quartil",IFERROR(IF(OR(C42="",Q42=0,Q42=""),"",($C42/$R42)),""),'Painel Geral'!$B$5="Maior Salário",IFERROR(IF(OR(C42="",Q42=0,Q42=""),"",($C42/$S42)),"")) -> 0.67182728 | U42: =IFS(OR(N42="",N42=0,C42="", C42=0),"",T42<=80%,"Muito Defasado",T42<=90%,"Defasado",T42<=100%,"Na Média",T42<=110%,"Competitivo",T42<=120%,"Muito Competitivo",T42>120%,"Agressivo") -> Muito Defasado | Z42: 21 | AA42: =-4466+1611*Z42-155*Z42*Z42+6.19*Z42*Z42*Z42 -> 18335.59 | AB42: =(AA42-AA41)/AA41 -> 0.20044455
A43: 37 | B43: =VLOOKUP(A43,Jobmatch!A:G,2,0) -> ENGENHEIRO SÊNIOR | C43: =IFERROR(AVERAGEIF('Folha de Pagamento'!A:A,A43,'Folha de Pagamento'!J:J),"") -> 14393.939 | D43: 5 | E43: =VLOOKUP(A43,Jobmatch!A:H,3,0) -> Edificação | F43: Engenheiro Sr | G43: =VLOOKUP(A43,Jobmatch!A:I,4,0) -> 44 - ADM PROJETOS | H43: =VLOOKUP(A43,Jobmatch!A:I,5,0) -> Tático | I43: =VLOOKUP(A43,Jobmatch!A:I,6,0) -> 212 | J43: =VLOOKUP(A43,Jobmatch!A:I,7,0) -> Engenheiro de Urbanismo | K43: =VLOOKUP(A43,Jobmatch!A:I,8,0) -> Indiferente | L43: =I43&K43 -> 212Indiferente | M43: =COUNTIF('Folha de Pagamento'!A:A,A43) -> 1 | N43: 20 | O43: =IFERROR(VLOOKUP(L43,'C-01'!$D:$L,5,0),"") -> 12766.6 | P43: =IFERROR(VLOOKUP(L43,'C-01'!$D:$L,6,0),"") -> 14293.39 | Q43: =IFERROR(VLOOKUP(L43,'C-01'!$D:$L,7,0),"") -> 15082.52 | R43: =IFERROR(VLOOKUP(L43,'C-01'!$D:$L,8,0),"") -> 16110.29 | S43: =IFERROR(VLOOKUP(L43,'C-01'!$D:$L,9,0),"") -> 16164.64 | T43: =IFS('Painel Geral'!$B$5="Mediana",IFERROR(IF(OR(C43="",Q43=0,Q43=""),"",($C43/$Q43)),""),'Painel Geral'!$B$5="Menor Salário",IFERROR(IF(OR(C43="",Q43=0,Q43=""),"",($C43/$N43)),""),'Painel Geral'!$B$5="1º Quartil",IFERROR(IF(OR(C43="",Q43=0,Q43=""),"",($C43/$O43)),""), 'Painel Geral'!$B$5="Média",IFERROR(IF(OR(C43="",Q43=0,Q43=""),"",($C43/$P43)),""),'Painel Geral'!$B$5="3º Quartil",IFERROR(IF(OR(C43="",Q43=0,Q43=""),"",($C43/$R43)),""),'Painel Geral'!$B$5="Maior Salário",IFERROR(IF(OR(C43="",Q43=0,Q43=""),"",($C43/$S43)),"")) -> 0.95434579 | U43: =IFS(OR(N43="",N43=0,C43="", C43=0),"",T43<=80%,"Muito Defasado",T43<=90%,"Defasado",T43<=100%,"Na Média",T43<=110%,"Competitivo",T43<=120%,"Muito Competitivo",T43>120%,"Agressivo") -> Na Média | Z43: 22 | AA43: =-4466+1611*Z43-155*Z43*Z43+6.19*Z43*Z43*Z43 -> 21867.12 | AB43: =(AA43-AA42)/AA42 -> 0.1926052
... A47: 33 | B47: =VLOOKUP(A47,Jobmatch!A:G,2,0) -> DIRETOR | C47: =IFERROR(AVERAGEIF('Folha de Pagamento'!A:A,A47,'Folha de Pagamento'!J:J),"") -> 55769.231 | D47: 2 | E47: =VLOOKUP(A47,Jobmatch!A:H,3,0) -> Comercial | F47: Diretor | G47: =VLOOKUP(A47,Jobmatch!A:I,4,0) -> 40 - ADM PROJETOS | H47: =VLOOKUP(A47,Jobmatch!A:I,5,0) -> Estratégico | I47: =VLOOKUP(A47,Jobmatch!A:I,6,0) -> 456 | J47: =VLOOKUP(A47,Jobmatch!A:I,7,0) -> CEO | K47: =VLOOKUP(A47,Jobmatch!A:I,8,0) -> Indiferente | L47: =I47&K47 -> 456Indiferente | M47: =COUNTIF('Folha de Pagamento'!A:A,A47) -> 1 | N47: 24 | O47: =IFERROR(VLOOKUP(L47,'C-01'!$D:$L,5,0),"") -> 24816.78 | P47: =IFERROR(VLOOKUP(L47,'C-01'!$D:$L,6,0),"") -> 32648.36 | Q47: =IFERROR(VLOOKUP(L47,'C-01'!$D:$L,7,0),"") -> 29147.75 | R47: =IFERROR(VLOOKUP(L47,'C-01'!$D:$L,8,0),"") -> 37122.89 | S47: =IFERROR(VLOOKUP(L47,'C-01'!$D:$L,9,0),"") -> 55429.54 | T47: =IFS('Painel Geral'!$B$5="Mediana",IFERROR(IF(OR(C47="",Q47=0,Q47=""),"",($C47/$Q47)),""),'Painel Geral'!$B$5="Menor Salário",IFERROR(IF(OR(C47="",Q47=0,Q47=""),"",($C47/$N47)),""),'Painel Geral'!$B$5="1º Quartil",IFERROR(IF(OR(C47="",Q47=0,Q47=""),"",($C47/$O47)),""), 'Painel Geral'!$B$5="Média",IFERROR(IF(OR(C47="",Q47=0,Q47=""),"",($C47/$P47)),""),'Painel Geral'!$B$5="3º Quartil",IFERROR(IF(OR(C47="",Q47=0,Q47=""),"",($C47/$R47)),""),'Painel Geral'!$B$5="Maior Salário",IFERROR(IF(OR(C47="",Q47=0,Q47=""),"",($C47/$S47)),"")) -> 1.9133288 | U47: =IFS(OR(N47="",N47=0,C47="", C47=0),"",T47<=80%,"Muito Defasado",T47<=90%,"Defasado",T47<=100%,"Na Média",T47<=110%,"Competitivo",T47<=120%,"Muito Competitivo",T47>120%,"Agressivo") -> Agressivo | Z47: 26 | AA47: =-4466+1611*Z47-155*Z47*Z47+6.19*Z47*Z47*Z47 -> 41435.44 | AB47: =(AA47-AA46)/AA46 -> 0.16219478
N48: 28 | Q48: 55769.231 | Z48: 27 | AA48: =-4466+1611*Z48-155*Z48*Z48+6.19*Z48*Z48*Z48 -> 47873.77 | AB48: =(AA48-AA47)/AA47 -> 0.1553822
Z49: 28 | AA49: =-4466+1611*Z49-155*Z49*Z49+6.19*Z49*Z49*Z49 -> 55004.88 | AB49: =(AA49-AA48)/AA48 -> 0.14895652

Sheet Tabela
I1: DADOS PARA COMPARAÇÃO | O1: ='Informações Relevantes Cenário'!A1 -> Cenário 01: Pesquisas Consolidadas - Nacional | T1: ="% Distância da "&'Painel Geral'!B5 -> % Distância da Mediana | U1: Posicionamento
A3: Cod. | B3: Cargos Empresa | C3: Média Empresa | D3: Cod. Área | E3: Diretoria | F3: Novo Cargo | G3: Centro de Custo | H3: Nível Organizacional | I3: Cod. Pesquisa | J3: Cargos Pesquisa | K3: Senioridade | L3: Código+Senioridade | M3: Número de Colaboradores | O3: 1º Quartil | P3: Média | Q3: Mediana | R3: 3º Quartil | S3: Maior Salário | T3: C-01 | U3: C-01 (Posicionamento)
A4: 22 | B4: =VLOOKUP(A4,Jobmatch!A:G,2,0) -> AUXILIAR DE ATENDIMENTO II | C4: =IFERROR(AVERAGEIF('Folha de Pagamento'!A:A,A4,'Folha de Pagamento'!J:J),"") -> 2560 | D4: 1 | E4: =VLOOKUP(A4,Jobmatch!A:H,3,0) -> Recepção | F4: Auxiliar Atendimento | G4: =VLOOKUP(A4,Jobmatch!A:I,4,0) -> 29 - ADM PROJETOS | H4: =VLOOKUP(A4,Jobmatch!A:I,5,0) -> Operacional | I4: =VLOOKUP(A4,Jobmatch!A:I,6,0) -> 318 | J4: =VLOOKUP(A4,Jobmatch!A:I,7,0) -> Auxiliar de Atendimento | K4: =VLOOKUP(A4,Jobmatch!A:I,8,0) -> Indiferente | L4: =I4&K4 -> 318Indiferente | M4: =COUNTIF('Folha de Pagamento'!A:A,A4) -> 1 | N4: 10 | O4: =IFERROR(VLOOKUP(L4,'C-01'!$D:$L,5,0),"") -> 1778.55 | P4: =IFERROR(VLOOKUP(L4,'C-01'!$D:$L,6,0),"") -> 2041.06 | Q4: =IFERROR(VLOOKUP(L4,'C-01'!$D:$L,7,0),"") -> 2052.94 | R4: =IFERROR(VLOOKUP(L4,'C-01'!$D:$L,8,0),"") -> 2169.15 | S4: =IFERROR(VLOOKUP(L4,'C-01'!$D:$L,9,0),"") -> 2574.08 | T4: =IFS('Painel Geral'!$B$5="Mediana",IFERROR(IF(OR(C4="",Q4=0,Q4=""),"",($C4/$Q4)),""),'Painel Geral'!$B$5="Menor Salário",IFERROR(IF(OR(C4="",Q4=0,Q4=""),"",($C4/$N4)),""),'Painel Geral'!$B$5="1º Quartil",IFERROR(IF(OR(C4="",Q4=0,Q4=""),"",($C4/$O4)),""), 'Painel Geral'!$B$5="Média",IFERROR(IF(OR(C4="",Q4=0,Q4=""),"",($C4/$P4)),""),'Painel Geral'!$B$5="3º Quartil",IFERROR(IF(OR(C4="",Q4=0,Q4=""),"",($C4/$R4)),""),'Painel Geral'!$B$5="Maior Salário",IFERROR(IF(OR(C4="",Q4=0,Q4=""),"",($C4/$S4)),"")) -> 1.2469921 | U4: =IFS(OR(N4="",N4=0,C4="", C4=0),"",T4<=80%,"Muito Defasado",T4<=90%,"Defasado",T4<=100%,"Na Média",T4<=110%,"Competitivo",T4<=120%,"Muito Competitivo",T4>120%,"Agressivo") -> Agressivo | V4: =Q4*1.2 -> 2463.528 | W4: =V4*1.2 -> 2956.2336 | X4: =W4*1.2 -> 3547.4803 | Y4: =X4*1.2 -> 4256.9764 | Z4: =Y4*1.2 -> 5108.3717 | AA4: =Z4*1.2 -> 6130.046 | AB4: =AA4*1.2 -> 7356.0552 | AC4: =AB4*1.2 -> 8827.2662 | AD4: =AC4*1.2 -> 10592.719 | ... AJ4: =AI4*1.2 -> 31629.691
A5: 20 | B5: =VLOOKUP(A5,Jobmatch!A:G,2,0) -> AUXILIAR ADMINISTRATIVO | C5: =IFERROR(AVERAGEIF('Folha de Pagamento'!A:A,A5,'Folha de Pagamento'!J:J),"") -> 2254 | D5: 1 | E5: =VLOOKUP(A5,Jobmatch!A:H,3,0) -> Administrativo | F5: Auxiliar Administrativo | G5: =VLOOKUP(A5,Jobmatch!A:I,4,0) -> 27 - ADM PROJETOS | H5: =VLOOKUP(A5,Jobmatch!A:I,5,0) -> Operacional | I5: =VLOOKUP(A5,Jobmatch!A:I,6,0) -> 83 | J5: =VLOOKUP(A5,Jobmatch!A:I,7,0) -> Auxiliar Administrativo | K5: =VLOOKUP(A5,Jobmatch!A:I,8,0) -> Indiferente | L5: =I5&K5 -> 83Indiferente | M5: =COUNTIF('Folha de Pagamento'!A:A,A5) -> 1 | N5: 10 | O5: =IFERROR(VLOOKUP(L5,'C-01'!$D:$L,5,0),"") -> 2128.74 | P5: =IFERROR(VLOOKUP(L5,'C-01'!$D:$L,6,0),"") -> 2292.87 | Q5: =IFERROR(VLOOKUP(L5,'C-01'!$D:$L,7,0),"") -> 2309.71 | R5: =IFERROR(VLOOKUP(L5,'C-01'!$D:$L,8,0),"") -> 2375.14 | S5: =IFERROR(VLOOKUP(L5,'C-01'!$D:$L,9,0),"") -> 3073.32 | T5: =IFS('Painel Geral'!$B$5="Mediana",IFERROR(IF(OR(C5="",Q5=0,Q5=""),"",($C5/$Q5)),""),'Painel Geral'!$B$5="Menor Salário",IFERROR(IF(OR(C5="",Q5=0,Q5=""),"",($C5/$N5)),""),'Painel Geral'!$B$5="1º Quartil",IFERROR(IF(OR(C5="",Q5=0,Q5=""),"",($C5/$O5)),""), 'Painel Geral'!$B$5="Média",IFERROR(IF(OR(C5="",Q5=0,Q5=""),"",($C5/$P5)),""),'Painel Geral'!$B$5="3º Quartil",IFERROR(IF(OR(C5="",Q5=0,Q5=""),"",($C5/$R5)),""),'Painel Geral'!$B$5="Maior Salário",IFERROR(IF(OR(C5="",Q5=0,Q5=""),"",($C5/$S5)),"")) -> 0.97588009 | U5: =IFS(OR(N5="",N5=0,C5="", C5=0),"",T5<=80%,"Muito Defasado",T5<=90%,"Defasado",T5<=100%,"Na Média",T5<=110%,"Competitivo",T5<=120%,"Muito Competitivo",T5>120%,"Agressivo") -> Na Média | V5: 10 | W5: 11 | X5: 12 | Y5: 13 | Z5: 14 | AA5: 15 | AB5: 16 | AC5: 17 | AD5: 18 | AE5: 19 | AF5: 20 | AG5: 21 | AH5: 22 | AI5: 23 | AJ5: 24
A6: 21 | B6: =VLOOKUP(A6,Jobmatch!A:G,2,0) -> AUXILIAR ADMINISTRATIVO III | C6: =IFERROR(AVERAGEIF('Folha de Pagamento'!A:A,A6,'Folha de Pagamento'!J:J),"") -> 2739.04 | D6: 1 | E6: =VLOOKUP(A6,Jobmatch!A:H,3,0) -> Administrativo | F6: Auxiliar Administrativo | G6: =VLOOKUP(A6,Jobmatch!A:I,4,0) -> 28 - ADM PROJETOS | H6: =VLOOKUP(A6,Jobmatch!A:I,5,0) -> Operacional | I6: =VLOOKUP(A6,Jobmatch!A:I,6,0) -> 83 | J6: =VLOOKUP(A6,Jobmatch!A:I,7,0) -> Auxiliar Administrativo | K6: =VLOOKUP(A6,Jobmatch!A:I,8,0) -> Indiferente | L6: =I6&K6 -> 83Indiferente | M6: =COUNTIF('Folha de Pagamento'!A:A,A6) -> 1 | N6: 10 | O6: =IFERROR(VLOOKUP(L6,'C-01'!$D:$L,5,0),"") -> 2128.74 | P6: =IFERROR(VLOOKUP(L6,'C-01'!$D:$L,6,0),"") -> 2292.87 | Q6: =IFERROR(VLOOKUP(L6,'C-01'!$D:$L,7,0),"") -> 2309.71 | R6: =IFERROR(VLOOKUP(L6,'C-01'!$D:$L,8,0),"") -> 2375.14 | S6: =IFERROR(VLOOKUP(L6,'C-01'!$D:$L,9,0),"") -> 3073.32 | T6: =IFS('Painel Geral'!$B$5="Mediana",IFERROR(IF(OR(C6="",Q6=0,Q6=""),"",($C6/$Q6)),""),'Painel Geral'!$B$5="Menor Salário",IFERROR(IF(OR(C6="",Q6=0,Q6=""),"",($C6/$N6)),""),'Painel Geral'!$B$5="1º Quartil",IFERROR(IF(OR(C6="",Q6=0,Q6=""),"",($C6/$O6)),""), 'Painel Geral'!$B$5="Média",IFERROR(IF(OR(C6="",Q6=0,Q6=""),"",($C6/$P6)),""),'Painel Geral'!$B$5="3º Quartil",IFERROR(IF(OR(C6="",Q6=0,Q6=""),"",($C6/$R6)),""),'Painel Geral'!$B$5="Maior Salário",IFERROR(IF(OR(C6="",Q6=0,Q6=""),"",($C6/$S6)),"")) -> 1.1858805 | U6: =IFS(OR(N6="",N6=0,C6="", C6=0),"",T6<=80%,"Muito Defasado",T6<=90%,"Defasado",T6<=100%,"Na Média",T6<=110%,"Competitivo",T6<=120%,"Muito Competitivo",T6>120%,"Agressivo") -> Muito Competitivo
A7: 18 | B7: =VLOOKUP(A7,Jobmatch!A:G,2,0) -> ASSISTENTE DE TI | C7: =IFERROR(AVERAGEIF('Folha de Pagamento'!A:A,A7,'Folha de Pagamento'!J:J),"") -> 2919 | D7: 1 | E7: =VLOOKUP(A7,Jobmatch!A:H,3,0) -> Tecnologia da Informação | F7: Assistente TI | G7: =VLOOKUP(A7,Jobmatch!A:I,4,0) -> 25 - ADM PROJETOS | H7: =VLOOKUP(A7,Jobmatch!A:I,5,0) -> Operacional | I7: =VLOOKUP(A7,Jobmatch!A:I,6,0) -> 31 | J7: =VLOOKUP(A7,Jobmatch!A:I,7,0) -> Assistente de Tecnologia da Informação | K7: =VLOOKUP(A7,Jobmatch!A:I,8,0) -> Indiferente | L7: =I7&K7 -> 31Indiferente | M7: =COUNTIF('Folha de Pagamento'!A:A,A7) -> 2 | N7: 10 | O7: =IFERROR(VLOOKUP(L7,'C-01'!$D:$L,5,0),"") -> 2066.4 | P7: =IFERROR(VLOOKUP(L7,'C-01'!$D:$L,6,0),"") -> 2589.89 | Q7: =IFERROR(VLOOKUP(L7,'C-01'!$D:$L,7,0),"") -> 2413.7 | R7: =IFERROR(VLOOKUP(L7,'C-01'!$D:$L,8,0),"") -> 3121.21 | S7: =IFERROR(VLOOKUP(L7,'C-01'!$D:$L,9,0),"") -> 3521.6 | T7: =IFS('Painel Geral'!$B$5="Mediana",IFERROR(IF(OR(C7="",Q7=0,Q7=""),"",($C7/$Q7)),""),'Painel Geral'!$B$5="Menor Salário",IFERROR(IF(OR(C7="",Q7=0,Q7=""),"",($C7/$N7)),""),'Painel Geral'!$B$5="1º Quartil",IFERROR(IF(OR(C7="",Q7=0,Q7=""),"",($C7/$O7)),""), 'Painel Geral'!$B$5="Média",IFERROR(IF(OR(C7="",Q7=0,Q7=""),"",($C7/$P7)),""),'Painel Geral'!$B$5="3º Quartil",IFERROR(IF(OR(C7="",Q7=0,Q7=""),"",($C7/$R7)),""),'Painel Geral'!$B$5="Maior Salário",IFERROR(IF(OR(C7="",Q7=0,Q7=""),"",($C7/$S7)),"")) -> 1.2093466 | U7: =IFS(OR(N7="",N7=0,C7="", C7=0),"",T7<=80%,"Muito Defasado",T7<=90%,"Defasado",T7<=100%,"Na Média",T7<=110%,"Competitivo",T7<=120%,"Muito Competitivo",T7>120%,"Agressivo") -> Agressivo
A8: 13 | B8: =VLOOKUP(A8,Jobmatch!A:G,2,0) -> ASSISTENTE ADMINISTRATIVO lll | C8: =IFERROR(AVERAGEIF('Folha de Pagamento'!A:A,A8,'Folha de Pagamento'!J:J),"") -> 3439.7 | D8: 1 | E8: =VLOOKUP(A8,Jobmatch!A:H,3,0) -> Administrativo | F8: Assistente Administrativo | G8: =VLOOKUP(A8,Jobmatch!A:I,4,0) -> 20 - ADM PROJETOS | H8: =VLOOKUP(A8,Jobmatch!A:I,5,0) -> Operacional | I8: =VLOOKUP(A8,Jobmatch!A:I,6,0) -> 59 | J8: =VLOOKUP(A8,Jobmatch!A:I,7,0) -> Assistente Administrativo | K8: =VLOOKUP(A8,Jobmatch!A:I,8,0) -> Indiferente | L8: =I8&K8 -> 59Indiferente | M8: =COUNTIF('Folha de Pagamento'!A:A,A8) -> 1 | N8: 11 | O8: =IFERROR(VLOOKUP(L8,'C-01'!$D:$L,5,0),"") -> 2329.53 | P8: =IFERROR(VLOOKUP(L8,'C-01'!$D:$L,6,0),"") -> 2673.92 | Q8: =IFERROR(VLOOKUP(L8,'C-01'!$D:$L,7,0),"") -> 2630.61 | R8: =IFERROR(VLOOKUP(L8,'C-01'!$D:$L,8,0),"") -> 2914.75 | S8: =IFERROR(VLOOKUP(L8,'C-01'!$D:$L,9,0),"") -> 3662.52 | T8: =IFS('Painel Geral'!$B$5="Mediana",IFERROR(IF(OR(C8="",Q8=0,Q8=""),"",($C8/$Q8)),""),'Painel Geral'!$B$5="Menor Salário",IFERROR(IF(OR(C8="",Q8=0,Q8=""),"",($C8/$N8)),""),'Painel Geral'!$B$5="1º Quartil",IFERROR(IF(OR(C8="",Q8=0,Q8=""),"",($C8/$O8)),""), 'Painel Geral'!$B$5="Média",IFERROR(IF(OR(C8="",Q8=0,Q8=""),"",($C8/$P8)),""),'Painel Geral'!$B$5="3º Quartil",IFERROR(IF(OR(C8="",Q8=0,Q8=""),"",($C8/$R8)),""),'Painel Geral'!$B$5="Maior Salário",IFERROR(IF(OR(C8="",Q8=0,Q8=""),"",($C8/$S8)),"")) -> 1.3075674 | U8: =IFS(OR(N8="",N8=0,C8="", C8=0),"",T8<=80%,"Muito Defasado",T8<=90%,"Defasado",T8<=100%,"Na Média",T8<=110%,"Competitivo",T8<=120%,"Muito Competitivo",T8>120%,"Agressivo") -> Agressivo
A9: 19 | B9: =VLOOKUP(A9,Jobmatch!A:G,2,0) -> ASSISTENTE FINANCEIRO CONTAS A PAGAR | C9: =IFERROR(AVERAGEIF('Folha de Pagamento'!A:A,A9,'Folha de Pagamento'!J:J),"") -> 3163.3333 | D9: 6 | E9: =VLOOKUP(A9,Jobmatch!A:H,3,0) -> Financeiro | F9: Assistente Financeiro Contas a Pagar | G9: =VLOOKUP(A9,Jobmatch!A:I,4,0) -> 26 - ADM PROJETOS | H9: =VLOOKUP(A9,Jobmatch!A:I,5,0) -> Operacional | I9: =VLOOKUP(A9,Jobmatch!A:I,6,0) -> 79 | J9: =VLOOKUP(A9,Jobmatch!A:I,7,0) -> Assistente Financeiro | K9: =VLOOKUP(A9,Jobmatch!A:I,8,0) -> Indiferente | L9: =I9&K9 -> 79Indiferente | M9: =COUNTIF('Folha de Pagamento'!A:A,A9) -> 3 | N9: 11 | O9: =IFERROR(VLOOKUP(L9,'C-01'!$D:$L,5,0),"") -> 2560.05 | P9: =IFERROR(VLOOKUP(L9,'C-01'!$D:$L,6,0),"") -> 2799.02 | Q9: =IFERROR(VLOOKUP(L9,'C-01'!$D:$L,7,0),"") -> 2658.89 | R9: =IFERROR(VLOOKUP(L9,'C-01'!$D:$L,8,0),"") -> 2935.06 | S9: =IFERROR(VLOOKUP(L9,'C-01'!$D:$L,9,0),"") -> 3630.87 | T9: =IFS('Painel Geral'!$B$5="Mediana",IFERROR(IF(OR(C9="",Q9=0,Q9=""),"",($C9/$Q9)),""),'Painel Geral'!$B$5="Menor Salário",IFERROR(IF(OR(C9="",Q9=0,Q9=""),"",($C9/$N9)),""),'Painel Geral'!$B$5="1º Quartil",IFERROR(IF(OR(C9="",Q9=0,Q9=""),"",($C9/$O9)),""), 'Painel Geral'!$B$5="Média",IFERROR(IF(OR(C9="",Q9=0,Q9=""),"",($C9/$P9)),""),'Painel Geral'!$B$5="3º Quartil",IFERROR(IF(OR(C9="",Q9=0,Q9=""),"",($C9/$R9)),""),'Painel Geral'!$B$5="Maior Salário",IFERROR(IF(OR(C9="",Q9=0,Q9=""),"",($C9/$S9)),"")) -> 1.1897195 | U9: =IFS(OR(N9="",N9=0,C9="", C9=0),"",T9<=80%,"Muito Defasado",T9<=90%,"Defasado",T9<=100%,"Na Média",T9<=110%,"Competitivo",T9<=120%,"Muito Competitivo",T9>120%,"Agressivo") -> Muito Competitivo
A10: 23 | B10: =VLOOKUP(A10,Jobmatch!A:G,2,0) -> AUXILIAR DE ENGENHARIA | C10: =IFERROR(AVERAGEIF('Folha de Pagamento'!A:A,A10,'Folha de Pagamento'!J:J),"") -> 2560 | D10: 10 | E10: =VLOOKUP(A10,Jobmatch!A:H,3,0) -> Urbanismo | F10: Auxiliar Engenharia | G10: =VLOOKUP(A10,Jobmatch!A:I,4,0) -> 30 - ADM PROJETOS | H10: =VLOOKUP(A10,Jobmatch!A:I,5,0) -> Operacional | I10: =VLOOKUP(A10,Jobmatch!A:I,6,0) -> 207 | J10: =VLOOKUP(A10,Jobmatch!A:I,7,0) -> Auxiliar de Engenharia | K10: =VLOOKUP(A10,Jobmatch!A:I,8,0) -> Indiferente | L10: =I10&K10 -> 207Indiferente | M10: =COUNTIF('Folha de Pagamento'!A:A,A10) -> 1 | N10: 11 | O10: =IFERROR(VLOOKUP(L10,'C-01'!$D:$L,5,0),"") -> 2644.47 | P10: =IFERROR(VLOOKUP(L10,'C-01'!$D:$L,6,0),"") -> 2819.08 | Q10: =IFERROR(VLOOKUP(L10,'C-01'!$D:$L,7,0),"") -> 2714.85 | R10: =IFERROR(VLOOKUP(L10,'C-01'!$D:$L,8,0),"") -> 2941.58 | S10: =IFERROR(VLOOKUP(L10,'C-01'!$D:$L,9,0),"") -> 3168.31 | T10: =IFS('Painel Geral'!$B$5="Mediana",IFERROR(IF(OR(C10="",Q10=0,Q10=""),"",($C10/$Q10)),""),'Painel Geral'!$B$5="Menor Salário",IFERROR(IF(OR(C10="",Q10=0,Q10=""),"",($C10/$N10)),""),'Painel Geral'!$B$5="1º Quartil",IFERROR(IF(OR(C10="",Q10=0,Q10=""),"",($C10/$O10)),""), 'Painel Geral'!$B$5="Média",IFERROR(IF(OR(C10="",Q10=0,Q10=""),"",($C10/$P10)),""),'Painel Geral'!$B$5="3º Quartil",IFERROR(IF(OR(C10="",Q10=0,Q10=""),"",($C10/$R10)),""),'Painel Geral'!$B$5="Maior Salário",IFERROR(IF(OR(C10="",Q10=0,Q10=""),"",($C10/$S10)),"")) -> 0.94296186 | U10: =IFS(OR(N10="",N10=0,C10="", C10=0),"",T10<=80%,"Muito Defasado",T10<=90%,"Defasado",T10<=100%,"Na Média",T10<=110%,"Competitivo",T10<=120%,"Muito Competitivo",T10>120%,"Agressivo") -> Na Média
A11: 14 | B11: =VLOOKUP(A11,Jobmatch!A:G,2,0) -> ASSISTENTE DE CONTROLADORIA III | C11: =IFERROR(AVERAGEIF('Folha de Pagamento'!A:A,A11,'Folha de Pagamento'!J:J),"") -> 3652 | D11: 3 | E11: =VLOOKUP(A11,Jobmatch!A:H,3,0) -> Controladoria | F11: Assistente Controladoria | G11: =VLOOKUP(A11,Jobmatch!A:I,4,0) -> 21 - ADM PROJETOS | H11: =VLOOKUP(A11,Jobmatch!A:I,5,0) -> Operacional | I11: =VLOOKUP(A11,Jobmatch!A:I,6,0) -> 150 | J11: =VLOOKUP(A11,Jobmatch!A:I,7,0) -> Assistente de Controladoria | K11: =VLOOKUP(A11,Jobmatch!A:I,8,0) -> Indiferente | L11: =I11&K11 -> 150Indiferente | M11: =COUNTIF('Folha de Pagamento'!A:A,A11) -> 1 | N11: 11 | O11: =IFERROR(VLOOKUP(L11,'C-01'!$D:$L,5,0),"") -> 2640.81 | P11: =IFERROR(VLOOKUP(L11,'C-01'!$D:$L,6,0),"") -> 2821.08 | Q11: =IFERROR(VLOOKUP(L11,'C-01'!$D:$L,7,0),"") -> 2766.4 | R11: =IFERROR(VLOOKUP(L11,'C-01'!$D:$L,8,0),"") -> 3222.24 | S11: =IFERROR(VLOOKUP(L11,'C-01'!$D:$L,9,0),"") -> 3327.42 | T11: =IFS('Painel Geral'!$B$5="Mediana",IFERROR(IF(OR(C11="",Q11=0,Q11=""),"",($C11/$Q11)),""),'Painel Geral'!$B$5="Menor Salário",IFERROR(IF(OR(C11="",Q11=0,Q11=""),"",($C11/$N11)),""),'Painel Geral'!$B$5="1º Quartil",IFERROR(IF(OR(C11="",Q11=0,Q11=""),"",($C11/$O11)),""), 'Painel Geral'!$B$5="Média",IFERROR(IF(OR(C11="",Q11=0,Q11=""),"",($C11/$P11)),""),'Painel Geral'!$B$5="3º Quartil",IFERROR(IF(OR(C11="",Q11=0,Q11=""),"",($C11/$R11)),""),'Painel Geral'!$B$5="Maior Salário",IFERROR(IF(OR(C11="",Q11=0,Q11=""),"",($C11/$S11)),"")) -> 1.3201272 | U11: =IFS(OR(N11="",N11=0,C11="", C11=0),"",T11<=80%,"Muito Defasado",T11<=90%,"Defasado",T11<=100%,"Na Média",T11<=110%,"Competitivo",T11<=120%,"Muito Competitivo",T11>120%,"Agressivo") -> Agressivo
A12: 16 | B12: =VLOOKUP(A12,Jobmatch!A:G,2,0) -> ASSISTENTE DE MARKETING | C12: =IFERROR(AVERAGEIF('Folha de Pagamento'!A:A,A12,'Folha de Pagamento'!J:J),"") -> 2919 | D12: 8 | E12: =VLOOKUP(A12,Jobmatch!A:H,3,0) -> Marketing | F12: Assistente Marketing | G12: =VLOOKUP(A12,Jobmatch!A:I,4,0) -> 23 - ADM PROJETOS | H12: =VLOOKUP(A12,Jobmatch!A:I,5,0) -> Operacional | I12: =VLOOKUP(A12,Jobmatch!A:I,6,0) -> 71 | J12: =VLOOKUP(A12,Jobmatch!A:I,7,0) -> Assistente de Marketing | K12: =VLOOKUP(A12,Jobmatch!A:I,8,0) -> Indiferente | L12: =I12&K12 -> 71Indiferente | M12: =COUNTIF('Folha de Pagamento'!A:A,A12) -> 1 | N12: 11 | O12: =IFERROR(VLOOKUP(L12,'C-01'!$D:$L,5,0),"") -> 2720.21 | P12: =IFERROR(VLOOKUP(L12,'C-01'!$D:$L,6,0),"") -> 3016.74 | Q12: =IFERROR(VLOOKUP(L12,'C-01'!$D:$L,7,0),"") -> 2882.27 | R12: =IFERROR(VLOOKUP(L12,'C-01'!$D:$L,8,0),"") -> 3152.81 | S12: =IFERROR(VLOOKUP(L12,'C-01'!$D:$L,9,0),"") -> 4078.78 | T12: =IFS('Painel Geral'!$B$5="Mediana",IFERROR(IF(OR(C12="",Q12=0,Q12=""),"",($C12/$Q12)),""),'Painel Geral'!$B$5="Menor Salário",IFERROR(IF(OR(C12="",Q12=0,Q12=""),"",($C12/$N12)),""),'Painel Geral'!$B$5="1º Quartil",IFERROR(IF(OR(C12="",Q12=0,Q12=""),"",($C12/$O12)),""), 'Painel Geral'!$B$5="Média",IFERROR(IF(OR(C12="",Q12=0,Q12=""),"",($C12/$P12)),""),'Painel Geral'!$B$5="3º Quartil",IFERROR(IF(OR(C12="",Q12=0,Q12=""),"",($C12/$R12)),""),'Painel Geral'!$B$5="Maior Salário",IFERROR(IF(OR(C12="",Q12=0,Q12=""),"",($C12/$S12)),"")) -> 1.0127434 | U12: =IFS(OR(N12="",N12=0,C12="", C12=0),"",T12<=80%,"Muito Defasado",T12<=90%,"Defasado",T12<=100%,"Na Média",T12<=110%,"Competitivo",T12<=120%,"Muito Competitivo",T12>120%,"Agressivo") -> Competitivo
A13: 17 | B13: =VLOOKUP(A13,Jobmatch!A:G,2,0) -> ASSISTENTE DE RECURSOS HUMANOS | C13: =IFERROR(AVERAGEIF('Folha de Pagamento'!A:A,A13,'Folha de Pagamento'!J:J),"") -> 2919 | D13: 4 | E13: =VLOOKUP(A13,Jobmatch!A:H,3,0) -> DHO | F13: Assistente Recursos Humanos | G13: =VLOOKUP(A13,Jobmatch!A:I,4,0) -> 24 - ADM PROJETOS | H13: =VLOOKUP(A13,Jobmatch!A:I,5,0) -> Operacional | I13: =VLOOKUP(A13,Jobmatch!A:I,6,0) -> 77 | J13: =VLOOKUP(A13,Jobmatch!A:I,7,0) -> Assistente de Recursos Humanos | K13: =VLOOKUP(A13,Jobmatch!A:I,8,0) -> Indiferente | L13: =I13&K13 -> 77Indiferente | M13: =COUNTIF('Folha de Pagamento'!A:A,A13) -> 1 | N13: 12 | O13: =IFERROR(VLOOKUP(L13,'C-01'!$D:$L,5,0),"") -> 2619.08 | P13: =IFERROR(VLOOKUP(L13,'C-01'!$D:$L,6,0),"") -> 3097.88 | Q13: =IFERROR(VLOOKUP(L13,'C-01'!$D:$L,7,0),"") -> 3080.23 | R13: =IFERROR(VLOOKUP(L13,'C-01'!$D:$L,8,0),"") -> 3491.33 | S13: =IFERROR(VLOOKUP(L13,'C-01'!$D:$L,9,0),"") -> 4078.78 | T13: =IFS('Painel Geral'!$B$5="Mediana",IFERROR(IF(OR(C13="",Q13=0,Q13=""),"",($C13/$Q13)),""),'Painel Geral'!$B$5="Menor Salário",IFERROR(IF(OR(C13="",Q13=0,Q13=""),"",($C13/$N13)),""),'Painel Geral'!$B$5="1º Quartil",IFERROR(IF(OR(C13="",Q13=0,Q13=""),"",($C13/$O13)),""), 'Painel Geral'!$B$5="Média",IFERROR(IF(OR(C13="",Q13=0,Q13=""),"",($C13/$P13)),""),'Painel Geral'!$B$5="3º Quartil",IFERROR(IF(OR(C13="",Q13=0,Q13=""),"",($C13/$R13)),""),'Painel Geral'!$B$5="Maior Salário",IFERROR(IF(OR(C13="",Q13=0,Q13=""),"",($C13/$S13)),"")) -> 0.94765651 | U13: =IFS(OR(N13="",N13=0,C13="", C13=0),"",T13<=80%,"Muito Defasado",T13<=90%,"Defasado",T13<=100%,"Na Média",T13<=110%,"Competitivo",T13<=120%,"Muito Competitivo",T13>120%,"Agressivo") -> Na Média
A14: 1 | B14: =VLOOKUP(A14,Jobmatch!A:G,2,0) -> ALMOXARIFE | C14: =IFERROR(AVERAGEIF('Folha de Pagamento'!A:A,A14,'Folha de Pagamento'!J:J),"") -> 3683 | D14: 5 | E14: =VLOOKUP(A14,Jobmatch!A:H,3,0) -> Edificação | F14: Almoxarife | G14: =VLOOKUP(A14,Jobmatch!A:I,4,0) -> 8 - ADM PROJETOS | H14: =VLOOKUP(A14,Jobmatch!A:I,5,0) -> Operacional | I14: =VLOOKUP(A14,Jobmatch!A:I,6,0) -> 203 | J14: =VLOOKUP(A14,Jobmatch!A:I,7,0) -> Almoxarife | K14: =VLOOKUP(A14,Jobmatch!A:I,8,0) -> Indiferente | L14: =I14&K14 -> 203Indiferente | M14: =COUNTIF('Folha de Pagamento'!A:A,A14) -> 2 | N14: 12 | O14: =IFERROR(VLOOKUP(L14,'C-01'!$D:$L,5,0),"") -> 3088.9 | P14: =IFERROR(VLOOKUP(L14,'C-01'!$D:$L,6,0),"") -> 3397.38 | Q14: =IFERROR(VLOOKUP(L14,'C-01'!$D:$L,7,0),"") -> 3088.9 | R14: =IFERROR(VLOOKUP(L14,'C-01'!$D:$L,8,0),"") -> 3703.26 | S14: =IFERROR(VLOOKUP(L14,'C-01'!$D:$L,9,0),"") -> 4425.21 | T14: =IFS('Painel Geral'!$B$5="Mediana",IFERROR(IF(OR(C14="",Q14=0,Q14=""),"",($C14/$Q14)),""),'Painel Geral'!$B$5="Menor Salário",IFERROR(IF(OR(C14="",Q14=0,Q14=""),"",($C14/$N14)),""),'Painel Geral'!$B$5="1º Quartil",IFERROR(IF(OR(C14="",Q14=0,Q14=""),"",($C14/$O14)),""), 'Painel Geral'!$B$5="Média",IFERROR(IF(OR(C14="",Q14=0,Q14=""),"",($C14/$P14)),""),'Painel Geral'!$B$5="3º Quartil",IFERROR(IF(OR(C14="",Q14=0,Q14=""),"",($C14/$R14)),""),'Painel Geral'!$B$5="Maior Salário",IFERROR(IF(OR(C14="",Q14=0,Q14=""),"",($C14/$S14)),"")) -> 1.1923338 | U14: =IFS(OR(N14="",N14=0,C14="", C14=0),"",T14<=80%,"Muito Defasado",T14<=90%,"Defasado",T14<=100%,"Na Média",T14<=110%,"Competitivo",T14<=120%,"Muito Competitivo",T14>120%,"Agressivo") -> Muito Competitivo
A15: 12 | B15: =VLOOKUP(A15,Jobmatch!A:G,2,0) -> ASSISTENTE ADM DE LEGALIZAÇÃO III | C15: =IFERROR(AVERAGEIF('Folha de Pagamento'!A:A,A15,'Folha de Pagamento'!J:J),"") -> 3652 | D15: 7 | E15: =VLOOKUP(A15,Jobmatch!A:H,3,0) -> Legalização | F15: Assistente Adm Legalização Sr | G15: =VLOOKUP(A15,Jobmatch!A:I,4,0) -> 19 - ADM PROJETOS | H15: =VLOOKUP(A15,Jobmatch!A:I,5,0) -> Operacional | I15: =VLOOKUP(A15,Jobmatch!A:I,6,0) -> 1201 | J15: =VLOOKUP(A15,Jobmatch!A:I,7,0) -> Assistente de Legalização | K15: =VLOOKUP(A15,Jobmatch!A:I,8,0) -> Indiferente | L15: =I15&K15 -> 1201Indiferente | M15: =COUNTIF('Folha de Pagamento'!A:A,A15) -> 2 | N15: 12 | O15: =IFERROR(VLOOKUP(L15,'C-01'!$D:$L,5,0),"") -> 2803.34 | P15: =IFERROR(VLOOKUP(L15,'C-01'!$D:$L,6,0),"") -> 3092.92 | Q15: =IFERROR(VLOOKUP(L15,'C-01'!$D:$L,7,0),"") -> 3092.92 | R15: =IFERROR(VLOOKUP(L15,'C-01'!$D:$L,8,0),"") -> 3382.51 | S15: =IFERROR(VLOOKUP(L15,'C-01'!$D:$L,9,0),"") -> 3672.09 | T15: =IFS('Painel Geral'!$B$5="Mediana",IFERROR(IF(OR(C15="",Q15=0,Q15=""),"",($C15/$Q15)),""),'Painel Geral'!$B$5="Menor Salário",IFERROR(IF(OR(C15="",Q15=0,Q15=""),"",($C15/$N15)),""),'Painel Geral'!$B$5="1º Quartil",IFERROR(IF(OR(C15="",Q15=0,Q15=""),"",($C15/$O15)),""), 'Painel Geral'!$B$5="Média",IFERROR(IF(OR(C15="",Q15=0,Q15=""),"",($C15/$P15)),""),'Painel Geral'!$B$5="3º Quartil",IFERROR(IF(OR(C15="",Q15=0,Q15=""),"",($C15/$R15)),""),'Painel Geral'!$B$5="Maior Salário",IFERROR(IF(OR(C15="",Q15=0,Q15=""),"",($C15/$S15)),"")) -> 1.1807612 | U15: =IFS(OR(N15="",N15=0,C15="", C15=0),"",T15<=80%,"Muito Defasado",T15<=90%,"Defasado",T15<=100%,"Na Média",T15<=110%,"Competitivo",T15<=120%,"Muito Competitivo",T15>120%,"Agressivo") -> Muito Competitivo | AP15: 0.03
A16: 11 | B16: =VLOOKUP(A16,Jobmatch!A:G,2,0) -> ANALISTA FINANCEIRO I | C16: =IFERROR(AVERAGEIF('Folha de Pagamento'!A:A,A16,'Folha de Pagamento'!J:J),"") -> 3993 | D16: 6 | E16: =VLOOKUP(A16,Jobmatch!A:H,3,0) -> Financeiro | F16: Analista Financeiro Jr | G16: =VLOOKUP(A16,Jobmatch!A:I,4,0) -> 18 - ADM PROJETOS | H16: =VLOOKUP(A16,Jobmatch!A:I,5,0) -> Operacional | I16: =VLOOKUP(A16,Jobmatch!A:I,6,0) -> 16 | J16: =VLOOKUP(A16,Jobmatch!A:I,7,0) -> Analista Financeiro | K16: =VLOOKUP(A16,Jobmatch!A:I,8,0) -> Júnior | L16: =I16&K16 -> 16Júnior | M16: =COUNTIF('Folha de Pagamento'!A:A,A16) -> 1 | N16: 12 | O16: =IFERROR(VLOOKUP(L16,'C-01'!$D:$L,5,0),"") -> 3176.35 | P16: =IFERROR(VLOOKUP(L16,'C-01'!$D:$L,6,0),"") -> 3539.11 | Q16: =IFERROR(VLOOKUP(L16,'C-01'!$D:$L,7,0),"") -> 3493.97 | R16: =IFERROR(VLOOKUP(L16,'C-01'!$D:$L,8,0),"") -> 3798.49 | S16: =IFERROR(VLOOKUP(L16,'C-01'!$D:$L,9,0),"") -> 4392.23 | T16: =IFS('Painel Geral'!$B$5="Mediana",IFERROR(IF(OR(C16="",Q16=0,Q16=""),"",($C16/$Q16)),""),'Painel Geral'!$B$5="Menor Salário",IFERROR(IF(OR(C16="",Q16=0,Q16=""),"",($C16/$N16)),""),'Painel Geral'!$B$5="1º Quartil",IFERROR(IF(OR(C16="",Q16=0,Q16=""),"",($C16/$O16)),""), 'Painel Geral'!$B$5="Média",IFERROR(IF(OR(C16="",Q16=0,Q16=""),"",($C16/$P16)),""),'Painel Geral'!$B$5="3º Quartil",IFERROR(IF(OR(C16="",Q16=0,Q16=""),"",($C16/$R16)),""),'Painel Geral'!$B$5="Maior Salário",IFERROR(IF(OR(C16="",Q16=0,Q16=""),"",($C16/$S16)),"")) -> 1.1428261 | U16: =IFS(OR(N16="",N16=0,C16="", C16=0),"",T16<=80%,"Muito Defasado",T16<=90%,"Defasado",T16<=100%,"Na Média",T16<=110%,"Competitivo",T16<=120%,"Muito Competitivo",T16>120%,"Agressivo") -> Muito Competitivo
A17: 6 | B17: =VLOOKUP(A17,Jobmatch!A:G,2,0) -> ANALISTA DE MARKETING l | C17: =IFERROR(AVERAGEIF('Folha de Pagamento'!A:A,A17,'Folha de Pagamento'!J:J),"") -> 4025.88 | D17: 8 | E17: =VLOOKUP(A17,Jobmatch!A:H,3,0) -> Marketing | F17: Analista Marketing Jr | G17: =VLOOKUP(A17,Jobmatch!A:I,4,0) -> 13 - ADM PROJETOS | H17: =VLOOKUP(A17,Jobmatch!A:I,5,0) -> Operacional | I17: =VLOOKUP(A17,Jobmatch!A:I,6,0) -> 42 | J17: =VLOOKUP(A17,Jobmatch!A:I,7,0) -> Analista de Marketing | K17: =VLOOKUP(A17,Jobmatch!A:I,8,0) -> Júnior | L17: =I17&K17 -> 42Júnior | M17: =COUNTIF('Folha de Pagamento'!A:A,A17) -> 1 | N17: 12 | O17: =IFERROR(VLOOKUP(L17,'C-01'!$D:$L,5,0),"") -> 3503.85 | P17: =IFERROR(VLOOKUP(L17,'C-01'!$D:$L,6,0),"") -> 3792.81 | Q17: =IFERROR(VLOOKUP(L17,'C-01'!$D:$L,7,0),"") -> 3674.96 | R17: =IFERROR(VLOOKUP(L17,'C-01'!$D:$L,8,0),"") -> 3977.13 | S17: =IFERROR(VLOOKUP(L17,'C-01'!$D:$L,9,0),"") -> 5225.68 | T17: =IFS('Painel Geral'!$B$5="Mediana",IFERROR(IF(OR(C17="",Q17=0,Q17=""),"",($C17/$Q17)),""),'Painel Geral'!$B$5="Menor Salário",IFERROR(IF(OR(C17="",Q17=0,Q17=""),"",($C17/$N17)),""),'Painel Geral'!$B$5="1º Quartil",IFERROR(IF(OR(C17="",Q17=0,Q17=""),"",($C17/$O17)),""), 'Painel Geral'!$B$5="Média",IFERROR(IF(OR(C17="",Q17=0,Q17=""),"",($C17/$P17)),""),'Painel Geral'!$B$5="3º Quartil",IFERROR(IF(OR(C17="",Q17=0,Q17=""),"",($C17/$R17)),""),'Painel Geral'!$B$5="Maior Salário",IFERROR(IF(OR(C17="",Q17=0,Q17=""),"",($C17/$S17)),"")) -> 1.0954895 | U17: =IFS(OR(N17="",N17=0,C17="", C17=0),"",T17<=80%,"Muito Defasado",T17<=90%,"Defasado",T17<=100%,"Na Média",T17<=110%,"Competitivo",T17<=120%,"Muito Competitivo",T17>120%,"Agressivo") -> Competitivo
A18: 15 | B18: =VLOOKUP(A18,Jobmatch!A:G,2,0) -> ASSISTENTE DE ENGENHARIA lll | C18: =IFERROR(AVERAGEIF('Folha de Pagamento'!A:A,A18,'Folha de Pagamento'!J:J),"") -> 3652 | D18: 5 | E18: =VLOOKUP(A18,Jobmatch!A:H,3,0) -> Edificação | F18: Assistente Engenharia | G18: =VLOOKUP(A18,Jobmatch!A:I,4,0) -> 22 - ADM PROJETOS | H18: =VLOOKUP(A18,Jobmatch!A:I,5,0) -> Operacional | I18: =VLOOKUP(A18,Jobmatch!A:I,6,0) -> 531 | J18: =VLOOKUP(A18,Jobmatch!A:I,7,0) -> Assistente de Engenharia | K18: =VLOOKUP(A18,Jobmatch!A:I,8,0) -> Indiferente | L18: =I18&K18 -> 531Indiferente | M18: =COUNTIF('Folha de Pagamento'!A:A,A18) -> 1 | N18: 13 | O18: =IFERROR(VLOOKUP(L18,'C-01'!$D:$L,5,0),"") -> 3945.44 | P18: =IFERROR(VLOOKUP(L18,'C-01'!$D:$L,6,0),"") -> 4031.84 | Q18: =IFERROR(VLOOKUP(L18,'C-01'!$D:$L,7,0),"") -> 3945.44 | R18: =IFERROR(VLOOKUP(L18,'C-01'!$D:$L,8,0),"") -> 3945.44 | S18: =IFERROR(VLOOKUP(L18,'C-01'!$D:$L,9,0),"") -> 5084.96 | T18: =IFS('Painel Geral'!$B$5="Mediana",IFERROR(IF(OR(C18="",Q18=0,Q18=""),"",($C18/$Q18)),""),'Painel Geral'!$B$5="Menor Salário",IFERROR(IF(OR(C18="",Q18=0,Q18=""),"",($C18/$N18)),""),'Painel Geral'!$B$5="1º Quartil",IFERROR(IF(OR(C18="",Q18=0,Q18=""),"",($C18/$O18)),""), 'Painel Geral'!$B$5="Média",IFERROR(IF(OR(C18="",Q18=0,Q18=""),"",($C18/$P18)),""),'Painel Geral'!$B$5="3º Quartil",IFERROR(IF(OR(C18="",Q18=0,Q18=""),"",($C18/$R18)),""),'Painel Geral'!$B$5="Maior Salário",IFERROR(IF(OR(C18="",Q18=0,Q18=""),"",($C18/$S18)),"")) -> 0.92562553 | U18: =IFS(OR(N18="",N18=0,C18="", C18=0),"",T18<=80%,"Muito Defasado",T18<=90%,"Defasado",T18<=100%,"Na Média",T18<=110%,"Competitivo",T18<=120%,"Muito Competitivo",T18>120%,"Agressivo") -> Na Média | AK18: 1907 | AL18: =AK18*AN27 -> 1922.4698
A19: 54 | B19: =VLOOKUP(A19,Jobmatch!A:G,2,0) -> TECNOLOGO EM CONSTRUÇÃO DE EDIFICIOS | C19: =IFERROR(AVERAGEIF('Folha de Pagamento'!A:A,A19,'Folha de Pagamento'!J:J),"") -> 8585 | D19: 5 | E19: =VLOOKUP(A19,Jobmatch!A:H,3,0) -> Edificação | F19: Tecnólogo Construção Edifícios | G19: =VLOOKUP(A19,Jobmatch!A:I,4,0) -> 61 - ADM PROJETOS | H19: =VLOOKUP(A19,Jobmatch!A:I,5,0) -> Operacional | I19: =VLOOKUP(A19,Jobmatch!A:I,6,0) -> 269 | J19: =VLOOKUP(A19,Jobmatch!A:I,7,0) -> Técnico em Edificações | K19: =VLOOKUP(A19,Jobmatch!A:I,8,0) -> Indiferente | L19: =I19&K19 -> 269Indiferente | M19: =COUNTIF('Folha de Pagamento'!A:A,A19) -> 1 | N19: 13 | O19: =IFERROR(VLOOKUP(L19,'C-01'!$D:$L,5,0),"") -> 3732.17 | P19: =IFERROR(VLOOKUP(L19,'C-01'!$D:$L,6,0),"") -> 4583.42 | Q19: =IFERROR(VLOOKUP(L19,'C-01'!$D:$L,7,0),"") -> 4022.01 | R19: =IFERROR(VLOOKUP(L19,'C-01'!$D:$L,8,0),"") -> 4417.17 | S19: =IFERROR(VLOOKUP(L19,'C-01'!$D:$L,9,0),"") -> 9075.39 | T19: =IFS('Painel Geral'!$B$5="Mediana",IFERROR(IF(OR(C19="",Q19=0,Q19=""),"",($C19/$Q19)),""),'Painel Geral'!$B$5="Menor Salário",IFERROR(IF(OR(C19="",Q19=0,Q19=""),"",($C19/$N19)),""),'Painel Geral'!$B$5="1º Quartil",IFERROR(IF(OR(C19="",Q19=0,Q19=""),"",($C19/$O19)),""), 'Painel Geral'!$B$5="Média",IFERROR(IF(OR(C19="",Q19=0,Q19=""),"",($C19/$P19)),""),'Painel Geral'!$B$5="3º Quartil",IFERROR(IF(OR(C19="",Q19=0,Q19=""),"",($C19/$R19)),""),'Painel Geral'!$B$5="Maior Salário",IFERROR(IF(OR(C19="",Q19=0,Q19=""),"",($C19/$S19)),"")) -> 2.1345049 | U19: =IFS(OR(N19="",N19=0,C19="", C19=0),"",T19<=80%,"Muito Defasado",T19<=90%,"Defasado",T19<=100%,"Na Média",T19<=110%,"Competitivo",T19<=120%,"Muito Competitivo",T19>120%,"Agressivo") -> Agressivo | AK19: 45778
A20: 3 | B20: =VLOOKUP(A20,Jobmatch!A:G,2,0) -> ANALISTA DE CRIAÇAO | C20: =IFERROR(AVERAGEIF('Folha de Pagamento'!A:A,A20,'Folha de Pagamento'!J:J),"") -> 5429 | D20: 8 | E20: =VLOOKUP(A20,Jobmatch!A:H,3,0) -> Marketing | F20: Analista Criação | G20: =VLOOKUP(A20,Jobmatch!A:I,4,0) -> 10 - ADM PROJETOS | H20: =VLOOKUP(A20,Jobmatch!A:I,5,0) -> Operacional | I20: =VLOOKUP(A20,Jobmatch!A:I,6,0) -> 45 | J20: =VLOOKUP(A20,Jobmatch!A:I,7,0) -> Analista de Criação | K20: =VLOOKUP(A20,Jobmatch!A:I,8,0) -> Indiferente | L20: =I20&K20 -> 45Indiferente | M20: =COUNTIF('Folha de Pagamento'!A:A,A20) -> 1 | N20: 13 | O20: =IFERROR(VLOOKUP(L20,'C-01'!$D:$L,5,0),"") -> 3527.33 | P20: =IFERROR(VLOOKUP(L20,'C-01'!$D:$L,6,0),"") -> 4325.16 | Q20: =IFERROR(VLOOKUP(L20,'C-01'!$D:$L,7,0),"") -> 4325.72 | R20: =IFERROR(VLOOKUP(L20,'C-01'!$D:$L,8,0),"") -> 4988.66 | S20: =IFERROR(VLOOKUP(L20,'C-01'!$D:$L,9,0),"") -> 6418.74 | T20: =IFS('Painel Geral'!$B$5="Mediana",IFERROR(IF(OR(C20="",Q20=0,Q20=""),"",($C20/$Q20)),""),'Painel Geral'!$B$5="Menor Salário",IFERROR(IF(OR(C20="",Q20=0,Q20=""),"",($C20/$N20)),""),'Painel Geral'!$B$5="1º Quartil",IFERROR(IF(OR(C20="",Q20=0,Q20=""),"",($C20/$O20)),""), 'Painel Geral'!$B$5="Média",IFERROR(IF(OR(C20="",Q20=0,Q20=""),"",($C20/$P20)),""),'Painel Geral'!$B$5="3º Quartil",IFERROR(IF(OR(C20="",Q20=0,Q20=""),"",($C20/$R20)),""),'Painel Geral'!$B$5="Maior Salário",IFERROR(IF(OR(C20="",Q20=0,Q20=""),"",($C20/$S20)),"")) -> 1.2550512 | U20: =IFS(OR(N20="",N20=0,C20="", C20=0),"",T20<=80%,"Muito Defasado",T20<=90%,"Defasado",T20<=100%,"Na Média",T20<=110%,"Competitivo",T20<=120%,"Muito Competitivo",T20>120%,"Agressivo") -> Agressivo | AK20: 0.23 | AL20: =1+(AK20/100) -> 1.0023 | AM20: =AL20 -> 1.0023
A21: 4 | B21: =VLOOKUP(A21,Jobmatch!A:G,2,0) -> ANALISTA DE INOVAÇÃO | C21: =IFERROR(AVERAGEIF('Folha de Pagamento'!A:A,A21,'Folha de Pagamento'!J:J),"") -> 7299.2701 | D21: 7 | E21: =VLOOKUP(A21,Jobmatch!A:H,3,0) -> Inovação | F21: Analista Inovação | G21: =VLOOKUP(A21,Jobmatch!A:I,4,0) -> 11 - ADM PROJETOS | H21: =VLOOKUP(A21,Jobmatch!A:I,5,0) -> Tático | I21: =VLOOKUP(A21,Jobmatch!A:I,6,0) -> 437 | J21: =VLOOKUP(A21,Jobmatch!A:I,7,0) -> Analista de Inovação | K21: =VLOOKUP(A21,Jobmatch!A:I,8,0) -> Indiferente | L21: =I21&K21 -> 437Indiferente | M21: =COUNTIF('Folha de Pagamento'!A:A,A21) -> 1 | N21: 14 | O21: =IFERROR(VLOOKUP(L21,'C-01'!$D:$L,5,0),"") -> 5268.47 | P21: =IFERROR(VLOOKUP(L21,'C-01'!$D:$L,6,0),"") -> 5831.57 | Q21: =IFERROR(VLOOKUP(L21,'C-01'!$D:$L,7,0),"") -> 5268.47 | R21: =IFERROR(VLOOKUP(L21,'C-01'!$D:$L,8,0),"") -> 6822.26 | S21: =IFERROR(VLOOKUP(L21,'C-01'!$D:$L,9,0),"") -> 7760.14 | T21: =IFS('Painel Geral'!$B$5="Mediana",IFERROR(IF(OR(C21="",Q21=0,Q21=""),"",($C21/$Q21)),""),'Painel Geral'!$B$5="Menor Salário",IFERROR(IF(OR(C21="",Q21=0,Q21=""),"",($C21/$N21)),""),'Painel Geral'!$B$5="1º Quartil",IFERROR(IF(OR(C21="",Q21=0,Q21=""),"",($C21/$O21)),""), 'Painel Geral'!$B$5="Média",IFERROR(IF(OR(C21="",Q21=0,Q21=""),"",($C21/$P21)),""),'Painel Geral'!$B$5="3º Quartil",IFERROR(IF(OR(C21="",Q21=0,Q21=""),"",($C21/$R21)),""),'Painel Geral'!$B$5="Maior Salário",IFERROR(IF(OR(C21="",Q21=0,Q21=""),"",($C21/$S21)),"")) -> 1.385463 | U21: =IFS(OR(N21="",N21=0,C21="", C21=0),"",T21<=80%,"Muito Defasado",T21<=90%,"Defasado",T21<=100%,"Na Média",T21<=110%,"Competitivo",T21<=120%,"Muito Competitivo",T21>120%,"Agressivo") -> Agressivo | AK21: 0.21 | AL21: =1+(AK21/100) -> 1.0021 | AM21: =AM20*AL21 -> 1.0044048
A22: 2 | B22: =VLOOKUP(A22,Jobmatch!A:G,2,0) -> ANALISTA DE COMPRAS | C22: =IFERROR(AVERAGEIF('Folha de Pagamento'!A:A,A22,'Folha de Pagamento'!J:J),"") -> 3780 | D22: 1 | E22: =VLOOKUP(A22,Jobmatch!A:H,3,0) -> Suprimentos | F22: Analista Compras | G22: =VLOOKUP(A22,Jobmatch!A:I,4,0) -> 9 - ADM PROJETOS | H22: =VLOOKUP(A22,Jobmatch!A:I,5,0) -> Operacional | I22: =VLOOKUP(A22,Jobmatch!A:I,6,0) -> 136 | J22: =VLOOKUP(A22,Jobmatch!A:I,7,0) -> Analista de Compras | K22: =VLOOKUP(A22,Jobmatch!A:I,8,0) -> Pleno | L22: =I22&K22 -> 136Pleno | M22: =COUNTIF('Folha de Pagamento'!A:A,A22) -> 1 | N22: 14 | O22: =IFERROR(VLOOKUP(L22,'C-01'!$D:$L,5,0),"") -> 4524.76 | P22: =IFERROR(VLOOKUP(L22,'C-01'!$D:$L,6,0),"") -> 6002.23 | Q22: =IFERROR(VLOOKUP(L22,'C-01'!$D:$L,7,0),"") -> 5275.87 | R22: =IFERROR(VLOOKUP(L22,'C-01'!$D:$L,8,0),"") -> 7842.89 | S22: =IFERROR(VLOOKUP(L22,'C-01'!$D:$L,9,0),"") -> 7842.89 | T22: =IFS('Painel Geral'!$B$5="Mediana",IFERROR(IF(OR(C22="",Q22=0,Q22=""),"",($C22/$Q22)),""),'Painel Geral'!$B$5="Menor Salário",IFERROR(IF(OR(C22="",Q22=0,Q22=""),"",($C22/$N22)),""),'Painel Geral'!$B$5="1º Quartil",IFERROR(IF(OR(C22="",Q22=0,Q22=""),"",($C22/$O22)),""), 'Painel Geral'!$B$5="Média",IFERROR(IF(OR(C22="",Q22=0,Q22=""),"",($C22/$P22)),""),'Painel Geral'!$B$5="3º Quartil",IFERROR(IF(OR(C22="",Q22=0,Q22=""),"",($C22/$R22)),""),'Painel Geral'!$B$5="Maior Salário",IFERROR(IF(OR(C22="",Q22=0,Q22=""),"",($C22/$S22)),"")) -> 0.71646951 | U22: =IFS(OR(N22="",N22=0,C22="", C22=0),"",T22<=80%,"Muito Defasado",T22<=90%,"Defasado",T22<=100%,"Na Média",T22<=110%,"Competitivo",T22<=120%,"Muito Competitivo",T22>120%,"Agressivo") -> Muito Defasado | AK22: -0.21 | AL22: =1+(AK22/100) -> 0.9979 | AM22: =AM21*AL22 -> 1.0022956
A23: 7 | B23: =VLOOKUP(A23,Jobmatch!A:G,2,0) -> ANALISTA DE PÓS VENDAS II | C23: =IFERROR(AVERAGEIF('Folha de Pagamento'!A:A,A23,'Folha de Pagamento'!J:J),"") -> 4550 | D23: 9 | E23: =VLOOKUP(A23,Jobmatch!A:H,3,0) -> Pós Vendas | F23: Analista Pós-Vendas Pl | G23: =VLOOKUP(A23,Jobmatch!A:I,4,0) -> 14 - ADM PROJETOS | H23: =VLOOKUP(A23,Jobmatch!A:I,5,0) -> Operacional | I23: =VLOOKUP(A23,Jobmatch!A:I,6,0) -> 19 | J23: =VLOOKUP(A23,Jobmatch!A:I,7,0) -> Analista Comercial | K23: =VLOOKUP(A23,Jobmatch!A:I,8,0) -> Pleno | L23: =I23&K23 -> 19Pleno | M23: =COUNTIF('Folha de Pagamento'!A:A,A23) -> 1 | N23: 15 | O23: =IFERROR(VLOOKUP(L23,'C-01'!$D:$L,5,0),"") -> 4898.28 | P23: =IFERROR(VLOOKUP(L23,'C-01'!$D:$L,6,0),"") -> 5747.37 | Q23: =IFERROR(VLOOKUP(L23,'C-01'!$D:$L,7,0),"") -> 5320.06 | R23: =IFERROR(VLOOKUP(L23,'C-01'!$D:$L,8,0),"") -> 6382.81 | S23: =IFERROR(VLOOKUP(L23,'C-01'!$D:$L,9,0),"") -> 7445.55 | T23: =IFS('Painel Geral'!$B$5="Mediana",IFERROR(IF(OR(C23="",Q23=0,Q23=""),"",($C23/$Q23)),""),'Painel Geral'!$B$5="Menor Salário",IFERROR(IF(OR(C23="",Q23=0,Q23=""),"",($C23/$N23)),""),'Painel Geral'!$B$5="1º Quartil",IFERROR(IF(OR(C23="",Q23=0,Q23=""),"",($C23/$O23)),""), 'Painel Geral'!$B$5="Média",IFERROR(IF(OR(C23="",Q23=0,Q23=""),"",($C23/$P23)),""),'Painel Geral'!$B$5="3º Quartil",IFERROR(IF(OR(C23="",Q23=0,Q23=""),"",($C23/$R23)),""),'Painel Geral'!$B$5="Maior Salário",IFERROR(IF(OR(C23="",Q23=0,Q23=""),"",($C23/$S23)),"")) -> 0.85525351 | U23: =IFS(OR(N23="",N23=0,C23="", C23=0),"",T23<=80%,"Muito Defasado",T23<=90%,"Defasado",T23<=100%,"Na Média",T23<=110%,"Competitivo",T23<=120%,"Muito Competitivo",T23>120%,"Agressivo") -> Defasado | AK23: 0.52 | AL23: =1+(AK23/100) -> 1.0052 | AM23: =AM22*AL23 -> 1.0075075
A24: 9 | B24: =VLOOKUP(A24,Jobmatch!A:G,2,0) -> ANALISTA FINANCEIRO COMERCIAL III | C24: =IFERROR(AVERAGEIF('Folha de Pagamento'!A:A,A24,'Folha de Pagamento'!J:J),"") -> 5213 | D24: 6 | E24: =VLOOKUP(A24,Jobmatch!A:H,3,0) -> Financeiro | F24: Analista Financeiro Comercial Sr | G24: =VLOOKUP(A24,Jobmatch!A:I,4,0) -> 16 - ADM PROJETOS | H24: =VLOOKUP(A24,Jobmatch!A:I,5,0) -> Operacional | I24: =VLOOKUP(A24,Jobmatch!A:I,6,0) -> 16 | J24: =VLOOKUP(A24,Jobmatch!A:I,7,0) -> Analista Financeiro | K24: =VLOOKUP(A24,Jobmatch!A:I,8,0) -> Sênior | L24: =I24&K24 -> 16Sênior | M24: =COUNTIF('Folha de Pagamento'!A:A,A24) -> 1 | N24: 15 | O24: =IFERROR(VLOOKUP(L24,'C-01'!$D:$L,5,0),"") -> 5489.27 | P24: =IFERROR(VLOOKUP(L24,'C-01'!$D:$L,6,0),"") -> 6172.24 | Q24: =IFERROR(VLOOKUP(L24,'C-01'!$D:$L,7,0),"") -> 5910.71 | R24: =IFERROR(VLOOKUP(L24,'C-01'!$D:$L,8,0),"") -> 6737.39 | S24: =IFERROR(VLOOKUP(L24,'C-01'!$D:$L,9,0),"") -> 8185.08 | T24: =IFS('Painel Geral'!$B$5="Mediana",IFERROR(IF(OR(C24="",Q24=0,Q24=""),"",($C24/$Q24)),""),'Painel Geral'!$B$5="Menor Salário",IFERROR(IF(OR(C24="",Q24=0,Q24=""),"",($C24/$N24)),""),'Painel Geral'!$B$5="1º Quartil",IFERROR(IF(OR(C24="",Q24=0,Q24=""),"",($C24/$O24)),""), 'Painel Geral'!$B$5="Média",IFERROR(IF(OR(C24="",Q24=0,Q24=""),"",($C24/$P24)),""),'Painel Geral'!$B$5="3º Quartil",IFERROR(IF(OR(C24="",Q24=0,Q24=""),"",($C24/$R24)),""),'Painel Geral'!$B$5="Maior Salário",IFERROR(IF(OR(C24="",Q24=0,Q24=""),"",($C24/$S24)),"")) -> 0.88195834 | U24: =IFS(OR(N24="",N24=0,C24="", C24=0),"",T24<=80%,"Muito Defasado",T24<=90%,"Defasado",T24<=100%,"Na Média",T24<=110%,"Competitivo",T24<=120%,"Muito Competitivo",T24>120%,"Agressivo") -> Defasado | AK24: 0.03 | AL24: =1+(AK24/100) -> 1.0003 | AM24: =AM23*AL24 -> 1.0078098
A25: 10 | B25: =VLOOKUP(A25,Jobmatch!A:G,2,0) -> ANALISTA FINANCEIRO DE CAPTAÇÃO DE RECURSOS III | C25: =IFERROR(AVERAGEIF('Folha de Pagamento'!A:A,A25,'Folha de Pagamento'!J:J),"") -> 5213 | D25: 6 | E25: =VLOOKUP(A25,Jobmatch!A:H,3,0) -> Financeiro | F25: Analista Financeiro Captação Recursos Sr | G25: =VLOOKUP(A25,Jobmatch!A:I,4,0) -> 17 - ADM PROJETOS | H25: =VLOOKUP(A25,Jobmatch!A:I,5,0) -> Operacional | I25: =VLOOKUP(A25,Jobmatch!A:I,6,0) -> 16 | J25: =VLOOKUP(A25,Jobmatch!A:I,7,0) -> Analista Financeiro | K25: =VLOOKUP(A25,Jobmatch!A:I,8,0) -> Sênior | L25: =I25&K25 -> 16Sênior | M25: =COUNTIF('Folha de Pagamento'!A:A,A25) -> 1 | N25: 15 | O25: =IFERROR(VLOOKUP(L25,'C-01'!$D:$L,5,0),"") -> 5489.27 | P25: =IFERROR(VLOOKUP(L25,'C-01'!$D:$L,6,0),"") -> 6172.24 | Q25: =IFERROR(VLOOKUP(L25,'C-01'!$D:$L,7,0),"") -> 5910.71 | R25: =IFERROR(VLOOKUP(L25,'C-01'!$D:$L,8,0),"") -> 6737.39 | S25: =IFERROR(VLOOKUP(L25,'C-01'!$D:$L,9,0),"") -> 8185.08 | T25: =IFS('Painel Geral'!$B$5="Mediana",IFERROR(IF(OR(C25="",Q25=0,Q25=""),"",($C25/$Q25)),""),'Painel Geral'!$B$5="Menor Salário",IFERROR(IF(OR(C25="",Q25=0,Q25=""),"",($C25/$N25)),""),'Painel Geral'!$B$5="1º Quartil",IFERROR(IF(OR(C25="",Q25=0,Q25=""),"",($C25/$O25)),""), 'Painel Geral'!$B$5="Média",IFERROR(IF(OR(C25="",Q25=0,Q25=""),"",($C25/$P25)),""),'Painel Geral'!$B$5="3º Quartil",IFERROR(IF(OR(C25="",Q25=0,Q25=""),"",($C25/$R25)),""),'Painel Geral'!$B$5="Maior Salário",IFERROR(IF(OR(C25="",Q25=0,Q25=""),"",($C25/$S25)),"")) -> 0.88195834 | U25: =IFS(OR(N25="",N25=0,C25="", C25=0),"",T25<=80%,"Muito Defasado",T25<=90%,"Defasado",T25<=100%,"Na Média",T25<=110%,"Competitivo",T25<=120%,"Muito Competitivo",T25>120%,"Agressivo") -> Defasado | AK25: 0.03 | AL25: =1+(AK25/100) -> 1.0003 | AM25: =AM24*AL25 -> 1.0081121
A26: 53 | B26: =VLOOKUP(A26,Jobmatch!A:G,2,0) -> TECNICO ANALISTA DE CUSTOS | C26: =IFERROR(AVERAGEIF('Folha de Pagamento'!A:A,A26,'Folha de Pagamento'!J:J),"") -> 7000 | D26: 5 | E26: =VLOOKUP(A26,Jobmatch!A:H,3,0) -> Edificação | F26: Técnico Analista Custos | G26: =VLOOKUP(A26,Jobmatch!A:I,4,0) -> 60 - ADM PROJETOS | H26: =VLOOKUP(A26,Jobmatch!A:I,5,0) -> Operacional | I26: =VLOOKUP(A26,Jobmatch!A:I,6,0) -> 876 | J26: =VLOOKUP(A26,Jobmatch!A:I,7,0) -> Analista de Custos | K26: =VLOOKUP(A26,Jobmatch!A:I,8,0) -> Indiferente | L26: =I26&K26 -> 876Indiferente | M26: =COUNTIF('Folha de Pagamento'!A:A,A26) -> 3 | N26: 16 | O26: =IFERROR(VLOOKUP(L26,'C-01'!$D:$L,5,0),"") -> 6868.23 | P26: =IFERROR(VLOOKUP(L26,'C-01'!$D:$L,6,0),"") -> 7611.25 | Q26: =IFERROR(VLOOKUP(L26,'C-01'!$D:$L,7,0),"") -> 7320.76 | R26: =IFERROR(VLOOKUP(L26,'C-01'!$D:$L,8,0),"") -> 8153.71 | S26: =IFERROR(VLOOKUP(L26,'C-01'!$D:$L,9,0),"") -> 9161.15 | T26: =IFS('Painel Geral'!$B$5="Mediana",IFERROR(IF(OR(C26="",Q26=0,Q26=""),"",($C26/$Q26)),""),'Painel Geral'!$B$5="Menor Salário",IFERROR(IF(OR(C26="",Q26=0,Q26=""),"",($C26/$N26)),""),'Painel Geral'!$B$5="1º Quartil",IFERROR(IF(OR(C26="",Q26=0,Q26=""),"",($C26/$O26)),""), 'Painel Geral'!$B$5="Média",IFERROR(IF(OR(C26="",Q26=0,Q26=""),"",($C26/$P26)),""),'Painel Geral'!$B$5="3º Quartil",IFERROR(IF(OR(C26="",Q26=0,Q26=""),"",($C26/$R26)),""),'Painel Geral'!$B$5="Maior Salário",IFERROR(IF(OR(C26="",Q26=0,Q26=""),"",($C26/$S26)),"")) -> 0.95618488 | U26: =IFS(OR(N26="",N26=0,C26="", C26=0),"",T26<=80%,"Muito Defasado",T26<=90%,"Defasado",T26<=100%,"Na Média",T26<=110%,"Competitivo",T26<=120%,"Muito Competitivo",T26>120%,"Agressivo") -> Na Média
A27: 35 | B27: =VLOOKUP(A27,Jobmatch!A:G,2,0) -> ENCARREGADO OBRAS/MANUTENCAO | C27: =IFERROR(AVERAGEIF('Folha de Pagamento'!A:A,A27,'Folha de Pagamento'!J:J),"") -> 8714 | D27: 5 | E27: =VLOOKUP(A27,Jobmatch!A:H,3,0) -> Edificação | F27: Encarregado Obras / Manutenção | G27: =VLOOKUP(A27,Jobmatch!A:I,4,0) -> 42 - ADM PROJETOS | H27: =VLOOKUP(A27,Jobmatch!A:I,5,0) -> Operacional | I27: =VLOOKUP(A27,Jobmatch!A:I,6,0) -> 470 | J27: =VLOOKUP(A27,Jobmatch!A:I,7,0) -> Mestre de Obras | K27: =VLOOKUP(A27,Jobmatch!A:I,8,0) -> Indiferente | L27: =I27&K27 -> 470Indiferente | M27: =COUNTIF('Folha de Pagamento'!A:A,A27) -> 1 | N27: 16 | O27: =IFERROR(VLOOKUP(L27,'C-01'!$D:$L,5,0),"") -> 5530.26 | P27: =IFERROR(VLOOKUP(L27,'C-01'!$D:$L,6,0),"") -> 7689.13 | Q27: =IFERROR(VLOOKUP(L27,'C-01'!$D:$L,7,0),"") -> 7460.82 | R27: =IFERROR(VLOOKUP(L27,'C-01'!$D:$L,8,0),"") -> 9785.54 | S27: =IFERROR(VLOOKUP(L27,'C-01'!$D:$L,9,0),"") -> 11138.95 | T27: =IFS('Painel Geral'!$B$5="Mediana",IFERROR(IF(OR(C27="",Q27=0,Q27=""),"",($C27/$Q27)),""),'Painel Geral'!$B$5="Menor Salário",IFERROR(IF(OR(C27="",Q27=0,Q27=""),"",($C27/$N27)),""),'Painel Geral'!$B$5="1º Quartil",IFERROR(IF(OR(C27="",Q27=0,Q27=""),"",($C27/$O27)),""), 'Painel Geral'!$B$5="Média",IFERROR(IF(OR(C27="",Q27=0,Q27=""),"",($C27/$P27)),""),'Painel Geral'!$B$5="3º Quartil",IFERROR(IF(OR(C27="",Q27=0,Q27=""),"",($C27/$R27)),""),'Painel Geral'!$B$5="Maior Salário",IFERROR(IF(OR(C27="",Q27=0,Q27=""),"",($C27/$S27)),"")) -> 1.1679681 | U27: =IFS(OR(N27="",N27=0,C27="", C27=0),"",T27<=80%,"Muito Defasado",T27<=90%,"Defasado",T27<=100%,"Na Média",T27<=110%,"Competitivo",T27<=120%,"Muito Competitivo",T27>120%,"Agressivo") -> Muito Competitivo | AN27: =AM25 -> 1.0081121
A28: 34 | B28: =VLOOKUP(A28,Jobmatch!A:G,2,0) -> ENCARREGADO DE OBRAS | C28: =IFERROR(AVERAGEIF('Folha de Pagamento'!A:A,A28,'Folha de Pagamento'!J:J),"") -> 10000.5 | D28: 10 | E28: =VLOOKUP(A28,Jobmatch!A:H,3,0) -> Urbanismo | F28: Encarregado Obras | G28: =VLOOKUP(A28,Jobmatch!A:I,4,0) -> 41 - ADM PROJETOS | H28: =VLOOKUP(A28,Jobmatch!A:I,5,0) -> Operacional | I28: =VLOOKUP(A28,Jobmatch!A:I,6,0) -> 470 | J28: =VLOOKUP(A28,Jobmatch!A:I,7,0) -> Mestre de Obras | K28: =VLOOKUP(A28,Jobmatch!A:I,8,0) -> Indiferente | L28: =I28&K28 -> 470Indiferente | M28: =COUNTIF('Folha de Pagamento'!A:A,A28) -> 2 | N28: 16 | O28: =IFERROR(VLOOKUP(L28,'C-01'!$D:$L,5,0),"") -> 5530.26 | P28: =IFERROR(VLOOKUP(L28,'C-01'!$D:$L,6,0),"") -> 7689.13 | Q28: =IFERROR(VLOOKUP(L28,'C-01'!$D:$L,7,0),"") -> 7460.82 | R28: =IFERROR(VLOOKUP(L28,'C-01'!$D:$L,8,0),"") -> 9785.54 | S28: =IFERROR(VLOOKUP(L28,'C-01'!$D:$L,9,0),"") -> 11138.95 | T28: =IFS('Painel Geral'!$B$5="Mediana",IFERROR(IF(OR(C28="",Q28=0,Q28=""),"",($C28/$Q28)),""),'Painel Geral'!$B$5="Menor Salário",IFERROR(IF(OR(C28="",Q28=0,Q28=""),"",($C28/$N28)),""),'Painel Geral'!$B$5="1º Quartil",IFERROR(IF(OR(C28="",Q28=0,Q28=""),"",($C28/$O28)),""), 'Painel Geral'!$B$5="Média",IFERROR(IF(OR(C28="",Q28=0,Q28=""),"",($C28/$P28)),""),'Painel Geral'!$B$5="3º Quartil",IFERROR(IF(OR(C28="",Q28=0,Q28=""),"",($C28/$R28)),""),'Painel Geral'!$B$5="Maior Salário",IFERROR(IF(OR(C28="",Q28=0,Q28=""),"",($C28/$S28)),"")) -> 1.3404023 | U28: =IFS(OR(N28="",N28=0,C28="", C28=0),"",T28<=80%,"Muito Defasado",T28<=90%,"Defasado",T28<=100%,"Na Média",T28<=110%,"Competitivo",T28<=120%,"Muito Competitivo",T28>120%,"Agressivo") -> Agressivo
A29: 32 | B29: =VLOOKUP(A29,Jobmatch!A:G,2,0) -> COORDENADOR FINANCEIRO | C29: =IFERROR(AVERAGEIF('Folha de Pagamento'!A:A,A29,'Folha de Pagamento'!J:J),"") -> 7947.0199 | D29: 6 | E29: =VLOOKUP(A29,Jobmatch!A:H,3,0) -> Financeiro | F29: Coordenador Financeiro | G29: =VLOOKUP(A29,Jobmatch!A:I,4,0) -> 39 - ADM PROJETOS | H29: =VLOOKUP(A29,Jobmatch!A:I,5,0) -> Tático | I29: =VLOOKUP(A29,Jobmatch!A:I,6,0) -> 122 | J29: =VLOOKUP(A29,Jobmatch!A:I,7,0) -> Coordenador Financeiro | K29: =VLOOKUP(A29,Jobmatch!A:I,8,0) -> Indiferente | L29: =I29&K29 -> 122Indiferente | M29: =COUNTIF('Folha de Pagamento'!A:A,A29) -> 1 | N29: 16 | O29: =IFERROR(VLOOKUP(L29,'C-01'!$D:$L,5,0),"") -> 6325.01 | P29: =IFERROR(VLOOKUP(L29,'C-01'!$D:$L,6,0),"") -> 7452.59 | Q29: =IFERROR(VLOOKUP(L29,'C-01'!$D:$L,7,0),"") -> 7558.57 | R29: =IFERROR(VLOOKUP(L29,'C-01'!$D:$L,8,0),"") -> 8691.7 | S29: =IFERROR(VLOOKUP(L29,'C-01'!$D:$L,9,0),"") -> 9982.25 | T29: =IFS('Painel Geral'!$B$5="Mediana",IFERROR(IF(OR(C29="",Q29=0,Q29=""),"",($C29/$Q29)),""),'Painel Geral'!$B$5="Menor Salário",IFERROR(IF(OR(C29="",Q29=0,Q29=""),"",($C29/$N29)),""),'Painel Geral'!$B$5="1º Quartil",IFERROR(IF(OR(C29="",Q29=0,Q29=""),"",($C29/$O29)),""), 'Painel Geral'!$B$5="Média",IFERROR(IF(OR(C29="",Q29=0,Q29=""),"",($C29/$P29)),""),'Painel Geral'!$B$5="3º Quartil",IFERROR(IF(OR(C29="",Q29=0,Q29=""),"",($C29/$R29)),""),'Painel Geral'!$B$5="Maior Salário",IFERROR(IF(OR(C29="",Q29=0,Q29=""),"",($C29/$S29)),"")) -> 1.051392 | U29: =IFS(OR(N29="",N29=0,C29="", C29=0),"",T29<=80%,"Muito Defasado",T29<=90%,"Defasado",T29<=100%,"Na Média",T29<=110%,"Competitivo",T29<=120%,"Muito Competitivo",T29>120%,"Agressivo") -> Competitivo
A30: 8 | B30: =VLOOKUP(A30,Jobmatch!A:G,2,0) -> ANALISTA DE URBANISMO | C30: =IFERROR(AVERAGEIF('Folha de Pagamento'!A:A,A30,'Folha de Pagamento'!J:J),"") -> 5830 | D30: 10 | E30: =VLOOKUP(A30,Jobmatch!A:H,3,0) -> Urbanismo | F30: Analista Urbanismo | G30: =VLOOKUP(A30,Jobmatch!A:I,4,0) -> 15 - ADM PROJETOS | H30: =VLOOKUP(A30,Jobmatch!A:I,5,0) -> Operacional | I30: =VLOOKUP(A30,Jobmatch!A:I,6,0) -> 1199 | J30: =VLOOKUP(A30,Jobmatch!A:I,7,0) -> Analista de Urbanismo | K30: =VLOOKUP(A30,Jobmatch!A:I,8,0) -> Indiferente | L30: =I30&K30 -> 1199Indiferente | M30: =COUNTIF('Folha de Pagamento'!A:A,A30) -> 1 | N30: 17 | O30: =IFERROR(VLOOKUP(L30,'C-01'!$D:$L,5,0),"") -> 6091.54 | P30: =IFERROR(VLOOKUP(L30,'C-01'!$D:$L,6,0),"") -> 7637.46 | Q30: =IFERROR(VLOOKUP(L30,'C-01'!$D:$L,7,0),"") -> 7848.45 | R30: =IFERROR(VLOOKUP(L30,'C-01'!$D:$L,8,0),"") -> 9161.15 | S30: =IFERROR(VLOOKUP(L30,'C-01'!$D:$L,9,0),"") -> 9161.15 | T30: =IFS('Painel Geral'!$B$5="Mediana",IFERROR(IF(OR(C30="",Q30=0,Q30=""),"",($C30/$Q30)),""),'Painel Geral'!$B$5="Menor Salário",IFERROR(IF(OR(C30="",Q30=0,Q30=""),"",($C30/$N30)),""),'Painel Geral'!$B$5="1º Quartil",IFERROR(IF(OR(C30="",Q30=0,Q30=""),"",($C30/$O30)),""), 'Painel Geral'!$B$5="Média",IFERROR(IF(OR(C30="",Q30=0,Q30=""),"",($C30/$P30)),""),'Painel Geral'!$B$5="3º Quartil",IFERROR(IF(OR(C30="",Q30=0,Q30=""),"",($C30/$R30)),""),'Painel Geral'!$B$5="Maior Salário",IFERROR(IF(OR(C30="",Q30=0,Q30=""),"",($C30/$S30)),"")) -> 0.74282183 | U30: =IFS(OR(N30="",N30=0,C30="", C30=0),"",T30<=80%,"Muito Defasado",T30<=90%,"Defasado",T30<=100%,"Na Média",T30<=110%,"Competitivo",T30<=120%,"Muito Competitivo",T30>120%,"Agressivo") -> Muito Defasado | Y30: 1907 | Z30: 1922.4698 | AA30: 2306.9638
A31: 29 | B31: =VLOOKUP(A31,Jobmatch!A:G,2,0) -> COORDENADOR DE MARKETING II | C31: =IFERROR(AVERAGEIF('Folha de Pagamento'!A:A,A31,'Folha de Pagamento'!J:J),"") -> 8647 | D31: 8 | E31: =VLOOKUP(A31,Jobmatch!A:H,3,0) -> Marketing | F31: Coordenador Marketing | G31: =VLOOKUP(A31,Jobmatch!A:I,4,0) -> 36 - ADM PROJETOS | H31: =VLOOKUP(A31,Jobmatch!A:I,5,0) -> Tático | I31: =VLOOKUP(A31,Jobmatch!A:I,6,0) -> 56 | J31: =VLOOKUP(A31,Jobmatch!A:I,7,0) -> Coordenador de Marketing | K31: =VLOOKUP(A31,Jobmatch!A:I,8,0) -> Indiferente | L31: =I31&K31 -> 56Indiferente | M31: =COUNTIF('Folha de Pagamento'!A:A,A31) -> 1 | N31: 17 | O31: =IFERROR(VLOOKUP(L31,'C-01'!$D:$L,5,0),"") -> 7141.59 | P31: =IFERROR(VLOOKUP(L31,'C-01'!$D:$L,6,0),"") -> 7927.07 | Q31: =IFERROR(VLOOKUP(L31,'C-01'!$D:$L,7,0),"") -> 7958.59 | R31: =IFERROR(VLOOKUP(L31,'C-01'!$D:$L,8,0),"") -> 8825.19 | S31: =IFERROR(VLOOKUP(L31,'C-01'!$D:$L,9,0),"") -> 10531.61 | T31: =IFS('Painel Geral'!$B$5="Mediana",IFERROR(IF(OR(C31="",Q31=0,Q31=""),"",($C31/$Q31)),""),'Painel Geral'!$B$5="Menor Salário",IFERROR(IF(OR(C31="",Q31=0,Q31=""),"",($C31/$N31)),""),'Painel Geral'!$B$5="1º Quartil",IFERROR(IF(OR(C31="",Q31=0,Q31=""),"",($C31/$O31)),""), 'Painel Geral'!$B$5="Média",IFERROR(IF(OR(C31="",Q31=0,Q31=""),"",($C31/$P31)),""),'Painel Geral'!$B$5="3º Quartil",IFERROR(IF(OR(C31="",Q31=0,Q31=""),"",($C31/$R31)),""),'Painel Geral'!$B$5="Maior Salário",IFERROR(IF(OR(C31="",Q31=0,Q31=""),"",($C31/$S31)),"")) -> 1.086499 | U31: =IFS(OR(N31="",N31=0,C31="", C31=0),"",T31<=80%,"Muito Defasado",T31<=90%,"Defasado",T31<=100%,"Na Média",T31<=110%,"Competitivo",T31<=120%,"Muito Competitivo",T31>120%,"Agressivo") -> Competitivo | Y31: 0.8 | Z31: grade | AA31: 1 | AN31: =AN29/AN27 -> 0
A32: 28 | B32: =VLOOKUP(A32,Jobmatch!A:G,2,0) -> COORDENADOR DE LEGAIZAÇÃO ll | C32: =IFERROR(AVERAGEIF('Folha de Pagamento'!A:A,A32,'Folha de Pagamento'!J:J),"") -> 8647 | D32: 7 | E32: =VLOOKUP(A32,Jobmatch!A:H,3,0) -> Legalização | F32: Coordenador Legalização Pl | G32: =VLOOKUP(A32,Jobmatch!A:I,4,0) -> 35 - ADM PROJETOS | H32: =VLOOKUP(A32,Jobmatch!A:I,5,0) -> Tático | I32: =VLOOKUP(A32,Jobmatch!A:I,6,0) -> 1203 | J32: =VLOOKUP(A32,Jobmatch!A:I,7,0) -> Coordenador de Legalização | K32: =VLOOKUP(A32,Jobmatch!A:I,8,0) -> Indiferente | L32: =I32&K32 -> 1203Indiferente | M32: =COUNTIF('Folha de Pagamento'!A:A,A32) -> 1 | N32: 17 | O32: =IFERROR(VLOOKUP(L32,'C-01'!$D:$L,5,0),"") -> 8783.31 | P32: =IFERROR(VLOOKUP(L32,'C-01'!$D:$L,6,0),"") -> 8872.04 | Q32: =IFERROR(VLOOKUP(L32,'C-01'!$D:$L,7,0),"") -> 8872.04 | R32: =IFERROR(VLOOKUP(L32,'C-01'!$D:$L,8,0),"") -> 8960.78 | S32: =IFERROR(VLOOKUP(L32,'C-01'!$D:$L,9,0),"") -> 9049.51 | T32: =IFS('Painel Geral'!$B$5="Mediana",IFERROR(IF(OR(C32="",Q32=0,Q32=""),"",($C32/$Q32)),""),'Painel Geral'!$B$5="Menor Salário",IFERROR(IF(OR(C32="",Q32=0,Q32=""),"",($C32/$N32)),""),'Painel Geral'!$B$5="1º Quartil",IFERROR(IF(OR(C32="",Q32=0,Q32=""),"",($C32/$O32)),""), 'Painel Geral'!$B$5="Média",IFERROR(IF(OR(C32="",Q32=0,Q32=""),"",($C32/$P32)),""),'Painel Geral'!$B$5="3º Quartil",IFERROR(IF(OR(C32="",Q32=0,Q32=""),"",($C32/$R32)),""),'Painel Geral'!$B$5="Maior Salário",IFERROR(IF(OR(C32="",Q32=0,Q32=""),"",($C32/$S32)),"")) -> 0.97463492 | U32: =IFS(OR(N32="",N32=0,C32="", C32=0),"",T32<=80%,"Muito Defasado",T32<=90%,"Defasado",T32<=100%,"Na Média",T32<=110%,"Competitivo",T32<=120%,"Muito Competitivo",T32>120%,"Agressivo") -> Na Média | Y32: =AA32*0.8 -> 1782.4 | Z32: 10 | AA32: =-6062+1720*Z32-145*Z32*Z32+5.59*Z32*Z32*Z32 -> 2228 | AC32: =$Z$30*1.2 -> 2306.9638
A33: 42 | B33: =VLOOKUP(A33,Jobmatch!A:G,2,0) -> GERENTE ADMINISTRATIVA | C33: =IFERROR(AVERAGEIF('Folha de Pagamento'!A:A,A33,'Folha de Pagamento'!J:J),"") -> 12242.424 | D33: 1 | E33: =VLOOKUP(A33,Jobmatch!A:H,3,0) -> Administrativo | F33: Gerente Administrativa | G33: =VLOOKUP(A33,Jobmatch!A:I,4,0) -> 49 - ADM PROJETOS | H33: =VLOOKUP(A33,Jobmatch!A:I,5,0) -> Tático | I33: =VLOOKUP(A33,Jobmatch!A:I,6,0) -> 106 | J33: =VLOOKUP(A33,Jobmatch!A:I,7,0) -> Gerente Administrativo | K33: =VLOOKUP(A33,Jobmatch!A:I,8,0) -> Indiferente | L33: =I33&K33 -> 106Indiferente | M33: =COUNTIF('Folha de Pagamento'!A:A,A33) -> 2 | N33: 18 | O33: =IFERROR(VLOOKUP(L33,'C-01'!$D:$L,5,0),"") -> 6616.13 | P33: =IFERROR(VLOOKUP(L33,'C-01'!$D:$L,6,0),"") -> 9881.52 | Q33: =IFERROR(VLOOKUP(L33,'C-01'!$D:$L,7,0),"") -> 10052.23 | R33: =IFERROR(VLOOKUP(L33,'C-01'!$D:$L,8,0),"") -> 12479.94 | S33: =IFERROR(VLOOKUP(L33,'C-01'!$D:$L,9,0),"") -> 15257.82 | T33: =IFS('Painel Geral'!$B$5="Mediana",IFERROR(IF(OR(C33="",Q33=0,Q33=""),"",($C33/$Q33)),""),'Painel Geral'!$B$5="Menor Salário",IFERROR(IF(OR(C33="",Q33=0,Q33=""),"",($C33/$N33)),""),'Painel Geral'!$B$5="1º Quartil",IFERROR(IF(OR(C33="",Q33=0,Q33=""),"",($C33/$O33)),""), 'Painel Geral'!$B$5="Média",IFERROR(IF(OR(C33="",Q33=0,Q33=""),"",($C33/$P33)),""),'Painel Geral'!$B$5="3º Quartil",IFERROR(IF(OR(C33="",Q33=0,Q33=""),"",($C33/$R33)),""),'Painel Geral'!$B$5="Maior Salário",IFERROR(IF(OR(C33="",Q33=0,Q33=""),"",($C33/$S33)),"")) -> 1.2178814 | U33: =IFS(OR(N33="",N33=0,C33="", C33=0),"",T33<=80%,"Muito Defasado",T33<=90%,"Defasado",T33<=100%,"Na Média",T33<=110%,"Competitivo",T33<=120%,"Muito Competitivo",T33>120%,"Agressivo") -> Agressivo | Z33: 11 | AA33: =-6062+1720*Z33-145*Z33*Z33+5.59*Z33*Z33*Z33 -> 2753.29 | AB33: =(AA33-AA32)/AA32 -> 0.2357675 | AC33: =AC32*1.2 -> 2768.3565
A34: 48 | B34: =VLOOKUP(A34,Jobmatch!A:G,2,0) -> GERENTE DE PARCERIAS | C34: =IFERROR(AVERAGEIF('Folha de Pagamento'!A:A,A34,'Folha de Pagamento'!J:J),"") -> 5345 | D34: 2 | E34: =VLOOKUP(A34,Jobmatch!A:H,3,0) -> Comercial | F34: Gerente Parcerias | G34: =VLOOKUP(A34,Jobmatch!A:I,4,0) -> 55 - ADM PROJETOS | H34: =VLOOKUP(A34,Jobmatch!A:I,5,0) -> Tático | I34: =VLOOKUP(A34,Jobmatch!A:I,6,0) -> 408 | J34: =VLOOKUP(A34,Jobmatch!A:I,7,0) -> Gerente de Relacionamento | K34: =VLOOKUP(A34,Jobmatch!A:I,8,0) -> Indiferente | L34: =I34&K34 -> 408Indiferente | M34: =COUNTIF('Folha de Pagamento'!A:A,A34) -> 2 | N34: 18 | O34: =IFERROR(VLOOKUP(L34,'C-01'!$D:$L,5,0),"") -> 7608.96 | P34: =IFERROR(VLOOKUP(L34,'C-01'!$D:$L,6,0),"") -> 10973.95 | Q34: =IFERROR(VLOOKUP(L34,'C-01'!$D:$L,7,0),"") -> 10996.97 | R34: =IFERROR(VLOOKUP(L34,'C-01'!$D:$L,8,0),"") -> 14004.27 | S34: =IFERROR(VLOOKUP(L34,'C-01'!$D:$L,9,0),"") -> 16628.86 | T34: =IFS('Painel Geral'!$B$5="Mediana",IFERROR(IF(OR(C34="",Q34=0,Q34=""),"",($C34/$Q34)),""),'Painel Geral'!$B$5="Menor Salário",IFERROR(IF(OR(C34="",Q34=0,Q34=""),"",($C34/$N34)),""),'Painel Geral'!$B$5="1º Quartil",IFERROR(IF(OR(C34="",Q34=0,Q34=""),"",($C34/$O34)),""), 'Painel Geral'!$B$5="Média",IFERROR(IF(OR(C34="",Q34=0,Q34=""),"",($C34/$P34)),""),'Painel Geral'!$B$5="3º Quartil",IFERROR(IF(OR(C34="",Q34=0,Q34=""),"",($C34/$R34)),""),'Painel Geral'!$B$5="Maior Salário",IFERROR(IF(OR(C34="",Q34=0,Q34=""),"",($C34/$S34)),"")) -> 0.48604297 | U34: =IFS(OR(N34="",N34=0,C34="", C34=0),"",T34<=80%,"Muito Defasado",T34<=90%,"Defasado",T34<=100%,"Na Média",T34<=110%,"Competitivo",T34<=120%,"Muito Competitivo",T34>120%,"Agressivo") -> Muito Defasado | Z34: 12 | AA34: =-6062+1720*Z34-145*Z34*Z34+5.59*Z34*Z34*Z34 -> 3357.52 | AB34: =(AA34-AA33)/AA33 -> 0.21945745 | AC34: =AC33*1.2 -> 3322.0278
A35: 49 | B35: =VLOOKUP(A35,Jobmatch!A:G,2,0) -> GERENTE DE PARCERIAS EXTERNAS | C35: =IFERROR(AVERAGEIF('Folha de Pagamento'!A:A,A35,'Folha de Pagamento'!J:J),"") -> 5000 | D35: 2 | E35: =VLOOKUP(A35,Jobmatch!A:H,3,0) -> Comercial | F35: Gerente Parcerias Externas | G35: =VLOOKUP(A35,Jobmatch!A:I,4,0) -> 56 - ADM PROJETOS | H35: =VLOOKUP(A35,Jobmatch!A:I,5,0) -> Tático | I35: =VLOOKUP(A35,Jobmatch!A:I,6,0) -> 408 | J35: =VLOOKUP(A35,Jobmatch!A:I,7,0) -> Gerente de Relacionamento | K35: =VLOOKUP(A35,Jobmatch!A:I,8,0) -> Indiferente | L35: =I35&K35 -> 408Indiferente | M35: =COUNTIF('Folha de Pagamento'!A:A,A35) -> 2 | N35: 18 | O35: =IFERROR(VLOOKUP(L35,'C-01'!$D:$L,5,0),"") -> 7608.96 | P35: =IFERROR(VLOOKUP(L35,'C-01'!$D:$L,6,0),"") -> 10973.95 | Q35: =IFERROR(VLOOKUP(L35,'C-01'!$D:$L,7,0),"") -> 10996.97 | R35: =IFERROR(VLOOKUP(L35,'C-01'!$D:$L,8,0),"") -> 14004.27 | S35: =IFERROR(VLOOKUP(L35,'C-01'!$D:$L,9,0),"") -> 16628.86 | T35: =IFS('Painel Geral'!$B$5="Mediana",IFERROR(IF(OR(C35="",Q35=0,Q35=""),"",($C35/$Q35)),""),'Painel Geral'!$B$5="Menor Salário",IFERROR(IF(OR(C35="",Q35=0,Q35=""),"",($C35/$N35)),""),'Painel Geral'!$B$5="1º Quartil",IFERROR(IF(OR(C35="",Q35=0,Q35=""),"",($C35/$O35)),""), 'Painel Geral'!$B$5="Média",IFERROR(IF(OR(C35="",Q35=0,Q35=""),"",($C35/$P35)),""),'Painel Geral'!$B$5="3º Quartil",IFERROR(IF(OR(C35="",Q35=0,Q35=""),"",($C35/$R35)),""),'Painel Geral'!$B$5="Maior Salário",IFERROR(IF(OR(C35="",Q35=0,Q35=""),"",($C35/$S35)),"")) -> 0.4546707 | U35: =IFS(OR(N35="",N35=0,C35="", C35=0),"",T35<=80%,"Muito Defasado",T35<=90%,"Defasado",T35<=100%,"Na Média",T35<=110%,"Competitivo",T35<=120%,"Muito Competitivo",T35>120%,"Agressivo") -> Muito Defasado | Z35: 13 | AA35: =-6062+1720*Z35-145*Z35*Z35+5.59*Z35*Z35*Z35 -> 4074.23 | AB35: =(AA35-AA34)/AA34 -> 0.2134641 | AC35: =AC34*1.2 -> 3986.4334
A36: 31 | B36: =VLOOKUP(A36,Jobmatch!A:G,2,0) -> COORDENADOR DE SUPRIMENTOS | C36: =IFERROR(AVERAGEIF('Folha de Pagamento'!A:A,A36,'Folha de Pagamento'!J:J),"") -> 10596.026 | D36: 1 | E36: =VLOOKUP(A36,Jobmatch!A:H,3,0) -> Suprimentos | F36: Coordenador Suprimentos | G36: =VLOOKUP(A36,Jobmatch!A:I,4,0) -> 38 - ADM PROJETOS | H36: =VLOOKUP(A36,Jobmatch!A:I,5,0) -> Tático | I36: =VLOOKUP(A36,Jobmatch!A:I,6,0) -> 137 | J36: =VLOOKUP(A36,Jobmatch!A:I,7,0) -> Coordenador de Compras | K36: =VLOOKUP(A36,Jobmatch!A:I,8,0) -> Indiferente | L36: =I36&K36 -> 137Indiferente | M36: =COUNTIF('Folha de Pagamento'!A:A,A36) -> 1 | N36: 18 | O36: =IFERROR(VLOOKUP(L36,'C-01'!$D:$L,5,0),"") -> 10557.77 | P36: =IFERROR(VLOOKUP(L36,'C-01'!$D:$L,6,0),"") -> 13345.69 | Q36: =IFERROR(VLOOKUP(L36,'C-01'!$D:$L,7,0),"") -> 11060.52 | R36: =IFERROR(VLOOKUP(L36,'C-01'!$D:$L,8,0),"") -> 14991.02 | S36: =IFERROR(VLOOKUP(L36,'C-01'!$D:$L,9,0),"") -> 18921.53 | T36: =IFS('Painel Geral'!$B$5="Mediana",IFERROR(IF(OR(C36="",Q36=0,Q36=""),"",($C36/$Q36)),""),'Painel Geral'!$B$5="Menor Salário",IFERROR(IF(OR(C36="",Q36=0,Q36=""),"",($C36/$N36)),""),'Painel Geral'!$B$5="1º Quartil",IFERROR(IF(OR(C36="",Q36=0,Q36=""),"",($C36/$O36)),""), 'Painel Geral'!$B$5="Média",IFERROR(IF(OR(C36="",Q36=0,Q36=""),"",($C36/$P36)),""),'Painel Geral'!$B$5="3º Quartil",IFERROR(IF(OR(C36="",Q36=0,Q36=""),"",($C36/$R36)),""),'Painel Geral'!$B$5="Maior Salário",IFERROR(IF(OR(C36="",Q36=0,Q36=""),"",($C36/$S36)),"")) -> 0.95800437 | U36: =IFS(OR(N36="",N36=0,C36="", C36=0),"",T36<=80%,"Muito Defasado",T36<=90%,"Defasado",T36<=100%,"Na Média",T36<=110%,"Competitivo",T36<=120%,"Muito Competitivo",T36>120%,"Agressivo") -> Na Média | Z36: 14 | AA36: =-6062+1720*Z36-145*Z36*Z36+5.59*Z36*Z36*Z36 -> 4936.96 | AB36: =(AA36-AA35)/AA35 -> 0.2117529 | AC36: =AC35*1.2 -> 4783.72
A37: 43 | B37: =VLOOKUP(A37,Jobmatch!A:G,2,0) -> GERENTE COMERCIAL | C37: =IFERROR(AVERAGEIF('Folha de Pagamento'!A:A,A37,'Folha de Pagamento'!J:J),"") -> 12090.909 | D37: 2 | E37: =VLOOKUP(A37,Jobmatch!A:H,3,0) -> Comercial | F37: Gerente Comercial | G37: =VLOOKUP(A37,Jobmatch!A:I,4,0) -> 50 - ADM PROJETOS | H37: =VLOOKUP(A37,Jobmatch!A:I,5,0) -> Tático | I37: =VLOOKUP(A37,Jobmatch!A:I,6,0) -> 107 | J37: =VLOOKUP(A37,Jobmatch!A:I,7,0) -> Gerente Comercial | K37: =VLOOKUP(A37,Jobmatch!A:I,8,0) -> Indiferente | L37: =I37&K37 -> 107Indiferente | M37: =COUNTIF('Folha de Pagamento'!A:A,A37) -> 4 | N37: 19 | O37: =IFERROR(VLOOKUP(L37,'C-01'!$D:$L,5,0),"") -> 9778.91 | P37: =IFERROR(VLOOKUP(L37,'C-01'!$D:$L,6,0),"") -> 12281.04 | Q37: =IFERROR(VLOOKUP(L37,'C-01'!$D:$L,7,0),"") -> 12107.57 | R37: =IFERROR(VLOOKUP(L37,'C-01'!$D:$L,8,0),"") -> 15321.87 | S37: =IFERROR(VLOOKUP(L37,'C-01'!$D:$L,9,0),"") -> 19289.48 | T37: =IFS('Painel Geral'!$B$5="Mediana",IFERROR(IF(OR(C37="",Q37=0,Q37=""),"",($C37/$Q37)),""),'Painel Geral'!$B$5="Menor Salário",IFERROR(IF(OR(C37="",Q37=0,Q37=""),"",($C37/$N37)),""),'Painel Geral'!$B$5="1º Quartil",IFERROR(IF(OR(C37="",Q37=0,Q37=""),"",($C37/$O37)),""), 'Painel Geral'!$B$5="Média",IFERROR(IF(OR(C37="",Q37=0,Q37=""),"",($C37/$P37)),""),'Painel Geral'!$B$5="3º Quartil",IFERROR(IF(OR(C37="",Q37=0,Q37=""),"",($C37/$R37)),""),'Painel Geral'!$B$5="Maior Salário",IFERROR(IF(OR(C37="",Q37=0,Q37=""),"",($C37/$S37)),"")) -> 0.99862393 | U37: =IFS(OR(N37="",N37=0,C37="", C37=0),"",T37<=80%,"Muito Defasado",T37<=90%,"Defasado",T37<=100%,"Na Média",T37<=110%,"Competitivo",T37<=120%,"Muito Competitivo",T37>120%,"Agressivo") -> Na Média | Z37: 15 | AA37: =-6062+1720*Z37-145*Z37*Z37+5.59*Z37*Z37*Z37 -> 5979.25 | AB37: =(AA37-AA36)/AA36 -> 0.2111198 | AC37: =AC36*1.2 -> 5740.4641
A38: 45 | B38: =VLOOKUP(A38,Jobmatch!A:G,2,0) -> GERENTE DE HOUSE | C38: =IFERROR(AVERAGEIF('Folha de Pagamento'!A:A,A38,'Folha de Pagamento'!J:J),"") -> 5125 | D38: 2 | E38: =VLOOKUP(A38,Jobmatch!A:H,3,0) -> Comercial | F38: Gerente House | G38: =VLOOKUP(A38,Jobmatch!A:I,4,0) -> 52 - ADM PROJETOS | H38: =VLOOKUP(A38,Jobmatch!A:I,5,0) -> Tático | I38: =VLOOKUP(A38,Jobmatch!A:I,6,0) -> 107 | J38: =VLOOKUP(A38,Jobmatch!A:I,7,0) -> Gerente Comercial | K38: =VLOOKUP(A38,Jobmatch!A:I,8,0) -> Indiferente | L38: =I38&K38 -> 107Indiferente | M38: =COUNTIF('Folha de Pagamento'!A:A,A38) -> 1 | N38: 19 | O38: =IFERROR(VLOOKUP(L38,'C-01'!$D:$L,5,0),"") -> 9778.91 | P38: =IFERROR(VLOOKUP(L38,'C-01'!$D:$L,6,0),"") -> 12281.04 | Q38: =IFERROR(VLOOKUP(L38,'C-01'!$D:$L,7,0),"") -> 12107.57 | R38: =IFERROR(VLOOKUP(L38,'C-01'!$D:$L,8,0),"") -> 15321.87 | S38: =IFERROR(VLOOKUP(L38,'C-01'!$D:$L,9,0),"") -> 19289.48 | T38: =IFS('Painel Geral'!$B$5="Mediana",IFERROR(IF(OR(C38="",Q38=0,Q38=""),"",($C38/$Q38)),""),'Painel Geral'!$B$5="Menor Salário",IFERROR(IF(OR(C38="",Q38=0,Q38=""),"",($C38/$N38)),""),'Painel Geral'!$B$5="1º Quartil",IFERROR(IF(OR(C38="",Q38=0,Q38=""),"",($C38/$O38)),""), 'Painel Geral'!$B$5="Média",IFERROR(IF(OR(C38="",Q38=0,Q38=""),"",($C38/$P38)),""),'Painel Geral'!$B$5="3º Quartil",IFERROR(IF(OR(C38="",Q38=0,Q38=""),"",($C38/$R38)),""),'Painel Geral'!$B$5="Maior Salário",IFERROR(IF(OR(C38="",Q38=0,Q38=""),"",($C38/$S38)),"")) -> 0.4232889 | U38: =IFS(OR(N38="",N38=0,C38="", C38=0),"",T38<=80%,"Muito Defasado",T38<=90%,"Defasado",T38<=100%,"Na Média",T38<=110%,"Competitivo",T38<=120%,"Muito Competitivo",T38>120%,"Agressivo") -> Muito Defasado | Z38: 16 | AA38: =-6062+1720*Z38-145*Z38*Z38+5.59*Z38*Z38*Z38 -> 7234.64 | AB38: =(AA38-AA37)/AA37 -> 0.20995777 | AC38: =AC37*1.2 -> 6888.5569
A39: 44 | B39: =VLOOKUP(A39,Jobmatch!A:G,2,0) -> GERENTE DE EDIFICAÇÕES | C39: =IFERROR(AVERAGEIF('Folha de Pagamento'!A:A,A39,'Folha de Pagamento'!J:J),"") -> 30106.061 | D39: 5 | E39: =VLOOKUP(A39,Jobmatch!A:H,3,0) -> Edificação | F39: Gerente Edificações | G39: =VLOOKUP(A39,Jobmatch!A:I,4,0) -> 51 - ADM PROJETOS | H39: =VLOOKUP(A39,Jobmatch!A:I,5,0) -> Tático | I39: =VLOOKUP(A39,Jobmatch!A:I,6,0) -> 311 | J39: =VLOOKUP(A39,Jobmatch!A:I,7,0) -> Gerente de Operações | K39: =VLOOKUP(A39,Jobmatch!A:I,8,0) -> Indiferente | L39: =I39&K39 -> 311Indiferente | M39: =COUNTIF('Folha de Pagamento'!A:A,A39) -> 1 | N39: 19 | O39: =IFERROR(VLOOKUP(L39,'C-01'!$D:$L,5,0),"") -> 10114.75 | P39: =IFERROR(VLOOKUP(L39,'C-01'!$D:$L,6,0),"") -> 12711.42 | Q39: =IFERROR(VLOOKUP(L39,'C-01'!$D:$L,7,0),"") -> 12517.82 | R39: =IFERROR(VLOOKUP(L39,'C-01'!$D:$L,8,0),"") -> 14749 | S39: =IFERROR(VLOOKUP(L39,'C-01'!$D:$L,9,0),"") -> 19098.65 | T39: =IFS('Painel Geral'!$B$5="Mediana",IFERROR(IF(OR(C39="",Q39=0,Q39=""),"",($C39/$Q39)),""),'Painel Geral'!$B$5="Menor Salário",IFERROR(IF(OR(C39="",Q39=0,Q39=""),"",($C39/$N39)),""),'Painel Geral'!$B$5="1º Quartil",IFERROR(IF(OR(C39="",Q39=0,Q39=""),"",($C39/$O39)),""), 'Painel Geral'!$B$5="Média",IFERROR(IF(OR(C39="",Q39=0,Q39=""),"",($C39/$P39)),""),'Painel Geral'!$B$5="3º Quartil",IFERROR(IF(OR(C39="",Q39=0,Q39=""),"",($C39/$R39)),""),'Painel Geral'!$B$5="Maior Salário",IFERROR(IF(OR(C39="",Q39=0,Q39=""),"",($C39/$S39)),"")) -> 2.4050562 | U39: =IFS(OR(N39="",N39=0,C39="", C39=0),"",T39<=80%,"Muito Defasado",T39<=90%,"Defasado",T39<=100%,"Na Média",T39<=110%,"Competitivo",T39<=120%,"Muito Competitivo",T39>120%,"Agressivo") -> Agressivo | Z39: 17 | AA39: =-6062+1720*Z39-145*Z39*Z39+5.59*Z39*Z39*Z39 -> 8736.67 | AB39: =(AA39-AA38)/AA38 -> 0.20761641 | AC39: =AC38*1.2 -> 8266.2682
A40: 50 | B40: =VLOOKUP(A40,Jobmatch!A:G,2,0) -> GERENTE DE URBANISMO | C40: =IFERROR(AVERAGEIF('Folha de Pagamento'!A:A,A40,'Folha de Pagamento'!J:J),"") -> 28030.303 | D40: 10 | E40: =VLOOKUP(A40,Jobmatch!A:H,3,0) -> Urbanismo | F40: Gerente Urbanismo | G40: =VLOOKUP(A40,Jobmatch!A:I,4,0) -> 57 - ADM PROJETOS | H40: =VLOOKUP(A40,Jobmatch!A:I,5,0) -> Tático | I40: =VLOOKUP(A40,Jobmatch!A:I,6,0) -> 311 | J40: =VLOOKUP(A40,Jobmatch!A:I,7,0) -> Gerente de Operações | K40: =VLOOKUP(A40,Jobmatch!A:I,8,0) -> Indiferente | L40: =I40&K40 -> 311Indiferente | M40: =COUNTIF('Folha de Pagamento'!A:A,A40) -> 2 | N40: 19 | O40: =IFERROR(VLOOKUP(L40,'C-01'!$D:$L,5,0),"") -> 10114.75 | P40: =IFERROR(VLOOKUP(L40,'C-01'!$D:$L,6,0),"") -> 12711.42 | Q40: =IFERROR(VLOOKUP(L40,'C-01'!$D:$L,7,0),"") -> 12517.82 | R40: =IFERROR(VLOOKUP(L40,'C-01'!$D:$L,8,0),"") -> 14749 | S40: =IFERROR(VLOOKUP(L40,'C-01'!$D:$L,9,0),"") -> 19098.65 | T40: =IFS('Painel Geral'!$B$5="Mediana",IFERROR(IF(OR(C40="",Q40=0,Q40=""),"",($C40/$Q40)),""),'Painel Geral'!$B$5="Menor Salário",IFERROR(IF(OR(C40="",Q40=0,Q40=""),"",($C40/$N40)),""),'Painel Geral'!$B$5="1º Quartil",IFERROR(IF(OR(C40="",Q40=0,Q40=""),"",($C40/$O40)),""), 'Painel Geral'!$B$5="Média",IFERROR(IF(OR(C40="",Q40=0,Q40=""),"",($C40/$P40)),""),'Painel Geral'!$B$5="3º Quartil",IFERROR(IF(OR(C40="",Q40=0,Q40=""),"",($C40/$R40)),""),'Painel Geral'!$B$5="Maior Salário",IFERROR(IF(OR(C40="",Q40=0,Q40=""),"",($C40/$S40)),"")) -> 2.239232 | U40: =IFS(OR(N40="",N40=0,C40="", C40=0),"",T40<=80%,"Muito Defasado",T40<=90%,"Defasado",T40<=100%,"Na Média",T40<=110%,"Competitivo",T40<=120%,"Muito Competitivo",T40>120%,"Agressivo") -> Agressivo | Z40: 18 | AA40: =-6062+1720*Z40-145*Z40*Z40+5.59*Z40*Z40*Z40 -> 10518.88 | AB40: =(AA40-AA39)/AA39 -> 0.20399191 | AC40: =AC39*1.2 -> 9919.5219
A41: 27 | B41: =VLOOKUP(A41,Jobmatch!A:G,2,0) -> COORDENADOR DE DHO | C41: =IFERROR(AVERAGEIF('Folha de Pagamento'!A:A,A41,'Folha de Pagamento'!J:J),"") -> 7420 | D41: 4 | E41: =VLOOKUP(A41,Jobmatch!A:H,3,0) -> DHO | F41: Coordenador DHO | G41: =VLOOKUP(A41,Jobmatch!A:I,4,0) -> 34 - ADM PROJETOS | H41: =VLOOKUP(A41,Jobmatch!A:I,5,0) -> Tático | I41: =VLOOKUP(A41,Jobmatch!A:I,6,0) -> 121 | J41: =VLOOKUP(A41,Jobmatch!A:I,7,0) -> Coordenador de Recursos Humanos | K41: =VLOOKUP(A41,Jobmatch!A:I,8,0) -> Indiferente | L41: =I41&K41 -> 121Indiferente | M41: =COUNTIF('Folha de Pagamento'!A:A,A41) -> 1 | N41: 19 | O41: =IFERROR(VLOOKUP(L41,'C-01'!$D:$L,5,0),"") -> 10014.8 | P41: =IFERROR(VLOOKUP(L41,'C-01'!$D:$L,6,0),"") -> 11303.85 | Q41: =IFERROR(VLOOKUP(L41,'C-01'!$D:$L,7,0),"") -> 12568.77 | R41: =IFERROR(VLOOKUP(L41,'C-01'!$D:$L,8,0),"") -> 13225.36 | S41: =IFERROR(VLOOKUP(L41,'C-01'!$D:$L,9,0),"") -> 13881.95 | T41: =IFS('Painel Geral'!$B$5="Mediana",IFERROR(IF(OR(C41="",Q41=0,Q41=""),"",($C41/$Q41)),""),'Painel Geral'!$B$5="Menor Salário",IFERROR(IF(OR(C41="",Q41=0,Q41=""),"",($C41/$N41)),""),'Painel Geral'!$B$5="1º Quartil",IFERROR(IF(OR(C41="",Q41=0,Q41=""),"",($C41/$O41)),""), 'Painel Geral'!$B$5="Média",IFERROR(IF(OR(C41="",Q41=0,Q41=""),"",($C41/$P41)),""),'Painel Geral'!$B$5="3º Quartil",IFERROR(IF(OR(C41="",Q41=0,Q41=""),"",($C41/$R41)),""),'Painel Geral'!$B$5="Maior Salário",IFERROR(IF(OR(C41="",Q41=0,Q41=""),"",($C41/$S41)),"")) -> 0.59035212 | U41: =IFS(OR(N41="",N41=0,C41="", C41=0),"",T41<=80%,"Muito Defasado",T41<=90%,"Defasado",T41<=100%,"Na Média",T41<=110%,"Competitivo",T41<=120%,"Muito Competitivo",T41>120%,"Agressivo") -> Muito Defasado | Z41: 19 | AA41: =-6062+1720*Z41-145*Z41*Z41+5.59*Z41*Z41*Z41 -> 12614.81 | AB41: =(AA41-AA40)/AA40 -> 0.1992541 | AC41: =AC40*1.2 -> 11903.426
A42: 26 | B42: =VLOOKUP(A42,Jobmatch!A:G,2,0) -> CONTROLLER TÉCNICO | C42: =IFERROR(AVERAGEIF('Folha de Pagamento'!A:A,A42,'Folha de Pagamento'!J:J),"") -> 9243.5037 | D42: 3 | E42: =VLOOKUP(A42,Jobmatch!A:H,3,0) -> Controladoria | F42: Controller Técnico | G42: =VLOOKUP(A42,Jobmatch!A:I,4,0) -> 33 - ADM PROJETOS | H42: =VLOOKUP(A42,Jobmatch!A:I,5,0) -> Tático | I42: =VLOOKUP(A42,Jobmatch!A:I,6,0) -> 26 | J42: =VLOOKUP(A42,Jobmatch!A:I,7,0) -> Analista de Controladoria | K42: =VLOOKUP(A42,Jobmatch!A:I,8,0) -> Especialista | L42: =I42&K42 -> 26Especialista | M42: =COUNTIF('Folha de Pagamento'!A:A,A42) -> 1 | N42: 19 | O42: =IFERROR(VLOOKUP(L42,'C-01'!$D:$L,5,0),"") -> 10665.2 | P42: =IFERROR(VLOOKUP(L42,'C-01'!$D:$L,6,0),"") -> 12572.61 | Q42: =IFERROR(VLOOKUP(L42,'C-01'!$D:$L,7,0),"") -> 13758.75 | R42: =IFERROR(VLOOKUP(L42,'C-01'!$D:$L,8,0),"") -> 15666.17 | S42: =IFERROR(VLOOKUP(L42,'C-01'!$D:$L,9,0),"") -> 15995.86 | T42: =IFS('Painel Geral'!$B$5="Mediana",IFERROR(IF(OR(C42="",Q42=0,Q42=""),"",($C42/$Q42)),""),'Painel Geral'!$B$5="Menor Salário",IFERROR(IF(OR(C42="",Q42=0,Q42=""),"",($C42/$N42)),""),'Painel Geral'!$B$5="1º Quartil",IFERROR(IF(OR(C42="",Q42=0,Q42=""),"",($C42/$O42)),""), 'Painel Geral'!$B$5="Média",IFERROR(IF(OR(C42="",Q42=0,Q42=""),"",($C42/$P42)),""),'Painel Geral'!$B$5="3º Quartil",IFERROR(IF(OR(C42="",Q42=0,Q42=""),"",($C42/$R42)),""),'Painel Geral'!$B$5="Maior Salário",IFERROR(IF(OR(C42="",Q42=0,Q42=""),"",($C42/$S42)),"")) -> 0.67182728 | U42: =IFS(OR(N42="",N42=0,C42="", C42=0),"",T42<=80%,"Muito Defasado",T42<=90%,"Defasado",T42<=100%,"Na Média",T42<=110%,"Competitivo",T42<=120%,"Muito Competitivo",T42>120%,"Agressivo") -> Muito Defasado | Z42: 20 | AA42: =-6062+1720*Z42-145*Z42*Z42+5.59*Z42*Z42*Z42 -> 15058 | AB42: =(AA42-AA41)/AA41 -> 0.19367632 | AC42: =AC41*1.2 -> 14284.112
A43: 37 | B43: =VLOOKUP(A43,Jobmatch!A:G,2,0) -> ENGENHEIRO SÊNIOR | C43: =IFERROR(AVERAGEIF('Folha de Pagamento'!A:A,A43,'Folha de Pagamento'!J:J),"") -> 14393.939 | D43: 5 | E43: =VLOOKUP(A43,Jobmatch!A:H,3,0) -> Edificação | F43: Engenheiro Sr | G43: =VLOOKUP(A43,Jobmatch!A:I,4,0) -> 44 - ADM PROJETOS | H43: =VLOOKUP(A43,Jobmatch!A:I,5,0) -> Tático | I43: =VLOOKUP(A43,Jobmatch!A:I,6,0) -> 212 | J43: =VLOOKUP(A43,Jobmatch!A:I,7,0) -> Engenheiro de Urbanismo | K43: =VLOOKUP(A43,Jobmatch!A:I,8,0) -> Indiferente | L43: =I43&K43 -> 212Indiferente | M43: =COUNTIF('Folha de Pagamento'!A:A,A43) -> 1 | N43: 20 | O43: =IFERROR(VLOOKUP(L43,'C-01'!$D:$L,5,0),"") -> 12766.6 | P43: =IFERROR(VLOOKUP(L43,'C-01'!$D:$L,6,0),"") -> 14293.39 | Q43: =IFERROR(VLOOKUP(L43,'C-01'!$D:$L,7,0),"") -> 15082.52 | R43: =IFERROR(VLOOKUP(L43,'C-01'!$D:$L,8,0),"") -> 16110.29 | S43: =IFERROR(VLOOKUP(L43,'C-01'!$D:$L,9,0),"") -> 16164.64 | T43: =IFS('Painel Geral'!$B$5="Mediana",IFERROR(IF(OR(C43="",Q43=0,Q43=""),"",($C43/$Q43)),""),'Painel Geral'!$B$5="Menor Salário",IFERROR(IF(OR(C43="",Q43=0,Q43=""),"",($C43/$N43)),""),'Painel Geral'!$B$5="1º Quartil",IFERROR(IF(OR(C43="",Q43=0,Q43=""),"",($C43/$O43)),""), 'Painel Geral'!$B$5="Média",IFERROR(IF(OR(C43="",Q43=0,Q43=""),"",($C43/$P43)),""),'Painel Geral'!$B$5="3º Quartil",IFERROR(IF(OR(C43="",Q43=0,Q43=""),"",($C43/$R43)),""),'Painel Geral'!$B$5="Maior Salário",IFERROR(IF(OR(C43="",Q43=0,Q43=""),"",($C43/$S43)),"")) -> 0.95434579 | U43: =IFS(OR(N43="",N43=0,C43="", C43=0),"",T43<=80%,"Muito Defasado",T43<=90%,"Defasado",T43<=100%,"Na Média",T43<=110%,"Competitivo",T43<=120%,"Muito Competitivo",T43>120%,"Agressivo") -> Na Média | Z43: 21 | AA43: =-6062+1720*Z43-145*Z43*Z43+5.59*Z43*Z43*Z43 -> 17881.99 | AB43: =(AA43-AA42)/AA42 -> 0.18754084 | AC43: =AC42*1.2 -> 17140.934
A44: 36 | B44: =VLOOKUP(A44,Jobmatch!A:G,2,0) -> ENGENHEIRO JUNIOR DE URBANISMO | C44: =IFERROR(AVERAGEIF('Folha de Pagamento'!A:A,A44,'Folha de Pagamento'!J:J),"") -> 5630.8725 | D44: 10 | E44: =VLOOKUP(A44,Jobmatch!A:H,3,0) -> Urbanismo | F44: Engenheiro Urbanismo Jr | G44: =VLOOKUP(A44,Jobmatch!A:I,4,0) -> 43 - ADM PROJETOS | H44: =VLOOKUP(A44,Jobmatch!A:I,5,0) -> Operacional | I44: =VLOOKUP(A44,Jobmatch!A:I,6,0) -> 212 | J44: =VLOOKUP(A44,Jobmatch!A:I,7,0) -> Engenheiro de Urbanismo | K44: =VLOOKUP(A44,Jobmatch!A:I,8,0) -> Indiferente | L44: =I44&K44 -> 212Indiferente | M44: =COUNTIF('Folha de Pagamento'!A:A,A44) -> 1 | N44: 20 | O44: =IFERROR(VLOOKUP(L44,'C-01'!$D:$L,5,0),"") -> 12766.6 | P44: =IFERROR(VLOOKUP(L44,'C-01'!$D:$L,6,0),"") -> 14293.39 | Q44: =IFERROR(VLOOKUP(L44,'C-01'!$D:$L,7,0),"") -> 15082.52 | R44: =IFERROR(VLOOKUP(L44,'C-01'!$D:$L,8,0),"") -> 16110.29 | S44: =IFERROR(VLOOKUP(L44,'C-01'!$D:$L,9,0),"") -> 16164.64 | T44: =IFS('Painel Geral'!$B$5="Mediana",IFERROR(IF(OR(C44="",Q44=0,Q44=""),"",($C44/$Q44)),""),'Painel Geral'!$B$5="Menor Salário",IFERROR(IF(OR(C44="",Q44=0,Q44=""),"",($C44/$N44)),""),'Painel Geral'!$B$5="1º Quartil",IFERROR(IF(OR(C44="",Q44=0,Q44=""),"",($C44/$O44)),""), 'Painel Geral'!$B$5="Média",IFERROR(IF(OR(C44="",Q44=0,Q44=""),"",($C44/$P44)),""),'Painel Geral'!$B$5="3º Quartil",IFERROR(IF(OR(C44="",Q44=0,Q44=""),"",($C44/$R44)),""),'Painel Geral'!$B$5="Maior Salário",IFERROR(IF(OR(C44="",Q44=0,Q44=""),"",($C44/$S44)),"")) -> 0.37333764 | U44: =IFS(OR(N44="",N44=0,C44="", C44=0),"",T44<=80%,"Muito Defasado",T44<=90%,"Defasado",T44<=100%,"Na Média",T44<=110%,"Competitivo",T44<=120%,"Muito Competitivo",T44>120%,"Agressivo") -> Muito Defasado | Z44: 22 | AA44: =-6062+1720*Z44-145*Z44*Z44+5.59*Z44*Z44*Z44 -> 21120.32 | AB44: =(AA44-AA43)/AA43 -> 0.1810945 | AC44: =AC43*1.2 -> 20569.121
... A46: 25 | B46: =VLOOKUP(A46,Jobmatch!A:G,2,0) -> CONTROLLER GERAL | C46: =IFERROR(AVERAGEIF('Folha de Pagamento'!A:A,A46,'Folha de Pagamento'!J:J),"") -> 11678.832 | D46: 3 | E46: =VLOOKUP(A46,Jobmatch!A:H,3,0) -> Controladoria | F46: Controller Geral | G46: =VLOOKUP(A46,Jobmatch!A:I,4,0) -> 32 - ADM PROJETOS | H46: =VLOOKUP(A46,Jobmatch!A:I,5,0) -> Tático | I46: =VLOOKUP(A46,Jobmatch!A:I,6,0) -> 95 | J46: =VLOOKUP(A46,Jobmatch!A:I,7,0) -> Controller | K46: =VLOOKUP(A46,Jobmatch!A:I,8,0) -> Indiferente | L46: =I46&K46 -> 95Indiferente | M46: =COUNTIF('Folha de Pagamento'!A:A,A46) -> 1 | N46: 21 | O46: =IFERROR(VLOOKUP(L46,'C-01'!$D:$L,5,0),"") -> 15472.01 | P46: =IFERROR(VLOOKUP(L46,'C-01'!$D:$L,6,0),"") -> 16594.35 | Q46: =IFERROR(VLOOKUP(L46,'C-01'!$D:$L,7,0),"") -> 16581.68 | R46: =IFERROR(VLOOKUP(L46,'C-01'!$D:$L,8,0),"") -> 17497.31 | S46: =IFERROR(VLOOKUP(L46,'C-01'!$D:$L,9,0),"") -> 18846.04 | T46: =IFS('Painel Geral'!$B$5="Mediana",IFERROR(IF(OR(C46="",Q46=0,Q46=""),"",($C46/$Q46)),""),'Painel Geral'!$B$5="Menor Salário",IFERROR(IF(OR(C46="",Q46=0,Q46=""),"",($C46/$N46)),""),'Painel Geral'!$B$5="1º Quartil",IFERROR(IF(OR(C46="",Q46=0,Q46=""),"",($C46/$O46)),""), 'Painel Geral'!$B$5="Média",IFERROR(IF(OR(C46="",Q46=0,Q46=""),"",($C46/$P46)),""),'Painel Geral'!$B$5="3º Quartil",IFERROR(IF(OR(C46="",Q46=0,Q46=""),"",($C46/$R46)),""),'Painel Geral'!$B$5="Maior Salário",IFERROR(IF(OR(C46="",Q46=0,Q46=""),"",($C46/$S46)),"")) -> 0.7043214 | U46: =IFS(OR(N46="",N46=0,C46="", C46=0),"",T46<=80%,"Muito Defasado",T46<=90%,"Defasado",T46<=100%,"Na Média",T46<=110%,"Competitivo",T46<=120%,"Muito Competitivo",T46>120%,"Agressivo") -> Muito Defasado | Z46: 24 | AA46: =-6062+1720*Z46-145*Z46*Z46+5.59*Z46*Z46*Z46 -> 28974.16 | AB46: =(AA46-AA45)/AA45 -> 0.16800536 | AC46: =AC45*1.2 -> 29619.534
