Workbook

Sheet Folha de Pagamento
C1: Folha de Pagamento | G1: CNPJ da empresa: Referência da Folha de Pagamento: Quantidade de horas mensais usada: Data de Construção:
A3: Cod. | B3: Cod. contrato funcionário | C3: Cargo atual | D3: Novo Cargo | E3: Senioridade | F3: Nível Organizacional | G3: Área | H3: Departamento | I3: Carga Horária | J3: Salários | K3: Salários Convertidos CLT | L3: Tipo de Contratação | M3: CBO | N3: Gênero | O3: Data de Admissão | P3: Unidade | Q3: Observações
A4: 1 | B4: 1362 | C4: ALMOXARIFE | E4: Não trabalhamos senioridade | F4: Operacional | G4: Edificação | I4: 220 | J4: 3683 | K4: 3683 | L4: CLT | M4: 818631 | N4: Masculino | O4: 45871
A5: 1 | B5: 1957 | C5: ALMOXARIFE | E5: Não trabalhamos senioridade | F5: Operacional | G5: Edificação | I5: 220 | J5: 3683 | K5: 3683 | L5: CLT | M5: 818631 | N5: Feminino | O5: 45870
A6: 2 | B6: 1964 | C6: ANALISTA DE COMPRAS | E6: Não trabalhamos senioridade | F6: Operacional | G6: Suprimentos | I6: 220 | J6: 3780 | K6: 3780 | L6: CLT | M6: 599850 | N6: Masculino | O6: 45872
A7: 3 | B7: 1910 | C7: ANALISTA DE CRIAÇAO | E7: Não trabalhamos senioridade | F7: Operacional | G7: Marketing | I7: 220 | J7: 5429 | K7: 5429 | L7: CLT | M7: 1423-35 | N7: Masculino | O7: 45873
A8: 4 | B8: PJ1 | C8: ANALISTA DE INOVAÇÃO | E8: Não trabalhamos senioridade | F8: Tático | G8: Inovação | I8: 220 | J8: 10000 | K8: =10000/1.37 -> 7299.2701 | L8: PJ | N8: Masculino | O8: 45874
A9: 5 | B9: 1373 | C9: ANALISTA DE MANUTENÇÃO II | E9: Pleno | F9: Operacional | G9: Edificação | I9: 220 | J9: 4550 | K9: 4550 | L9: CLT | M9: 5143-25 | N9: Masculino | O9: 45875
A10: 6 | B10: 139 | C10: ANALISTA DE MARKETING l | E10: Não trabalhamos senioridade | F10: Operacional | G10: Marketing | I10: 220 | J10: 4025.88 | K10: 4025.88 | L10: CLT | M10: 1423-35 | N10: Feminino | O10: 45876
A11: 7 | B11: 1962 | C11: ANALISTA DE PÓS VENDAS II | E11: Pleno | F11: Operacional | G11: Pós Vendas | I11: 220 | J11: 4550 | K11: 4550 | L11: CLT | M11: 226938 | N11: Masculino | O11: 45877
A12: 8 | B12: 187 | C12: ANALISTA DE URBANISMO | E12: Não trabalhamos senioridade | F12: Operacional | G12: Urbanismo | I12: 220 | J12: 5830 | K12: 5830 | L12: CLT | M12: 446083 | N12: Feminino | O12: 45878
A13: 9 | B13: 1868 | C13: ANALISTA FINANCEIRO COMERCIAL III | E13: Sênior | F13: Operacional | G13: Financeiro | I13: 220 | J13: 5213 | K13: 5213 | L13: CLT | M13: 226938 | N13: Feminino | O13: 45879
A14: 10 | B14: 176 | C14: ANALISTA FINANCEIRO DE CAPTAÇÃO DE RECURSOS III | E14: Sênior | F14: Operacional | G14: Financeiro | I14: 220 | J14: 5213 | K14: 5213 | L14: CLT | M14: 2525-45 | N14: Feminino | O14: 45880
A15: 11 | B15: 1927 | C15: ANALISTA FINANCEIRO I | E15: Júnior | F15: Operacional | G15: Financeiro | I15: 220 | J15: 3993 | K15: 3993 | L15: CLT | M15: 226938 | N15: Feminino | O15: 45881
A16: 12 | B16: 164 | C16: ASSISTENTE ADM DE LEGALIZAÇÃO III | E16: Sênior | F16: Operacional | G16: Legalização | I16: 220 | J16: 3652 | K16: 3652 | L16: CLT | M16: 807461 | N16: Feminino | O16: 45882
A17: 13 | B17: 1892 | C17: ASSISTENTE ADMINISTRATIVO lll | E17: Sênior | F17: Operacional | G17: Administrativo | I17: 220 | J17: 3439.7 | K17: 3439.7 | L17: CLT | M17: 807461 | N17: Feminino | O17: 45883
A18: 14 | B18: 1940 | C18: ASSISTENTE DE CONTROLADORIA III | E18: Sênior | F18: Operacional | G18: Controladoria | I18: 220 | J18: 3652 | K18: 3652 | L18: CLT | M18: 807461 | N18: Feminino | O18: 45884
A19: 15 | B19: 1963 | C19: ASSISTENTE DE ENGENHARIA lll | E19: Sênior | F19: Operacional | G19: Edificação | I19: 220 | J19: 3652 | K19: 3652 | L19: CLT | M19: 446083 | N19: Feminino | O19: 45885
A20: 16 | B20: 190 | C20: ASSISTENTE DE MARKETING | E20: Não trabalhamos senioridade | F20: Operacional | G20: Marketing | I20: 220 | J20: 2919 | K20: 2919 | L20: CLT | M20: 807461 | N20: Feminino | O20: 45886
A21: 17 | B21: 189 | C21: ASSISTENTE DE RECURSOS HUMANOS | E21: Não trabalhamos senioridade | F21: Operacional | G21: DHO | I21: 220 | J21: 2919 | K21: 2919 | L21: CLT | M21: 807461 | N21: Feminino | O21: 45887
A22: 18 | B22: 1656 | C22: ASSISTENTE DE TI | E22: Não trabalhamos senioridade | F22: Operacional | G22: Tecnologia da Informação | I22: 220 | J22: 2919 | K22: 2919 | L22: CLT | M22: 464864 | N22: Masculino | O22: 45888
A23: 19 | B23: 192 | C23: ASSISTENTE FINANCEIRO CONTAS A PAGAR | E23: Não trabalhamos senioridade | F23: Operacional | G23: Financeiro | I23: 220 | J23: 2919 | K23: 2919 | L23: CLT | M23: 815131 | N23: Masculino | O23: 45889
A24: 19 | B24: 193 | C24: ASSISTENTE FINANCEIRO CONTAS A PAGAR | E24: Não trabalhamos senioridade | F24: Operacional | G24: Financeiro | I24: 220 | J24: 2919 | K24: 2919 | L24: CLT | M24: 815131 | N24: Masculino | O24: 45890
A25: 19 | B25: 1941 | C25: ASSISTENTE FINANCEIRO CONTAS A PAGAR III | E25: Não trabalhamos senioridade | F25: Operacional | G25: Financeiro | I25: 220 | J25: 3652 | K25: 3652 | L25: CLT | M25: 815131 | N25: Masculino | O25: 45891
A26: 20 | B26: 1961 | C26: AUXILIAR ADMINISTRATIVO | E26: Não trabalhamos senioridade | F26: Operacional | G26: Administrativo | I26: 220 | J26: 2254 | K26: 2254 | L26: CLT | M26: 807308 | N26: Feminino | O26: 45892
A27: 20 | B27: 184 | C27: AUXILIAR ADMINISTRATIVO III | D27: AUXILIAR ADMINISTRATIVO | E27: Sênior | F27: Operacional | G27: Administrativo | I27: 220 | J27: 2739.04 | K27: 2739.04 | L27: CLT | M27: 807308 | N27: Feminino | O27: 45893
A28: 22 | B28: 1951 | C28: AUXILIAR DE ATENDIMENTO II | E28: Pleno | F28: Operacional | G28: Recepção | I28: 220 | J28: 2560 | K28: 2560 | L28: CLT | M28: 807308 | N28: Feminino | O28: 45894
A29: 23 | B29: 191 | C29: AUXILIAR DE ENGENHARIA | E29: Não trabalhamos senioridade | F29: Operacional | G29: Urbanismo | I29: 220 | J29: 2560 | K29: 2560 | L29: CLT | M29: 446083 | N29: Masculino | O29: 45895
A30: 24 | B30: PJ2 | C30: CONTROLER JURÍDICO | E30: Não trabalhamos senioridade | F30: Tático | G30: Administrativo | I30: 220 | J30: 11339 | K30: =11339/1.37 -> 8276.6423 | L30: PJ | N30: Feminino | O30: 45896
A31: 25 | B31: PJ3 | C31: CONTROLLER GERAL | E31: Não trabalhamos senioridade | F31: Tático | G31: Controladoria | I31: 220 | J31: 16000 | K31: =16000/1.37 -> 11678.832 | L31: PJ | N31: Feminino | O31: 45897
A32: 26 | B32: PJ4 | C32: CONTROLLER TÉCNICO | E32: Não trabalhamos senioridade | F32: Tático | G32: Controladoria | I32: 220 | J32: 12663.6 | K32: =12663.6/1.37 -> 9243.5037 | L32: PJ | N32: Masculino | O32: 45898
A33: 27 | B33: 1959 | C33: COORDENADOR DE DHO | E33: Não trabalhamos senioridade | F33: Tático | G33: DHO | I33: 220 | J33: 7420 | K33: 7420 | L33: CLT | M33: 1422-05 | N33: Feminino | O33: 45899
A34: 28 | B34: 151 | C34: COORDENADOR DE LEGAIZAÇÃO ll | E34: Pleno | F34: Tático | G34: Legalização | I34: 220 | J34: 8647 | K34: 8647 | L34: CLT | M34: 840698 | N34: Masculino | O34: 45900
A35: 29 | B35: 1911 | C35: COORDENADOR DE MARKETING II | E35: Pleno | F35: Tático | G35: Marketing | I35: 220 | J35: 8647 | K35: 8647 | L35: CLT | M35: 1423-15 | N35: Feminino | O35: 45870
A36: 30 | B36: 1452 | C36: COORDENADOR DE OBRAS | E36: Não trabalhamos senioridade | F36: Operacional | G36: Edificação | I36: 220 | J36: 8714 | K36: 8714 | L36: CLT | M36: 1413-05 | N36: Masculino | O36: 45871
A37: 31 | B37: PJ5 | C37: COORDENADOR DE SUPRIMENTOS | E37: Não trabalhamos senioridade | F37: Tático | G37: Suprimentos | I37: 220 | J37: 16000 | K37: =16000/1.51 -> 10596.026 | L37: PJ | N37: Feminino | O37: 45872
A38: 32 | B38: PJ6 | C38: COORDENADOR FINANCEIRO | E38: Não trabalhamos senioridade | F38: Tático | G38: Financeiro | I38: 220 | J38: 12000 | K38: =12000/1.51 -> 7947.0199 | L38: PJ | N38: Masculino | O38: 45873
A39: 33 | B39: PJ7 | C39: DIRETOR | E39: Não trabalhamos senioridade | F39: Estratégico | G39: Comercial | I39: 220 | J39: 58000 | K39: =58000/1.04 -> 55769.231 | L39: PJ | N39: Masculino | O39: 45874
A40: 34 | B40: 132 | C40: ENCARREGADO DE OBRAS | E40: Não trabalhamos senioridade | F40: Operacional | G40: Urbanismo | I40: 220 | J40: 8461 | K40: 8461 | L40: CLT | M40: 1900113 | N40: Masculino | O40: 45875
A41: 34 | B41: 182 | C41: ENCARREGADO DE OBRAS | E41: Não trabalhamos senioridade | F41: Operacional | G41: Urbanismo | I41: 220 | J41: 11540 | K41: 11540 | L41: CLT | M41: 1900113 | N41: Masculino | O41: 45876
A42: 35 | B42: 1351 | C42: ENCARREGADO OBRAS/MANUTENCAO | E42: Não trabalhamos senioridade | F42: Operacional | G42: Edificação | I42: 220 | J42: 8714 | K42: 8714 | L42: CLT | M42: 5143-25 | N42: Masculino
A43: 36 | B43: PJ8 | C43: ENGENHEIRO JUNIOR DE URBANISMO | E43: Júnior | F43: Operacional | G43: Urbanismo | I43: 220 | J43: 8390 | K43: =8390/1.49 -> 5630.8725 | L43: PJ | N43: Masculino
A44: 37 | B44: PJ9 | C44: ENGENHEIRO SÊNIOR | E44: Sênior | F44: Tático | G44: Edificação | I44: 220 | J44: 19000 | K44: =19000/1.32 -> 14393.939 | L44: PJ | N44: Feminino
A45: 38 | B45: E01 | C45: ESTAGIARIO (A) | E45: Não trabalhamos senioridade | F45: Operacional | G45: Novos Negócios | I45: 150 | J45: 1521 | K45: 1521 | L45: Estagiário | M45: 446083 | N45: Feminino
A46: 39 | B46: E03 | C46: ESTAGIÁRIO(A) ADM | E46: Não trabalhamos senioridade | F46: Operacional | G46: Administrativo | I46: 150 | J46: 1521 | K46: 1521 | L46: Estagiário | M46: 807308 | N46: Masculino
A47: 40 | B47: E04 | C47: ESTAGIARIO(A) ENG. CIVIL | E47: Não trabalhamos senioridade | F47: Operacional | G47: Urbanismo | I47: 150 | J47: 1521 | K47: 1521 | L47: Estagiário | N47: Feminino
A48: 41 | B48: 1940 | C48: ESTAGIÁRIO(A) RH/DP | E48: Não trabalhamos senioridade | F48: Operacional | G48: DHO | I48: 100 | J48: 1014 | K48: =(1014/I48)*150 -> 1521 | L48: Estagiário | M48: 807308 | N48: Feminino
A49: 42 | B49: PJ10 | C49: GERENTE ADMINISTRATIVA | E49: Não trabalhamos senioridade | F49: Tático | G49: Administrativo | I49: 220 | J49: 16160 | K49: =16160/1.32 -> 12242.424 | L49: PJ | N49: Feminino
A50: 43 | B50: PJ11 | C50: GERENTE COMERCIAL | E50: Não trabalhamos senioridade | F50: Tático | G50: Comercial | I50: 220 | J50: 15960 | K50: =15960/1.32 -> 12090.909 | L50: PJ | N50: Masculino
A51: 44 | B51: PJ12 | C51: GERENTE DE EDIFICAÇÕES | E51: Não trabalhamos senioridade | F51: Tático | G51: Edificação | I51: 220 | J51: 39740 | K51: =39740/1.32 -> 30106.061 | L51: PJ | N51: Masculino
A52: 45 | B52: PJ13 | C52: GERENTE DE HOUSE | E52: Não trabalhamos senioridade | F52: Tático | G52: Comercial | I52: 220 | J52: 5125 | K52: =5125/1.32 -> 3882.5758 | L52: PJ | N52: Feminino
A53: 46 | B53: PJ14 | C53: GERENTE DE IMOBILIÁRIAS EXTERNAS | E53: Não trabalhamos senioridade | F53: Tático | G53: Comercial | I53: 220 | J53: 5266 | K53: =5266/1.32 -> 3989.3939 | L53: PJ | N53: Masculino
A54: 46 | B54: PJ15 | C54: GERENTE DE IMOBILIÁRIAS EXTERNAS | E54: Não trabalhamos senioridade | F54: Tático | G54: Comercial | I54: 220 | J54: 5795 | K54: =5795/1.32 -> 4390.1515 | L54: PJ | N54: Masculino
A55: 47 | B55: PJ16 | C55: GERENTE DE INCORPORAÇÃO | E55: Não trabalhamos senioridade | F55: Tático | G55: Incorporação | I55: 220 | J55: 18540 | K55: =18540/1.32 -> 14045.455 | L55: PJ | N55: Feminino
A56: 48 | B56: PJ17 | C56: GERENTE DE PARCERIAS | E56: Não trabalhamos senioridade | F56: Tático | G56: Comercial | I56: 220 | J56: 5640 | K56: =5640/1.32 -> 4272.7273 | L56: PJ | N56: Feminino
A57: 48 | B57: PJ18 | C57: GERENTE DE PARCERIAS | E57: Não trabalhamos senioridade | F57: Tático | G57: Comercial | I57: 220 | J57: 5050 | K57: =5050/1.32 -> 3825.7576 | L57: PJ | N57: Feminino
A58: 49 | B58: PJ19 | C58: GERENTE DE PARCERIAS EXTERNAS | E58: Não trabalhamos senioridade | F58: Tático | G58: Comercial | I58: 220 | J58: 5000 | K58: =5000/1.32 -> 3787.8788 | L58: PJ | N58: Masculino
A59: 50 | B59: PJ20 | C59: GERENTE DE URBANISMO | E59: Não trabalhamos senioridade | F59: Tático | G59: Urbanismo | I59: 220 | J59: 37000 | K59: =37000/1.32 -> 28030.303 | L59: PJ | N59: Masculino
A60: 51 | B60: PJ21 | C60: SUPERVISOR DE NOVOS NEGÓCIOS | E60: Não trabalhamos senioridade | F60: Tático | G60: Novos Negócios | I60: 220 | J60: 12000 | K60: =12000/1.37 -> 8759.1241 | L60: PJ | N60: Masculino
A61: 52 | B61: 186 | C61: SUPERVISOR(A) FINANCEIRO I | E61: Júnior | F61: Operacional | G61: Financeiro | I61: 220 | J61: 5955.08 | K61: 5955.08 | L61: CLT | M61: 4102-35 | N61: Feminino
A62: 53 | B62: PJ22 | C62: TECNICO ANALISTA DE CUSTOS | E62: Não trabalhamos senioridade | F62: Operacional | G62: Edificação | I62: 220 | J62: 10430 | K62: =10430/1.49 -> 7000 | L62: PJ | N62: Masculino
A63: 54 | B63: 1871 | C63: TECNOLOGO EM CONSTRUÇÃO DE EDIFICIOS | E63: Não trabalhamos senioridade | F63: Operacional | G63: Edificação | I63: 220 | J63: 8585 | K63: 8585 | L63: CLT | M63: 2142-80 | N63: Masculino

Sheet Jobmatch
A1: Jobmatch
A3: Cod. | B3: Cargos Empresa | C3: Área | D3: Departamento | E3: Nível Organizacional | F3: Cod. Pesquisa | G3: Cargos Pesquisa | H3: Senioridade | I3: Observações | J3: Tipo de Contrato | K3: Pesquisa | L3: Pesquisas
A4: 13 | B4: =VLOOKUP(A4,'Folha de Pagamento'!A:C,3,0) -> ASSISTENTE ADMINISTRATIVO lll | C4: =VLOOKUP(A4,'Folha de Pagamento'!A:G,7,0) -> Administrativo | D4: 20 - ADM PROJETOS | E4: =VLOOKUP(A4,'Folha de Pagamento'!A:F,6,0) -> Operacional | F4: 59 | G4: Assistente Administrativo | H4: Indiferente | O4: Geral
A5: 20 | B5: =VLOOKUP(A5,'Folha de Pagamento'!A:C,3,0) -> AUXILIAR ADMINISTRATIVO | C5: =VLOOKUP(A5,'Folha de Pagamento'!A:G,7,0) -> Administrativo | D5: 27 - ADM PROJETOS | E5: =VLOOKUP(A5,'Folha de Pagamento'!A:F,6,0) -> Operacional | F5: 83 | G5: Auxiliar Administrativo | H5: Indiferente | L5: Construção | O5: Geral
A6: 24 | B6: =VLOOKUP(A6,'Folha de Pagamento'!A:C,3,0) -> CONTROLER JURÍDICO | C6: =VLOOKUP(A6,'Folha de Pagamento'!A:G,7,0) -> Administrativo | D6: 31 - ADM PROJETOS | E6: =VLOOKUP(A6,'Folha de Pagamento'!A:F,6,0) -> Tático | F6: 9 | G6: Advogado | H6: Sênior | M6: TI | O6: Geral
A7: 39 | B7: =VLOOKUP(A7,'Folha de Pagamento'!A:C,3,0) -> ESTAGIÁRIO(A) ADM | C7: =VLOOKUP(A7,'Folha de Pagamento'!A:G,7,0) -> Administrativo | D7: 46 - ADM PROJETOS | E7: =VLOOKUP(A7,'Folha de Pagamento'!A:F,6,0) -> Operacional | F7: 338 | G7: Estagiário Administrativo | H7: Indiferente | L7: Construção | M7: TI | N7: Industria | O7: Geral
A8: 42 | B8: =VLOOKUP(A8,'Folha de Pagamento'!A:C,3,0) -> GERENTE ADMINISTRATIVA | C8: =VLOOKUP(A8,'Folha de Pagamento'!A:G,7,0) -> Administrativo | D8: 49 - ADM PROJETOS | E8: =VLOOKUP(A8,'Folha de Pagamento'!A:F,6,0) -> Tático | F8: 106 | G8: Gerente Administrativo | H8: Indiferente
A9: 33 | B9: =VLOOKUP(A9,'Folha de Pagamento'!A:C,3,0) -> DIRETOR | C9: =VLOOKUP(A9,'Folha de Pagamento'!A:G,7,0) -> Comercial | D9: 40 - ADM PROJETOS | E9: =VLOOKUP(A9,'Folha de Pagamento'!A:F,6,0) -> Estratégico | F9: 456 | G9: CEO | H9: Indiferente | L9: Construção | M9: TI | N9: Industria | O9: Geral
A10: 43 | B10: =VLOOKUP(A10,'Folha de Pagamento'!A:C,3,0) -> GERENTE COMERCIAL | C10: =VLOOKUP(A10,'Folha de Pagamento'!A:G,7,0) -> Comercial | D10: 50 - ADM PROJETOS | E10: =VLOOKUP(A10,'Folha de Pagamento'!A:F,6,0) -> Tático | F10: 107 | G10: Gerente Comercial | H10: Indiferente | L10: Construção | M10: TI | O10: Geral
A11: 45 | B11: =VLOOKUP(A11,'Folha de Pagamento'!A:C,3,0) -> GERENTE DE HOUSE | C11: =VLOOKUP(A11,'Folha de Pagamento'!A:G,7,0) -> Comercial | D11: 52 - ADM PROJETOS | E11: =VLOOKUP(A11,'Folha de Pagamento'!A:F,6,0) -> Tático | F11: 107 | G11: Gerente Comercial | H11: Indiferente
A12: 46 | B12: =VLOOKUP(A12,'Folha de Pagamento'!A:C,3,0) -> GERENTE DE IMOBILIÁRIAS EXTERNAS | C12: =VLOOKUP(A12,'Folha de Pagamento'!A:G,7,0) -> Comercial | D12: 53 - ADM PROJETOS | E12: =VLOOKUP(A12,'Folha de Pagamento'!A:F,6,0) -> Tático | F12: 1205 | G12: Gerente de Imobiliárias | H12: Indiferente | L12: Construção | O12: Geral
A13: 48 | B13: =VLOOKUP(A13,'Folha de Pagamento'!A:C,3,0) -> GERENTE DE PARCERIAS | C13: =VLOOKUP(A13,'Folha de Pagamento'!A:G,7,0) -> Comercial | D13: 55 - ADM PROJETOS | E13: =VLOOKUP(A13,'Folha de Pagamento'!A:F,6,0) -> Tático | F13: 408 | G13: Gerente de Relacionamento | H13: Indiferente
A14: 49 | B14: =VLOOKUP(A14,'Folha de Pagamento'!A:C,3,0) -> GERENTE DE PARCERIAS EXTERNAS | C14: =VLOOKUP(A14,'Folha de Pagamento'!A:G,7,0) -> Comercial | D14: 56 - ADM PROJETOS | E14: =VLOOKUP(A14,'Folha de Pagamento'!A:F,6,0) -> Tático | F14: 408 | G14: Gerente de Relacionamento | H14: Indiferente | L14: Construção | M14: TI | N14: Industria | O14: Geral
A15: 14 | B15: =VLOOKUP(A15,'Folha de Pagamento'!A:C,3,0) -> ASSISTENTE DE CONTROLADORIA III | C15: =VLOOKUP(A15,'Folha de Pagamento'!A:G,7,0) -> Controladoria | D15: 21 - ADM PROJETOS | E15: =VLOOKUP(A15,'Folha de Pagamento'!A:F,6,0) -> Operacional | F15: 150 | G15: Assistente de Controladoria | H15: Indiferente
A16: 25 | B16: =VLOOKUP(A16,'Folha de Pagamento'!A:C,3,0) -> CONTROLLER GERAL | C16: =VLOOKUP(A16,'Folha de Pagamento'!A:G,7,0) -> Controladoria | D16: 32 - ADM PROJETOS | E16: =VLOOKUP(A16,'Folha de Pagamento'!A:F,6,0) -> Tático | F16: 95 | G16: Controller | H16: Indiferente | M16: TI | N16: Industria | O16: Geral
A17: 26 | B17: =VLOOKUP(A17,'Folha de Pagamento'!A:C,3,0) -> CONTROLLER TÉCNICO | C17: =VLOOKUP(A17,'Folha de Pagamento'!A:G,7,0) -> Controladoria | D17: 33 - ADM PROJETOS | E17: =VLOOKUP(A17,'Folha de Pagamento'!A:F,6,0) -> Tático | F17: 26 | G17: Analista de Controladoria | H17: Especialista | M17: TI | O17: Geral
A18: 17 | B18: =VLOOKUP(A18,'Folha de Pagamento'!A:C,3,0) -> ASSISTENTE DE RECURSOS HUMANOS | C18: =VLOOKUP(A18,'Folha de Pagamento'!A:G,7,0) -> DHO | D18: 24 - ADM PROJETOS | E18: =VLOOKUP(A18,'Folha de Pagamento'!A:F,6,0) -> Operacional | F18: 77 | G18: Assistente de Recursos Humanos | H18: Indiferente | L18: Construção | M18: TI | N18: Industria | O18: Geral
A19: 27 | B19: =VLOOKUP(A19,'Folha de Pagamento'!A:C,3,0) -> COORDENADOR DE DHO | C19: =VLOOKUP(A19,'Folha de Pagamento'!A:G,7,0) -> DHO | D19: 34 - ADM PROJETOS | E19: =VLOOKUP(A19,'Folha de Pagamento'!A:F,6,0) -> Tático | F19: 121 | G19: Coordenador de Recursos Humanos | H19: Indiferente | L19: Construção | M19: TI | N19: Industria | O19: Geral
A20: 41 | B20: =VLOOKUP(A20,'Folha de Pagamento'!A:C,3,0) -> ESTAGIÁRIO(A) RH/DP | C20: =VLOOKUP(A20,'Folha de Pagamento'!A:G,7,0) -> DHO | D20: 48 - ADM PROJETOS | E20: =VLOOKUP(A20,'Folha de Pagamento'!A:F,6,0) -> Operacional | F20: 338 | G20: Estagiário Administrativo | H20: Indiferente | L20: Construção | M20: TI | O20: Geral
A21: 1 | B21: =VLOOKUP(A21,'Folha de Pagamento'!A:C,3,0) -> ALMOXARIFE | C21: =VLOOKUP(A21,'Folha de Pagamento'!A:G,7,0) -> Edificação | D21: 8 - ADM PROJETOS | E21: =VLOOKUP(A21,'Folha de Pagamento'!A:F,6,0) -> Operacional | F21: 203 | G21: Almoxarife | H21: Indiferente | L21: Construção | M21: TI | O21: Geral
A22: 5 | B22: =VLOOKUP(A22,'Folha de Pagamento'!A:C,3,0) -> ANALISTA DE MANUTENÇÃO II | C22: =VLOOKUP(A22,'Folha de Pagamento'!A:G,7,0) -> Edificação | D22: 12 - ADM PROJETOS | E22: =VLOOKUP(A22,'Folha de Pagamento'!A:F,6,0) -> Operacional | F22: 820 | G22: Encarregado de Manutenção | H22: Indiferente | L22: Construção | M22: TI | O22: Geral
A23: 15 | B23: =VLOOKUP(A23,'Folha de Pagamento'!A:C,3,0) -> ASSISTENTE DE ENGENHARIA lll | C23: =VLOOKUP(A23,'Folha de Pagamento'!A:G,7,0) -> Edificação | D23: 22 - ADM PROJETOS | E23: =VLOOKUP(A23,'Folha de Pagamento'!A:F,6,0) -> Operacional | F23: 531 | G23: Assistente de Engenharia | H23: Indiferente | O23: Geral
A24: 30 | B24: =VLOOKUP(A24,'Folha de Pagamento'!A:C,3,0) -> COORDENADOR DE OBRAS | C24: =VLOOKUP(A24,'Folha de Pagamento'!A:G,7,0) -> Edificação | D24: 37 - ADM PROJETOS | E24: Tático | F24: 209 | G24: Coordenador de Obras | H24: Indiferente | L24: Construção | M24: TI | N24: Industria | O24: Geral
A25: 35 | B25: =VLOOKUP(A25,'Folha de Pagamento'!A:C,3,0) -> ENCARREGADO OBRAS/MANUTENCAO | C25: =VLOOKUP(A25,'Folha de Pagamento'!A:G,7,0) -> Edificação | D25: 42 - ADM PROJETOS | E25: =VLOOKUP(A25,'Folha de Pagamento'!A:F,6,0) -> Operacional | F25: 470 | G25: Mestre de Obras | H25: Indiferente
A26: 37 | B26: =VLOOKUP(A26,'Folha de Pagamento'!A:C,3,0) -> ENGENHEIRO SÊNIOR | C26: =VLOOKUP(A26,'Folha de Pagamento'!A:G,7,0) -> Edificação | D26: 44 - ADM PROJETOS | E26: =VLOOKUP(A26,'Folha de Pagamento'!A:F,6,0) -> Tático | F26: 212 | G26: Engenheiro de Urbanismo | H26: Indiferente | L26: Construção | O26: Geral
A27: 44 | B27: =VLOOKUP(A27,'Folha de Pagamento'!A:C,3,0) -> GERENTE DE EDIFICAÇÕES | C27: =VLOOKUP(A27,'Folha de Pagamento'!A:G,7,0) -> Edificação | D27: 51 - ADM PROJETOS | E27: =VLOOKUP(A27,'Folha de Pagamento'!A:F,6,0) -> Tático | F27: 213 | G27: Gerente de Engenharia | H27: Indiferente | N27: Industria | O27: Geral
A28: 53 | B28: =VLOOKUP(A28,'Folha de Pagamento'!A:C,3,0) -> TECNICO ANALISTA DE CUSTOS | C28: =VLOOKUP(A28,'Folha de Pagamento'!A:G,7,0) -> Edificação | D28: 60 - ADM PROJETOS | E28: =VLOOKUP(A28,'Folha de Pagamento'!A:F,6,0) -> Operacional | F28: 876 | G28: Analista de Custos | H28: Indiferente | O28: Geral
A29: 54 | B29: =VLOOKUP(A29,'Folha de Pagamento'!A:C,3,0) -> TECNOLOGO EM CONSTRUÇÃO DE EDIFICIOS | C29: =VLOOKUP(A29,'Folha de Pagamento'!A:G,7,0) -> Edificação | D29: 61 - ADM PROJETOS | E29: =VLOOKUP(A29,'Folha de Pagamento'!A:F,6,0) -> Operacional | F29: 269 | G29: Técnico em Edificações | H29: Indiferente | L29: Construção | M29: TI | N29: Industria | O29: Geral
A30: 9 | B30: =VLOOKUP(A30,'Folha de Pagamento'!A:C,3,0) -> ANALISTA FINANCEIRO COMERCIAL III | C30: =VLOOKUP(A30,'Folha de Pagamento'!A:G,7,0) -> Financeiro | D30: 16 - ADM PROJETOS | E30: =VLOOKUP(A30,'Folha de Pagamento'!A:F,6,0) -> Operacional | F30: 16 | G30: Analista Financeiro | H30: Sênior | L30: Construção | M30: TI | O30: Geral
A31: 10 | B31: =VLOOKUP(A31,'Folha de Pagamento'!A:C,3,0) -> ANALISTA FINANCEIRO DE CAPTAÇÃO DE RECURSOS III | C31: =VLOOKUP(A31,'Folha de Pagamento'!A:G,7,0) -> Financeiro | D31: 17 - ADM PROJETOS | E31: =VLOOKUP(A31,'Folha de Pagamento'!A:F,6,0) -> Operacional | F31: 16 | G31: Analista Financeiro | H31: Sênior | L31: Construção | M31: TI | N31: Industria | O31: Geral
A32: 11 | B32: =VLOOKUP(A32,'Folha de Pagamento'!A:C,3,0) -> ANALISTA FINANCEIRO I | C32: =VLOOKUP(A32,'Folha de Pagamento'!A:G,7,0) -> Financeiro | D32: 18 - ADM PROJETOS | E32: =VLOOKUP(A32,'Folha de Pagamento'!A:F,6,0) -> Operacional | F32: 16 | G32: Analista Financeiro | H32: Júnior | L32: Construção | M32: TI | N32: Industria | O32: Geral
A33: 19 | B33: =VLOOKUP(A33,'Folha de Pagamento'!A:C,3,0) -> ASSISTENTE FINANCEIRO CONTAS A PAGAR | C33: =VLOOKUP(A33,'Folha de Pagamento'!A:G,7,0) -> Financeiro | D33: 26 - ADM PROJETOS | E33: =VLOOKUP(A33,'Folha de Pagamento'!A:F,6,0) -> Operacional | F33: 79 | G33: Assistente Financeiro | H33: Indiferente | L33: Construção | M33: TI | O33: Geral
A34: 32 | B34: =VLOOKUP(A34,'Folha de Pagamento'!A:C,3,0) -> COORDENADOR FINANCEIRO | C34: =VLOOKUP(A34,'Folha de Pagamento'!A:G,7,0) -> Financeiro | D34: 39 - ADM PROJETOS | E34: =VLOOKUP(A34,'Folha de Pagamento'!A:F,6,0) -> Tático | F34: 122 | G34: Coordenador Financeiro | H34: Indiferente | L34: Construção | M34: TI | O34: Geral
A35: 52 | B35: =VLOOKUP(A35,'Folha de Pagamento'!A:C,3,0) -> SUPERVISOR(A) FINANCEIRO I | C35: =VLOOKUP(A35,'Folha de Pagamento'!A:G,7,0) -> Financeiro | D35: 59 - ADM PROJETOS | E35: =VLOOKUP(A35,'Folha de Pagamento'!A:F,6,0) -> Operacional | F35: 469 | G35: Supervisor Financeiro | H35: Indiferente | L35: Construção | O35: Geral
A36: 47 | B36: =VLOOKUP(A36,'Folha de Pagamento'!A:C,3,0) -> GERENTE DE INCORPORAÇÃO | C36: =VLOOKUP(A36,'Folha de Pagamento'!A:G,7,0) -> Incorporação | D36: 54 - ADM PROJETOS | E36: =VLOOKUP(A36,'Folha de Pagamento'!A:F,6,0) -> Tático | F36: 548 | G36: Gerente de Incorporação | H36: Indiferente | L36: Construção | M36: TI | N36: Industria | O36: Geral
A37: 4 | B37: =VLOOKUP(A37,'Folha de Pagamento'!A:C,3,0) -> ANALISTA DE INOVAÇÃO | C37: =VLOOKUP(A37,'Folha de Pagamento'!A:G,7,0) -> Inovação | D37: 11 - ADM PROJETOS | E37: =VLOOKUP(A37,'Folha de Pagamento'!A:F,6,0) -> Tático | F37: 437 | G37: Analista de Inovação | H37: Indiferente
A38: 12 | B38: =VLOOKUP(A38,'Folha de Pagamento'!A:C,3,0) -> ASSISTENTE ADM DE LEGALIZAÇÃO III | C38: =VLOOKUP(A38,'Folha de Pagamento'!A:G,7,0) -> Legalização | D38: 19 - ADM PROJETOS | E38: =VLOOKUP(A38,'Folha de Pagamento'!A:F,6,0) -> Operacional | F38: 1201 | G38: Assistente de Legalização | H38: Indiferente
A39: 28 | B39: =VLOOKUP(A39,'Folha de Pagamento'!A:C,3,0) -> COORDENADOR DE LEGAIZAÇÃO ll | C39: =VLOOKUP(A39,'Folha de Pagamento'!A:G,7,0) -> Legalização | D39: 35 - ADM PROJETOS | E39: =VLOOKUP(A39,'Folha de Pagamento'!A:F,6,0) -> Tático | F39: 1203 | G39: Coordenador de Legalização | H39: Indiferente | L39: Construção | M39: TI | N39: Industria | O39: Geral
A40: 3 | B40: =VLOOKUP(A40,'Folha de Pagamento'!A:C,3,0) -> ANALISTA DE CRIAÇAO | C40: =VLOOKUP(A40,'Folha de Pagamento'!A:G,7,0) -> Marketing | D40: 10 - ADM PROJETOS | E40: =VLOOKUP(A40,'Folha de Pagamento'!A:F,6,0) -> Operacional | F40: 45 | G40: Analista de Criação | H40: Indiferente | L40: Construção | O40: Geral
A41: 6 | B41: =VLOOKUP(A41,'Folha de Pagamento'!A:C,3,0) -> ANALISTA DE MARKETING l | C41: =VLOOKUP(A41,'Folha de Pagamento'!A:G,7,0) -> Marketing | D41: 13 - ADM PROJETOS | E41: =VLOOKUP(A41,'Folha de Pagamento'!A:F,6,0) -> Operacional | F41: 42 | G41: Analista de Marketing | H41: Júnior | O41: Geral
A42: 16 | B42: =VLOOKUP(A42,'Folha de Pagamento'!A:C,3,0) -> ASSISTENTE DE MARKETING | C42: =VLOOKUP(A42,'Folha de Pagamento'!A:G,7,0) -> Marketing | D42: 23 - ADM PROJETOS | E42: =VLOOKUP(A42,'Folha de Pagamento'!A:F,6,0) -> Operacional | F42: 71 | G42: Assistente de Marketing | H42: Indiferente | L42: Construção | M42: TI | O42: Geral
A43: 29 | B43: =VLOOKUP(A43,'Folha de Pagamento'!A:C,3,0) -> COORDENADOR DE MARKETING II | C43: =VLOOKUP(A43,'Folha de Pagamento'!A:G,7,0) -> Marketing | D43: 36 - ADM PROJETOS | E43: =VLOOKUP(A43,'Folha de Pagamento'!A:F,6,0) -> Tático | F43: 56 | G43: Coordenador de Marketing | H43: Indiferente | L43: Construção | M43: TI | N43: Industria | O43: Geral
A44: 38 | B44: =VLOOKUP(A44,'Folha de Pagamento'!A:C,3,0) -> ESTAGIARIO (A) | C44: =VLOOKUP(A44,'Folha de Pagamento'!A:G,7,0) -> Novos Negócios | D44: 45 - ADM PROJETOS | E44: =VLOOKUP(A44,'Folha de Pagamento'!A:F,6,0) -> Operacional | F44: 338 | G44: Estagiário Administrativo | H44: Indiferente | L44: Construção | M44: TI | N44: Industria | O44: Geral
A45: 51 | B45: =VLOOKUP(A45,'Folha de Pagamento'!A:C,3,0) -> SUPERVISOR DE NOVOS NEGÓCIOS | C45: =VLOOKUP(A45,'Folha de Pagamento'!A:G,7,0) -> Novos Negócios | D45: 58 - ADM PROJETOS | E45: =VLOOKUP(A45,'Folha de Pagamento'!A:F,6,0) -> Tático | F45: 583 | G45: Supervisor de Negócios | H45: Indiferente | L45: Construção | M45: TI | N45: Industria | O45: Geral
A46: 7 | B46: =VLOOKUP(A46,'Folha de Pagamento'!A:C,3,0) -> ANALISTA DE PÓS VENDAS II | C46: =VLOOKUP(A46,'Folha de Pagamento'!A:G,7,0) -> Pós Vendas | D46: 14 - ADM PROJETOS | E46: =VLOOKUP(A46,'Folha de Pagamento'!A:F,6,0) -> Operacional | F46: 376 | G46: Analista de Relacionamento | H46: Indiferente | O46: Geral
A47: 22 | B47: =VLOOKUP(A47,'Folha de Pagamento'!A:C,3,0) -> AUXILIAR DE ATENDIMENTO II | C47: =VLOOKUP(A47,'Folha de Pagamento'!A:G,7,0) -> Recepção | D47: 29 - ADM PROJETOS | E47: =VLOOKUP(A47,'Folha de Pagamento'!A:F,6,0) -> Operacional | F47: 318 | G47: Auxiliar de Atendimento | H47: Indiferente | L47: Construção | M47: TI | O47: Geral
A48: 2 | B48: =VLOOKUP(A48,'Folha de Pagamento'!A:C,3,0) -> ANALISTA DE COMPRAS | C48: =VLOOKUP(A48,'Folha de Pagamento'!A:G,7,0) -> Suprimentos | D48: 9 - ADM PROJETOS | E48: =VLOOKUP(A48,'Folha de Pagamento'!A:F,6,0) -> Operacional | F48: 136 | G48: Analista de Compras | H48: Pleno | L48: Construção | M48: TI | N48: Industria | O48: Geral
A49: 31 | B49: =VLOOKUP(A49,'Folha de Pagamento'!A:C,3,0) -> COORDENADOR DE SUPRIMENTOS | C49: =VLOOKUP(A49,'Folha de Pagamento'!A:G,7,0) -> Suprimentos | D49: 38 - ADM PROJETOS | E49: =VLOOKUP(A49,'Folha de Pagamento'!A:F,6,0) -> Tático | F49: 137 | G49: Coordenador de Compras | H49: Indiferente | L49: Construção | M49: TI | O49: Geral
A50: 18 | B50: =VLOOKUP(A50,'Folha de Pagamento'!A:C,3,0) -> ASSISTENTE DE TI | C50: =VLOOKUP(A50,'Folha de Pagamento'!A:G,7,0) -> Tecnologia da Informação | D50: 25 - ADM PROJETOS | E50: =VLOOKUP(A50,'Folha de Pagamento'!A:F,6,0) -> Operacional | F50: 31 | G50: Assistente de Tecnologia da Informação | H50: Indiferente | L50: Construção | O50: Geral
A51: 8 | B51: =VLOOKUP(A51,'Folha de Pagamento'!A:C,3,0) -> ANALISTA DE URBANISMO | C51: =VLOOKUP(A51,'Folha de Pagamento'!A:G,7,0) -> Urbanismo | D51: 15 - ADM PROJETOS | E51: =VLOOKUP(A51,'Folha de Pagamento'!A:F,6,0) -> Operacional | F51: 1199 | G51: Analista de Urbanismo | H51: Indiferente | L51: Construção | M51: TI | N51: Industria | O51: Geral
A52: 23 | B52: =VLOOKUP(A52,'Folha de Pagamento'!A:C,3,0) -> AUXILIAR DE ENGENHARIA | C52: =VLOOKUP(A52,'Folha de Pagamento'!A:G,7,0) -> Urbanismo | D52: 30 - ADM PROJETOS | E52: =VLOOKUP(A52,'Folha de Pagamento'!A:F,6,0) -> Operacional | F52: 207 | G52: Auxiliar de Engenharia | H52: Indiferente | M52: TI | O52: Geral
A53: 34 | B53: =VLOOKUP(A53,'Folha de Pagamento'!A:C,3,0) -> ENCARREGADO DE OBRAS | C53: =VLOOKUP(A53,'Folha de Pagamento'!A:G,7,0) -> Urbanismo | D53: 41 - ADM PROJETOS | E53: =VLOOKUP(A53,'Folha de Pagamento'!A:F,6,0) -> Operacional | F53: 470 | G53: Mestre de Obras | H53: Indiferente | L53: Construção | M53: TI | O53: Geral
A54: 36 | B54: =VLOOKUP(A54,'Folha de Pagamento'!A:C,3,0) -> ENGENHEIRO JUNIOR DE URBANISMO | C54: =VLOOKUP(A54,'Folha de Pagamento'!A:G,7,0) -> Urbanismo | D54: 43 - ADM PROJETOS | E54: =VLOOKUP(A54,'Folha de Pagamento'!A:F,6,0) -> Operacional | F54: 212 | G54: Engenheiro de Urbanismo | H54: Indiferente | L54: Construção | M54: TI | O54: Geral
A55: 40 | B55: =VLOOKUP(A55,'Folha de Pagamento'!A:C,3,0) -> ESTAGIARIO(A) ENG. CIVIL | C55: =VLOOKUP(A55,'Folha de Pagamento'!A:G,7,0) -> Urbanismo | D55: 47 - ADM PROJETOS | E55: =VLOOKUP(A55,'Folha de Pagamento'!A:F,6,0) -> Operacional | F55: 1204 | G55: Estagiário de Engenharia Civil | H55: Indiferente | O55: Geral
A56: 50 | B56: =VLOOKUP(A56,'Folha de Pagamento'!A:C,3,0) -> GERENTE DE URBANISMO | C56: =VLOOKUP(A56,'Folha de Pagamento'!A:G,7,0) -> Urbanismo | D56: 57 - ADM PROJETOS | E56: =VLOOKUP(A56,'Folha de Pagamento'!A:F,6,0) -> Tático | F56: 473 | G56: Gerente de Urbanismo | H56: Indiferente | L56: Construção | M56: TI | N56: Industria | O56: Geral

Sheet Cálculos Comparativos
H1: DADOS PARA COMPARAÇÃO | M1: ='Informações Relevantes Pesquisa'!A1 -> Pesquisa Contrução Civil e Consolidadas | S1: ="% Distância da "&'Painel Geral'!B5 -> % Distância da Mediana | T1: Posicionamento
A3: Cod. | B3: Cargos Empresa | C3: Média Empresa CLT | D3: Cod. Área | E3: Diretoria | F3: Centro de Custo | G3: Nível Organizacional | H3: Cod. Pesquisa | I3: Cargos Pesquisa | J3: Senioridade | K3: Código+Senioridade | L3: Número de Colaboradores | M3: Menor Salário | N3: 1º Quartil | O3: Média | P3: Mediana | Q3: 3º Quartil | R3: Maior Salário | S3: C-01 | T3: C-01 (Posicionamento)
A4: 1 | B4: =VLOOKUP(A4,Jobmatch!A:G,2,0) -> ALMOXARIFE | C4: =IFERROR(AVERAGEIF('Folha de Pagamento'!A:A,A4,'Folha de Pagamento'!K:K),"") -> 3683 | D4: 5 | E4: =VLOOKUP(A4,Jobmatch!A:H,3,0) -> Edificação | F4: =VLOOKUP(A4,Jobmatch!A:I,4,0) -> 8 - ADM PROJETOS | G4: =VLOOKUP(A4,Jobmatch!A:I,5,0) -> Operacional | H4: =VLOOKUP(A4,Jobmatch!A:I,6,0) -> 203 | I4: =VLOOKUP(A4,Jobmatch!A:I,7,0) -> Almoxarife | J4: =VLOOKUP(A4,Jobmatch!A:I,8,0) -> Indiferente | K4: =H4&J4 -> 203Indiferente | L4: =COUNTIF('Folha de Pagamento'!A:A,A4) -> 2 | M4: =IFERROR(VLOOKUP(K4,Pesquisa!$D:$L,4,0),"") -> 2973.35 | N4: =IFERROR(VLOOKUP(K4,Pesquisa!$D:$L,5,0),"") -> 3096.32 | O4: =IFERROR(VLOOKUP(K4,Pesquisa!$D:$L,6,0),"") -> 3405.54 | P4: =IFERROR(VLOOKUP(K4,Pesquisa!$D:$L,7,0),"") -> 3096.32 | Q4: =IFERROR(VLOOKUP(K4,Pesquisa!$D:$L,8,0),"") -> 3712.15 | R4: =IFERROR(VLOOKUP(K4,Pesquisa!$D:$L,9,0),"") -> 4435.84 | S4: =IFS('Painel Geral'!$B$5="Mediana",IFERROR(IF(OR(C4="",P4=0,P4=""),"",($C4/$P4)),""),'Painel Geral'!$B$5="Menor Salário",IFERROR(IF(OR(C4="",P4=0,P4=""),"",($C4/$M4)),""),'Painel Geral'!$B$5="1º Quartil",IFERROR(IF(OR(C4="",P4=0,P4=""),"",($C4/$N4)),""), 'Painel Geral'!$B$5="Média",IFERROR(IF(OR(C4="",P4=0,P4=""),"",($C4/$O4)),""),'Painel Geral'!$B$5="3º Quartil",IFERROR(IF(OR(C4="",P4=0,P4=""),"",($C4/$Q4)),""),'Painel Geral'!$B$5="Maior Salário",IFERROR(IF(OR(C4="",P4=0,P4=""),"",($C4/$R4)),"")) -> 1.1894765 | T4: =IFS(OR(M4="",M4=0,C4="", C4=0),"",S4<=80%,"Muito Defasado",S4<=90%,"Defasado",S4<=100%,"Na Média",S4<=110%,"Na Média",S4<=120%,"Muito Competitivo",S4>120%,"Agressivo") -> Muito Competitivo
A5: 2 | B5: =VLOOKUP(A5,Jobmatch!A:G,2,0) -> ANALISTA DE COMPRAS | C5: =IFERROR(AVERAGEIF('Folha de Pagamento'!A:A,A5,'Folha de Pagamento'!K:K),"") -> 3780 | D5: 1 | E5: =VLOOKUP(A5,Jobmatch!A:H,3,0) -> Suprimentos | F5: =VLOOKUP(A5,Jobmatch!A:I,4,0) -> 9 - ADM PROJETOS | G5: =VLOOKUP(A5,Jobmatch!A:I,5,0) -> Operacional | H5: =VLOOKUP(A5,Jobmatch!A:I,6,0) -> 136 | I5: =VLOOKUP(A5,Jobmatch!A:I,7,0) -> Analista de Compras | J5: =VLOOKUP(A5,Jobmatch!A:I,8,0) -> Pleno | K5: =H5&J5 -> 136Pleno | L5: =COUNTIF('Folha de Pagamento'!A:A,A5) -> 1 | M5: =IFERROR(VLOOKUP(K5,Pesquisa!$D:$L,4,0),"") -> 4535.62 | N5: =IFERROR(VLOOKUP(K5,Pesquisa!$D:$L,5,0),"") -> 4535.62 | O5: =IFERROR(VLOOKUP(K5,Pesquisa!$D:$L,6,0),"") -> 6016.64 | P5: =IFERROR(VLOOKUP(K5,Pesquisa!$D:$L,7,0),"") -> 5288.53 | Q5: =IFERROR(VLOOKUP(K5,Pesquisa!$D:$L,8,0),"") -> 7861.72 | R5: =IFERROR(VLOOKUP(K5,Pesquisa!$D:$L,9,0),"") -> 7861.72 | S5: =IFS('Painel Geral'!$B$5="Mediana",IFERROR(IF(OR(C5="",P5=0,P5=""),"",($C5/$P5)),""),'Painel Geral'!$B$5="Menor Salário",IFERROR(IF(OR(C5="",P5=0,P5=""),"",($C5/$M5)),""),'Painel Geral'!$B$5="1º Quartil",IFERROR(IF(OR(C5="",P5=0,P5=""),"",($C5/$N5)),""), 'Painel Geral'!$B$5="Média",IFERROR(IF(OR(C5="",P5=0,P5=""),"",($C5/$O5)),""),'Painel Geral'!$B$5="3º Quartil",IFERROR(IF(OR(C5="",P5=0,P5=""),"",($C5/$Q5)),""),'Painel Geral'!$B$5="Maior Salário",IFERROR(IF(OR(C5="",P5=0,P5=""),"",($C5/$R5)),"")) -> 0.71475438 | T5: =IFS(OR(M5="",M5=0,C5="", C5=0),"",S5<=80%,"Muito Defasado",S5<=90%,"Defasado",S5<=100%,"Na Média",S5<=110%,"Na Média",S5<=120%,"Muito Competitivo",S5>120%,"Agressivo") -> Muito Defasado
A6: 3 | B6: =VLOOKUP(A6,Jobmatch!A:G,2,0) -> ANALISTA DE CRIAÇAO | C6: =IFERROR(AVERAGEIF('Folha de Pagamento'!A:A,A6,'Folha de Pagamento'!K:K),"") -> 5429 | D6: 8 | E6: =VLOOKUP(A6,Jobmatch!A:H,3,0) -> Marketing | F6: =VLOOKUP(A6,Jobmatch!A:I,4,0) -> 10 - ADM PROJETOS | G6: =VLOOKUP(A6,Jobmatch!A:I,5,0) -> Operacional | H6: =VLOOKUP(A6,Jobmatch!A:I,6,0) -> 45 | I6: =VLOOKUP(A6,Jobmatch!A:I,7,0) -> Analista de Criação | J6: =VLOOKUP(A6,Jobmatch!A:I,8,0) -> Indiferente | K6: =H6&J6 -> 45Indiferente | L6: =COUNTIF('Folha de Pagamento'!A:A,A6) -> 1 | M6: =IFERROR(VLOOKUP(K6,Pesquisa!$D:$L,4,0),"") -> 2771.48 | N6: =IFERROR(VLOOKUP(K6,Pesquisa!$D:$L,5,0),"") -> 3527.33 | O6: =IFERROR(VLOOKUP(K6,Pesquisa!$D:$L,6,0),"") -> 4325.16 | P6: =IFERROR(VLOOKUP(K6,Pesquisa!$D:$L,7,0),"") -> 4325.72 | Q6: =IFERROR(VLOOKUP(K6,Pesquisa!$D:$L,8,0),"") -> 4988.66 | R6: =IFERROR(VLOOKUP(K6,Pesquisa!$D:$L,9,0),"") -> 6418.74 | S6: =IFS('Painel Geral'!$B$5="Mediana",IFERROR(IF(OR(C6="",P6=0,P6=""),"",($C6/$P6)),""),'Painel Geral'!$B$5="Menor Salário",IFERROR(IF(OR(C6="",P6=0,P6=""),"",($C6/$M6)),""),'Painel Geral'!$B$5="1º Quartil",IFERROR(IF(OR(C6="",P6=0,P6=""),"",($C6/$N6)),""), 'Painel Geral'!$B$5="Média",IFERROR(IF(OR(C6="",P6=0,P6=""),"",($C6/$O6)),""),'Painel Geral'!$B$5="3º Quartil",IFERROR(IF(OR(C6="",P6=0,P6=""),"",($C6/$Q6)),""),'Painel Geral'!$B$5="Maior Salário",IFERROR(IF(OR(C6="",P6=0,P6=""),"",($C6/$R6)),"")) -> 1.2550512 | T6: =IFS(OR(M6="",M6=0,C6="", C6=0),"",S6<=80%,"Muito Defasado",S6<=90%,"Defasado",S6<=100%,"Na Média",S6<=110%,"Na Média",S6<=120%,"Muito Competitivo",S6>120%,"Agressivo") -> Agressivo
A7: 4 | B7: =VLOOKUP(A7,Jobmatch!A:G,2,0) -> ANALISTA DE INOVAÇÃO | C7: =IFERROR(AVERAGEIF('Folha de Pagamento'!A:A,A7,'Folha de Pagamento'!K:K),"") -> 7299.2701 | D7: 7 | E7: =VLOOKUP(A7,Jobmatch!A:H,3,0) -> Inovação | F7: =VLOOKUP(A7,Jobmatch!A:I,4,0) -> 11 - ADM PROJETOS | G7: =VLOOKUP(A7,Jobmatch!A:I,5,0) -> Tático | H7: =VLOOKUP(A7,Jobmatch!A:I,6,0) -> 437 | I7: =VLOOKUP(A7,Jobmatch!A:I,7,0) -> Analista de Inovação | J7: =VLOOKUP(A7,Jobmatch!A:I,8,0) -> Indiferente | K7: =H7&J7 -> 437Indiferente | L7: =COUNTIF('Folha de Pagamento'!A:A,A7) -> 1 | M7: =IFERROR(VLOOKUP(K7,Pesquisa!$D:$L,4,0),"") -> 5039.5 | N7: =IFERROR(VLOOKUP(K7,Pesquisa!$D:$L,5,0),"") -> 5955.7727 | O7: =IFERROR(VLOOKUP(K7,Pesquisa!$D:$L,6,0),"") -> 6515.7172 | P7: =IFERROR(VLOOKUP(K7,Pesquisa!$D:$L,7,0),"") -> 6872.0455 | Q7: =IFERROR(VLOOKUP(K7,Pesquisa!$D:$L,8,0),"") -> 7253.8258 | R7: =IFERROR(VLOOKUP(K7,Pesquisa!$D:$L,9,0),"") -> 7635.6061 | S7: =IFS('Painel Geral'!$B$5="Mediana",IFERROR(IF(OR(C7="",P7=0,P7=""),"",($C7/$P7)),""),'Painel Geral'!$B$5="Menor Salário",IFERROR(IF(OR(C7="",P7=0,P7=""),"",($C7/$M7)),""),'Painel Geral'!$B$5="1º Quartil",IFERROR(IF(OR(C7="",P7=0,P7=""),"",($C7/$N7)),""), 'Painel Geral'!$B$5="Média",IFERROR(IF(OR(C7="",P7=0,P7=""),"",($C7/$O7)),""),'Painel Geral'!$B$5="3º Quartil",IFERROR(IF(OR(C7="",P7=0,P7=""),"",($C7/$Q7)),""),'Painel Geral'!$B$5="Maior Salário",IFERROR(IF(OR(C7="",P7=0,P7=""),"",($C7/$R7)),"")) -> 1.0621685 | T7: =IFS(OR(M7="",M7=0,C7="", C7=0),"",S7<=80%,"Muito Defasado",S7<=90%,"Defasado",S7<=100%,"Na Média",S7<=110%,"Na Média",S7<=120%,"Muito Competitivo",S7>120%,"Agressivo") -> Na Média
A8: 5 | B8: =VLOOKUP(A8,Jobmatch!A:G,2,0) -> ANALISTA DE MANUTENÇÃO II | C8: =IFERROR(AVERAGEIF('Folha de Pagamento'!A:A,A8,'Folha de Pagamento'!K:K),"") -> 4550 | D8: 5 | E8: =VLOOKUP(A8,Jobmatch!A:H,3,0) -> Edificação | F8: =VLOOKUP(A8,Jobmatch!A:I,4,0) -> 12 - ADM PROJETOS | G8: =VLOOKUP(A8,Jobmatch!A:I,5,0) -> Operacional | H8: =VLOOKUP(A8,Jobmatch!A:I,6,0) -> 820 | I8: =VLOOKUP(A8,Jobmatch!A:I,7,0) -> Encarregado de Manutenção | J8: =VLOOKUP(A8,Jobmatch!A:I,8,0) -> Indiferente | K8: =H8&J8 -> 820Indiferente | L8: =COUNTIF('Folha de Pagamento'!A:A,A8) -> 1 | M8: =IFERROR(VLOOKUP(K8,Pesquisa!$D:$L,4,0),"") -> 4348.38 | N8: =IFERROR(VLOOKUP(K8,Pesquisa!$D:$L,5,0),"") -> 5743.67 | O8: =IFERROR(VLOOKUP(K8,Pesquisa!$D:$L,6,0),"") -> 6811.3 | P8: =IFERROR(VLOOKUP(K8,Pesquisa!$D:$L,7,0),"") -> 6232.3 | Q8: =IFERROR(VLOOKUP(K8,Pesquisa!$D:$L,8,0),"") -> 8417.62 | R8: =IFERROR(VLOOKUP(K8,Pesquisa!$D:$L,9,0),"") -> 9486.51 | S8: =IFS('Painel Geral'!$B$5="Mediana",IFERROR(IF(OR(C8="",P8=0,P8=""),"",($C8/$P8)),""),'Painel Geral'!$B$5="Menor Salário",IFERROR(IF(OR(C8="",P8=0,P8=""),"",($C8/$M8)),""),'Painel Geral'!$B$5="1º Quartil",IFERROR(IF(OR(C8="",P8=0,P8=""),"",($C8/$N8)),""), 'Painel Geral'!$B$5="Média",IFERROR(IF(OR(C8="",P8=0,P8=""),"",($C8/$O8)),""),'Painel Geral'!$B$5="3º Quartil",IFERROR(IF(OR(C8="",P8=0,P8=""),"",($C8/$Q8)),""),'Painel Geral'!$B$5="Maior Salário",IFERROR(IF(OR(C8="",P8=0,P8=""),"",($C8/$R8)),"")) -> 0.73006755 | T8: =IFS(OR(M8="",M8=0,C8="", C8=0),"",S8<=80%,"Muito Defasado",S8<=90%,"Defasado",S8<=100%,"Na Média",S8<=110%,"Na Média",S8<=120%,"Muito Competitivo",S8>120%,"Agressivo") -> Muito Defasado
A9: 6 | B9: =VLOOKUP(A9,Jobmatch!A:G,2,0) -> ANALISTA DE MARKETING l | C9: =IFERROR(AVERAGEIF('Folha de Pagamento'!A:A,A9,'Folha de Pagamento'!K:K),"") -> 4025.88 | D9: 8 | E9: =VLOOKUP(A9,Jobmatch!A:H,3,0) -> Marketing | F9: =VLOOKUP(A9,Jobmatch!A:I,4,0) -> 13 - ADM PROJETOS | G9: =VLOOKUP(A9,Jobmatch!A:I,5,0) -> Operacional | H9: =VLOOKUP(A9,Jobmatch!A:I,6,0) -> 42 | I9: =VLOOKUP(A9,Jobmatch!A:I,7,0) -> Analista de Marketing | J9: =VLOOKUP(A9,Jobmatch!A:I,8,0) -> Júnior | K9: =H9&J9 -> 42Júnior | L9: =COUNTIF('Folha de Pagamento'!A:A,A9) -> 1 | M9: =IFERROR(VLOOKUP(K9,Pesquisa!$D:$L,4,0),"") -> 3225.33 | N9: =IFERROR(VLOOKUP(K9,Pesquisa!$D:$L,5,0),"") -> 3261.57 | O9: =IFERROR(VLOOKUP(K9,Pesquisa!$D:$L,6,0),"") -> 4114.38 | P9: =IFERROR(VLOOKUP(K9,Pesquisa!$D:$L,7,0),"") -> 3297.81 | Q9: =IFERROR(VLOOKUP(K9,Pesquisa!$D:$L,8,0),"") -> 4558.91 | R9: =IFERROR(VLOOKUP(K9,Pesquisa!$D:$L,9,0),"") -> 5820.01 | S9: =IFS('Painel Geral'!$B$5="Mediana",IFERROR(IF(OR(C9="",P9=0,P9=""),"",($C9/$P9)),""),'Painel Geral'!$B$5="Menor Salário",IFERROR(IF(OR(C9="",P9=0,P9=""),"",($C9/$M9)),""),'Painel Geral'!$B$5="1º Quartil",IFERROR(IF(OR(C9="",P9=0,P9=""),"",($C9/$N9)),""), 'Painel Geral'!$B$5="Média",IFERROR(IF(OR(C9="",P9=0,P9=""),"",($C9/$O9)),""),'Painel Geral'!$B$5="3º Quartil",IFERROR(IF(OR(C9="",P9=0,P9=""),"",($C9/$Q9)),""),'Painel Geral'!$B$5="Maior Salário",IFERROR(IF(OR(C9="",P9=0,P9=""),"",($C9/$R9)),"")) -> 1.2207738 | T9: =IFS(OR(M9="",M9=0,C9="", C9=0),"",S9<=80%,"Muito Defasado",S9<=90%,"Defasado",S9<=100%,"Na Média",S9<=110%,"Na Média",S9<=120%,"Muito Competitivo",S9>120%,"Agressivo") -> Agressivo
A10: 7 | B10: =VLOOKUP(A10,Jobmatch!A:G,2,0) -> ANALISTA DE PÓS VENDAS II | C10: =IFERROR(AVERAGEIF('Folha de Pagamento'!A:A,A10,'Folha de Pagamento'!K:K),"") -> 4550 | D10: 9 | E10: =VLOOKUP(A10,Jobmatch!A:H,3,0) -> Pós Vendas | F10: =VLOOKUP(A10,Jobmatch!A:I,4,0) -> 14 - ADM PROJETOS | G10: =VLOOKUP(A10,Jobmatch!A:I,5,0) -> Operacional | H10: =VLOOKUP(A10,Jobmatch!A:I,6,0) -> 376 | I10: =VLOOKUP(A10,Jobmatch!A:I,7,0) -> Analista de Relacionamento | J10: =VLOOKUP(A10,Jobmatch!A:I,8,0) -> Indiferente | K10: =H10&J10 -> 376Indiferente | L10: =COUNTIF('Folha de Pagamento'!A:A,A10) -> 1 | M10: =IFERROR(VLOOKUP(K10,Pesquisa!$D:$L,4,0),"") -> 2872.56 | N10: =IFERROR(VLOOKUP(K10,Pesquisa!$D:$L,5,0),"") -> 3241.46 | O10: =IFERROR(VLOOKUP(K10,Pesquisa!$D:$L,6,0),"") -> 3918.59 | P10: =IFERROR(VLOOKUP(K10,Pesquisa!$D:$L,7,0),"") -> 3830.08 | Q10: =IFERROR(VLOOKUP(K10,Pesquisa!$D:$L,8,0),"") -> 4233.24 | R10: =IFERROR(VLOOKUP(K10,Pesquisa!$D:$L,9,0),"") -> 5820.01 | S10: =IFS('Painel Geral'!$B$5="Mediana",IFERROR(IF(OR(C10="",P10=0,P10=""),"",($C10/$P10)),""),'Painel Geral'!$B$5="Menor Salário",IFERROR(IF(OR(C10="",P10=0,P10=""),"",($C10/$M10)),""),'Painel Geral'!$B$5="1º Quartil",IFERROR(IF(OR(C10="",P10=0,P10=""),"",($C10/$N10)),""), 'Painel Geral'!$B$5="Média",IFERROR(IF(OR(C10="",P10=0,P10=""),"",($C10/$O10)),""),'Painel Geral'!$B$5="3º Quartil",IFERROR(IF(OR(C10="",P10=0,P10=""),"",($C10/$Q10)),""),'Painel Geral'!$B$5="Maior Salário",IFERROR(IF(OR(C10="",P10=0,P10=""),"",($C10/$R10)),"")) -> 1.1879647 | T10: =IFS(OR(M10="",M10=0,C10="", C10=0),"",S10<=80%,"Muito Defasado",S10<=90%,"Defasado",S10<=100%,"Na Média",S10<=110%,"Na Média",S10<=120%,"Muito Competitivo",S10>120%,"Agressivo") -> Muito Competitivo
A11: 8 | B11: =VLOOKUP(A11,Jobmatch!A:G,2,0) -> ANALISTA DE URBANISMO | C11: =IFERROR(AVERAGEIF('Folha de Pagamento'!A:A,A11,'Folha de Pagamento'!K:K),"") -> 5830 | D11: 10 | E11: =VLOOKUP(A11,Jobmatch!A:H,3,0) -> Urbanismo | F11: =VLOOKUP(A11,Jobmatch!A:I,4,0) -> 15 - ADM PROJETOS | G11: =VLOOKUP(A11,Jobmatch!A:I,5,0) -> Operacional | H11: =VLOOKUP(A11,Jobmatch!A:I,6,0) -> 1199 | I11: =VLOOKUP(A11,Jobmatch!A:I,7,0) -> Analista de Urbanismo | J11: =VLOOKUP(A11,Jobmatch!A:I,8,0) -> Indiferente | K11: =H11&J11 -> 1199Indiferente | L11: =COUNTIF('Folha de Pagamento'!A:A,A11) -> 1 | M11: =IFERROR(VLOOKUP(K11,Pesquisa!$D:$L,4,0),"") -> 5876.15 | N11: =IFERROR(VLOOKUP(K11,Pesquisa!$D:$L,5,0),"") -> 6106.16 | O11: =IFERROR(VLOOKUP(K11,Pesquisa!$D:$L,6,0),"") -> 7655.79 | P11: =IFERROR(VLOOKUP(K11,Pesquisa!$D:$L,7,0),"") -> 7867.3 | Q11: =IFERROR(VLOOKUP(K11,Pesquisa!$D:$L,8,0),"") -> 9183.14 | R11: =IFERROR(VLOOKUP(K11,Pesquisa!$D:$L,9,0),"") -> 9183.14 | S11: =IFS('Painel Geral'!$B$5="Mediana",IFERROR(IF(OR(C11="",P11=0,P11=""),"",($C11/$P11)),""),'Painel Geral'!$B$5="Menor Salário",IFERROR(IF(OR(C11="",P11=0,P11=""),"",($C11/$M11)),""),'Painel Geral'!$B$5="1º Quartil",IFERROR(IF(OR(C11="",P11=0,P11=""),"",($C11/$N11)),""), 'Painel Geral'!$B$5="Média",IFERROR(IF(OR(C11="",P11=0,P11=""),"",($C11/$O11)),""),'Painel Geral'!$B$5="3º Quartil",IFERROR(IF(OR(C11="",P11=0,P11=""),"",($C11/$Q11)),""),'Painel Geral'!$B$5="Maior Salário",IFERROR(IF(OR(C11="",P11=0,P11=""),"",($C11/$R11)),"")) -> 0.74104203 | T11: =IFS(OR(M11="",M11=0,C11="", C11=0),"",S11<=80%,"Muito Defasado",S11<=90%,"Defasado",S11<=100%,"Na Média",S11<=110%,"Na Média",S11<=120%,"Muito Competitivo",S11>120%,"Agressivo") -> Muito Defasado
A12: 9 | B12: =VLOOKUP(A12,Jobmatch!A:G,2,0) -> ANALISTA FINANCEIRO COMERCIAL III | C12: =IFERROR(AVERAGEIF('Folha de Pagamento'!A:A,A12,'Folha de Pagamento'!K:K),"") -> 5213 | D12: 6 | E12: =VLOOKUP(A12,Jobmatch!A:H,3,0) -> Financeiro | F12: =VLOOKUP(A12,Jobmatch!A:I,4,0) -> 16 - ADM PROJETOS | G12: =VLOOKUP(A12,Jobmatch!A:I,5,0) -> Operacional | H12: =VLOOKUP(A12,Jobmatch!A:I,6,0) -> 16 | I12: =VLOOKUP(A12,Jobmatch!A:I,7,0) -> Analista Financeiro | J12: =VLOOKUP(A12,Jobmatch!A:I,8,0) -> Sênior | K12: =H12&J12 -> 16Sênior | L12: =COUNTIF('Folha de Pagamento'!A:A,A12) -> 1 | M12: =IFERROR(VLOOKUP(K12,Pesquisa!$D:$L,4,0),"") -> 4882.37 | N12: =IFERROR(VLOOKUP(K12,Pesquisa!$D:$L,5,0),"") -> 5489.27 | O12: =IFERROR(VLOOKUP(K12,Pesquisa!$D:$L,6,0),"") -> 6172.24 | P12: =IFERROR(VLOOKUP(K12,Pesquisa!$D:$L,7,0),"") -> 5910.71 | Q12: =IFERROR(VLOOKUP(K12,Pesquisa!$D:$L,8,0),"") -> 6737.39 | R12: =IFERROR(VLOOKUP(K12,Pesquisa!$D:$L,9,0),"") -> 8185.08 | S12: =IFS('Painel Geral'!$B$5="Mediana",IFERROR(IF(OR(C12="",P12=0,P12=""),"",($C12/$P12)),""),'Painel Geral'!$B$5="Menor Salário",IFERROR(IF(OR(C12="",P12=0,P12=""),"",($C12/$M12)),""),'Painel Geral'!$B$5="1º Quartil",IFERROR(IF(OR(C12="",P12=0,P12=""),"",($C12/$N12)),""), 'Painel Geral'!$B$5="Média",IFERROR(IF(OR(C12="",P12=0,P12=""),"",($C12/$O12)),""),'Painel Geral'!$B$5="3º Quartil",IFERROR(IF(OR(C12="",P12=0,P12=""),"",($C12/$Q12)),""),'Painel Geral'!$B$5="Maior Salário",IFERROR(IF(OR(C12="",P12=0,P12=""),"",($C12/$R12)),"")) -> 0.88195834 | T12: =IFS(OR(M12="",M12=0,C12="", C12=0),"",S12<=80%,"Muito Defasado",S12<=90%,"Defasado",S12<=100%,"Na Média",S12<=110%,"Na Média",S12<=120%,"Muito Competitivo",S12>120%,"Agressivo") -> Defasado
A13: 10 | B13: =VLOOKUP(A13,Jobmatch!A:G,2,0) -> ANALISTA FINANCEIRO DE CAPTAÇÃO DE RECURSOS III | C13: =IFERROR(AVERAGEIF('Folha de Pagamento'!A:A,A13,'Folha de Pagamento'!K:K),"") -> 5213 | D13: 6 | E13: =VLOOKUP(A13,Jobmatch!A:H,3,0) -> Financeiro | F13: =VLOOKUP(A13,Jobmatch!A:I,4,0) -> 17 - ADM PROJETOS | G13: =VLOOKUP(A13,Jobmatch!A:I,5,0) -> Operacional | H13: =VLOOKUP(A13,Jobmatch!A:I,6,0) -> 16 | I13: =VLOOKUP(A13,Jobmatch!A:I,7,0) -> Analista Financeiro | J13: =VLOOKUP(A13,Jobmatch!A:I,8,0) -> Sênior | K13: =H13&J13 -> 16Sênior | L13: =COUNTIF('Folha de Pagamento'!A:A,A13) -> 1 | M13: =IFERROR(VLOOKUP(K13,Pesquisa!$D:$L,4,0),"") -> 4882.37 | N13: =IFERROR(VLOOKUP(K13,Pesquisa!$D:$L,5,0),"") -> 5489.27 | O13: =IFERROR(VLOOKUP(K13,Pesquisa!$D:$L,6,0),"") -> 6172.24 | P13: =IFERROR(VLOOKUP(K13,Pesquisa!$D:$L,7,0),"") -> 5910.71 | Q13: =IFERROR(VLOOKUP(K13,Pesquisa!$D:$L,8,0),"") -> 6737.39 | R13: =IFERROR(VLOOKUP(K13,Pesquisa!$D:$L,9,0),"") -> 8185.08 | S13: =IFS('Painel Geral'!$B$5="Mediana",IFERROR(IF(OR(C13="",P13=0,P13=""),"",($C13/$P13)),""),'Painel Geral'!$B$5="Menor Salário",IFERROR(IF(OR(C13="",P13=0,P13=""),"",($C13/$M13)),""),'Painel Geral'!$B$5="1º Quartil",IFERROR(IF(OR(C13="",P13=0,P13=""),"",($C13/$N13)),""), 'Painel Geral'!$B$5="Média",IFERROR(IF(OR(C13="",P13=0,P13=""),"",($C13/$O13)),""),'Painel Geral'!$B$5="3º Quartil",IFERROR(IF(OR(C13="",P13=0,P13=""),"",($C13/$Q13)),""),'Painel Geral'!$B$5="Maior Salário",IFERROR(IF(OR(C13="",P13=0,P13=""),"",($C13/$R13)),"")) -> 0.88195834 | T13: =IFS(OR(M13="",M13=0,C13="", C13=0),"",S13<=80%,"Muito Defasado",S13<=90%,"Defasado",S13<=100%,"Na Média",S13<=110%,"Na Média",S13<=120%,"Muito Competitivo",S13>120%,"Agressivo") -> Defasado
A14: 11 | B14: =VLOOKUP(A14,Jobmatch!A:G,2,0) -> ANALISTA FINANCEIRO I | C14: =IFERROR(AVERAGEIF('Folha de Pagamento'!A:A,A14,'Folha de Pagamento'!K:K),"") -> 3993 | D14: 6 | E14: =VLOOKUP(A14,Jobmatch!A:H,3,0) -> Financeiro | F14: =VLOOKUP(A14,Jobmatch!A:I,4,0) -> 18 - ADM PROJETOS | G14: =VLOOKUP(A14,Jobmatch!A:I,5,0) -> Operacional | H14: =VLOOKUP(A14,Jobmatch!A:I,6,0) -> 16 | I14: =VLOOKUP(A14,Jobmatch!A:I,7,0) -> Analista Financeiro | J14: =VLOOKUP(A14,Jobmatch!A:I,8,0) -> Júnior | K14: =H14&J14 -> 16Júnior | L14: =COUNTIF('Folha de Pagamento'!A:A,A14) -> 1 | M14: =IFERROR(VLOOKUP(K14,Pesquisa!$D:$L,4,0),"") -> 2937.55 | N14: =IFERROR(VLOOKUP(K14,Pesquisa!$D:$L,5,0),"") -> 3176.35 | O14: =IFERROR(VLOOKUP(K14,Pesquisa!$D:$L,6,0),"") -> 3539.11 | P14: =IFERROR(VLOOKUP(K14,Pesquisa!$D:$L,7,0),"") -> 3493.97 | Q14: =IFERROR(VLOOKUP(K14,Pesquisa!$D:$L,8,0),"") -> 3798.49 | R14: =IFERROR(VLOOKUP(K14,Pesquisa!$D:$L,9,0),"") -> 4392.23 | S14: =IFS('Painel Geral'!$B$5="Mediana",IFERROR(IF(OR(C14="",P14=0,P14=""),"",($C14/$P14)),""),'Painel Geral'!$B$5="Menor Salário",IFERROR(IF(OR(C14="",P14=0,P14=""),"",($C14/$M14)),""),'Painel Geral'!$B$5="1º Quartil",IFERROR(IF(OR(C14="",P14=0,P14=""),"",($C14/$N14)),""), 'Painel Geral'!$B$5="Média",IFERROR(IF(OR(C14="",P14=0,P14=""),"",($C14/$O14)),""),'Painel Geral'!$B$5="3º Quartil",IFERROR(IF(OR(C14="",P14=0,P14=""),"",($C14/$Q14)),""),'Painel Geral'!$B$5="Maior Salário",IFERROR(IF(OR(C14="",P14=0,P14=""),"",($C14/$R14)),"")) -> 1.1428261 | T14: =IFS(OR(M14="",M14=0,C14="", C14=0),"",S14<=80%,"Muito Defasado",S14<=90%,"Defasado",S14<=100%,"Na Média",S14<=110%,"Na Média",S14<=120%,"Muito Competitivo",S14>120%,"Agressivo") -> Muito Competitivo
A15: 12 | B15: =VLOOKUP(A15,Jobmatch!A:G,2,0) -> ASSISTENTE ADM DE LEGALIZAÇÃO III | C15: =IFERROR(AVERAGEIF('Folha de Pagamento'!A:A,A15,'Folha de Pagamento'!K:K),"") -> 3652 | D15: 7 | E15: =VLOOKUP(A15,Jobmatch!A:H,3,0) -> Legalização | F15: =VLOOKUP(A15,Jobmatch!A:I,4,0) -> 19 - ADM PROJETOS | G15: =VLOOKUP(A15,Jobmatch!A:I,5,0) -> Operacional | H15: =VLOOKUP(A15,Jobmatch!A:I,6,0) -> 1201 | I15: =VLOOKUP(A15,Jobmatch!A:I,7,0) -> Assistente de Legalização | J15: =VLOOKUP(A15,Jobmatch!A:I,8,0) -> Indiferente | K15: =H15&J15 -> 1201Indiferente | L15: =COUNTIF('Folha de Pagamento'!A:A,A15) -> 1 | M15: =IFERROR(VLOOKUP(K15,Pesquisa!$D:$L,4,0),"") -> 2513.75 | N15: =IFERROR(VLOOKUP(K15,Pesquisa!$D:$L,5,0),"") -> 2803.34 | O15: =IFERROR(VLOOKUP(K15,Pesquisa!$D:$L,6,0),"") -> 3092.92 | P15: =IFERROR(VLOOKUP(K15,Pesquisa!$D:$L,7,0),"") -> 3092.92 | Q15: =IFERROR(VLOOKUP(K15,Pesquisa!$D:$L,8,0),"") -> 3382.51 | R15: =IFERROR(VLOOKUP(K15,Pesquisa!$D:$L,9,0),"") -> 3672.09 | S15: =IFS('Painel Geral'!$B$5="Mediana",IFERROR(IF(OR(C15="",P15=0,P15=""),"",($C15/$P15)),""),'Painel Geral'!$B$5="Menor Salário",IFERROR(IF(OR(C15="",P15=0,P15=""),"",($C15/$M15)),""),'Painel Geral'!$B$5="1º Quartil",IFERROR(IF(OR(C15="",P15=0,P15=""),"",($C15/$N15)),""), 'Painel Geral'!$B$5="Média",IFERROR(IF(OR(C15="",P15=0,P15=""),"",($C15/$O15)),""),'Painel Geral'!$B$5="3º Quartil",IFERROR(IF(OR(C15="",P15=0,P15=""),"",($C15/$Q15)),""),'Painel Geral'!$B$5="Maior Salário",IFERROR(IF(OR(C15="",P15=0,P15=""),"",($C15/$R15)),"")) -> 1.1807612 | T15: =IFS(OR(M15="",M15=0,C15="", C15=0),"",S15<=80%,"Muito Defasado",S15<=90%,"Defasado",S15<=100%,"Na Média",S15<=110%,"Na Média",S15<=120%,"Muito Competitivo",S15>120%,"Agressivo") -> Muito Competitivo
... A56: 54 | B56: =VLOOKUP(A56,Jobmatch!A:G,2,0) -> TECNOLOGO EM CONSTRUÇÃO DE EDIFICIOS | C56: =IFERROR(AVERAGEIF('Folha de Pagamento'!A:A,A56,'Folha de Pagamento'!K:K),"") -> 8585 | D56: 5 | E56: =VLOOKUP(A56,Jobmatch!A:H,3,0) -> Edificação | F56: =VLOOKUP(A56,Jobmatch!A:I,4,0) -> 61 - ADM PROJETOS | G56: =VLOOKUP(A56,Jobmatch!A:I,5,0) -> Operacional | H56: =VLOOKUP(A56,Jobmatch!A:I,6,0) -> 269 | I56: =VLOOKUP(A56,Jobmatch!A:I,7,0) -> Técnico em Edificações | J56: =VLOOKUP(A56,Jobmatch!A:I,8,0) -> Indiferente | K56: =H56&J56 -> 269Indiferente | L56: =COUNTIF('Folha de Pagamento'!A:A,A56) -> 1 | M56: =IFERROR(VLOOKUP(K56,Pesquisa!$D:$L,4,0),"") -> 3023.75 | N56: =IFERROR(VLOOKUP(K56,Pesquisa!$D:$L,5,0),"") -> 3741.13 | O56: =IFERROR(VLOOKUP(K56,Pesquisa!$D:$L,6,0),"") -> 4594.42 | P56: =IFERROR(VLOOKUP(K56,Pesquisa!$D:$L,7,0),"") -> 4031.66 | Q56: =IFERROR(VLOOKUP(K56,Pesquisa!$D:$L,8,0),"") -> 4427.77 | R56: =IFERROR(VLOOKUP(K56,Pesquisa!$D:$L,9,0),"") -> 9097.17 | S56: =IFS('Painel Geral'!$B$5="Mediana",IFERROR(IF(OR(C56="",P56=0,P56=""),"",($C56/$P56)),""),'Painel Geral'!$B$5="Menor Salário",IFERROR(IF(OR(C56="",P56=0,P56=""),"",($C56/$M56)),""),'Painel Geral'!$B$5="1º Quartil",IFERROR(IF(OR(C56="",P56=0,P56=""),"",($C56/$N56)),""), 'Painel Geral'!$B$5="Média",IFERROR(IF(OR(C56="",P56=0,P56=""),"",($C56/$O56)),""),'Painel Geral'!$B$5="3º Quartil",IFERROR(IF(OR(C56="",P56=0,P56=""),"",($C56/$Q56)),""),'Painel Geral'!$B$5="Maior Salário",IFERROR(IF(OR(C56="",P56=0,P56=""),"",($C56/$R56)),"")) -> 2.1293958 | T56: =IFS(OR(M56="",M56=0,C56="", C56=0),"",S56<=80%,"Muito Defasado",S56<=90%,"Defasado",S56<=100%,"Na Média",S56<=110%,"Na Média",S56<=120%,"Muito Competitivo",S56>120%,"Agressivo") -> Agressivo

Sheet Painel Geral
B3: Posicionamento e Gráficos em Relação à: | F3: ="Legenda (em relação à "&B5&"):" -> Legenda (em relação à Mediana):
F4: ▇ | G4: <=80% | H4: Muito Defasado
B5: Mediana | F5: ▇ | G5: 80% - 90% | H5: Defasado
F6: ▇ | G6: 90% - 100% | H6: Na Média
F7: ▇ | G7: 100% - 110% | H7: Na Média
F8: ▇ | G8: 110% - 120% | H8: Muito Competitivo
F9: ▇ | G9: >120% | H9: Agressivo
B12: Pesquisa
D15: =D41 -> 51
D17: cargos com amostra
D24: =IF(SUM(C36:C37)>SUM(C39:C40),SUM(C36:C37),SUM(C39:C40)) -> 0.37254902
D26: =IF(SUM(C36:C37)>SUM(C39:C40),"dos cargos abaixo "&IF(B5="Mediana","da ",IF(B5="Média","da ","do "))&B5,"dos cargos acima "&IF(B5="Mediana","da ",IF(B5="Média","da ","do "))&B5) -> dos cargos abaixo da Mediana
B35: Posição | C35: Percentual | D35: Qtde de Cargos
B36: Muito Defasado | C36: =IFERROR(D36/$D$41,0) -> 0.23529412 | D36: =COUNTIF('Cálculos Comparativos'!T:T,$B36) -> 12
B37: Defasado | C37: =IFERROR(D37/$D$41,0) -> 0.1372549 | D37: =COUNTIF('Cálculos Comparativos'!T:T,$B37) -> 7
B38: Na Média | C38: =IFERROR(D38/$D$41,0) -> 0.29411765 | D38: =COUNTIF('Cálculos Comparativos'!T:T,$B38) -> 15
B39: Muito Competitivo | C39: =IFERROR(D39/$D$41,0) -> 0.11764706 | D39: =COUNTIF('Cálculos Comparativos'!T:T,$B39) -> 6
B40: Agressivo | C40: =IFERROR(D40/$D$41,0) -> 0.21568627 | D40: =COUNTIF('Cálculos Comparativos'!T:T,$B40) -> 11
B41: Total Geral | C41: =SUM(C36:C40) -> 1 | D41: =SUM(D36:D40) -> 51
B44: ANÁLISE DE SALÁRIOS
B45: NÍVEIS ORGANIZACIONAIS
B48: Operacional
B51: Posição | C51: Pesquisa
B52: Muito Defasado | C52: =IFERROR(COUNTIFS('Cálculos Comparativos'!G:G,$B$48,'Cálculos Comparativos'!T:T,$B52)/C$57, 0) -> 0.12903226
B53: Defasado | C53: =IFERROR(COUNTIFS('Cálculos Comparativos'!G:G,$B$48,'Cálculos Comparativos'!T:T,$B53)/C$57, 0) -> 0.16129032
B54: Na Média | C54: =IFERROR(COUNTIFS('Cálculos Comparativos'!G:G,$B$48,'Cálculos Comparativos'!T:T,$B54)/C$57, 0) -> 0.25806452
B55: Muito Competitivo | C55: =IFERROR(COUNTIFS('Cálculos Comparativos'!G:G,$B$48,'Cálculos Comparativos'!T:T,$B55)/C$57, 0) -> 0.19354839
B56: Agressivo | C56: =IFERROR(COUNTIFS('Cálculos Comparativos'!G:G,$B$48,'Cálculos Comparativos'!T:T,$B56)/C$57, 0) -> 0.25806452
B57: Nº de Cargos Total | C57: =COUNTIFS('Cálculos Comparativos'!G:G,B48,'Cálculos Comparativos'!T:T,"?*") -> 31
G65: =IF(SUM(C52:C53)>SUM(C55:C56),SUM(C52:C53),SUM(C55:C56)) -> 0.4516129 | H65: =IF(SUM(C52:C53)>SUM(C55:C56),"dos cargos abaixo "&IF(B5="Mediana","da ",IF(B5="Média","da ","do "))&B5,"dos cargos acima "&IF(B5="Mediana","da ",IF(B5="Média","da ","do "))&B5) -> dos cargos acima da Mediana
B70: ="5 Maiores Salários acima "&IF(B5="Mediana","da ",IF(B5="Média","da ","do "))&B5 -> 5 Maiores Salários acima da Mediana
B72: Classificado pelo C-01 | E72: Pesquisa
B73: Cargos Empresa | C73: Cargos Pesquisa | D73: Média empresa | E73: =$B$5 -> Mediana | F73: Posição
A74: {=INDEX('Cálculos Comparativos'!A:A, MATCH(LARGE('Cálculos Comparativos'!S:S, ROW(A1)), 'Cálculos Comparativos'!S:S, 0))} -> 54 | B74: =iferror(VLOOKUP($A74,'Cálculos Comparativos'!$A:$T,2,0),"") -> TECNOLOGO EM CONSTRUÇÃO DE EDIFICIOS | C74: =iferror(VLOOKUP($A74,'Cálculos Comparativos'!$A:$T,9,0)&" "&if(VLOOKUP($A74,'Cálculos Comparativos'!$A:$T,10,0)="Indiferente","",VLOOKUP($A74,'Cálculos Comparativos'!$A:$T,10,0)),"") -> Técnico em Edificações | D74: =VLOOKUP(A74,'Cálculos Comparativos'!$A:$T,3,0) -> 8585 | E74: =IFS($B$5="Mediana",VLOOKUP(A74,'Cálculos Comparativos'!A:T,16,0),$B$5="Menor Salário",VLOOKUP(A74,'Cálculos Comparativos'!A:T,13,0),$B$5="1º Quartil",VLOOKUP(A74,'Cálculos Comparativos'!A:T,13,0),$B$5="Média",VLOOKUP(A74,'Cálculos Comparativos'!A:T,15,0),$B$5="3º Quartil",VLOOKUP(A74,'Cálculos Comparativos'!A:T,17,0),$B$5="Maior Salário",VLOOKUP(A74,'Cálculos Comparativos'!A:T,18,0)) -> 4031.66 | F74: =VLOOKUP(A74,'Cálculos Comparativos'!$A:$T,19,0) -> 2.1293958
A75: {=INDEX('Cálculos Comparativos'!A:A, MATCH(LARGE('Cálculos Comparativos'!S:S, ROW(A2)), 'Cálculos Comparativos'!S:S, 0))} -> 33 | B75: =iferror(VLOOKUP($A75,'Cálculos Comparativos'!$A:$T,2,0),"") -> DIRETOR | C75: =iferror(VLOOKUP($A75,'Cálculos Comparativos'!$A:$T,9,0)&" "&if(VLOOKUP($A75,'Cálculos Comparativos'!$A:$T,10,0)="Indiferente","",VLOOKUP($A75,'Cálculos Comparativos'!$A:$T,10,0)),"") -> CEO | D75: =VLOOKUP(A75,'Cálculos Comparativos'!$A:$T,3,0) -> 55769.231 | E75: =IFS($B$5="Mediana",VLOOKUP(A75,'Cálculos Comparativos'!A:T,16,0),$B$5="Menor Salário",VLOOKUP(A75,'Cálculos Comparativos'!A:T,13,0),$B$5="1º Quartil",VLOOKUP(A75,'Cálculos Comparativos'!A:T,13,0),$B$5="Média",VLOOKUP(A75,'Cálculos Comparativos'!A:T,15,0),$B$5="3º Quartil",VLOOKUP(A75,'Cálculos Comparativos'!A:T,17,0),$B$5="Maior Salário",VLOOKUP(A75,'Cálculos Comparativos'!A:T,18,0)) -> 29147.75 | F75: =VLOOKUP(A75,'Cálculos Comparativos'!$A:$T,19,0) -> 1.9133288
A76: {=INDEX('Cálculos Comparativos'!A:A, MATCH(LARGE('Cálculos Comparativos'!S:S, ROW(A3)), 'Cálculos Comparativos'!S:S, 0))} -> 44 | B76: =iferror(VLOOKUP($A76,'Cálculos Comparativos'!$A:$T,2,0),"") -> GERENTE DE EDIFICAÇÕES | C76: =iferror(VLOOKUP($A76,'Cálculos Comparativos'!$A:$T,9,0)&" "&if(VLOOKUP($A76,'Cálculos Comparativos'!$A:$T,10,0)="Indiferente","",VLOOKUP($A76,'Cálculos Comparativos'!$A:$T,10,0)),"") -> Gerente de Engenharia | D76: =VLOOKUP(A76,'Cálculos Comparativos'!$A:$T,3,0) -> 30106.061 | E76: =IFS($B$5="Mediana",VLOOKUP(A76,'Cálculos Comparativos'!A:T,16,0),$B$5="Menor Salário",VLOOKUP(A76,'Cálculos Comparativos'!A:T,13,0),$B$5="1º Quartil",VLOOKUP(A76,'Cálculos Comparativos'!A:T,13,0),$B$5="Média",VLOOKUP(A76,'Cálculos Comparativos'!A:T,15,0),$B$5="3º Quartil",VLOOKUP(A76,'Cálculos Comparativos'!A:T,17,0),$B$5="Maior Salário",VLOOKUP(A76,'Cálculos Comparativos'!A:T,18,0)) -> 19054.35 | F76: =VLOOKUP(A76,'Cálculos Comparativos'!$A:$T,19,0) -> 1.5800098
A77: {=INDEX('Cálculos Comparativos'!A:A, MATCH(LARGE('Cálculos Comparativos'!S:S, ROW(A4)), 'Cálculos Comparativos'!S:S, 0))} -> 50 | B77: =iferror(VLOOKUP($A77,'Cálculos Comparativos'!$A:$T,2,0),"") -> GERENTE DE URBANISMO | C77: =iferror(VLOOKUP($A77,'Cálculos Comparativos'!$A:$T,9,0)&" "&if(VLOOKUP($A77,'Cálculos Comparativos'!$A:$T,10,0)="Indiferente","",VLOOKUP($A77,'Cálculos Comparativos'!$A:$T,10,0)),"") -> Gerente de Urbanismo | D77: =VLOOKUP(A77,'Cálculos Comparativos'!$A:$T,3,0) -> 28030.303 | E77: =IFS($B$5="Mediana",VLOOKUP(A77,'Cálculos Comparativos'!A:T,16,0),$B$5="Menor Salário",VLOOKUP(A77,'Cálculos Comparativos'!A:T,13,0),$B$5="1º Quartil",VLOOKUP(A77,'Cálculos Comparativos'!A:T,13,0),$B$5="Média",VLOOKUP(A77,'Cálculos Comparativos'!A:T,15,0),$B$5="3º Quartil",VLOOKUP(A77,'Cálculos Comparativos'!A:T,17,0),$B$5="Maior Salário",VLOOKUP(A77,'Cálculos Comparativos'!A:T,18,0)) -> 20040.08 | F77: =VLOOKUP(A77,'Cálculos Comparativos'!$A:$T,19,0) -> 1.3987121
A78: {=INDEX('Cálculos Comparativos'!A:A, MATCH(LARGE('Cálculos Comparativos'!S:S, ROW(A5)), 'Cálculos Comparativos'!S:S, 0))} -> 34 | B78: =iferror(VLOOKUP($A78,'Cálculos Comparativos'!$A:$T,2,0),"") -> ENCARREGADO DE OBRAS | C78: =iferror(VLOOKUP($A78,'Cálculos Comparativos'!$A:$T,9,0)&" "&if(VLOOKUP($A78,'Cálculos Comparativos'!$A:$T,10,0)="Indiferente","",VLOOKUP($A78,'Cálculos Comparativos'!$A:$T,10,0)),"") -> Mestre de Obras | D78: =VLOOKUP(A78,'Cálculos Comparativos'!$A:$T,3,0) -> 10000.5 | E78: =IFS($B$5="Mediana",VLOOKUP(A78,'Cálculos Comparativos'!A:T,16,0),$B$5="Menor Salário",VLOOKUP(A78,'Cálculos Comparativos'!A:T,13,0),$B$5="1º Quartil",VLOOKUP(A78,'Cálculos Comparativos'!A:T,13,0),$B$5="Média",VLOOKUP(A78,'Cálculos Comparativos'!A:T,15,0),$B$5="3º Quartil",VLOOKUP(A78,'Cálculos Comparativos'!A:T,17,0),$B$5="Maior Salário",VLOOKUP(A78,'Cálculos Comparativos'!A:T,18,0)) -> 7478.73 | F78: =VLOOKUP(A78,'Cálculos Comparativos'!$A:$T,19,0) -> 1.3371923
B82: ="5 Menores Salários abaixo "&IF(B5="Mediana","da ",IF(B5="Média","da ","do "))&B5 -> 5 Menores Salários abaixo da Mediana
B84: Classificado pelo C-01 | E84: Pesquisa
B85: Cargos Empresa | C85: Cargos Pesquisa | D85: Média empresa | E85: =$B$5 -> Mediana | F85: Posição
A86: {=INDEX('Cálculos Comparativos'!A:A, MATCH(SMALL('Cálculos Comparativos'!S:S, ROW(A1)), 'Cálculos Comparativos'!S:S, 0))} -> 45 | B86: =iferror(VLOOKUP($A86,'Cálculos Comparativos'!$A:$T,2,0),"") -> GERENTE DE HOUSE | C86: =iferror(VLOOKUP($A86,'Cálculos Comparativos'!$A:$T,9,0)&" "&if(VLOOKUP($A86,'Cálculos Comparativos'!$A:$T,10,0)="Indiferente","",VLOOKUP($A86,'Cálculos Comparativos'!$A:$T,10,0)),"") -> Gerente Comercial | D86: =VLOOKUP(A86,'Cálculos Comparativos'!$A:$T,3,0) -> 3882.5758 | E86: =IFS($B$5="Mediana",VLOOKUP(A86,'Cálculos Comparativos'!A:T,16,0),$B$5="Menor Salário",VLOOKUP(A86,'Cálculos Comparativos'!A:T,13,0),$B$5="1º Quartil",VLOOKUP(A86,'Cálculos Comparativos'!A:T,14,0),$B$5="Média",VLOOKUP(A86,'Cálculos Comparativos'!A:T,14,0),$B$5="3º Quartil",VLOOKUP(A86,'Cálculos Comparativos'!A:T,17,0),$B$5="Maior Salário",VLOOKUP(A86,'Cálculos Comparativos'!A:T,18,0)) -> 12107.57 | F86: =VLOOKUP(A86,'Cálculos Comparativos'!$A:$T,19,0) -> 0.32067341
A87: {=INDEX('Cálculos Comparativos'!A:A, MATCH(SMALL('Cálculos Comparativos'!S:S, ROW(A2)), 'Cálculos Comparativos'!S:S, 0))} -> 49 | B87: =iferror(VLOOKUP($A87,'Cálculos Comparativos'!$A:$T,2,0),"") -> GERENTE DE PARCERIAS EXTERNAS | C87: =iferror(VLOOKUP($A87,'Cálculos Comparativos'!$A:$T,9,0)&" "&if(VLOOKUP($A87,'Cálculos Comparativos'!$A:$T,10,0)="Indiferente","",VLOOKUP($A87,'Cálculos Comparativos'!$A:$T,10,0)),"") -> Gerente de Relacionamento | D87: =VLOOKUP(A87,'Cálculos Comparativos'!$A:$T,3,0) -> 3787.8788 | E87: =IFS($B$5="Mediana",VLOOKUP(A87,'Cálculos Comparativos'!A:T,16,0),$B$5="Menor Salário",VLOOKUP(A87,'Cálculos Comparativos'!A:T,13,0),$B$5="1º Quartil",VLOOKUP(A87,'Cálculos Comparativos'!A:T,14,0),$B$5="Média",VLOOKUP(A87,'Cálculos Comparativos'!A:T,14,0),$B$5="3º Quartil",VLOOKUP(A87,'Cálculos Comparativos'!A:T,17,0),$B$5="Maior Salário",VLOOKUP(A87,'Cálculos Comparativos'!A:T,18,0)) -> 10996.97 | F87: =VLOOKUP(A87,'Cálculos Comparativos'!$A:$T,19,0) -> 0.3444475
A88: {=INDEX('Cálculos Comparativos'!A:A, MATCH(SMALL('Cálculos Comparativos'!S:S, ROW(A3)), 'Cálculos Comparativos'!S:S, 0))} -> 48 | B88: =iferror(VLOOKUP($A88,'Cálculos Comparativos'!$A:$T,2,0),"") -> GERENTE DE PARCERIAS | C88: =iferror(VLOOKUP($A88,'Cálculos Comparativos'!$A:$T,9,0)&" "&if(VLOOKUP($A88,'Cálculos Comparativos'!$A:$T,10,0)="Indiferente","",VLOOKUP($A88,'Cálculos Comparativos'!$A:$T,10,0)),"") -> Gerente de Relacionamento | D88: =VLOOKUP(A88,'Cálculos Comparativos'!$A:$T,3,0) -> 4049.2424 | E88: =IFS($B$5="Mediana",VLOOKUP(A88,'Cálculos Comparativos'!A:T,16,0),$B$5="Menor Salário",VLOOKUP(A88,'Cálculos Comparativos'!A:T,13,0),$B$5="1º Quartil",VLOOKUP(A88,'Cálculos Comparativos'!A:T,14,0),$B$5="Média",VLOOKUP(A88,'Cálculos Comparativos'!A:T,14,0),$B$5="3º Quartil",VLOOKUP(A88,'Cálculos Comparativos'!A:T,17,0),$B$5="Maior Salário",VLOOKUP(A88,'Cálculos Comparativos'!A:T,18,0)) -> 10996.97 | F88: =VLOOKUP(A88,'Cálculos Comparativos'!$A:$T,19,0) -> 0.36821437
A89: {=INDEX('Cálculos Comparativos'!A:A, MATCH(SMALL('Cálculos Comparativos'!S:S, ROW(A4)), 'Cálculos Comparativos'!S:S, 0))} -> 36 | B89: =iferror(VLOOKUP($A89,'Cálculos Comparativos'!$A:$T,2,0),"") -> ENGENHEIRO JUNIOR DE URBANISMO | C89: =iferror(VLOOKUP($A89,'Cálculos Comparativos'!$A:$T,9,0)&" "&if(VLOOKUP($A89,'Cálculos Comparativos'!$A:$T,10,0)="Indiferente","",VLOOKUP($A89,'Cálculos Comparativos'!$A:$T,10,0)),"") -> Engenheiro de Urbanismo | D89: =VLOOKUP(A89,'Cálculos Comparativos'!$A:$T,3,0) -> 5630.8725 | E89: =IFS($B$5="Mediana",VLOOKUP(A89,'Cálculos Comparativos'!A:T,16,0),$B$5="Menor Salário",VLOOKUP(A89,'Cálculos Comparativos'!A:T,13,0),$B$5="1º Quartil",VLOOKUP(A89,'Cálculos Comparativos'!A:T,14,0),$B$5="Média",VLOOKUP(A89,'Cálculos Comparativos'!A:T,14,0),$B$5="3º Quartil",VLOOKUP(A89,'Cálculos Comparativos'!A:T,17,0),$B$5="Maior Salário",VLOOKUP(A89,'Cálculos Comparativos'!A:T,18,0)) -> 15118.5 | F89: =VLOOKUP(A89,'Cálculos Comparativos'!$A:$T,19,0) -> 0.37244915
A90: {=INDEX('Cálculos Comparativos'!A:A, MATCH(SMALL('Cálculos Comparativos'!S:S, ROW(A5)), 'Cálculos Comparativos'!S:S, 0))} -> 26 | B90: =iferror(VLOOKUP($A90,'Cálculos Comparativos'!$A:$T,2,0),"") -> CONTROLLER TÉCNICO | C90: =iferror(VLOOKUP($A90,'Cálculos Comparativos'!$A:$T,9,0)&" "&if(VLOOKUP($A90,'Cálculos Comparativos'!$A:$T,10,0)="Indiferente","",VLOOKUP($A90,'Cálculos Comparativos'!$A:$T,10,0)),"") -> Analista de Controladoria Especialista | D90: =VLOOKUP(A90,'Cálculos Comparativos'!$A:$T,3,0) -> 9243.5037 | E90: =IFS($B$5="Mediana",VLOOKUP(A90,'Cálculos Comparativos'!A:T,16,0),$B$5="Menor Salário",VLOOKUP(A90,'Cálculos Comparativos'!A:T,13,0),$B$5="1º Quartil",VLOOKUP(A90,'Cálculos Comparativos'!A:T,14,0),$B$5="Média",VLOOKUP(A90,'Cálculos Comparativos'!A:T,14,0),$B$5="3º Quartil",VLOOKUP(A90,'Cálculos Comparativos'!A:T,17,0),$B$5="Maior Salário",VLOOKUP(A90,'Cálculos Comparativos'!A:T,18,0)) -> 13758.75 | F90: =VLOOKUP(A90,'Cálculos Comparativos'!$A:$T,19,0) -> 0.67182728

Sheet Painel Áreas
E1: Pesquisa | P1: Administrativo, Recepção, Suprimentos, Tecnologia da Informação | Q1: 1
P2: Comercial | Q2: 2
B3: Posicionamento e Gráficos em Relação à: | P3: Controladoria | Q3: 3
E4: =$D$27 -> 4 | P4: DHO | Q4: 4
B5: ='Painel Geral'!$B$5 -> Mediana | P5: Edificação | Q5: 5
E6: cargos com amostra | P6: Financeiro | Q6: 6
B7: (Para alterar o dado de comparação use a aba Painel Geral) | P7: Incorporação, Inovação, Legalização | Q7: 7
P8: Marketing | Q8: 8
B9: ANÁLISE DE | P9: Novos Negócios, Pós Vendas | Q9: 9
B10: COMPARATIVOS SALARIAIS | P10: Urbanismo | Q10: 10
B11: POR ÁREAS | E11: =IF(SUM(C22:C24)>SUM(C25:C26),SUM(C22:C24),SUM(C25:C26)) -> 0.75
B13: Incorporação, Inovação, Legalização | E13: =IF(SUM(C22:C24)>SUM(C25:C26),"dos cargos abaixo "&IF(B5="Mediana","da ",IF(B5="Média","da ","do "))&B5,"dos cargos acima "&IF(B5="Mediana","da ",IF(B5="Média","da ","do "))&B5) -> dos cargos abaixo da Mediana
B15: =VLOOKUP(B13,P:Q,2,0) -> 7
A20: 2 | C20: Pesquisa | H20: Posição | I20: Percentual
B21: Posição | C21: Percentual | D21: Qtd Cargos | H21: Muito Defasado | I21: =C22 -> 0.25
B22: Muito Defasado | C22: =iferror(D22/D$27,0) -> 0.25 | D22: =COUNTIFS('Cálculos Comparativos'!T:T,$B22,'Cálculos Comparativos'!D:D,$B$15) -> 1 | H22: Defasado | I22: =C23 -> 0
B23: Defasado | C23: =iferror(D23/D$27,0) -> 0 | D23: =COUNTIFS('Cálculos Comparativos'!T:T,$B23,'Cálculos Comparativos'!D:D,$B$15) -> 0 | H23: Na Média | I23: =C24 -> 0.5
B24: Na Média | C24: =iferror(D24/D$27,0) -> 0.5 | D24: =COUNTIFS('Cálculos Comparativos'!T:T,$B24,'Cálculos Comparativos'!D:D,$B$15) -> 2 | H24: Muito Competitivo | I24: =C25 -> 0.25
B25: Muito Competitivo | C25: =iferror(D25/D$27,0) -> 0.25 | D25: =COUNTIFS('Cálculos Comparativos'!T:T,$B25,'Cálculos Comparativos'!D:D,$B$15) -> 1 | H25: Agressivo | I25: =C26 -> 0
A26: 2 | B26: Agressivo | C26: =iferror(D26/D$27,0) -> 0 | D26: =COUNTIFS('Cálculos Comparativos'!T:T,$B26,'Cálculos Comparativos'!D:D,$B$15) -> 0 | H26: Total Geral | I26: =SUM(I21:I25) -> 1
B27: Total Geral | C27: =SUM(C22:C26) -> 1 | D27: =SUM(D22:D26) -> 4
E29: Pesquisa
B30: Cargos Empresa | C30: Cargos Pesquisa | D30: Média Empresa | E30: =B5 -> Mediana | F30: Posição
A31: =IFERROR(__xludf.DUMMYFUNCTION("FILTER('Cálculos Comparativos'!A:A,'Cálculos Comparativos'!D:D=$B$15,'Cálculos Comparativos'!T:T<>"""")"),"4") -> 4 | B31: =IFERROR(VLOOKUP($A31,'Cálculos Comparativos'!$A:$T,2,0),"") -> ANALISTA DE INOVAÇÃO | C31: =IFERROR(VLOOKUP($A31,'Cálculos Comparativos'!$A:$T,9,0)&" "&if(VLOOKUP($A31,'Cálculos Comparativos'!$A:$T,10,0)="Indiferente","",VLOOKUP($A31,'Cálculos Comparativos'!$A:$T,10,0)),"") -> Analista de Inovação | D31: =IFERROR(VLOOKUP(A31,'Cálculos Comparativos'!A:L,3,0),"") -> 7299.2701 | E31: =IFERROR(IFS($B$5="Mediana",VLOOKUP(A31,'Cálculos Comparativos'!A:T,16,0),$B$5="Menor Salário",VLOOKUP(A31,'Cálculos Comparativos'!A:T,13,0),$B$5="1º Quartil",VLOOKUP(A31,'Cálculos Comparativos'!A:T,14,0),$B$5="Média",VLOOKUP(A31,'Cálculos Comparativos'!A:T,15,0),$B$5="3º Quartil",VLOOKUP(A31,'Cálculos Comparativos'!A:T,17,0),$B$5="Maior Salário",VLOOKUP(A31,'Cálculos Comparativos'!A:T,18,0)),"") -> 6872.0455 | F31: =IFERROR(VLOOKUP($A31,'Cálculos Comparativos'!$A:$T,19,0),"") -> 1.0621685 | G31: =IFERROR(VLOOKUP($A31,'Cálculos Comparativos'!$A:$T,20,0),"") -> Na Média
A32: =IFERROR(__xludf.DUMMYFUNCTION("""COMPUTED_VALUE"""),"12") -> 12 | B32: =IFERROR(VLOOKUP($A32,'Cálculos Comparativos'!$A:$T,2,0),"") -> ASSISTENTE ADM DE LEGALIZAÇÃO III | C32: =IFERROR(VLOOKUP($A32,'Cálculos Comparativos'!$A:$T,9,0)&" "&if(VLOOKUP($A32,'Cálculos Comparativos'!$A:$T,10,0)="Indiferente","",VLOOKUP($A32,'Cálculos Comparativos'!$A:$T,10,0)),"") -> Assistente de Legalização | D32: =IFERROR(VLOOKUP(A32,'Cálculos Comparativos'!A:L,3,0),"") -> 3652 | E32: =IFERROR(IFS($B$5="Mediana",VLOOKUP(A32,'Cálculos Comparativos'!A:T,16,0),$B$5="Menor Salário",VLOOKUP(A32,'Cálculos Comparativos'!A:T,13,0),$B$5="1º Quartil",VLOOKUP(A32,'Cálculos Comparativos'!A:T,14,0),$B$5="Média",VLOOKUP(A32,'Cálculos Comparativos'!A:T,15,0),$B$5="3º Quartil",VLOOKUP(A32,'Cálculos Comparativos'!A:T,17,0),$B$5="Maior Salário",VLOOKUP(A32,'Cálculos Comparativos'!A:T,18,0)),"") -> 3092.92 | F32: =IFERROR(VLOOKUP($A32,'Cálculos Comparativos'!$A:$T,19,0),"") -> 1.1807612 | G32: =IFERROR(VLOOKUP($A32,'Cálculos Comparativos'!$A:$T,20,0),"") -> Muito Competitivo
A33: =IFERROR(__xludf.DUMMYFUNCTION("""COMPUTED_VALUE"""),"28") -> 28 | B33: =IFERROR(VLOOKUP($A33,'Cálculos Comparativos'!$A:$T,2,0),"") -> COORDENADOR DE LEGAIZAÇÃO ll | C33: =IFERROR(VLOOKUP($A33,'Cálculos Comparativos'!$A:$T,9,0)&" "&if(VLOOKUP($A33,'Cálculos Comparativos'!$A:$T,10,0)="Indiferente","",VLOOKUP($A33,'Cálculos Comparativos'!$A:$T,10,0)),"") -> Coordenador de Legalização | D33: =IFERROR(VLOOKUP(A33,'Cálculos Comparativos'!A:L,3,0),"") -> 8647 | E33: =IFERROR(IFS($B$5="Mediana",VLOOKUP(A33,'Cálculos Comparativos'!A:T,16,0),$B$5="Menor Salário",VLOOKUP(A33,'Cálculos Comparativos'!A:T,13,0),$B$5="1º Quartil",VLOOKUP(A33,'Cálculos Comparativos'!A:T,14,0),$B$5="Média",VLOOKUP(A33,'Cálculos Comparativos'!A:T,15,0),$B$5="3º Quartil",VLOOKUP(A33,'Cálculos Comparativos'!A:T,17,0),$B$5="Maior Salário",VLOOKUP(A33,'Cálculos Comparativos'!A:T,18,0)),"") -> 8872.04 | F33: =IFERROR(VLOOKUP($A33,'Cálculos Comparativos'!$A:$T,19,0),"") -> 0.97463492 | G33: =IFERROR(VLOOKUP($A33,'Cálculos Comparativos'!$A:$T,20,0),"") -> Na Média
A34: =IFERROR(__xludf.DUMMYFUNCTION("""COMPUTED_VALUE"""),"47") -> 47 | B34: =IFERROR(VLOOKUP($A34,'Cálculos Comparativos'!$A:$T,2,0),"") -> GERENTE DE INCORPORAÇÃO | C34: =IFERROR(VLOOKUP($A34,'Cálculos Comparativos'!$A:$T,9,0)&" "&if(VLOOKUP($A34,'Cálculos Comparativos'!$A:$T,10,0)="Indiferente","",VLOOKUP($A34,'Cálculos Comparativos'!$A:$T,10,0)),"") -> Gerente de Incorporação | D34: =IFERROR(VLOOKUP(A34,'Cálculos Comparativos'!A:L,3,0),"") -> 14045.455 | E34: =IFERROR(IFS($B$5="Mediana",VLOOKUP(A34,'Cálculos Comparativos'!A:T,16,0),$B$5="Menor Salário",VLOOKUP(A34,'Cálculos Comparativos'!A:T,13,0),$B$5="1º Quartil",VLOOKUP(A34,'Cálculos Comparativos'!A:T,14,0),$B$5="Média",VLOOKUP(A34,'Cálculos Comparativos'!A:T,15,0),$B$5="3º Quartil",VLOOKUP(A34,'Cálculos Comparativos'!A:T,17,0),$B$5="Maior Salário",VLOOKUP(A34,'Cálculos Comparativos'!A:T,18,0)),"") -> 18908.464 | F34: =IFERROR(VLOOKUP($A34,'Cálculos Comparativos'!$A:$T,19,0),"") -> 0.7428131 | G34: =IFERROR(VLOOKUP($A34,'Cálculos Comparativos'!$A:$T,20,0),"") -> Muito Defasado
B35: =IFERROR(VLOOKUP($A35,'Cálculos Comparativos'!$A:$T,2,0),"") | C35: =IFERROR(VLOOKUP($A35,'Cálculos Comparativos'!$A:$T,9,0)&" "&if(VLOOKUP($A35,'Cálculos Comparativos'!$A:$T,10,0)="Indiferente","",VLOOKUP($A35,'Cálculos Comparativos'!$A:$T,10,0)),"") | D35: =IFERROR(VLOOKUP(A35,'Cálculos Comparativos'!A:L,3,0),"") | E35: =IFERROR(IFS($B$5="Mediana",VLOOKUP(A35,'Cálculos Comparativos'!A:T,16,0),$B$5="Menor Salário",VLOOKUP(A35,'Cálculos Comparativos'!A:T,13,0),$B$5="1º Quartil",VLOOKUP(A35,'Cálculos Comparativos'!A:T,14,0),$B$5="Média",VLOOKUP(A35,'Cálculos Comparativos'!A:T,15,0),$B$5="3º Quartil",VLOOKUP(A35,'Cálculos Comparativos'!A:T,17,0),$B$5="Maior Salário",VLOOKUP(A35,'Cálculos Comparativos'!A:T,18,0)),"") | F35: =IFERROR(VLOOKUP($A35,'Cálculos Comparativos'!$A:$T,19,0),"") | G35: =IFERROR(VLOOKUP($A35,'Cálculos Comparativos'!$A:$T,20,0),"")
B36: =IFERROR(VLOOKUP($A36,'Cálculos Comparativos'!$A:$T,2,0),"") | C36: =IFERROR(VLOOKUP($A36,'Cálculos Comparativos'!$A:$T,9,0)&" "&if(VLOOKUP($A36,'Cálculos Comparativos'!$A:$T,10,0)="Indiferente","",VLOOKUP($A36,'Cálculos Comparativos'!$A:$T,10,0)),"") | D36: =IFERROR(VLOOKUP(A36,'Cálculos Comparativos'!A:L,3,0),"") | E36: =IFERROR(IFS($B$5="Mediana",VLOOKUP(A36,'Cálculos Comparativos'!A:T,16,0),$B$5="Menor Salário",VLOOKUP(A36,'Cálculos Comparativos'!A:T,13,0),$B$5="1º Quartil",VLOOKUP(A36,'Cálculos Comparativos'!A:T,14,0),$B$5="Média",VLOOKUP(A36,'Cálculos Comparativos'!A:T,15,0),$B$5="3º Quartil",VLOOKUP(A36,'Cálculos Comparativos'!A:T,17,0),$B$5="Maior Salário",VLOOKUP(A36,'Cálculos Comparativos'!A:T,18,0)),"") | F36: =IFERROR(VLOOKUP($A36,'Cálculos Comparativos'!$A:$T,19,0),"") | G36: =IFERROR(VLOOKUP($A36,'Cálculos Comparativos'!$A:$T,20,0),"")
B37: =IFERROR(VLOOKUP($A37,'Cálculos Comparativos'!$A:$T,2,0),"") | C37: =IFERROR(VLOOKUP($A37,'Cálculos Comparativos'!$A:$T,9,0)&" "&if(VLOOKUP($A37,'Cálculos Comparativos'!$A:$T,10,0)="Indiferente","",VLOOKUP($A37,'Cálculos Comparativos'!$A:$T,10,0)),"") | D37: =IFERROR(VLOOKUP(A37,'Cálculos Comparativos'!A:L,3,0),"") | E37: =IFERROR(IFS($B$5="Mediana",VLOOKUP(A37,'Cálculos Comparativos'!A:T,16,0),$B$5="Menor Salário",VLOOKUP(A37,'Cálculos Comparativos'!A:T,13,0),$B$5="1º Quartil",VLOOKUP(A37,'Cálculos Comparativos'!A:T,14,0),$B$5="Média",VLOOKUP(A37,'Cálculos Comparativos'!A:T,15,0),$B$5="3º Quartil",VLOOKUP(A37,'Cálculos Comparativos'!A:T,17,0),$B$5="Maior Salário",VLOOKUP(A37,'Cálculos Comparativos'!A:T,18,0)),"") | F37: =IFERROR(VLOOKUP($A37,'Cálculos Comparativos'!$A:$T,19,0),"") | G37: =IFERROR(VLOOKUP($A37,'Cálculos Comparativos'!$A:$T,20,0),"")
B38: =IFERROR(VLOOKUP($A38,'Cálculos Comparativos'!$A:$T,2,0),"") | C38: =IFERROR(VLOOKUP($A38,'Cálculos Comparativos'!$A:$T,9,0)&" "&if(VLOOKUP($A38,'Cálculos Comparativos'!$A:$T,10,0)="Indiferente","",VLOOKUP($A38,'Cálculos Comparativos'!$A:$T,10,0)),"") | D38: =IFERROR(VLOOKUP(A38,'Cálculos Comparativos'!A:L,3,0),"") | E38: =IFERROR(IFS($B$5="Mediana",VLOOKUP(A38,'Cálculos Comparativos'!A:T,16,0),$B$5="Menor Salário",VLOOKUP(A38,'Cálculos Comparativos'!A:T,13,0),$B$5="1º Quartil",VLOOKUP(A38,'Cálculos Comparativos'!A:T,14,0),$B$5="Média",VLOOKUP(A38,'Cálculos Comparativos'!A:T,15,0),$B$5="3º Quartil",VLOOKUP(A38,'Cálculos Comparativos'!A:T,17,0),$B$5="Maior Salário",VLOOKUP(A38,'Cálculos Comparativos'!A:T,18,0)),"") | F38: =IFERROR(VLOOKUP($A38,'Cálculos Comparativos'!$A:$T,19,0),"") | G38: =IFERROR(VLOOKUP($A38,'Cálculos Comparativos'!$A:$T,20,0),"")
B39: =IFERROR(VLOOKUP($A39,'Cálculos Comparativos'!$A:$T,2,0),"") | C39: =IFERROR(VLOOKUP($A39,'Cálculos Comparativos'!$A:$T,9,0)&" "&if(VLOOKUP($A39,'Cálculos Comparativos'!$A:$T,10,0)="Indiferente","",VLOOKUP($A39,'Cálculos Comparativos'!$A:$T,10,0)),"") | D39: =IFERROR(VLOOKUP(A39,'Cálculos Comparativos'!A:L,3,0),"") | E39: =IFERROR(IFS($B$5="Mediana",VLOOKUP(A39,'Cálculos Comparativos'!A:T,16,0),$B$5="Menor Salário",VLOOKUP(A39,'Cálculos Comparativos'!A:T,13,0),$B$5="1º Quartil",VLOOKUP(A39,'Cálculos Comparativos'!A:T,14,0),$B$5="Média",VLOOKUP(A39,'Cálculos Comparativos'!A:T,15,0),$B$5="3º Quartil",VLOOKUP(A39,'Cálculos Comparativos'!A:T,17,0),$B$5="Maior Salário",VLOOKUP(A39,'Cálculos Comparativos'!A:T,18,0)),"") | F39: =IFERROR(VLOOKUP($A39,'Cálculos Comparativos'!$A:$T,19,0),"") | G39: =IFERROR(VLOOKUP($A39,'Cálculos Comparativos'!$A:$T,20,0),"")
B40: =IFERROR(VLOOKUP($A40,'Cálculos Comparativos'!$A:$T,2,0),"") | C40: =IFERROR(VLOOKUP($A40,'Cálculos Comparativos'!$A:$T,9,0)&" "&if(VLOOKUP($A40,'Cálculos Comparativos'!$A:$T,10,0)="Indiferente","",VLOOKUP($A40,'Cálculos Comparativos'!$A:$T,10,0)),"") | D40: =IFERROR(VLOOKUP(A40,'Cálculos Comparativos'!A:L,3,0),"") | E40: =IFERROR(IFS($B$5="Mediana",VLOOKUP(A40,'Cálculos Comparativos'!A:T,16,0),$B$5="Menor Salário",VLOOKUP(A40,'Cálculos Comparativos'!A:T,13,0),$B$5="1º Quartil",VLOOKUP(A40,'Cálculos Comparativos'!A:T,14,0),$B$5="Média",VLOOKUP(A40,'Cálculos Comparativos'!A:T,15,0),$B$5="3º Quartil",VLOOKUP(A40,'Cálculos Comparativos'!A:T,17,0),$B$5="Maior Salário",VLOOKUP(A40,'Cálculos Comparativos'!A:T,18,0)),"") | F40: =IFERROR(VLOOKUP($A40,'Cálculos Comparativos'!$A:$T,19,0),"") | G40: =IFERROR(VLOOKUP($A40,'Cálculos Comparativos'!$A:$T,20,0),"")
B41: =IFERROR(VLOOKUP($A41,'Cálculos Comparativos'!$A:$T,2,0),"") | C41: =IFERROR(VLOOKUP($A41,'Cálculos Comparativos'!$A:$T,9,0)&" "&if(VLOOKUP($A41,'Cálculos Comparativos'!$A:$T,10,0)="Indiferente","",VLOOKUP($A41,'Cálculos Comparativos'!$A:$T,10,0)),"") | D41: =IFERROR(VLOOKUP(A41,'Cálculos Comparativos'!A:L,3,0),"") | E41: =IFERROR(IFS($B$5="Mediana",VLOOKUP(A41,'Cálculos Comparativos'!A:T,16,0),$B$5="Menor Salário",VLOOKUP(A41,'Cálculos Comparativos'!A:T,13,0),$B$5="1º Quartil",VLOOKUP(A41,'Cálculos Comparativos'!A:T,14,0),$B$5="Média",VLOOKUP(A41,'Cálculos Comparativos'!A:T,15,0),$B$5="3º Quartil",VLOOKUP(A41,'Cálculos Comparativos'!A:T,17,0),$B$5="Maior Salário",VLOOKUP(A41,'Cálculos Comparativos'!A:T,18,0)),"") | F41: =IFERROR(VLOOKUP($A41,'Cálculos Comparativos'!$A:$T,19,0),"") | G41: =IFERROR(VLOOKUP($A41,'Cálculos Comparativos'!$A:$T,20,0),"")
B42: =IFERROR(VLOOKUP($A42,'Cálculos Comparativos'!$A:$T,2,0),"") | C42: =IFERROR(VLOOKUP($A42,'Cálculos Comparativos'!$A:$T,9,0)&" "&if(VLOOKUP($A42,'Cálculos Comparativos'!$A:$T,10,0)="Indiferente","",VLOOKUP($A42,'Cálculos Comparativos'!$A:$T,10,0)),"") | D42: =IFERROR(VLOOKUP(A42,'Cálculos Comparativos'!A:L,3,0),"") | E42: =IFERROR(IFS($B$5="Mediana",VLOOKUP(A42,'Cálculos Comparativos'!A:T,16,0),$B$5="Menor Salário",VLOOKUP(A42,'Cálculos Comparativos'!A:T,13,0),$B$5="1º Quartil",VLOOKUP(A42,'Cálculos Comparativos'!A:T,14,0),$B$5="Média",VLOOKUP(A42,'Cálculos Comparativos'!A:T,15,0),$B$5="3º Quartil",VLOOKUP(A42,'Cálculos Comparativos'!A:T,17,0),$B$5="Maior Salário",VLOOKUP(A42,'Cálculos Comparativos'!A:T,18,0)),"") | F42: =IFERROR(VLOOKUP($A42,'Cálculos Comparativos'!$A:$T,19,0),"") | G42: =IFERROR(VLOOKUP($A42,'Cálculos Comparativos'!$A:$T,20,0),"")
B43: =IFERROR(VLOOKUP($A43,'Cálculos Comparativos'!$A:$T,2,0),"") | C43: =IFERROR(VLOOKUP($A43,'Cálculos Comparativos'!$A:$T,9,0)&" "&if(VLOOKUP($A43,'Cálculos Comparativos'!$A:$T,10,0)="Indiferente","",VLOOKUP($A43,'Cálculos Comparativos'!$A:$T,10,0)),"") | D43: =IFERROR(VLOOKUP(A43,'Cálculos Comparativos'!A:L,3,0),"") | E43: =IFERROR(IFS($B$5="Mediana",VLOOKUP(A43,'Cálculos Comparativos'!A:T,16,0),$B$5="Menor Salário",VLOOKUP(A43,'Cálculos Comparativos'!A:T,13,0),$B$5="1º Quartil",VLOOKUP(A43,'Cálculos Comparativos'!A:T,14,0),$B$5="Média",VLOOKUP(A43,'Cálculos Comparativos'!A:T,15,0),$B$5="3º Quartil",VLOOKUP(A43,'Cálculos Comparativos'!A:T,17,0),$B$5="Maior Salário",VLOOKUP(A43,'Cálculos Comparativos'!A:T,18,0)),"") | F43: =IFERROR(VLOOKUP($A43,'Cálculos Comparativos'!$A:$T,19,0),"") | G43: =IFERROR(VLOOKUP($A43,'Cálculos Comparativos'!$A:$T,20,0),"")
B44: =IFERROR(VLOOKUP($A44,'Cálculos Comparativos'!$A:$T,2,0),"") | C44: =IFERROR(VLOOKUP($A44,'Cálculos Comparativos'!$A:$T,9,0)&" "&if(VLOOKUP($A44,'Cálculos Comparativos'!$A:$T,10,0)="Indiferente","",VLOOKUP($A44,'Cálculos Comparativos'!$A:$T,10,0)),"") | D44: =IFERROR(VLOOKUP(A44,'Cálculos Comparativos'!A:L,3,0),"") | E44: =IFERROR(IFS($B$5="Mediana",VLOOKUP(A44,'Cálculos Comparativos'!A:T,16,0),$B$5="Menor Salário",VLOOKUP(A44,'Cálculos Comparativos'!A:T,13,0),$B$5="1º Quartil",VLOOKUP(A44,'Cálculos Comparativos'!A:T,14,0),$B$5="Média",VLOOKUP(A44,'Cálculos Comparativos'!A:T,15,0),$B$5="3º Quartil",VLOOKUP(A44,'Cálculos Comparativos'!A:T,17,0),$B$5="Maior Salário",VLOOKUP(A44,'Cálculos Comparativos'!A:T,18,0)),"") | F44: =IFERROR(VLOOKUP($A44,'Cálculos Comparativos'!$A:$T,19,0),"") | G44: =IFERROR(VLOOKUP($A44,'Cálculos Comparativos'!$A:$T,20,0),"")
B45: =IFERROR(VLOOKUP($A45,'Cálculos Comparativos'!$A:$T,2,0),"") | C45: =IFERROR(VLOOKUP($A45,'Cálculos Comparativos'!$A:$T,9,0)&" "&if(VLOOKUP($A45,'Cálculos Comparativos'!$A:$T,10,0)="Indiferente","",VLOOKUP($A45,'Cálculos Comparativos'!$A:$T,10,0)),"") | D45: =IFERROR(VLOOKUP(A45,'Cálculos Comparativos'!A:L,3,0),"") | E45: =IFERROR(IFS($B$5="Mediana",VLOOKUP(A45,'Cálculos Comparativos'!A:T,16,0),$B$5="Menor Salário",VLOOKUP(A45,'Cálculos Comparativos'!A:T,13,0),$B$5="1º Quartil",VLOOKUP(A45,'Cálculos Comparativos'!A:T,14,0),$B$5="Média",VLOOKUP(A45,'Cálculos Comparativos'!A:T,15,0),$B$5="3º Quartil",VLOOKUP(A45,'Cálculos Comparativos'!A:T,17,0),$B$5="Maior Salário",VLOOKUP(A45,'Cálculos Comparativos'!A:T,18,0)),"") | F45: =IFERROR(VLOOKUP($A45,'Cálculos Comparativos'!$A:$T,19,0),"") | G45: =IFERROR(VLOOKUP($A45,'Cálculos Comparativos'!$A:$T,20,0),"")
B46: =IFERROR(VLOOKUP($A46,'Cálculos Comparativos'!$A:$T,2,0),"") | C46: =IFERROR(VLOOKUP($A46,'Cálculos Comparativos'!$A:$T,9,0)&" "&if(VLOOKUP($A46,'Cálculos Comparativos'!$A:$T,10,0)="Indiferente","",VLOOKUP($A46,'Cálculos Comparativos'!$A:$T,10,0)),"") | D46: =IFERROR(VLOOKUP(A46,'Cálculos Comparativos'!A:L,3,0),"") | E46: =IFERROR(IFS($B$5="Mediana",VLOOKUP(A46,'Cálculos Comparativos'!A:T,16,0),$B$5="Menor Salário",VLOOKUP(A46,'Cálculos Comparativos'!A:T,13,0),$B$5="1º Quartil",VLOOKUP(A46,'Cálculos Comparativos'!A:T,14,0),$B$5="Média",VLOOKUP(A46,'Cálculos Comparativos'!A:T,15,0),$B$5="3º Quartil",VLOOKUP(A46,'Cálculos Comparativos'!A:T,17,0),$B$5="Maior Salário",VLOOKUP(A46,'Cálculos Comparativos'!A:T,18,0)),"") | F46: =IFERROR(VLOOKUP($A46,'Cálculos Comparativos'!$A:$T,19,0),"") | G46: =IFERROR(VLOOKUP($A46,'Cálculos Comparativos'!$A:$T,20,0),"")
... B61: =IFERROR(VLOOKUP($A61,'Cálculos Comparativos'!$A:$T,2,0),"") | C61: =IFERROR(VLOOKUP($A61,'Cálculos Comparativos'!$A:$T,9,0)&" "&if(VLOOKUP($A61,'Cálculos Comparativos'!$A:$T,10,0)="Indiferente","",VLOOKUP($A61,'Cálculos Comparativos'!$A:$T,10,0)),"") | D61: =IFERROR(VLOOKUP(A61,'Cálculos Comparativos'!A:L,3,0),"") | E61: =IFERROR(IFS($B$5="Mediana",VLOOKUP(A61,'Cálculos Comparativos'!A:T,16,0),$B$5="Menor Salário",VLOOKUP(A61,'Cálculos Comparativos'!A:T,13,0),$B$5="1º Quartil",VLOOKUP(A61,'Cálculos Comparativos'!A:T,14,0),$B$5="Média",VLOOKUP(A61,'Cálculos Comparativos'!A:T,15,0),$B$5="3º Quartil",VLOOKUP(A61,'Cálculos Comparativos'!A:T,17,0),$B$5="Maior Salário",VLOOKUP(A61,'Cálculos Comparativos'!A:T,18,0)),"") | F61: =IFERROR(VLOOKUP($A61,'Cálculos Comparativos'!$A:$T,19,0),"") | G61: =IFERROR(VLOOKUP($A61,'Cálculos Comparativos'!$A:$T,20,0),"")
B63: Posicionamento por Quantidade de Colaboradores por Cargo
B86: Cód Cargo | C86: Cargo Empresa | F86: Muito Defasado | G86: Defasado | H86: Na Média | I86: Competitivo | J86: Muito Competitivo | K86: Agressivo
B87: =A31 -> 4 | C87: =IFERROR(VLOOKUP(B87,'Cálculos Comparativos'!A:B,2,0),"") -> ANALISTA DE INOVAÇÃO | E87: =IF(C87="","",C87&" "&D87) -> ANALISTA DE INOVAÇÃO | F87: =IF(E87="","",IFERROR(COUNTIFS('Comparativo por Funcionário'!A:A,B87,'Comparativo por Funcionário'!U:U,F$86),0)) -> 0 | G87: =IF(E87="","",IFERROR(COUNTIFS('Comparativo por Funcionário'!$A:$A,$B87,'Comparativo por Funcionário'!$U:$U,G$86),0)) -> 0 | H87: =IF(E87="","",IFERROR(COUNTIFS('Comparativo por Funcionário'!$A:$A,$B87,'Comparativo por Funcionário'!$U:$U,H$86),0)) -> 1 | I87: =IF(E87="","",IFERROR(COUNTIFS('Comparativo por Funcionário'!$A:$A,$B87,'Comparativo por Funcionário'!$U:$U,I$86),0)) -> 0 | J87: =IF(E87="","",IFERROR(COUNTIFS('Comparativo por Funcionário'!$A:$A,$B87,'Comparativo por Funcionário'!$U:$U,J$86),0)) -> 0 | K87: =IF(E87="","",IFERROR(COUNTIFS('Comparativo por Funcionário'!$A:$A,$B87,'Comparativo por Funcionário'!$U:$U,K$86),0)) -> 0
B88: =A32 -> 12 | C88: =IFERROR(VLOOKUP(B88,'Cálculos Comparativos'!A:B,2,0),"") -> ASSISTENTE ADM DE LEGALIZAÇÃO III | E88: =IF(C88="","",C88&" "&D88) -> ASSISTENTE ADM DE LEGALIZAÇÃO III | F88: =IF(E88="","",IFERROR(COUNTIFS('Comparativo por Funcionário'!A:A,B88,'Comparativo por Funcionário'!U:U,F$86),0)) -> 0 | G88: =IF(E88="","",IFERROR(COUNTIFS('Comparativo por Funcionário'!$A:$A,$B88,'Comparativo por Funcionário'!$U:$U,G$86),0)) -> 0 | H88: =IF(E88="","",IFERROR(COUNTIFS('Comparativo por Funcionário'!$A:$A,$B88,'Comparativo por Funcionário'!$U:$U,H$86),0)) -> 0 | I88: =IF(E88="","",IFERROR(COUNTIFS('Comparativo por Funcionário'!$A:$A,$B88,'Comparativo por Funcionário'!$U:$U,I$86),0)) -> 0 | J88: =IF(E88="","",IFERROR(COUNTIFS('Comparativo por Funcionário'!$A:$A,$B88,'Comparativo por Funcionário'!$U:$U,J$86),0)) -> 1 | K88: =IF(E88="","",IFERROR(COUNTIFS('Comparativo por Funcionário'!$A:$A,$B88,'Comparativo por Funcionário'!$U:$U,K$86),0)) -> 0
B89: =A33 -> 28 | C89: =IFERROR(VLOOKUP(B89,'Cálculos Comparativos'!A:B,2,0),"") -> COORDENADOR DE LEGAIZAÇÃO ll | E89: =IF(C89="","",C89&" "&D89) -> COORDENADOR DE LEGAIZAÇÃO ll | F89: =IF(E89="","",IFERROR(COUNTIFS('Comparativo por Funcionário'!A:A,B89,'Comparativo por Funcionário'!U:U,F$86),0)) -> 0 | G89: =IF(E89="","",IFERROR(COUNTIFS('Comparativo por Funcionário'!$A:$A,$B89,'Comparativo por Funcionário'!$U:$U,G$86),0)) -> 0 | H89: =IF(E89="","",IFERROR(COUNTIFS('Comparativo por Funcionário'!$A:$A,$B89,'Comparativo por Funcionário'!$U:$U,H$86),0)) -> 1 | I89: =IF(E89="","",IFERROR(COUNTIFS('Comparativo por Funcionário'!$A:$A,$B89,'Comparativo por Funcionário'!$U:$U,I$86),0)) -> 0 | J89: =IF(E89="","",IFERROR(COUNTIFS('Comparativo por Funcionário'!$A:$A,$B89,'Comparativo por Funcionário'!$U:$U,J$86),0)) -> 0 | K89: =IF(E89="","",IFERROR(COUNTIFS('Comparativo por Funcionário'!$A:$A,$B89,'Comparativo por Funcionário'!$U:$U,K$86),0)) -> 0
B90: =A34 -> 47 | C90: =IFERROR(VLOOKUP(B90,'Cálculos Comparativos'!A:B,2,0),"") -> GERENTE DE INCORPORAÇÃO | E90: =IF(C90="","",C90&" "&D90) -> GERENTE DE INCORPORAÇÃO | F90: =IF(E90="","",IFERROR(COUNTIFS('Comparativo por Funcionário'!A:A,B90,'Comparativo por Funcionário'!U:U,F$86),0)) -> 1 | G90: =IF(E90="","",IFERROR(COUNTIFS('Comparativo por Funcionário'!$A:$A,$B90,'Comparativo por Funcionário'!$U:$U,G$86),0)) -> 0 | H90: =IF(E90="","",IFERROR(COUNTIFS('Comparativo por Funcionário'!$A:$A,$B90,'Comparativo por Funcionário'!$U:$U,H$86),0)) -> 0 | I90: =IF(E90="","",IFERROR(COUNTIFS('Comparativo por Funcionário'!$A:$A,$B90,'Comparativo por Funcionário'!$U:$U,I$86),0)) -> 0 | J90: =IF(E90="","",IFERROR(COUNTIFS('Comparativo por Funcionário'!$A:$A,$B90,'Comparativo por Funcionário'!$U:$U,J$86),0)) -> 0 | K90: =IF(E90="","",IFERROR(COUNTIFS('Comparativo por Funcionário'!$A:$A,$B90,'Comparativo por Funcionário'!$U:$U,K$86),0)) -> 0
B91: =A35 | C91: =IFERROR(VLOOKUP(B91,'Cálculos Comparativos'!A:B,2,0),"") | E91: =IF(C91="","",C91&" "&D91) | F91: =IF(E91="","",IFERROR(COUNTIFS('Comparativo por Funcionário'!A:A,B91,'Comparativo por Funcionário'!U:U,F$86),0)) | G91: =IF(E91="","",IFERROR(COUNTIFS('Comparativo por Funcionário'!$A:$A,$B91,'Comparativo por Funcionário'!$U:$U,G$86),0)) | H91: =IF(E91="","",IFERROR(COUNTIFS('Comparativo por Funcionário'!$A:$A,$B91,'Comparativo por Funcionário'!$U:$U,H$86),0)) | I91: =IF(E91="","",IFERROR(COUNTIFS('Comparativo por Funcionário'!$A:$A,$B91,'Comparativo por Funcionário'!$U:$U,I$86),0)) | J91: =IF(E91="","",IFERROR(COUNTIFS('Comparativo por Funcionário'!$A:$A,$B91,'Comparativo por Funcionário'!$U:$U,J$86),0)) | K91: =IF(E91="","",IFERROR(COUNTIFS('Comparativo por Funcionário'!$A:$A,$B91,'Comparativo por Funcionário'!$U:$U,K$86),0))
B92: =A36 | C92: =IFERROR(VLOOKUP(B92,'Cálculos Comparativos'!A:B,2,0),"") | E92: =IF(C92="","",C92&" "&D92) | F92: =IF(E92="","",IFERROR(COUNTIFS('Comparativo por Funcionário'!A:A,B92,'Comparativo por Funcionário'!U:U,F$86),0)) | G92: =IF(E92="","",IFERROR(COUNTIFS('Comparativo por Funcionário'!$A:$A,$B92,'Comparativo por Funcionário'!$U:$U,G$86),0)) | H92: =IF(E92="","",IFERROR(COUNTIFS('Comparativo por Funcionário'!$A:$A,$B92,'Comparativo por Funcionário'!$U:$U,H$86),0)) | I92: =IF(E92="","",IFERROR(COUNTIFS('Comparativo por Funcionário'!$A:$A,$B92,'Comparativo por Funcionário'!$U:$U,I$86),0)) | J92: =IF(E92="","",IFERROR(COUNTIFS('Comparativo por Funcionário'!$A:$A,$B92,'Comparativo por Funcionário'!$U:$U,J$86),0)) | K92: =IF(E92="","",IFERROR(COUNTIFS('Comparativo por Funcionário'!$A:$A,$B92,'Comparativo por Funcionário'!$U:$U,K$86),0))
B93: =A37 | C93: =IFERROR(VLOOKUP(B93,'Cálculos Comparativos'!A:B,2,0),"") | E93: =IF(C93="","",C93&" "&D93) | F93: =IF(E93="","",IFERROR(COUNTIFS('Comparativo por Funcionário'!A:A,B93,'Comparativo por Funcionário'!U:U,F$86),0)) | G93: =IF(E93="","",IFERROR(COUNTIFS('Comparativo por Funcionário'!$A:$A,$B93,'Comparativo por Funcionário'!$U:$U,G$86),0)) | H93: =IF(E93="","",IFERROR(COUNTIFS('Comparativo por Funcionário'!$A:$A,$B93,'Comparativo por Funcionário'!$U:$U,H$86),0)) | I93: =IF(E93="","",IFERROR(COUNTIFS('Comparativo por Funcionário'!$A:$A,$B93,'Comparativo por Funcionário'!$U:$U,I$86),0)) | J93: =IF(E93="","",IFERROR(COUNTIFS('Comparativo por Funcionário'!$A:$A,$B93,'Comparativo por Funcionário'!$U:$U,J$86),0)) | K93: =IF(E93="","",IFERROR(COUNTIFS('Comparativo por Funcionário'!$A:$A,$B93,'Comparativo por Funcionário'!$U:$U,K$86),0))
B94: =A38 | C94: =IFERROR(VLOOKUP(B94,'Cálculos Comparativos'!A:B,2,0),"") | E94: =IF(C94="","",C94&" "&D94) | F94: =IF(E94="","",IFERROR(COUNTIFS('Comparativo por Funcionário'!A:A,B94,'Comparativo por Funcionário'!U:U,F$86),0)) | G94: =IF(E94="","",IFERROR(COUNTIFS('Comparativo por Funcionário'!$A:$A,$B94,'Comparativo por Funcionário'!$U:$U,G$86),0)) | H94: =IF(E94="","",IFERROR(COUNTIFS('Comparativo por Funcionário'!$A:$A,$B94,'Comparativo por Funcionário'!$U:$U,H$86),0)) | I94: =IF(E94="","",IFERROR(COUNTIFS('Comparativo por Funcionário'!$A:$A,$B94,'Comparativo por Funcionário'!$U:$U,I$86),0)) | J94: =IF(E94="","",IFERROR(COUNTIFS('Comparativo por Funcionário'!$A:$A,$B94,'Comparativo por Funcionário'!$U:$U,J$86),0)) | K94: =IF(E94="","",IFERROR(COUNTIFS('Comparativo por Funcionário'!$A:$A,$B94,'Comparativo por Funcionário'!$U:$U,K$86),0))
B95: =A39 | C95: =IFERROR(VLOOKUP(B95,'Cálculos Comparativos'!A:B,2,0),"") | E95: =IF(C95="","",C95&" "&D95) | F95: =IF(E95="","",IFERROR(COUNTIFS('Comparativo por Funcionário'!A:A,B95,'Comparativo por Funcionário'!U:U,F$86),0)) | G95: =IF(E95="","",IFERROR(COUNTIFS('Comparativo por Funcionário'!$A:$A,$B95,'Comparativo por Funcionário'!$U:$U,G$86),0)) | H95: =IF(E95="","",IFERROR(COUNTIFS('Comparativo por Funcionário'!$A:$A,$B95,'Comparativo por Funcionário'!$U:$U,H$86),0)) | I95: =IF(E95="","",IFERROR(COUNTIFS('Comparativo por Funcionário'!$A:$A,$B95,'Comparativo por Funcionário'!$U:$U,I$86),0)) | J95: =IF(E95="","",IFERROR(COUNTIFS('Comparativo por Funcionário'!$A:$A,$B95,'Comparativo por Funcionário'!$U:$U,J$86),0)) | K95: =IF(E95="","",IFERROR(COUNTIFS('Comparativo por Funcionário'!$A:$A,$B95,'Comparativo por Funcionário'!$U:$U,K$86),0))
B96: =A40 | C96: =IFERROR(VLOOKUP(B96,'Cálculos Comparativos'!A:B,2,0),"") | E96: =IF(C96="","",C96&" "&D96) | F96: =IF(E96="","",IFERROR(COUNTIFS('Comparativo por Funcionário'!A:A,B96,'Comparativo por Funcionário'!U:U,F$86),0)) | G96: =IF(E96="","",IFERROR(COUNTIFS('Comparativo por Funcionário'!$A:$A,$B96,'Comparativo por Funcionário'!$U:$U,G$86),0)) | H96: =IF(E96="","",IFERROR(COUNTIFS('Comparativo por Funcionário'!$A:$A,$B96,'Comparativo por Funcionário'!$U:$U,H$86),0)) | I96: =IF(E96="","",IFERROR(COUNTIFS('Comparativo por Funcionário'!$A:$A,$B96,'Comparativo por Funcionário'!$U:$U,I$86),0)) | J96: =IF(E96="","",IFERROR(COUNTIFS('Comparativo por Funcionário'!$A:$A,$B96,'Comparativo por Funcionário'!$U:$U,J$86),0)) | K96: =IF(E96="","",IFERROR(COUNTIFS('Comparativo por Funcionário'!$A:$A,$B96,'Comparativo por Funcionário'!$U:$U,K$86),0))
B97: =A41 | C97: =IFERROR(VLOOKUP(B97,'Cálculos Comparativos'!A:B,2,0),"") | E97: =IF(C97="","",C97&" "&D97) | F97: =IF(E97="","",IFERROR(COUNTIFS('Comparativo por Funcionário'!A:A,B97,'Comparativo por Funcionário'!U:U,F$86),0)) | G97: =IF(E97="","",IFERROR(COUNTIFS('Comparativo por Funcionário'!$A:$A,$B97,'Comparativo por Funcionário'!$U:$U,G$86),0)) | H97: =IF(E97="","",IFERROR(COUNTIFS('Comparativo por Funcionário'!$A:$A,$B97,'Comparativo por Funcionário'!$U:$U,H$86),0)) | I97: =IF(E97="","",IFERROR(COUNTIFS('Comparativo por Funcionário'!$A:$A,$B97,'Comparativo por Funcionário'!$U:$U,I$86),0)) | J97: =IF(E97="","",IFERROR(COUNTIFS('Comparativo por Funcionário'!$A:$A,$B97,'Comparativo por Funcionário'!$U:$U,J$86),0)) | K97: =IF(E97="","",IFERROR(COUNTIFS('Comparativo por Funcionário'!$A:$A,$B97,'Comparativo por Funcionário'!$U:$U,K$86),0))
B98: =A42 | C98: =IFERROR(VLOOKUP(B98,'Cálculos Comparativos'!A:B,2,0),"") | E98: =IF(C98="","",C98&" "&D98) | F98: =IF(E98="","",IFERROR(COUNTIFS('Comparativo por Funcionário'!A:A,B98,'Comparativo por Funcionário'!U:U,F$86),0)) | G98: =IF(E98="","",IFERROR(COUNTIFS('Comparativo por Funcionário'!$A:$A,$B98,'Comparativo por Funcionário'!$U:$U,G$86),0)) | H98: =IF(E98="","",IFERROR(COUNTIFS('Comparativo por Funcionário'!$A:$A,$B98,'Comparativo por Funcionário'!$U:$U,H$86),0)) | I98: =IF(E98="","",IFERROR(COUNTIFS('Comparativo por Funcionário'!$A:$A,$B98,'Comparativo por Funcionário'!$U:$U,I$86),0)) | J98: =IF(E98="","",IFERROR(COUNTIFS('Comparativo por Funcionário'!$A:$A,$B98,'Comparativo por Funcionário'!$U:$U,J$86),0)) | K98: =IF(E98="","",IFERROR(COUNTIFS('Comparativo por Funcionário'!$A:$A,$B98,'Comparativo por Funcionário'!$U:$U,K$86),0))
... B116: =A60 | C116: =IFERROR(VLOOKUP(B116,'Cálculos Comparativos'!A:B,2,0),"") | E116: =IF(C116="","",C116&" "&D116) | F116: =IF(E116="","",IFERROR(COUNTIFS('Comparativo por Funcionário'!A:A,B116,'Comparativo por Funcionário'!U:U,F$86),0)) | G116: =IF(E116="","",IFERROR(COUNTIFS('Comparativo por Funcionário'!$A:$A,$B116,'Comparativo por Funcionário'!$U:$U,G$86),0)) | H116: =IF(E116="","",IFERROR(COUNTIFS('Comparativo por Funcionário'!$A:$A,$B116,'Comparativo por Funcionário'!$U:$U,H$86),0)) | I116: =IF(E116="","",IFERROR(COUNTIFS('Comparativo por Funcionário'!$A:$A,$B116,'Comparativo por Funcionário'!$U:$U,I$86),0)) | J116: =IF(E116="","",IFERROR(COUNTIFS('Comparativo por Funcionário'!$A:$A,$B116,'Comparativo por Funcionário'!$U:$U,J$86),0)) | K116: =IF(E116="","",IFERROR(COUNTIFS('Comparativo por Funcionário'!$A:$A,$B116,'Comparativo por Funcionário'!$U:$U,K$86),0))
B120: Abaixo da Mediana | C120: Pesquisa
B121: Setor | C121: Pesquisa
A122: 1 | B122: Administrativo, Recepção, Suprimentos, Tecnologia da Informação | C122: =(COUNTIFS('Cálculos Comparativos'!T:T,$B$22,'Cálculos Comparativos'!D:D,A122)+COUNTIFS('Cálculos Comparativos'!T:T,$B$23,'Cálculos Comparativos'!D:D,A122)+COUNTIFS('Cálculos Comparativos'!T:T,$B$24,'Cálculos Comparativos'!D:D,A122))/(COUNTIFS('Cálculos Comparativos'!T:T,$B$22,'Cálculos Comparativos'!D:D,A122)+COUNTIFS('Cálculos Comparativos'!T:T,$B$23,'Cálculos Comparativos'!D:D,A122)+COUNTIFS('Cálculos Comparativos'!T:T,$B$24,'Cálculos Comparativos'!D:D,A122)+COUNTIFS('Cálculos Comparativos'!T:T,#REF!,'Cálculos Comparativos'!D:D,A122)+COUNTIFS('Cálculos Comparativos'!T:T,$B$25,'Cálculos Comparativos'!D:D,A122)+COUNTIFS('Cálculos Comparativos'!T:T,$B$26,'Cálculos Comparativos'!D:D,A122)) -> 0.66666667 | F122: =IFERROR(__xludf.DUMMYFUNCTION("QUERY(B122:C131, ""select B, C order by C desc"", 0)"),"DHO") -> DHO | G122: =IFERROR(__xludf.DUMMYFUNCTION("""COMPUTED_VALUE"""),1.0) -> 1
A123: 2 | B123: Comercial | C123: =(COUNTIFS('Cálculos Comparativos'!T:T,$B$22,'Cálculos Comparativos'!D:D,A123)+COUNTIFS('Cálculos Comparativos'!T:T,$B$23,'Cálculos Comparativos'!D:D,A123)+COUNTIFS('Cálculos Comparativos'!T:T,$B$24,'Cálculos Comparativos'!D:D,A123))/(COUNTIFS('Cálculos Comparativos'!T:T,$B$22,'Cálculos Comparativos'!D:D,A123)+COUNTIFS('Cálculos Comparativos'!T:T,$B$23,'Cálculos Comparativos'!D:D,A123)+COUNTIFS('Cálculos Comparativos'!T:T,$B$24,'Cálculos Comparativos'!D:D,A123)+COUNTIFS('Cálculos Comparativos'!T:T,#REF!,'Cálculos Comparativos'!D:D,A123)+COUNTIFS('Cálculos Comparativos'!T:T,$B$25,'Cálculos Comparativos'!D:D,A123)+COUNTIFS('Cálculos Comparativos'!T:T,$B$26,'Cálculos Comparativos'!D:D,A123)) -> 0.8 | F123: =IFERROR(__xludf.DUMMYFUNCTION("""COMPUTED_VALUE"""),"Comercial") -> Comercial | G123: =IFERROR(__xludf.DUMMYFUNCTION("""COMPUTED_VALUE"""),0.8) -> 0.8
A124: 3 | B124: Controladoria | C124: =(COUNTIFS('Cálculos Comparativos'!T:T,$B$22,'Cálculos Comparativos'!D:D,A124)+COUNTIFS('Cálculos Comparativos'!T:T,$B$23,'Cálculos Comparativos'!D:D,A124)+COUNTIFS('Cálculos Comparativos'!T:T,$B$24,'Cálculos Comparativos'!D:D,A124))/(COUNTIFS('Cálculos Comparativos'!T:T,$B$22,'Cálculos Comparativos'!D:D,A124)+COUNTIFS('Cálculos Comparativos'!T:T,$B$23,'Cálculos Comparativos'!D:D,A124)+COUNTIFS('Cálculos Comparativos'!T:T,$B$24,'Cálculos Comparativos'!D:D,A124)+COUNTIFS('Cálculos Comparativos'!T:T,#REF!,'Cálculos Comparativos'!D:D,A124)+COUNTIFS('Cálculos Comparativos'!T:T,$B$25,'Cálculos Comparativos'!D:D,A124)+COUNTIFS('Cálculos Comparativos'!T:T,$B$26,'Cálculos Comparativos'!D:D,A124)) -> 0.66666667 | F124: =IFERROR(__xludf.DUMMYFUNCTION("""COMPUTED_VALUE"""),"Incorporação, Inovação, Legalização") -> Incorporação, Inovação, Legalização | G124: =IFERROR(__xludf.DUMMYFUNCTION("""COMPUTED_VALUE"""),0.75) -> 0.75
A125: 4 | B125: DHO | C125: =(COUNTIFS('Cálculos Comparativos'!T:T,$B$22,'Cálculos Comparativos'!D:D,A125)+COUNTIFS('Cálculos Comparativos'!T:T,$B$23,'Cálculos Comparativos'!D:D,A125)+COUNTIFS('Cálculos Comparativos'!T:T,$B$24,'Cálculos Comparativos'!D:D,A125))/(COUNTIFS('Cálculos Comparativos'!T:T,$B$22,'Cálculos Comparativos'!D:D,A125)+COUNTIFS('Cálculos Comparativos'!T:T,$B$23,'Cálculos Comparativos'!D:D,A125)+COUNTIFS('Cálculos Comparativos'!T:T,$B$24,'Cálculos Comparativos'!D:D,A125)+COUNTIFS('Cálculos Comparativos'!T:T,#REF!,'Cálculos Comparativos'!D:D,A125)+COUNTIFS('Cálculos Comparativos'!T:T,$B$25,'Cálculos Comparativos'!D:D,A125)+COUNTIFS('Cálculos Comparativos'!T:T,$B$26,'Cálculos Comparativos'!D:D,A125)) -> 1 | F125: =IFERROR(__xludf.DUMMYFUNCTION("""COMPUTED_VALUE"""),"Administrativo, Recepção, Suprimentos, Tecnologia da Informação") -> Administrativo, Recepção, Suprimentos, Tecnologia da Informação | G125: =IFERROR(__xludf.DUMMYFUNCTION("""COMPUTED_VALUE"""),0.6666666666666666) -> 0.66666667
A126: 5 | B126: Edificação | C126: =(COUNTIFS('Cálculos Comparativos'!T:T,$B$22,'Cálculos Comparativos'!D:D,A126)+COUNTIFS('Cálculos Comparativos'!T:T,$B$23,'Cálculos Comparativos'!D:D,A126)+COUNTIFS('Cálculos Comparativos'!T:T,$B$24,'Cálculos Comparativos'!D:D,A126))/(COUNTIFS('Cálculos Comparativos'!T:T,$B$22,'Cálculos Comparativos'!D:D,A126)+COUNTIFS('Cálculos Comparativos'!T:T,$B$23,'Cálculos Comparativos'!D:D,A126)+COUNTIFS('Cálculos Comparativos'!T:T,$B$24,'Cálculos Comparativos'!D:D,A126)+COUNTIFS('Cálculos Comparativos'!T:T,#REF!,'Cálculos Comparativos'!D:D,A126)+COUNTIFS('Cálculos Comparativos'!T:T,$B$25,'Cálculos Comparativos'!D:D,A126)+COUNTIFS('Cálculos Comparativos'!T:T,$B$26,'Cálculos Comparativos'!D:D,A126)) -> 0.55555556 | F126: =IFERROR(__xludf.DUMMYFUNCTION("""COMPUTED_VALUE"""),"Controladoria") -> Controladoria | G126: =IFERROR(__xludf.DUMMYFUNCTION("""COMPUTED_VALUE"""),0.6666666666666666) -> 0.66666667
A127: 6 | B127: Financeiro | C127: =(COUNTIFS('Cálculos Comparativos'!T:T,$B$22,'Cálculos Comparativos'!D:D,A127)+COUNTIFS('Cálculos Comparativos'!T:T,$B$23,'Cálculos Comparativos'!D:D,A127)+COUNTIFS('Cálculos Comparativos'!T:T,$B$24,'Cálculos Comparativos'!D:D,A127))/(COUNTIFS('Cálculos Comparativos'!T:T,$B$22,'Cálculos Comparativos'!D:D,A127)+COUNTIFS('Cálculos Comparativos'!T:T,$B$23,'Cálculos Comparativos'!D:D,A127)+COUNTIFS('Cálculos Comparativos'!T:T,$B$24,'Cálculos Comparativos'!D:D,A127)+COUNTIFS('Cálculos Comparativos'!T:T,#REF!,'Cálculos Comparativos'!D:D,A127)+COUNTIFS('Cálculos Comparativos'!T:T,$B$25,'Cálculos Comparativos'!D:D,A127)+COUNTIFS('Cálculos Comparativos'!T:T,$B$26,'Cálculos Comparativos'!D:D,A127)) -> 0.66666667 | F127: =IFERROR(__xludf.DUMMYFUNCTION("""COMPUTED_VALUE"""),"Financeiro") -> Financeiro | G127: =IFERROR(__xludf.DUMMYFUNCTION("""COMPUTED_VALUE"""),0.6666666666666666) -> 0.66666667
A128: 7 | B128: Incorporação, Inovação, Legalização | C128: =(COUNTIFS('Cálculos Comparativos'!T:T,$B$22,'Cálculos Comparativos'!D:D,A128)+COUNTIFS('Cálculos Comparativos'!T:T,$B$23,'Cálculos Comparativos'!D:D,A128)+COUNTIFS('Cálculos Comparativos'!T:T,$B$24,'Cálculos Comparativos'!D:D,A128))/(COUNTIFS('Cálculos Comparativos'!T:T,$B$22,'Cálculos Comparativos'!D:D,A128)+COUNTIFS('Cálculos Comparativos'!T:T,$B$23,'Cálculos Comparativos'!D:D,A128)+COUNTIFS('Cálculos Comparativos'!T:T,$B$24,'Cálculos Comparativos'!D:D,A128)+COUNTIFS('Cálculos Comparativos'!T:T,#REF!,'Cálculos Comparativos'!D:D,A128)+COUNTIFS('Cálculos Comparativos'!T:T,$B$25,'Cálculos Comparativos'!D:D,A128)+COUNTIFS('Cálculos Comparativos'!T:T,$B$26,'Cálculos Comparativos'!D:D,A128)) -> 0.75 | F128: =IFERROR(__xludf.DUMMYFUNCTION("""COMPUTED_VALUE"""),"Urbanismo") -> Urbanismo | G128: =IFERROR(__xludf.DUMMYFUNCTION("""COMPUTED_VALUE"""),0.6666666666666666) -> 0.66666667
A129: 8 | B129: Marketing | C129: =(COUNTIFS('Cálculos Comparativos'!T:T,$B$22,'Cálculos Comparativos'!D:D,A129)+COUNTIFS('Cálculos Comparativos'!T:T,$B$23,'Cálculos Comparativos'!D:D,A129)+COUNTIFS('Cálculos Comparativos'!T:T,$B$24,'Cálculos Comparativos'!D:D,A129))/(COUNTIFS('Cálculos Comparativos'!T:T,$B$22,'Cálculos Comparativos'!D:D,A129)+COUNTIFS('Cálculos Comparativos'!T:T,$B$23,'Cálculos Comparativos'!D:D,A129)+COUNTIFS('Cálculos Comparativos'!T:T,$B$24,'Cálculos Comparativos'!D:D,A129)+COUNTIFS('Cálculos Comparativos'!T:T,#REF!,'Cálculos Comparativos'!D:D,A129)+COUNTIFS('Cálculos Comparativos'!T:T,$B$25,'Cálculos Comparativos'!D:D,A129)+COUNTIFS('Cálculos Comparativos'!T:T,$B$26,'Cálculos Comparativos'!D:D,A129)) -> 0.5 | F129: =IFERROR(__xludf.DUMMYFUNCTION("""COMPUTED_VALUE"""),"Edificação") -> Edificação | G129: =IFERROR(__xludf.DUMMYFUNCTION("""COMPUTED_VALUE"""),0.5555555555555556) -> 0.55555556
A130: 9 | B130: Novos Negócios, Pós Vendas | C130: =(COUNTIFS('Cálculos Comparativos'!T:T,$B$22,'Cálculos Comparativos'!D:D,A130)+COUNTIFS('Cálculos Comparativos'!T:T,$B$23,'Cálculos Comparativos'!D:D,A130)+COUNTIFS('Cálculos Comparativos'!T:T,$B$24,'Cálculos Comparativos'!D:D,A130))/(COUNTIFS('Cálculos Comparativos'!T:T,$B$22,'Cálculos Comparativos'!D:D,A130)+COUNTIFS('Cálculos Comparativos'!T:T,$B$23,'Cálculos Comparativos'!D:D,A130)+COUNTIFS('Cálculos Comparativos'!T:T,$B$24,'Cálculos Comparativos'!D:D,A130)+COUNTIFS('Cálculos Comparativos'!T:T,#REF!,'Cálculos Comparativos'!D:D,A130)+COUNTIFS('Cálculos Comparativos'!T:T,$B$25,'Cálculos Comparativos'!D:D,A130)+COUNTIFS('Cálculos Comparativos'!T:T,$B$26,'Cálculos Comparativos'!D:D,A130)) -> 0.5 | F130: =IFERROR(__xludf.DUMMYFUNCTION("""COMPUTED_VALUE"""),"Marketing") -> Marketing | G130: =IFERROR(__xludf.DUMMYFUNCTION("""COMPUTED_VALUE"""),0.5) -> 0.5
A131: 10 | B131: Urbanismo | C131: =(COUNTIFS('Cálculos Comparativos'!T:T,$B$22,'Cálculos Comparativos'!D:D,A131)+COUNTIFS('Cálculos Comparativos'!T:T,$B$23,'Cálculos Comparativos'!D:D,A131)+COUNTIFS('Cálculos Comparativos'!T:T,$B$24,'Cálculos Comparativos'!D:D,A131))/(COUNTIFS('Cálculos Comparativos'!T:T,$B$22,'Cálculos Comparativos'!D:D,A131)+COUNTIFS('Cálculos Comparativos'!T:T,$B$23,'Cálculos Comparativos'!D:D,A131)+COUNTIFS('Cálculos Comparativos'!T:T,$B$24,'Cálculos Comparativos'!D:D,A131)+COUNTIFS('Cálculos Comparativos'!T:T,#REF!,'Cálculos Comparativos'!D:D,A131)+COUNTIFS('Cálculos Comparativos'!T:T,$B$25,'Cálculos Comparativos'!D:D,A131)+COUNTIFS('Cálculos Comparativos'!T:T,$B$26,'Cálculos Comparativos'!D:D,A131)) -> 0.66666667 | F131: =IFERROR(__xludf.DUMMYFUNCTION("""COMPUTED_VALUE"""),"Novos Negócios, Pós Vendas") -> Novos Negócios, Pós Vendas | G131: =IFERROR(__xludf.DUMMYFUNCTION("""COMPUTED_VALUE"""),0.5) -> 0.5
B148: Acima da Mediana | C148: Pesquisa
B149: Setor | C149: Pesquisa | F149: Áreas | G149: Acima | H149: Abaixo
A150: 1 | B150: Administrativo, Recepção, Suprimentos, Tecnologia da Informação | C150: =(COUNTIFS('Cálculos Comparativos'!T:T,$B$26,'Cálculos Comparativos'!D:D,A150)+COUNTIFS('Cálculos Comparativos'!T:T,$B$25,'Cálculos Comparativos'!D:D,A150)+COUNTIFS('Cálculos Comparativos'!T:T,#REF!,'Cálculos Comparativos'!D:D,A150))/(COUNTIFS('Cálculos Comparativos'!T:T,$B$22,'Cálculos Comparativos'!D:D,A150)+COUNTIFS('Cálculos Comparativos'!T:T,$B$23,'Cálculos Comparativos'!D:D,A150)+COUNTIFS('Cálculos Comparativos'!T:T,$B$24,'Cálculos Comparativos'!D:D,A150)+COUNTIFS('Cálculos Comparativos'!T:T,#REF!,'Cálculos Comparativos'!D:D,A150)+COUNTIFS('Cálculos Comparativos'!T:T,$B$25,'Cálculos Comparativos'!D:D,A150)+COUNTIFS('Cálculos Comparativos'!T:T,$B$26,'Cálculos Comparativos'!D:D,A150)) -> 0.33333333 | F150: =IFERROR(__xludf.DUMMYFUNCTION("QUERY(B150:C159, ""select B, C order by C desc"", 0)"),"Marketing") -> Marketing | G150: =IFERROR(__xludf.DUMMYFUNCTION("""COMPUTED_VALUE"""),0.5) -> 0.5 | H150: =VLOOKUP(F150,F$122:G$131,2,0) -> 0.5
A151: 2 | B151: Comercial | C151: =(COUNTIFS('Cálculos Comparativos'!T:T,$B$26,'Cálculos Comparativos'!D:D,A151)+COUNTIFS('Cálculos Comparativos'!T:T,$B$25,'Cálculos Comparativos'!D:D,A151)+COUNTIFS('Cálculos Comparativos'!T:T,#REF!,'Cálculos Comparativos'!D:D,A151))/(COUNTIFS('Cálculos Comparativos'!T:T,$B$22,'Cálculos Comparativos'!D:D,A151)+COUNTIFS('Cálculos Comparativos'!T:T,$B$23,'Cálculos Comparativos'!D:D,A151)+COUNTIFS('Cálculos Comparativos'!T:T,$B$24,'Cálculos Comparativos'!D:D,A151)+COUNTIFS('Cálculos Comparativos'!T:T,#REF!,'Cálculos Comparativos'!D:D,A151)+COUNTIFS('Cálculos Comparativos'!T:T,$B$25,'Cálculos Comparativos'!D:D,A151)+COUNTIFS('Cálculos Comparativos'!T:T,$B$26,'Cálculos Comparativos'!D:D,A151)) -> 0.2 | F151: =IFERROR(__xludf.DUMMYFUNCTION("""COMPUTED_VALUE"""),"Novos Negócios, Pós Vendas") -> Novos Negócios, Pós Vendas | G151: =IFERROR(__xludf.DUMMYFUNCTION("""COMPUTED_VALUE"""),0.5) -> 0.5 | H151: =VLOOKUP(F151,F$122:G$131,2,0) -> 0.5
A152: 3 | B152: Controladoria | C152: =(COUNTIFS('Cálculos Comparativos'!T:T,$B$26,'Cálculos Comparativos'!D:D,A152)+COUNTIFS('Cálculos Comparativos'!T:T,$B$25,'Cálculos Comparativos'!D:D,A152)+COUNTIFS('Cálculos Comparativos'!T:T,#REF!,'Cálculos Comparativos'!D:D,A152))/(COUNTIFS('Cálculos Comparativos'!T:T,$B$22,'Cálculos Comparativos'!D:D,A152)+COUNTIFS('Cálculos Comparativos'!T:T,$B$23,'Cálculos Comparativos'!D:D,A152)+COUNTIFS('Cálculos Comparativos'!T:T,$B$24,'Cálculos Comparativos'!D:D,A152)+COUNTIFS('Cálculos Comparativos'!T:T,#REF!,'Cálculos Comparativos'!D:D,A152)+COUNTIFS('Cálculos Comparativos'!T:T,$B$25,'Cálculos Comparativos'!D:D,A152)+COUNTIFS('Cálculos Comparativos'!T:T,$B$26,'Cálculos Comparativos'!D:D,A152)) -> 0.33333333 | F152: =IFERROR(__xludf.DUMMYFUNCTION("""COMPUTED_VALUE"""),"Edificação") -> Edificação | G152: =IFERROR(__xludf.DUMMYFUNCTION("""COMPUTED_VALUE"""),0.4444444444444444) -> 0.44444444 | H152: =VLOOKUP(F152,F$122:G$131,2,0) -> 0.55555556
A153: 4 | B153: DHO | C153: =(COUNTIFS('Cálculos Comparativos'!T:T,$B$26,'Cálculos Comparativos'!D:D,A153)+COUNTIFS('Cálculos Comparativos'!T:T,$B$25,'Cálculos Comparativos'!D:D,A153)+COUNTIFS('Cálculos Comparativos'!T:T,#REF!,'Cálculos Comparativos'!D:D,A153))/(COUNTIFS('Cálculos Comparativos'!T:T,$B$22,'Cálculos Comparativos'!D:D,A153)+COUNTIFS('Cálculos Comparativos'!T:T,$B$23,'Cálculos Comparativos'!D:D,A153)+COUNTIFS('Cálculos Comparativos'!T:T,$B$24,'Cálculos Comparativos'!D:D,A153)+COUNTIFS('Cálculos Comparativos'!T:T,#REF!,'Cálculos Comparativos'!D:D,A153)+COUNTIFS('Cálculos Comparativos'!T:T,$B$25,'Cálculos Comparativos'!D:D,A153)+COUNTIFS('Cálculos Comparativos'!T:T,$B$26,'Cálculos Comparativos'!D:D,A153)) -> 0 | F153: =IFERROR(__xludf.DUMMYFUNCTION("""COMPUTED_VALUE"""),"Administrativo, Recepção, Suprimentos, Tecnologia da Informação") -> Administrativo, Recepção, Suprimentos, Tecnologia da Informação | G153: =IFERROR(__xludf.DUMMYFUNCTION("""COMPUTED_VALUE"""),0.3333333333333333) -> 0.33333333 | H153: =VLOOKUP(F153,F$122:G$131,2,0) -> 0.66666667
A154: 5 | B154: Edificação | C154: =(COUNTIFS('Cálculos Comparativos'!T:T,$B$26,'Cálculos Comparativos'!D:D,A154)+COUNTIFS('Cálculos Comparativos'!T:T,$B$25,'Cálculos Comparativos'!D:D,A154)+COUNTIFS('Cálculos Comparativos'!T:T,#REF!,'Cálculos Comparativos'!D:D,A154))/(COUNTIFS('Cálculos Comparativos'!T:T,$B$22,'Cálculos Comparativos'!D:D,A154)+COUNTIFS('Cálculos Comparativos'!T:T,$B$23,'Cálculos Comparativos'!D:D,A154)+COUNTIFS('Cálculos Comparativos'!T:T,$B$24,'Cálculos Comparativos'!D:D,A154)+COUNTIFS('Cálculos Comparativos'!T:T,#REF!,'Cálculos Comparativos'!D:D,A154)+COUNTIFS('Cálculos Comparativos'!T:T,$B$25,'Cálculos Comparativos'!D:D,A154)+COUNTIFS('Cálculos Comparativos'!T:T,$B$26,'Cálculos Comparativos'!D:D,A154)) -> 0.44444444 | F154: =IFERROR(__xludf.DUMMYFUNCTION("""COMPUTED_VALUE"""),"Controladoria") -> Controladoria | G154: =IFERROR(__xludf.DUMMYFUNCTION("""COMPUTED_VALUE"""),0.3333333333333333) -> 0.33333333 | H154: =VLOOKUP(F154,F$122:G$131,2,0) -> 0.66666667
A155: 6 | B155: Financeiro | C155: =(COUNTIFS('Cálculos Comparativos'!T:T,$B$26,'Cálculos Comparativos'!D:D,A155)+COUNTIFS('Cálculos Comparativos'!T:T,$B$25,'Cálculos Comparativos'!D:D,A155)+COUNTIFS('Cálculos Comparativos'!T:T,#REF!,'Cálculos Comparativos'!D:D,A155))/(COUNTIFS('Cálculos Comparativos'!T:T,$B$22,'Cálculos Comparativos'!D:D,A155)+COUNTIFS('Cálculos Comparativos'!T:T,$B$23,'Cálculos Comparativos'!D:D,A155)+COUNTIFS('Cálculos Comparativos'!T:T,$B$24,'Cálculos Comparativos'!D:D,A155)+COUNTIFS('Cálculos Comparativos'!T:T,#REF!,'Cálculos Comparativos'!D:D,A155)+COUNTIFS('Cálculos Comparativos'!T:T,$B$25,'Cálculos Comparativos'!D:D,A155)+COUNTIFS('Cálculos Comparativos'!T:T,$B$26,'Cálculos Comparativos'!D:D,A155)) -> 0.33333333 | F155: =IFERROR(__xludf.DUMMYFUNCTION("""COMPUTED_VALUE"""),"Financeiro") -> Financeiro | G155: =IFERROR(__xludf.DUMMYFUNCTION("""COMPUTED_VALUE"""),0.3333333333333333) -> 0.33333333 | H155: =VLOOKUP(F155,F$122:G$131,2,0) -> 0.66666667
A156: 7 | B156: Incorporação, Inovação, Legalização | C156: =(COUNTIFS('Cálculos Comparativos'!T:T,$B$26,'Cálculos Comparativos'!D:D,A156)+COUNTIFS('Cálculos Comparativos'!T:T,$B$25,'Cálculos Comparativos'!D:D,A156)+COUNTIFS('Cálculos Comparativos'!T:T,#REF!,'Cálculos Comparativos'!D:D,A156))/(COUNTIFS('Cálculos Comparativos'!T:T,$B$22,'Cálculos Comparativos'!D:D,A156)+COUNTIFS('Cálculos Comparativos'!T:T,$B$23,'Cálculos Comparativos'!D:D,A156)+COUNTIFS('Cálculos Comparativos'!T:T,$B$24,'Cálculos Comparativos'!D:D,A156)+COUNTIFS('Cálculos Comparativos'!T:T,#REF!,'Cálculos Comparativos'!D:D,A156)+COUNTIFS('Cálculos Comparativos'!T:T,$B$25,'Cálculos Comparativos'!D:D,A156)+COUNTIFS('Cálculos Comparativos'!T:T,$B$26,'Cálculos Comparativos'!D:D,A156)) -> 0.25 | F156: =IFERROR(__xludf.DUMMYFUNCTION("""COMPUTED_VALUE"""),"Urbanismo") -> Urbanismo | G156: =IFERROR(__xludf.DUMMYFUNCTION("""COMPUTED_VALUE"""),0.3333333333333333) -> 0.33333333 | H156: =VLOOKUP(F156,F$122:G$131,2,0) -> 0.66666667
A157: 8 | B157: Marketing | C157: =(COUNTIFS('Cálculos Comparativos'!T:T,$B$26,'Cálculos Comparativos'!D:D,A157)+COUNTIFS('Cálculos Comparativos'!T:T,$B$25,'Cálculos Comparativos'!D:D,A157)+COUNTIFS('Cálculos Comparativos'!T:T,#REF!,'Cálculos Comparativos'!D:D,A157))/(COUNTIFS('Cálculos Comparativos'!T:T,$B$22,'Cálculos Comparativos'!D:D,A157)+COUNTIFS('Cálculos Comparativos'!T:T,$B$23,'Cálculos Comparativos'!D:D,A157)+COUNTIFS('Cálculos Comparativos'!T:T,$B$24,'Cálculos Comparativos'!D:D,A157)+COUNTIFS('Cálculos Comparativos'!T:T,#REF!,'Cálculos Comparativos'!D:D,A157)+COUNTIFS('Cálculos Comparativos'!T:T,$B$25,'Cálculos Comparativos'!D:D,A157)+COUNTIFS('Cálculos Comparativos'!T:T,$B$26,'Cálculos Comparativos'!D:D,A157)) -> 0.5 | F157: =IFERROR(__xludf.DUMMYFUNCTION("""COMPUTED_VALUE"""),"Incorporação, Inovação, Legalização") -> Incorporação, Inovação, Legalização | G157: =IFERROR(__xludf.DUMMYFUNCTION("""COMPUTED_VALUE"""),0.25) -> 0.25 | H157: =VLOOKUP(F157,F$122:G$131,2,0) -> 0.75
A158: 9 | B158: Novos Negócios, Pós Vendas | C158: =(COUNTIFS('Cálculos Comparativos'!T:T,$B$26,'Cálculos Comparativos'!D:D,A158)+COUNTIFS('Cálculos Comparativos'!T:T,$B$25,'Cálculos Comparativos'!D:D,A158)+COUNTIFS('Cálculos Comparativos'!T:T,#REF!,'Cálculos Comparativos'!D:D,A158))/(COUNTIFS('Cálculos Comparativos'!T:T,$B$22,'Cálculos Comparativos'!D:D,A158)+COUNTIFS('Cálculos Comparativos'!T:T,$B$23,'Cálculos Comparativos'!D:D,A158)+COUNTIFS('Cálculos Comparativos'!T:T,$B$24,'Cálculos Comparativos'!D:D,A158)+COUNTIFS('Cálculos Comparativos'!T:T,#REF!,'Cálculos Comparativos'!D:D,A158)+COUNTIFS('Cálculos Comparativos'!T:T,$B$25,'Cálculos Comparativos'!D:D,A158)+COUNTIFS('Cálculos Comparativos'!T:T,$B$26,'Cálculos Comparativos'!D:D,A158)) -> 0.5 | F158: =IFERROR(__xludf.DUMMYFUNCTION("""COMPUTED_VALUE"""),"Comercial") -> Comercial | G158: =IFERROR(__xludf.DUMMYFUNCTION("""COMPUTED_VALUE"""),0.2) -> 0.2 | H158: =VLOOKUP(F158,F$122:G$131,2,0) -> 0.8
A159: 10 | B159: Urbanismo | C159: =(COUNTIFS('Cálculos Comparativos'!T:T,$B$26,'Cálculos Comparativos'!D:D,A159)+COUNTIFS('Cálculos Comparativos'!T:T,$B$25,'Cálculos Comparativos'!D:D,A159)+COUNTIFS('Cálculos Comparativos'!T:T,#REF!,'Cálculos Comparativos'!D:D,A159))/(COUNTIFS('Cálculos Comparativos'!T:T,$B$22,'Cálculos Comparativos'!D:D,A159)+COUNTIFS('Cálculos Comparativos'!T:T,$B$23,'Cálculos Comparativos'!D:D,A159)+COUNTIFS('Cálculos Comparativos'!T:T,$B$24,'Cálculos Comparativos'!D:D,A159)+COUNTIFS('Cálculos Comparativos'!T:T,#REF!,'Cálculos Comparativos'!D:D,A159)+COUNTIFS('Cálculos Comparativos'!T:T,$B$25,'Cálculos Comparativos'!D:D,A159)+COUNTIFS('Cálculos Comparativos'!T:T,$B$26,'Cálculos Comparativos'!D:D,A159)) -> 0.33333333 | F159: =IFERROR(__xludf.DUMMYFUNCTION("""COMPUTED_VALUE"""),"DHO") -> DHO | G159: =IFERROR(__xludf.DUMMYFUNCTION("""COMPUTED_VALUE"""),0.0) -> 0 | H159: =VLOOKUP(F159,F$122:G$131,2,0) -> 1

Sheet Comparativo por Funcionário
A1: DADOS PARA COMPARAÇÃO - POR FUNCIONÁRIO | N1: ='Informações Relevantes Pesquisa'!A1 -> Pesquisa Contrução Civil e Consolidadas | T1: ="% da "&'Painel Geral'!B5 -> % da Mediana | U1: Posicionamento
A3: Cod. | B3: Cod. do funcionário | C3: Cargos Empresa | D3: Diretoria | E3: Centro de Custo | F3: Nível Organizacional | G3: Data de Admissão | H3: Tempo de empresa (anos) | I3: Cod. Pesquisa | J3: Cargos Pesquisa | K3: Senioridade | L3: Código+Senioridade | M3: Salário Funcionário CLT | N3: Menor Salário | O3: 1º Quartil | P3: Média | Q3: Mediana | R3: 3º Quartil | S3: Maior Salário | T3: C-01 | U3: C-01 (Posicionamento) | V3: Cod. Setor
A4: 45 | B4: PJ13 | C4: =VLOOKUP(A4,Jobmatch!A:F,2,0) -> GERENTE DE HOUSE | D4: =VLOOKUP(B4,'Folha de Pagamento'!B:G,6,0) -> Comercial | E4: =VLOOKUP(A4,Jobmatch!A:F,4,0) -> 52 - ADM PROJETOS | F4: =VLOOKUP(A4,Jobmatch!A:F,5,0) -> Tático | G4: =VLOOKUP(B4,'Folha de Pagamento'!B:O,13,0) -> Feminino | H4: =(TODAY()-G4)/365 -> #VALUE! | I4: =VLOOKUP(A4,Jobmatch!A:G,6,0) -> 107 | J4: =VLOOKUP(A4,Jobmatch!A:H,7,0) -> Gerente Comercial | K4: =VLOOKUP(A4,Jobmatch!A:I,8,0) -> Indiferente | L4: =I4&K4 -> 107Indiferente | M4: =IFERROR(VLOOKUP(B4,'Folha de Pagamento'!B:K,10,0),"") -> 3882.5758 | N4: =IFERROR(VLOOKUP(L4,Pesquisa!$D:$L,4,0),"") -> 5570.67 | O4: =IFERROR(VLOOKUP(L4,Pesquisa!$D:$L,5,0),"") -> 9778.91 | P4: =IFERROR(VLOOKUP(L4,Pesquisa!$D:$L,6,0),"") -> 12281.04 | Q4: =IFERROR(VLOOKUP(L4,Pesquisa!$D:$L,7,0),"") -> 12107.57 | R4: =IFERROR(VLOOKUP(L4,Pesquisa!$D:$L,8,0),"") -> 15321.87 | S4: =IFERROR(VLOOKUP(L4,Pesquisa!$D:$L,9,0),"") -> 19289.48 | T4: =IFS('Painel Geral'!$B$5="Mediana",IFERROR(IF(OR(M4="",Q4=0,Q4=""),"",($M4/$Q4)),""),'Painel Geral'!$B$5="Menor Salário",IFERROR(IF(OR(M4="",Q4=0,Q4=""),"",($M4/$N4)),""),'Painel Geral'!$B$5="1º Quartil",IFERROR(IF(OR(M4="",Q4=0,Q4=""),"",($M4/$O4)),""),'Painel Geral'!$B$5="Média",IFERROR(IF(OR(M4="",Q4=0,Q4=""),"",($M4/$P4)),""),'Painel Geral'!$B$5="3º Quartil",IFERROR(IF(OR(M4="",Q4=0,Q4=""),"",($M4/$R4)),""),'Painel Geral'!$B$5="Maior Salário",IFERROR(IF(OR(M4="",Q4=0,Q4=""),"",($M4/$S4)),"")) -> 0.32067341 | U4: =IFS(OR(N4="",N4=0,M4="", M4=0),"",T4<=80%,"Muito Defasado",T4<=90%,"Defasado",T4<=100%,"Na Média",T4<=110%,"Na Média",T4<=120%,"Muito Competitivo",T4>120%,"Agressivo") -> Muito Defasado | V4: =VLOOKUP(A4,'Cálculos Comparativos'!$A:$E,4,0) -> 2
A5: 49 | B5: PJ19 | C5: =VLOOKUP(A5,Jobmatch!A:F,2,0) -> GERENTE DE PARCERIAS EXTERNAS | D5: =VLOOKUP(B5,'Folha de Pagamento'!B:G,6,0) -> Comercial | E5: =VLOOKUP(A5,Jobmatch!A:F,4,0) -> 56 - ADM PROJETOS | F5: =VLOOKUP(A5,Jobmatch!A:F,5,0) -> Tático | G5: =VLOOKUP(B5,'Folha de Pagamento'!B:O,13,0) -> Masculino | H5: =(TODAY()-G5)/365 -> #VALUE! | I5: =VLOOKUP(A5,Jobmatch!A:G,6,0) -> 408 | J5: =VLOOKUP(A5,Jobmatch!A:H,7,0) -> Gerente de Relacionamento | K5: =VLOOKUP(A5,Jobmatch!A:I,8,0) -> Indiferente | L5: =I5&K5 -> 408Indiferente | M5: =IFERROR(VLOOKUP(B5,'Folha de Pagamento'!B:K,10,0),"") -> 3787.8788 | N5: =IFERROR(VLOOKUP(L5,Pesquisa!$D:$L,4,0),"") -> 5772.56 | O5: =IFERROR(VLOOKUP(L5,Pesquisa!$D:$L,5,0),"") -> 7608.96 | P5: =IFERROR(VLOOKUP(L5,Pesquisa!$D:$L,6,0),"") -> 10973.95 | Q5: =IFERROR(VLOOKUP(L5,Pesquisa!$D:$L,7,0),"") -> 10996.97 | R5: =IFERROR(VLOOKUP(L5,Pesquisa!$D:$L,8,0),"") -> 14004.27 | S5: =IFERROR(VLOOKUP(L5,Pesquisa!$D:$L,9,0),"") -> 16628.86 | T5: =IFS('Painel Geral'!$B$5="Mediana",IFERROR(IF(OR(M5="",Q5=0,Q5=""),"",($M5/$Q5)),""),'Painel Geral'!$B$5="Menor Salário",IFERROR(IF(OR(M5="",Q5=0,Q5=""),"",($M5/$N5)),""),'Painel Geral'!$B$5="1º Quartil",IFERROR(IF(OR(M5="",Q5=0,Q5=""),"",($M5/$O5)),""),'Painel Geral'!$B$5="Média",IFERROR(IF(OR(M5="",Q5=0,Q5=""),"",($M5/$P5)),""),'Painel Geral'!$B$5="3º Quartil",IFERROR(IF(OR(M5="",Q5=0,Q5=""),"",($M5/$R5)),""),'Painel Geral'!$B$5="Maior Salário",IFERROR(IF(OR(M5="",Q5=0,Q5=""),"",($M5/$S5)),"")) -> 0.3444475 | U5: =IFS(OR(N5="",N5=0,M5="", M5=0),"",T5<=80%,"Muito Defasado",T5<=90%,"Defasado",T5<=100%,"Na Média",T5<=110%,"Na Média",T5<=120%,"Muito Competitivo",T5>120%,"Agressivo") -> Muito Defasado | V5: =VLOOKUP(A5,'Cálculos Comparativos'!$A:$E,4,0) -> 2
A6: 48 | B6: PJ18 | C6: =VLOOKUP(A6,Jobmatch!A:F,2,0) -> GERENTE DE PARCERIAS | D6: =VLOOKUP(B6,'Folha de Pagamento'!B:G,6,0) -> Comercial | E6: =VLOOKUP(A6,Jobmatch!A:F,4,0) -> 55 - ADM PROJETOS | F6: =VLOOKUP(A6,Jobmatch!A:F,5,0) -> Tático | G6: =VLOOKUP(B6,'Folha de Pagamento'!B:O,13,0) -> Feminino | H6: =(TODAY()-G6)/365 -> #VALUE! | I6: =VLOOKUP(A6,Jobmatch!A:G,6,0) -> 408 | J6: =VLOOKUP(A6,Jobmatch!A:H,7,0) -> Gerente de Relacionamento | K6: =VLOOKUP(A6,Jobmatch!A:I,8,0) -> Indiferente | L6: =I6&K6 -> 408Indiferente | M6: =IFERROR(VLOOKUP(B6,'Folha de Pagamento'!B:K,10,0),"") -> 3825.7576 | N6: =IFERROR(VLOOKUP(L6,Pesquisa!$D:$L,4,0),"") -> 5772.56 | O6: =IFERROR(VLOOKUP(L6,Pesquisa!$D:$L,5,0),"") -> 7608.96 | P6: =IFERROR(VLOOKUP(L6,Pesquisa!$D:$L,6,0),"") -> 10973.95 | Q6: =IFERROR(VLOOKUP(L6,Pesquisa!$D:$L,7,0),"") -> 10996.97 | R6: =IFERROR(VLOOKUP(L6,Pesquisa!$D:$L,8,0),"") -> 14004.27 | S6: =IFERROR(VLOOKUP(L6,Pesquisa!$D:$L,9,0),"") -> 16628.86 | T6: =IFS('Painel Geral'!$B$5="Mediana",IFERROR(IF(OR(M6="",Q6=0,Q6=""),"",($M6/$Q6)),""),'Painel Geral'!$B$5="Menor Salário",IFERROR(IF(OR(M6="",Q6=0,Q6=""),"",($M6/$N6)),""),'Painel Geral'!$B$5="1º Quartil",IFERROR(IF(OR(M6="",Q6=0,Q6=""),"",($M6/$O6)),""),'Painel Geral'!$B$5="Média",IFERROR(IF(OR(M6="",Q6=0,Q6=""),"",($M6/$P6)),""),'Painel Geral'!$B$5="3º Quartil",IFERROR(IF(OR(M6="",Q6=0,Q6=""),"",($M6/$R6)),""),'Painel Geral'!$B$5="Maior Salário",IFERROR(IF(OR(M6="",Q6=0,Q6=""),"",($M6/$S6)),"")) -> 0.34789197 | U6: =IFS(OR(N6="",N6=0,M6="", M6=0),"",T6<=80%,"Muito Defasado",T6<=90%,"Defasado",T6<=100%,"Na Média",T6<=110%,"Na Média",T6<=120%,"Muito Competitivo",T6>120%,"Agressivo") -> Muito Defasado | V6: =VLOOKUP(A6,'Cálculos Comparativos'!$A:$E,4,0) -> 2
A7: 36 | B7: PJ8 | C7: =VLOOKUP(A7,Jobmatch!A:F,2,0) -> ENGENHEIRO JUNIOR DE URBANISMO | D7: =VLOOKUP(B7,'Folha de Pagamento'!B:G,6,0) -> Urbanismo | E7: =VLOOKUP(A7,Jobmatch!A:F,4,0) -> 43 - ADM PROJETOS | F7: =VLOOKUP(A7,Jobmatch!A:F,5,0) -> Operacional | G7: =VLOOKUP(B7,'Folha de Pagamento'!B:O,13,0) -> Masculino | H7: =(TODAY()-G7)/365 -> #VALUE! | I7: =VLOOKUP(A7,Jobmatch!A:G,6,0) -> 212 | J7: =VLOOKUP(A7,Jobmatch!A:H,7,0) -> Engenheiro de Urbanismo | K7: =VLOOKUP(A7,Jobmatch!A:I,8,0) -> Indiferente | L7: =I7&K7 -> 212Indiferente | M7: =IFERROR(VLOOKUP(B7,'Folha de Pagamento'!B:K,10,0),"") -> 5630.8725 | N7: =IFERROR(VLOOKUP(L7,Pesquisa!$D:$L,4,0),"") -> 13744.09 | O7: =IFERROR(VLOOKUP(L7,Pesquisa!$D:$L,5,0),"") -> 14781.36 | P7: =IFERROR(VLOOKUP(L7,Pesquisa!$D:$L,6,0),"") -> 15210.85 | Q7: =IFERROR(VLOOKUP(L7,Pesquisa!$D:$L,7,0),"") -> 15118.5 | R7: =IFERROR(VLOOKUP(L7,Pesquisa!$D:$L,8,0),"") -> 16203.19 | S7: =IFERROR(VLOOKUP(L7,Pesquisa!$D:$L,9,0),"") -> 16203.19 | T7: =IFS('Painel Geral'!$B$5="Mediana",IFERROR(IF(OR(M7="",Q7=0,Q7=""),"",($M7/$Q7)),""),'Painel Geral'!$B$5="Menor Salário",IFERROR(IF(OR(M7="",Q7=0,Q7=""),"",($M7/$N7)),""),'Painel Geral'!$B$5="1º Quartil",IFERROR(IF(OR(M7="",Q7=0,Q7=""),"",($M7/$O7)),""),'Painel Geral'!$B$5="Média",IFERROR(IF(OR(M7="",Q7=0,Q7=""),"",($M7/$P7)),""),'Painel Geral'!$B$5="3º Quartil",IFERROR(IF(OR(M7="",Q7=0,Q7=""),"",($M7/$R7)),""),'Painel Geral'!$B$5="Maior Salário",IFERROR(IF(OR(M7="",Q7=0,Q7=""),"",($M7/$S7)),"")) -> 0.37244915 | U7: =IFS(OR(N7="",N7=0,M7="", M7=0),"",T7<=80%,"Muito Defasado",T7<=90%,"Defasado",T7<=100%,"Na Média",T7<=110%,"Na Média",T7<=120%,"Muito Competitivo",T7>120%,"Agressivo") -> Muito Defasado | V7: =VLOOKUP(A7,'Cálculos Comparativos'!$A:$E,4,0) -> 10
A8: 48 | B8: PJ17 | C8: =VLOOKUP(A8,Jobmatch!A:F,2,0) -> GERENTE DE PARCERIAS | D8: =VLOOKUP(B8,'Folha de Pagamento'!B:G,6,0) -> Comercial | E8: =VLOOKUP(A8,Jobmatch!A:F,4,0) -> 55 - ADM PROJETOS | F8: =VLOOKUP(A8,Jobmatch!A:F,5,0) -> Tático | G8: =VLOOKUP(B8,'Folha de Pagamento'!B:O,13,0) -> Feminino | H8: =(TODAY()-G8)/365 -> #VALUE! | I8: =VLOOKUP(A8,Jobmatch!A:G,6,0) -> 408 | J8: =VLOOKUP(A8,Jobmatch!A:H,7,0) -> Gerente de Relacionamento | K8: =VLOOKUP(A8,Jobmatch!A:I,8,0) -> Indiferente | L8: =I8&K8 -> 408Indiferente | M8: =IFERROR(VLOOKUP(B8,'Folha de Pagamento'!B:K,10,0),"") -> 4272.7273 | N8: =IFERROR(VLOOKUP(L8,Pesquisa!$D:$L,4,0),"") -> 5772.56 | O8: =IFERROR(VLOOKUP(L8,Pesquisa!$D:$L,5,0),"") -> 7608.96 | P8: =IFERROR(VLOOKUP(L8,Pesquisa!$D:$L,6,0),"") -> 10973.95 | Q8: =IFERROR(VLOOKUP(L8,Pesquisa!$D:$L,7,0),"") -> 10996.97 | R8: =IFERROR(VLOOKUP(L8,Pesquisa!$D:$L,8,0),"") -> 14004.27 | S8: =IFERROR(VLOOKUP(L8,Pesquisa!$D:$L,9,0),"") -> 16628.86 | T8: =IFS('Painel Geral'!$B$5="Mediana",IFERROR(IF(OR(M8="",Q8=0,Q8=""),"",($M8/$Q8)),""),'Painel Geral'!$B$5="Menor Salário",IFERROR(IF(OR(M8="",Q8=0,Q8=""),"",($M8/$N8)),""),'Painel Geral'!$B$5="1º Quartil",IFERROR(IF(OR(M8="",Q8=0,Q8=""),"",($M8/$O8)),""),'Painel Geral'!$B$5="Média",IFERROR(IF(OR(M8="",Q8=0,Q8=""),"",($M8/$P8)),""),'Painel Geral'!$B$5="3º Quartil",IFERROR(IF(OR(M8="",Q8=0,Q8=""),"",($M8/$R8)),""),'Painel Geral'!$B$5="Maior Salário",IFERROR(IF(OR(M8="",Q8=0,Q8=""),"",($M8/$S8)),"")) -> 0.38853678 | U8: =IFS(OR(N8="",N8=0,M8="", M8=0),"",T8<=80%,"Muito Defasado",T8<=90%,"Defasado",T8<=100%,"Na Média",T8<=110%,"Na Média",T8<=120%,"Muito Competitivo",T8>120%,"Agressivo") -> Muito Defasado | V8: =VLOOKUP(A8,'Cálculos Comparativos'!$A:$E,4,0) -> 2
A9: 26 | B9: PJ4 | C9: =VLOOKUP(A9,Jobmatch!A:F,2,0) -> CONTROLLER TÉCNICO | D9: =VLOOKUP(B9,'Folha de Pagamento'!B:G,6,0) -> Controladoria | E9: =VLOOKUP(A9,Jobmatch!A:F,4,0) -> 33 - ADM PROJETOS | F9: =VLOOKUP(A9,Jobmatch!A:F,5,0) -> Tático | G9: =VLOOKUP(B9,'Folha de Pagamento'!B:O,13,0) -> Masculino | H9: =(TODAY()-G9)/365 -> #VALUE! | I9: =VLOOKUP(A9,Jobmatch!A:G,6,0) -> 26 | J9: =VLOOKUP(A9,Jobmatch!A:H,7,0) -> Analista de Controladoria | K9: =VLOOKUP(A9,Jobmatch!A:I,8,0) -> Especialista | L9: =I9&K9 -> 26Especialista | M9: =IFERROR(VLOOKUP(B9,'Folha de Pagamento'!B:K,10,0),"") -> 9243.5037 | N9: =IFERROR(VLOOKUP(L9,Pesquisa!$D:$L,4,0),"") -> 6777.08 | O9: =IFERROR(VLOOKUP(L9,Pesquisa!$D:$L,5,0),"") -> 10665.2 | P9: =IFERROR(VLOOKUP(L9,Pesquisa!$D:$L,6,0),"") -> 12572.61 | Q9: =IFERROR(VLOOKUP(L9,Pesquisa!$D:$L,7,0),"") -> 13758.75 | R9: =IFERROR(VLOOKUP(L9,Pesquisa!$D:$L,8,0),"") -> 15666.17 | S9: =IFERROR(VLOOKUP(L9,Pesquisa!$D:$L,9,0),"") -> 15995.86 | T9: =IFS('Painel Geral'!$B$5="Mediana",IFERROR(IF(OR(M9="",Q9=0,Q9=""),"",($M9/$Q9)),""),'Painel Geral'!$B$5="Menor Salário",IFERROR(IF(OR(M9="",Q9=0,Q9=""),"",($M9/$N9)),""),'Painel Geral'!$B$5="1º Quartil",IFERROR(IF(OR(M9="",Q9=0,Q9=""),"",($M9/$O9)),""),'Painel Geral'!$B$5="Média",IFERROR(IF(OR(M9="",Q9=0,Q9=""),"",($M9/$P9)),""),'Painel Geral'!$B$5="3º Quartil",IFERROR(IF(OR(M9="",Q9=0,Q9=""),"",($M9/$R9)),""),'Painel Geral'!$B$5="Maior Salário",IFERROR(IF(OR(M9="",Q9=0,Q9=""),"",($M9/$S9)),"")) -> 0.67182728 | U9: =IFS(OR(N9="",N9=0,M9="", M9=0),"",T9<=80%,"Muito Defasado",T9<=90%,"Defasado",T9<=100%,"Na Média",T9<=110%,"Na Média",T9<=120%,"Muito Competitivo",T9>120%,"Agressivo") -> Muito Defasado | V9: =VLOOKUP(A9,'Cálculos Comparativos'!$A:$E,4,0) -> 3
A10: 25 | B10: PJ3 | C10: =VLOOKUP(A10,Jobmatch!A:F,2,0) -> CONTROLLER GERAL | D10: =VLOOKUP(B10,'Folha de Pagamento'!B:G,6,0) -> Controladoria | E10: =VLOOKUP(A10,Jobmatch!A:F,4,0) -> 32 - ADM PROJETOS | F10: =VLOOKUP(A10,Jobmatch!A:F,5,0) -> Tático | G10: =VLOOKUP(B10,'Folha de Pagamento'!B:O,13,0) -> Feminino | H10: =(TODAY()-G10)/365 -> #VALUE! | I10: =VLOOKUP(A10,Jobmatch!A:G,6,0) -> 95 | J10: =VLOOKUP(A10,Jobmatch!A:H,7,0) -> Controller | K10: =VLOOKUP(A10,Jobmatch!A:I,8,0) -> Indiferente | L10: =I10&K10 -> 95Indiferente | M10: =IFERROR(VLOOKUP(B10,'Folha de Pagamento'!B:K,10,0),"") -> 11678.832 | N10: =IFERROR(VLOOKUP(L10,Pesquisa!$D:$L,4,0),"") -> 14652.03 | O10: =IFERROR(VLOOKUP(L10,Pesquisa!$D:$L,5,0),"") -> 15472.01 | P10: =IFERROR(VLOOKUP(L10,Pesquisa!$D:$L,6,0),"") -> 16594.35 | Q10: =IFERROR(VLOOKUP(L10,Pesquisa!$D:$L,7,0),"") -> 16581.68 | R10: =IFERROR(VLOOKUP(L10,Pesquisa!$D:$L,8,0),"") -> 17497.31 | S10: =IFERROR(VLOOKUP(L10,Pesquisa!$D:$L,9,0),"") -> 18846.04 | T10: =IFS('Painel Geral'!$B$5="Mediana",IFERROR(IF(OR(M10="",Q10=0,Q10=""),"",($M10/$Q10)),""),'Painel Geral'!$B$5="Menor Salário",IFERROR(IF(OR(M10="",Q10=0,Q10=""),"",($M10/$N10)),""),'Painel Geral'!$B$5="1º Quartil",IFERROR(IF(OR(M10="",Q10=0,Q10=""),"",($M10/$O10)),""),'Painel Geral'!$B$5="Média",IFERROR(IF(OR(M10="",Q10=0,Q10=""),"",($M10/$P10)),""),'Painel Geral'!$B$5="3º Quartil",IFERROR(IF(OR(M10="",Q10=0,Q10=""),"",($M10/$R10)),""),'Painel Geral'!$B$5="Maior Salário",IFERROR(IF(OR(M10="",Q10=0,Q10=""),"",($M10/$S10)),"")) -> 0.7043214 | U10: =IFS(OR(N10="",N10=0,M10="", M10=0),"",T10<=80%,"Muito Defasado",T10<=90%,"Defasado",T10<=100%,"Na Média",T10<=110%,"Na Média",T10<=120%,"Muito Competitivo",T10>120%,"Agressivo") -> Muito Defasado | V10: =VLOOKUP(A10,'Cálculos Comparativos'!$A:$E,4,0) -> 3
A11: 2 | B11: 1964 | C11: =VLOOKUP(A11,Jobmatch!A:F,2,0) -> ANALISTA DE COMPRAS | D11: =VLOOKUP(B11,'Folha de Pagamento'!B:G,6,0) -> Suprimentos | E11: =VLOOKUP(A11,Jobmatch!A:F,4,0) -> 9 - ADM PROJETOS | F11: =VLOOKUP(A11,Jobmatch!A:F,5,0) -> Operacional | G11: =VLOOKUP(B11,'Folha de Pagamento'!B:O,13,0) -> Masculino | H11: =(TODAY()-G11)/365 -> #VALUE! | I11: =VLOOKUP(A11,Jobmatch!A:G,6,0) -> 136 | J11: =VLOOKUP(A11,Jobmatch!A:H,7,0) -> Analista de Compras | K11: =VLOOKUP(A11,Jobmatch!A:I,8,0) -> Pleno | L11: =I11&K11 -> 136Pleno | M11: =IFERROR(VLOOKUP(B11,'Folha de Pagamento'!B:K,10,0),"") -> 3780 | N11: =IFERROR(VLOOKUP(L11,Pesquisa!$D:$L,4,0),"") -> 4535.62 | O11: =IFERROR(VLOOKUP(L11,Pesquisa!$D:$L,5,0),"") -> 4535.62 | P11: =IFERROR(VLOOKUP(L11,Pesquisa!$D:$L,6,0),"") -> 6016.64 | Q11: =IFERROR(VLOOKUP(L11,Pesquisa!$D:$L,7,0),"") -> 5288.53 | R11: =IFERROR(VLOOKUP(L11,Pesquisa!$D:$L,8,0),"") -> 7861.72 | S11: =IFERROR(VLOOKUP(L11,Pesquisa!$D:$L,9,0),"") -> 7861.72 | T11: =IFS('Painel Geral'!$B$5="Mediana",IFERROR(IF(OR(M11="",Q11=0,Q11=""),"",($M11/$Q11)),""),'Painel Geral'!$B$5="Menor Salário",IFERROR(IF(OR(M11="",Q11=0,Q11=""),"",($M11/$N11)),""),'Painel Geral'!$B$5="1º Quartil",IFERROR(IF(OR(M11="",Q11=0,Q11=""),"",($M11/$O11)),""),'Painel Geral'!$B$5="Média",IFERROR(IF(OR(M11="",Q11=0,Q11=""),"",($M11/$P11)),""),'Painel Geral'!$B$5="3º Quartil",IFERROR(IF(OR(M11="",Q11=0,Q11=""),"",($M11/$R11)),""),'Painel Geral'!$B$5="Maior Salário",IFERROR(IF(OR(M11="",Q11=0,Q11=""),"",($M11/$S11)),"")) -> 0.71475438 | U11: =IFS(OR(N11="",N11=0,M11="", M11=0),"",T11<=80%,"Muito Defasado",T11<=90%,"Defasado",T11<=100%,"Na Média",T11<=110%,"Na Média",T11<=120%,"Muito Competitivo",T11>120%,"Agressivo") -> Muito Defasado | V11: =VLOOKUP(A11,'Cálculos Comparativos'!$A:$E,4,0) -> 1
A12: 5 | B12: 1373 | C12: =VLOOKUP(A12,Jobmatch!A:F,2,0) -> ANALISTA DE MANUTENÇÃO II | D12: =VLOOKUP(B12,'Folha de Pagamento'!B:G,6,0) -> Edificação | E12: =VLOOKUP(A12,Jobmatch!A:F,4,0) -> 12 - ADM PROJETOS | F12: =VLOOKUP(A12,Jobmatch!A:F,5,0) -> Operacional | G12: =VLOOKUP(B12,'Folha de Pagamento'!B:O,13,0) -> Masculino | H12: =(TODAY()-G12)/365 -> #VALUE! | I12: =VLOOKUP(A12,Jobmatch!A:G,6,0) -> 820 | J12: =VLOOKUP(A12,Jobmatch!A:H,7,0) -> Encarregado de Manutenção | K12: =VLOOKUP(A12,Jobmatch!A:I,8,0) -> Indiferente | L12: =I12&K12 -> 820Indiferente | M12: =IFERROR(VLOOKUP(B12,'Folha de Pagamento'!B:K,10,0),"") -> 4550 | N12: =IFERROR(VLOOKUP(L12,Pesquisa!$D:$L,4,0),"") -> 4348.38 | O12: =IFERROR(VLOOKUP(L12,Pesquisa!$D:$L,5,0),"") -> 5743.67 | P12: =IFERROR(VLOOKUP(L12,Pesquisa!$D:$L,6,0),"") -> 6811.3 | Q12: =IFERROR(VLOOKUP(L12,Pesquisa!$D:$L,7,0),"") -> 6232.3 | R12: =IFERROR(VLOOKUP(L12,Pesquisa!$D:$L,8,0),"") -> 8417.62 | S12: =IFERROR(VLOOKUP(L12,Pesquisa!$D:$L,9,0),"") -> 9486.51 | T12: =IFS('Painel Geral'!$B$5="Mediana",IFERROR(IF(OR(M12="",Q12=0,Q12=""),"",($M12/$Q12)),""),'Painel Geral'!$B$5="Menor Salário",IFERROR(IF(OR(M12="",Q12=0,Q12=""),"",($M12/$N12)),""),'Painel Geral'!$B$5="1º Quartil",IFERROR(IF(OR(M12="",Q12=0,Q12=""),"",($M12/$O12)),""),'Painel Geral'!$B$5="Média",IFERROR(IF(OR(M12="",Q12=0,Q12=""),"",($M12/$P12)),""),'Painel Geral'!$B$5="3º Quartil",IFERROR(IF(OR(M12="",Q12=0,Q12=""),"",($M12/$R12)),""),'Painel Geral'!$B$5="Maior Salário",IFERROR(IF(OR(M12="",Q12=0,Q12=""),"",($M12/$S12)),"")) -> 0.73006755 | U12: =IFS(OR(N12="",N12=0,M12="", M12=0),"",T12<=80%,"Muito Defasado",T12<=90%,"Defasado",T12<=100%,"Na Média",T12<=110%,"Na Média",T12<=120%,"Muito Competitivo",T12>120%,"Agressivo") -> Muito Defasado | V12: =VLOOKUP(A12,'Cálculos Comparativos'!$A:$E,4,0) -> 5
A13: 30 | B13: 1452 | C13: =VLOOKUP(A13,Jobmatch!A:F,2,0) -> COORDENADOR DE OBRAS | D13: =VLOOKUP(B13,'Folha de Pagamento'!B:G,6,0) -> Edificação | E13: =VLOOKUP(A13,Jobmatch!A:F,4,0) -> 37 - ADM PROJETOS | F13: =VLOOKUP(A13,Jobmatch!A:F,5,0) -> Tático | G13: =VLOOKUP(B13,'Folha de Pagamento'!B:O,13,0) -> Masculino | H13: =(TODAY()-G13)/365 -> #VALUE! | I13: =VLOOKUP(A13,Jobmatch!A:G,6,0) -> 209 | J13: =VLOOKUP(A13,Jobmatch!A:H,7,0) -> Coordenador de Obras | K13: =VLOOKUP(A13,Jobmatch!A:I,8,0) -> Indiferente | L13: =I13&K13 -> 209Indiferente | M13: =IFERROR(VLOOKUP(B13,'Folha de Pagamento'!B:K,10,0),"") -> 8714 | N13: =IFERROR(VLOOKUP(L13,Pesquisa!$D:$L,4,0),"") -> 5608.9635 | O13: =IFERROR(VLOOKUP(L13,Pesquisa!$D:$L,5,0),"") -> 9662.3485 | P13: =IFERROR(VLOOKUP(L13,Pesquisa!$D:$L,6,0),"") -> 10653.144 | Q13: =IFERROR(VLOOKUP(L13,Pesquisa!$D:$L,7,0),"") -> 11847.831 | R13: =IFERROR(VLOOKUP(L13,Pesquisa!$D:$L,8,0),"") -> 12838.627 | S13: =IFERROR(VLOOKUP(L13,Pesquisa!$D:$L,9,0),"") -> 13307.951 | T13: =IFS('Painel Geral'!$B$5="Mediana",IFERROR(IF(OR(M13="",Q13=0,Q13=""),"",($M13/$Q13)),""),'Painel Geral'!$B$5="Menor Salário",IFERROR(IF(OR(M13="",Q13=0,Q13=""),"",($M13/$N13)),""),'Painel Geral'!$B$5="1º Quartil",IFERROR(IF(OR(M13="",Q13=0,Q13=""),"",($M13/$O13)),""),'Painel Geral'!$B$5="Média",IFERROR(IF(OR(M13="",Q13=0,Q13=""),"",($M13/$P13)),""),'Painel Geral'!$B$5="3º Quartil",IFERROR(IF(OR(M13="",Q13=0,Q13=""),"",($M13/$R13)),""),'Painel Geral'!$B$5="Maior Salário",IFERROR(IF(OR(M13="",Q13=0,Q13=""),"",($M13/$S13)),"")) -> 0.73549327 | U13: =IFS(OR(N13="",N13=0,M13="", M13=0),"",T13<=80%,"Muito Defasado",T13<=90%,"Defasado",T13<=100%,"Na Média",T13<=110%,"Na Média",T13<=120%,"Muito Competitivo",T13>120%,"Agressivo") -> Muito Defasado | V13: =VLOOKUP(A13,'Cálculos Comparativos'!$A:$E,4,0) -> 5
A14: 8 | B14: 187 | C14: =VLOOKUP(A14,Jobmatch!A:F,2,0) -> ANALISTA DE URBANISMO | D14: =VLOOKUP(B14,'Folha de Pagamento'!B:G,6,0) -> Urbanismo | E14: =VLOOKUP(A14,Jobmatch!A:F,4,0) -> 15 - ADM PROJETOS | F14: =VLOOKUP(A14,Jobmatch!A:F,5,0) -> Operacional | G14: =VLOOKUP(B14,'Folha de Pagamento'!B:O,13,0) -> Feminino | H14: =(TODAY()-G14)/365 -> #VALUE! | I14: =VLOOKUP(A14,Jobmatch!A:G,6,0) -> 1199 | J14: =VLOOKUP(A14,Jobmatch!A:H,7,0) -> Analista de Urbanismo | K14: =VLOOKUP(A14,Jobmatch!A:I,8,0) -> Indiferente | L14: =I14&K14 -> 1199Indiferente | M14: =IFERROR(VLOOKUP(B14,'Folha de Pagamento'!B:K,10,0),"") -> 5830 | N14: =IFERROR(VLOOKUP(L14,Pesquisa!$D:$L,4,0),"") -> 5876.15 | O14: =IFERROR(VLOOKUP(L14,Pesquisa!$D:$L,5,0),"") -> 6106.16 | P14: =IFERROR(VLOOKUP(L14,Pesquisa!$D:$L,6,0),"") -> 7655.79 | Q14: =IFERROR(VLOOKUP(L14,Pesquisa!$D:$L,7,0),"") -> 7867.3 | R14: =IFERROR(VLOOKUP(L14,Pesquisa!$D:$L,8,0),"") -> 9183.14 | S14: =IFERROR(VLOOKUP(L14,Pesquisa!$D:$L,9,0),"") -> 9183.14 | T14: =IFS('Painel Geral'!$B$5="Mediana",IFERROR(IF(OR(M14="",Q14=0,Q14=""),"",($M14/$Q14)),""),'Painel Geral'!$B$5="Menor Salário",IFERROR(IF(OR(M14="",Q14=0,Q14=""),"",($M14/$N14)),""),'Painel Geral'!$B$5="1º Quartil",IFERROR(IF(OR(M14="",Q14=0,Q14=""),"",($M14/$O14)),""),'Painel Geral'!$B$5="Média",IFERROR(IF(OR(M14="",Q14=0,Q14=""),"",($M14/$P14)),""),'Painel Geral'!$B$5="3º Quartil",IFERROR(IF(OR(M14="",Q14=0,Q14=""),"",($M14/$R14)),""),'Painel Geral'!$B$5="Maior Salário",IFERROR(IF(OR(M14="",Q14=0,Q14=""),"",($M14/$S14)),"")) -> 0.74104203 | U14: =IFS(OR(N14="",N14=0,M14="", M14=0),"",T14<=80%,"Muito Defasado",T14<=90%,"Defasado",T14<=100%,"Na Média",T14<=110%,"Na Média",T14<=120%,"Muito Competitivo",T14>120%,"Agressivo") -> Muito Defasado | V14: =VLOOKUP(A14,'Cálculos Comparativos'!$A:$E,4,0) -> 10
A15: 47 | B15: PJ16 | C15: =VLOOKUP(A15,Jobmatch!A:F,2,0) -> GERENTE DE INCORPORAÇÃO | D15: =VLOOKUP(B15,'Folha de Pagamento'!B:G,6,0) -> Incorporação | E15: =VLOOKUP(A15,Jobmatch!A:F,4,0) -> 54 - ADM PROJETOS | F15: =VLOOKUP(A15,Jobmatch!A:F,5,0) -> Tático | G15: =VLOOKUP(B15,'Folha de Pagamento'!B:O,13,0) -> Feminino | H15: =(TODAY()-G15)/365 -> #VALUE! | I15: =VLOOKUP(A15,Jobmatch!A:G,6,0) -> 548 | J15: =VLOOKUP(A15,Jobmatch!A:H,7,0) -> Gerente de Incorporação | K15: =VLOOKUP(A15,Jobmatch!A:I,8,0) -> Indiferente | L15: =I15&K15 -> 548Indiferente | M15: =IFERROR(VLOOKUP(B15,'Folha de Pagamento'!B:K,10,0),"") -> 14045.455 | N15: =IFERROR(VLOOKUP(L15,Pesquisa!$D:$L,4,0),"") -> 9162.7273 | O15: =IFERROR(VLOOKUP(L15,Pesquisa!$D:$L,5,0),"") -> 13744.091 | P15: =IFERROR(VLOOKUP(L15,Pesquisa!$D:$L,6,0),"") -> 18683.553 | Q15: =IFERROR(VLOOKUP(L15,Pesquisa!$D:$L,7,0),"") -> 18908.464 | R15: =IFERROR(VLOOKUP(L15,Pesquisa!$D:$L,8,0),"") -> 23847.926 | S15: =IFERROR(VLOOKUP(L15,Pesquisa!$D:$L,9,0),"") -> 27754.557 | T15: =IFS('Painel Geral'!$B$5="Mediana",IFERROR(IF(OR(M15="",Q15=0,Q15=""),"",($M15/$Q15)),""),'Painel Geral'!$B$5="Menor Salário",IFERROR(IF(OR(M15="",Q15=0,Q15=""),"",($M15/$N15)),""),'Painel Geral'!$B$5="1º Quartil",IFERROR(IF(OR(M15="",Q15=0,Q15=""),"",($M15/$O15)),""),'Painel Geral'!$B$5="Média",IFERROR(IF(OR(M15="",Q15=0,Q15=""),"",($M15/$P15)),""),'Painel Geral'!$B$5="3º Quartil",IFERROR(IF(OR(M15="",Q15=0,Q15=""),"",($M15/$R15)),""),'Painel Geral'!$B$5="Maior Salário",IFERROR(IF(OR(M15="",Q15=0,Q15=""),"",($M15/$S15)),"")) -> 0.7428131 | U15: =IFS(OR(N15="",N15=0,M15="", M15=0),"",T15<=80%,"Muito Defasado",T15<=90%,"Defasado",T15<=100%,"Na Média",T15<=110%,"Na Média",T15<=120%,"Muito Competitivo",T15>120%,"Agressivo") -> Muito Defasado | V15: =VLOOKUP(A15,'Cálculos Comparativos'!$A:$E,4,0) -> 7
A16: 24 | B16: PJ2 | C16: =VLOOKUP(A16,Jobmatch!A:F,2,0) -> CONTROLER JURÍDICO | D16: =VLOOKUP(B16,'Folha de Pagamento'!B:G,6,0) -> Administrativo | E16: =VLOOKUP(A16,Jobmatch!A:F,4,0) -> 31 - ADM PROJETOS | F16: =VLOOKUP(A16,Jobmatch!A:F,5,0) -> Tático | G16: =VLOOKUP(B16,'Folha de Pagamento'!B:O,13,0) -> Feminino | H16: =(TODAY()-G16)/365 -> #VALUE! | I16: =VLOOKUP(A16,Jobmatch!A:G,6,0) -> 9 | J16: =VLOOKUP(A16,Jobmatch!A:H,7,0) -> Advogado | K16: =VLOOKUP(A16,Jobmatch!A:I,8,0) -> Sênior | L16: =I16&K16 -> 9Sênior | M16: =IFERROR(VLOOKUP(B16,'Folha de Pagamento'!B:K,10,0),"") -> 8276.6423 | N16: =IFERROR(VLOOKUP(L16,Pesquisa!$D:$L,4,0),"") -> 8566.38 | O16: =IFERROR(VLOOKUP(L16,Pesquisa!$D:$L,5,0),"") -> 9284.95 | P16: =IFERROR(VLOOKUP(L16,Pesquisa!$D:$L,6,0),"") -> 11453.66 | Q16: =IFERROR(VLOOKUP(L16,Pesquisa!$D:$L,7,0),"") -> 10957.61 | R16: =IFERROR(VLOOKUP(L16,Pesquisa!$D:$L,8,0),"") -> 10957.61 | S16: =IFERROR(VLOOKUP(L16,Pesquisa!$D:$L,9,0),"") -> 17501.76 | T16: =IFS('Painel Geral'!$B$5="Mediana",IFERROR(IF(OR(M16="",Q16=0,Q16=""),"",($M16/$Q16)),""),'Painel Geral'!$B$5="Menor Salário",IFERROR(IF(OR(M16="",Q16=0,Q16=""),"",($M16/$N16)),""),'Painel Geral'!$B$5="1º Quartil",IFERROR(IF(OR(M16="",Q16=0,Q16=""),"",($M16/$O16)),""),'Painel Geral'!$B$5="Média",IFERROR(IF(OR(M16="",Q16=0,Q16=""),"",($M16/$P16)),""),'Painel Geral'!$B$5="3º Quartil",IFERROR(IF(OR(M16="",Q16=0,Q16=""),"",($M16/$R16)),""),'Painel Geral'!$B$5="Maior Salário",IFERROR(IF(OR(M16="",Q16=0,Q16=""),"",($M16/$S16)),"")) -> 0.75533281 | U16: =IFS(OR(N16="",N16=0,M16="", M16=0),"",T16<=80%,"Muito Defasado",T16<=90%,"Defasado",T16<=100%,"Na Média",T16<=110%,"Na Média",T16<=120%,"Muito Competitivo",T16>120%,"Agressivo") -> Muito Defasado | V16: =VLOOKUP(A16,'Cálculos Comparativos'!$A:$E,4,0) -> 1
A17: 42 | B17: PJ10 | C17: =VLOOKUP(A17,Jobmatch!A:F,2,0) -> GERENTE ADMINISTRATIVA | D17: =VLOOKUP(B17,'Folha de Pagamento'!B:G,6,0) -> Administrativo | E17: =VLOOKUP(A17,Jobmatch!A:F,4,0) -> 49 - ADM PROJETOS | F17: =VLOOKUP(A17,Jobmatch!A:F,5,0) -> Tático | G17: =VLOOKUP(B17,'Folha de Pagamento'!B:O,13,0) -> Feminino | H17: =(TODAY()-G17)/365 -> #VALUE! | I17: =VLOOKUP(A17,Jobmatch!A:G,6,0) -> 106 | J17: =VLOOKUP(A17,Jobmatch!A:H,7,0) -> Gerente Administrativo | K17: =VLOOKUP(A17,Jobmatch!A:I,8,0) -> Indiferente | L17: =I17&K17 -> 106Indiferente | M17: =IFERROR(VLOOKUP(B17,'Folha de Pagamento'!B:K,10,0),"") -> 12242.424 | N17: =IFERROR(VLOOKUP(L17,Pesquisa!$D:$L,4,0),"") -> 8080.79 | O17: =IFERROR(VLOOKUP(L17,Pesquisa!$D:$L,5,0),"") -> 10525.48 | P17: =IFERROR(VLOOKUP(L17,Pesquisa!$D:$L,6,0),"") -> 13820.95 | Q17: =IFERROR(VLOOKUP(L17,Pesquisa!$D:$L,7,0),"") -> 13996.93 | R17: =IFERROR(VLOOKUP(L17,Pesquisa!$D:$L,8,0),"") -> 16850.54 | S17: =IFERROR(VLOOKUP(L17,Pesquisa!$D:$L,9,0),"") -> 27754.56 | T17: =IFS('Painel Geral'!$B$5="Mediana",IFERROR(IF(OR(M17="",Q17=0,Q17=""),"",($M17/$Q17)),""),'Painel Geral'!$B$5="Menor Salário",IFERROR(IF(OR(M17="",Q17=0,Q17=""),"",($M17/$N17)),""),'Painel Geral'!$B$5="1º Quartil",IFERROR(IF(OR(M17="",Q17=0,Q17=""),"",($M17/$O17)),""),'Painel Geral'!$B$5="Média",IFERROR(IF(OR(M17="",Q17=0,Q17=""),"",($M17/$P17)),""),'Painel Geral'!$B$5="3º Quartil",IFERROR(IF(OR(M17="",Q17=0,Q17=""),"",($M17/$R17)),""),'Painel Geral'!$B$5="Maior Salário",IFERROR(IF(OR(M17="",Q17=0,Q17=""),"",($M17/$S17)),"")) -> 0.87465067 | U17: =IFS(OR(N17="",N17=0,M17="", M17=0),"",T17<=80%,"Muito Defasado",T17<=90%,"Defasado",T17<=100%,"Na Média",T17<=110%,"Na Média",T17<=120%,"Muito Competitivo",T17>120%,"Agressivo") -> Defasado | V17: =VLOOKUP(A17,'Cálculos Comparativos'!$A:$E,4,0) -> 1
A18: 39 | B18: E03 | C18: =VLOOKUP(A18,Jobmatch!A:F,2,0) -> ESTAGIÁRIO(A) ADM | D18: =VLOOKUP(B18,'Folha de Pagamento'!B:G,6,0) -> Administrativo | E18: =VLOOKUP(A18,Jobmatch!A:F,4,0) -> 46 - ADM PROJETOS | F18: =VLOOKUP(A18,Jobmatch!A:F,5,0) -> Operacional | G18: =VLOOKUP(B18,'Folha de Pagamento'!B:O,13,0) -> Masculino | H18: =(TODAY()-G18)/365 -> #VALUE! | I18: =VLOOKUP(A18,Jobmatch!A:G,6,0) -> 338 | J18: =VLOOKUP(A18,Jobmatch!A:H,7,0) -> Estagiário Administrativo | K18: =VLOOKUP(A18,Jobmatch!A:I,8,0) -> Indiferente | L18: =I18&K18 -> 338Indiferente | M18: =IFERROR(VLOOKUP(B18,'Folha de Pagamento'!B:K,10,0),"") -> 1521 | N18: =IFERROR(VLOOKUP(L18,Pesquisa!$D:$L,4,0),"") -> 1562.2705 | O18: =IFERROR(VLOOKUP(L18,Pesquisa!$D:$L,5,0),"") -> 1618.9636 | P18: =IFERROR(VLOOKUP(L18,Pesquisa!$D:$L,6,0),"") -> 1757.55 | Q18: =IFERROR(VLOOKUP(L18,Pesquisa!$D:$L,7,0),"") -> 1726.0568 | R18: =IFERROR(VLOOKUP(L18,Pesquisa!$D:$L,8,0),"") -> 1864.6432 | S18: =IFERROR(VLOOKUP(L18,Pesquisa!$D:$L,9,0),"") -> 2015.8295 | T18: =IFS('Painel Geral'!$B$5="Mediana",IFERROR(IF(OR(M18="",Q18=0,Q18=""),"",($M18/$Q18)),""),'Painel Geral'!$B$5="Menor Salário",IFERROR(IF(OR(M18="",Q18=0,Q18=""),"",($M18/$N18)),""),'Painel Geral'!$B$5="1º Quartil",IFERROR(IF(OR(M18="",Q18=0,Q18=""),"",($M18/$O18)),""),'Painel Geral'!$B$5="Média",IFERROR(IF(OR(M18="",Q18=0,Q18=""),"",($M18/$P18)),""),'Painel Geral'!$B$5="3º Quartil",IFERROR(IF(OR(M18="",Q18=0,Q18=""),"",($M18/$R18)),""),'Painel Geral'!$B$5="Maior Salário",IFERROR(IF(OR(M18="",Q18=0,Q18=""),"",($M18/$S18)),"")) -> 0.88119927 | U18: =IFS(OR(N18="",N18=0,M18="", M18=0),"",T18<=80%,"Muito Defasado",T18<=90%,"Defasado",T18<=100%,"Na Média",T18<=110%,"Na Média",T18<=120%,"Muito Competitivo",T18>120%,"Agressivo") -> Defasado | V18: =VLOOKUP(A18,'Cálculos Comparativos'!$A:$E,4,0) -> 1
A19: 38 | B19: E01 | C19: =VLOOKUP(A19,Jobmatch!A:F,2,0) -> ESTAGIARIO (A) | D19: =VLOOKUP(B19,'Folha de Pagamento'!B:G,6,0) -> Novos Negócios | E19: =VLOOKUP(A19,Jobmatch!A:F,4,0) -> 45 - ADM PROJETOS | F19: =VLOOKUP(A19,Jobmatch!A:F,5,0) -> Operacional | G19: =VLOOKUP(B19,'Folha de Pagamento'!B:O,13,0) -> Feminino | H19: =(TODAY()-G19)/365 -> #VALUE! | I19: =VLOOKUP(A19,Jobmatch!A:G,6,0) -> 338 | J19: =VLOOKUP(A19,Jobmatch!A:H,7,0) -> Estagiário Administrativo | K19: =VLOOKUP(A19,Jobmatch!A:I,8,0) -> Indiferente | L19: =I19&K19 -> 338Indiferente | M19: =IFERROR(VLOOKUP(B19,'Folha de Pagamento'!B:K,10,0),"") -> 1521 | N19: =IFERROR(VLOOKUP(L19,Pesquisa!$D:$L,4,0),"") -> 1562.2705 | O19: =IFERROR(VLOOKUP(L19,Pesquisa!$D:$L,5,0),"") -> 1618.9636 | P19: =IFERROR(VLOOKUP(L19,Pesquisa!$D:$L,6,0),"") -> 1757.55 | Q19: =IFERROR(VLOOKUP(L19,Pesquisa!$D:$L,7,0),"") -> 1726.0568 | R19: =IFERROR(VLOOKUP(L19,Pesquisa!$D:$L,8,0),"") -> 1864.6432 | S19: =IFERROR(VLOOKUP(L19,Pesquisa!$D:$L,9,0),"") -> 2015.8295 | T19: =IFS('Painel Geral'!$B$5="Mediana",IFERROR(IF(OR(M19="",Q19=0,Q19=""),"",($M19/$Q19)),""),'Painel Geral'!$B$5="Menor Salário",IFERROR(IF(OR(M19="",Q19=0,Q19=""),"",($M19/$N19)),""),'Painel Geral'!$B$5="1º Quartil",IFERROR(IF(OR(M19="",Q19=0,Q19=""),"",($M19/$O19)),""),'Painel Geral'!$B$5="Média",IFERROR(IF(OR(M19="",Q19=0,Q19=""),"",($M19/$P19)),""),'Painel Geral'!$B$5="3º Quartil",IFERROR(IF(OR(M19="",Q19=0,Q19=""),"",($M19/$R19)),""),'Painel Geral'!$B$5="Maior Salário",IFERROR(IF(OR(M19="",Q19=0,Q19=""),"",($M19/$S19)),"")) -> 0.88119927 | U19: =IFS(OR(N19="",N19=0,M19="", M19=0),"",T19<=80%,"Muito Defasado",T19<=90%,"Defasado",T19<=100%,"Na Média",T19<=110%,"Na Média",T19<=120%,"Muito Competitivo",T19>120%,"Agressivo") -> Defasado | V19: =VLOOKUP(A19,'Cálculos Comparativos'!$A:$E,4,0) -> 9
A20: 9 | B20: 1868 | C20: =VLOOKUP(A20,Jobmatch!A:F,2,0) -> ANALISTA FINANCEIRO COMERCIAL III | D20: =VLOOKUP(B20,'Folha de Pagamento'!B:G,6,0) -> Financeiro | E20: =VLOOKUP(A20,Jobmatch!A:F,4,0) -> 16 - ADM PROJETOS | F20: =VLOOKUP(A20,Jobmatch!A:F,5,0) -> Operacional | G20: =VLOOKUP(B20,'Folha de Pagamento'!B:O,13,0) -> Feminino | H20: =(TODAY()-G20)/365 -> #VALUE! | I20: =VLOOKUP(A20,Jobmatch!A:G,6,0) -> 16 | J20: =VLOOKUP(A20,Jobmatch!A:H,7,0) -> Analista Financeiro | K20: =VLOOKUP(A20,Jobmatch!A:I,8,0) -> Sênior | L20: =I20&K20 -> 16Sênior | M20: =IFERROR(VLOOKUP(B20,'Folha de Pagamento'!B:K,10,0),"") -> 5213 | N20: =IFERROR(VLOOKUP(L20,Pesquisa!$D:$L,4,0),"") -> 4882.37 | O20: =IFERROR(VLOOKUP(L20,Pesquisa!$D:$L,5,0),"") -> 5489.27 | P20: =IFERROR(VLOOKUP(L20,Pesquisa!$D:$L,6,0),"") -> 6172.24 | Q20: =IFERROR(VLOOKUP(L20,Pesquisa!$D:$L,7,0),"") -> 5910.71 | R20: =IFERROR(VLOOKUP(L20,Pesquisa!$D:$L,8,0),"") -> 6737.39 | S20: =IFERROR(VLOOKUP(L20,Pesquisa!$D:$L,9,0),"") -> 8185.08 | T20: =IFS('Painel Geral'!$B$5="Mediana",IFERROR(IF(OR(M20="",Q20=0,Q20=""),"",($M20/$Q20)),""),'Painel Geral'!$B$5="Menor Salário",IFERROR(IF(OR(M20="",Q20=0,Q20=""),"",($M20/$N20)),""),'Painel Geral'!$B$5="1º Quartil",IFERROR(IF(OR(M20="",Q20=0,Q20=""),"",($M20/$O20)),""),'Painel Geral'!$B$5="Média",IFERROR(IF(OR(M20="",Q20=0,Q20=""),"",($M20/$P20)),""),'Painel Geral'!$B$5="3º Quartil",IFERROR(IF(OR(M20="",Q20=0,Q20=""),"",($M20/$R20)),""),'Painel Geral'!$B$5="Maior Salário",IFERROR(IF(OR(M20="",Q20=0,Q20=""),"",($M20/$S20)),"")) -> 0.88195834 | U20: =IFS(OR(N20="",N20=0,M20="", M20=0),"",T20<=80%,"Muito Defasado",T20<=90%,"Defasado",T20<=100%,"Na Média",T20<=110%,"Na Média",T20<=120%,"Muito Competitivo",T20>120%,"Agressivo") -> Defasado | V20: =VLOOKUP(A20,'Cálculos Comparativos'!$A:$E,4,0) -> 6
A21: 10 | B21: 176 | C21: =VLOOKUP(A21,Jobmatch!A:F,2,0) -> ANALISTA FINANCEIRO DE CAPTAÇÃO DE RECURSOS III | D21: =VLOOKUP(B21,'Folha de Pagamento'!B:G,6,0) -> Financeiro | E21: =VLOOKUP(A21,Jobmatch!A:F,4,0) -> 17 - ADM PROJETOS | F21: =VLOOKUP(A21,Jobmatch!A:F,5,0) -> Operacional | G21: =VLOOKUP(B21,'Folha de Pagamento'!B:O,13,0) -> Feminino | H21: =(TODAY()-G21)/365 -> #VALUE! | I21: =VLOOKUP(A21,Jobmatch!A:G,6,0) -> 16 | J21: =VLOOKUP(A21,Jobmatch!A:H,7,0) -> Analista Financeiro | K21: =VLOOKUP(A21,Jobmatch!A:I,8,0) -> Sênior | L21: =I21&K21 -> 16Sênior | M21: =IFERROR(VLOOKUP(B21,'Folha de Pagamento'!B:K,10,0),"") -> 5213 | N21: =IFERROR(VLOOKUP(L21,Pesquisa!$D:$L,4,0),"") -> 4882.37 | O21: =IFERROR(VLOOKUP(L21,Pesquisa!$D:$L,5,0),"") -> 5489.27 | P21: =IFERROR(VLOOKUP(L21,Pesquisa!$D:$L,6,0),"") -> 6172.24 | Q21: =IFERROR(VLOOKUP(L21,Pesquisa!$D:$L,7,0),"") -> 5910.71 | R21: =IFERROR(VLOOKUP(L21,Pesquisa!$D:$L,8,0),"") -> 6737.39 | S21: =IFERROR(VLOOKUP(L21,Pesquisa!$D:$L,9,0),"") -> 8185.08 | T21: =IFS('Painel Geral'!$B$5="Mediana",IFERROR(IF(OR(M21="",Q21=0,Q21=""),"",($M21/$Q21)),""),'Painel Geral'!$B$5="Menor Salário",IFERROR(IF(OR(M21="",Q21=0,Q21=""),"",($M21/$N21)),""),'Painel Geral'!$B$5="1º Quartil",IFERROR(IF(OR(M21="",Q21=0,Q21=""),"",($M21/$O21)),""),'Painel Geral'!$B$5="Média",IFERROR(IF(OR(M21="",Q21=0,Q21=""),"",($M21/$P21)),""),'Painel Geral'!$B$5="3º Quartil",IFERROR(IF(OR(M21="",Q21=0,Q21=""),"",($M21/$R21)),""),'Painel Geral'!$B$5="Maior Salário",IFERROR(IF(OR(M21="",Q21=0,Q21=""),"",($M21/$S21)),"")) -> 0.88195834 | U21: =IFS(OR(N21="",N21=0,M21="", M21=0),"",T21<=80%,"Muito Defasado",T21<=90%,"Defasado",T21<=100%,"Na Média",T21<=110%,"Na Média",T21<=120%,"Muito Competitivo",T21>120%,"Agressivo") -> Defasado | V21: =VLOOKUP(A21,'Cálculos Comparativos'!$A:$E,4,0) -> 6
A22: 31 | B22: PJ5 | C22: =VLOOKUP(A22,Jobmatch!A:F,2,0) -> COORDENADOR DE SUPRIMENTOS | D22: =VLOOKUP(B22,'Folha de Pagamento'!B:G,6,0) -> Suprimentos | E22: =VLOOKUP(A22,Jobmatch!A:F,4,0) -> 38 - ADM PROJETOS | F22: =VLOOKUP(A22,Jobmatch!A:F,5,0) -> Tático | G22: =VLOOKUP(B22,'Folha de Pagamento'!B:O,13,0) -> Feminino | H22: =(TODAY()-G22)/365 -> #VALUE! | I22: =VLOOKUP(A22,Jobmatch!A:G,6,0) -> 137 | J22: =VLOOKUP(A22,Jobmatch!A:H,7,0) -> Coordenador de Compras | K22: =VLOOKUP(A22,Jobmatch!A:I,8,0) -> Indiferente | L22: =I22&K22 -> 137Indiferente | M22: =IFERROR(VLOOKUP(B22,'Folha de Pagamento'!B:K,10,0),"") -> 10596.026 | N22: =IFERROR(VLOOKUP(L22,Pesquisa!$D:$L,4,0),"") -> 5608.9635 | O22: =IFERROR(VLOOKUP(L22,Pesquisa!$D:$L,5,0),"") -> 9662.3485 | P22: =IFERROR(VLOOKUP(L22,Pesquisa!$D:$L,6,0),"") -> 10653.144 | Q22: =IFERROR(VLOOKUP(L22,Pesquisa!$D:$L,7,0),"") -> 11847.831 | R22: =IFERROR(VLOOKUP(L22,Pesquisa!$D:$L,8,0),"") -> 12838.627 | S22: =IFERROR(VLOOKUP(L22,Pesquisa!$D:$L,9,0),"") -> 13307.951 | T22: =IFS('Painel Geral'!$B$5="Mediana",IFERROR(IF(OR(M22="",Q22=0,Q22=""),"",($M22/$Q22)),""),'Painel Geral'!$B$5="Menor Salário",IFERROR(IF(OR(M22="",Q22=0,Q22=""),"",($M22/$N22)),""),'Painel Geral'!$B$5="1º Quartil",IFERROR(IF(OR(M22="",Q22=0,Q22=""),"",($M22/$O22)),""),'Painel Geral'!$B$5="Média",IFERROR(IF(OR(M22="",Q22=0,Q22=""),"",($M22/$P22)),""),'Painel Geral'!$B$5="3º Quartil",IFERROR(IF(OR(M22="",Q22=0,Q22=""),"",($M22/$R22)),""),'Painel Geral'!$B$5="Maior Salário",IFERROR(IF(OR(M22="",Q22=0,Q22=""),"",($M22/$S22)),"")) -> 0.89434314 | U22: =IFS(OR(N22="",N22=0,M22="", M22=0),"",T22<=80%,"Muito Defasado",T22<=90%,"Defasado",T22<=100%,"Na Média",T22<=110%,"Na Média",T22<=120%,"Muito Competitivo",T22>120%,"Agressivo") -> Defasado | V22: =VLOOKUP(A22,'Cálculos Comparativos'!$A:$E,4,0) -> 1
A23: 15 | B23: 1963 | C23: =VLOOKUP(A23,Jobmatch!A:F,2,0) -> ASSISTENTE DE ENGENHARIA lll | D23: =VLOOKUP(B23,'Folha de Pagamento'!B:G,6,0) -> Edificação | E23: =VLOOKUP(A23,Jobmatch!A:F,4,0) -> 22 - ADM PROJETOS | F23: =VLOOKUP(A23,Jobmatch!A:F,5,0) -> Operacional | G23: =VLOOKUP(B23,'Folha de Pagamento'!B:O,13,0) -> Feminino | H23: =(TODAY()-G23)/365 -> #VALUE! | I23: =VLOOKUP(A23,Jobmatch!A:G,6,0) -> 531 | J23: =VLOOKUP(A23,Jobmatch!A:H,7,0) -> Assistente de Engenharia | K23: =VLOOKUP(A23,Jobmatch!A:I,8,0) -> Indiferente | L23: =I23&K23 -> 531Indiferente | M23: =IFERROR(VLOOKUP(B23,'Folha de Pagamento'!B:K,10,0),"") -> 3652 | N23: =IFERROR(VLOOKUP(L23,Pesquisa!$D:$L,4,0),"") -> 3154.02 | O23: =IFERROR(VLOOKUP(L23,Pesquisa!$D:$L,5,0),"") -> 3954.91 | P23: =IFERROR(VLOOKUP(L23,Pesquisa!$D:$L,6,0),"") -> 4041.52 | Q23: =IFERROR(VLOOKUP(L23,Pesquisa!$D:$L,7,0),"") -> 3954.91 | R23: =IFERROR(VLOOKUP(L23,Pesquisa!$D:$L,8,0),"") -> 3954.91 | S23: =IFERROR(VLOOKUP(L23,Pesquisa!$D:$L,9,0),"") -> 5097.17 | T23: =IFS('Painel Geral'!$B$5="Mediana",IFERROR(IF(OR(M23="",Q23=0,Q23=""),"",($M23/$Q23)),""),'Painel Geral'!$B$5="Menor Salário",IFERROR(IF(OR(M23="",Q23=0,Q23=""),"",($M23/$N23)),""),'Painel Geral'!$B$5="1º Quartil",IFERROR(IF(OR(M23="",Q23=0,Q23=""),"",($M23/$O23)),""),'Painel Geral'!$B$5="Média",IFERROR(IF(OR(M23="",Q23=0,Q23=""),"",($M23/$P23)),""),'Painel Geral'!$B$5="3º Quartil",IFERROR(IF(OR(M23="",Q23=0,Q23=""),"",($M23/$R23)),""),'Painel Geral'!$B$5="Maior Salário",IFERROR(IF(OR(M23="",Q23=0,Q23=""),"",($M23/$S23)),"")) -> 0.92340913 | U23: =IFS(OR(N23="",N23=0,M23="", M23=0),"",T23<=80%,"Muito Defasado",T23<=90%,"Defasado",T23<=100%,"Na Média",T23<=110%,"Na Média",T23<=120%,"Muito Competitivo",T23>120%,"Agressivo") -> Na Média | V23: =VLOOKUP(A23,'Cálculos Comparativos'!$A:$E,4,0) -> 5
A24: 40 | B24: E04 | C24: =VLOOKUP(A24,Jobmatch!A:F,2,0) -> ESTAGIARIO(A) ENG. CIVIL | D24: =VLOOKUP(B24,'Folha de Pagamento'!B:G,6,0) -> Urbanismo | E24: =VLOOKUP(A24,Jobmatch!A:F,4,0) -> 47 - ADM PROJETOS | F24: =VLOOKUP(A24,Jobmatch!A:F,5,0) -> Operacional | G24: =VLOOKUP(B24,'Folha de Pagamento'!B:O,13,0) -> Feminino | H24: =(TODAY()-G24)/365 -> #VALUE! | I24: =VLOOKUP(A24,Jobmatch!A:G,6,0) -> 1204 | J24: =VLOOKUP(A24,Jobmatch!A:H,7,0) -> Estagiário de Engenharia Civil | K24: =VLOOKUP(A24,Jobmatch!A:I,8,0) -> Indiferente | L24: =I24&K24 -> 1204Indiferente | M24: =IFERROR(VLOOKUP(B24,'Folha de Pagamento'!B:K,10,0),"") -> 1521 | N24: =IFERROR(VLOOKUP(L24,Pesquisa!$D:$L,4,0),"") -> 1511.85 | O24: =IFERROR(VLOOKUP(L24,Pesquisa!$D:$L,5,0),"") -> 1564.2608 | P24: =IFERROR(VLOOKUP(L24,Pesquisa!$D:$L,6,0),"") -> 1711.5102 | Q24: =IFERROR(VLOOKUP(L24,Pesquisa!$D:$L,7,0),"") -> 1637.8375 | R24: =IFERROR(VLOOKUP(L24,Pesquisa!$D:$L,8,0),"") -> 1814.22 | S24: =IFERROR(VLOOKUP(L24,Pesquisa!$D:$L,9,0),"") -> 2267.775 | T24: =IFS('Painel Geral'!$B$5="Mediana",IFERROR(IF(OR(M24="",Q24=0,Q24=""),"",($M24/$Q24)),""),'Painel Geral'!$B$5="Menor Salário",IFERROR(IF(OR(M24="",Q24=0,Q24=""),"",($M24/$N24)),""),'Painel Geral'!$B$5="1º Quartil",IFERROR(IF(OR(M24="",Q24=0,Q24=""),"",($M24/$O24)),""),'Painel Geral'!$B$5="Média",IFERROR(IF(OR(M24="",Q24=0,Q24=""),"",($M24/$P24)),""),'Painel Geral'!$B$5="3º Quartil",IFERROR(IF(OR(M24="",Q24=0,Q24=""),"",($M24/$R24)),""),'Painel Geral'!$B$5="Maior Salário",IFERROR(IF(OR(M24="",Q24=0,Q24=""),"",($M24/$S24)),"")) -> 0.92866356 | U24: =IFS(OR(N24="",N24=0,M24="", M24=0),"",T24<=80%,"Muito Defasado",T24<=90%,"Defasado",T24<=100%,"Na Média",T24<=110%,"Na Média",T24<=120%,"Muito Competitivo",T24>120%,"Agressivo") -> Na Média | V24: =VLOOKUP(A24,'Cálculos Comparativos'!$A:$E,4,0) -> 10
A25: 23 | B25: 191 | C25: =VLOOKUP(A25,Jobmatch!A:F,2,0) -> AUXILIAR DE ENGENHARIA | D25: =VLOOKUP(B25,'Folha de Pagamento'!B:G,6,0) -> Urbanismo | E25: =VLOOKUP(A25,Jobmatch!A:F,4,0) -> 30 - ADM PROJETOS | F25: =VLOOKUP(A25,Jobmatch!A:F,5,0) -> Operacional | G25: =VLOOKUP(B25,'Folha de Pagamento'!B:O,13,0) -> Masculino | H25: =(TODAY()-G25)/365 -> #VALUE! | I25: =VLOOKUP(A25,Jobmatch!A:G,6,0) -> 207 | J25: =VLOOKUP(A25,Jobmatch!A:H,7,0) -> Auxiliar de Engenharia | K25: =VLOOKUP(A25,Jobmatch!A:I,8,0) -> Indiferente | L25: =I25&K25 -> 207Indiferente | M25: =IFERROR(VLOOKUP(B25,'Folha de Pagamento'!B:K,10,0),"") -> 2560 | N25: =IFERROR(VLOOKUP(L25,Pesquisa!$D:$L,4,0),"") -> 2580.26 | O25: =IFERROR(VLOOKUP(L25,Pesquisa!$D:$L,5,0),"") -> 2650.82 | P25: =IFERROR(VLOOKUP(L25,Pesquisa!$D:$L,6,0),"") -> 2825.85 | Q25: =IFERROR(VLOOKUP(L25,Pesquisa!$D:$L,7,0),"") -> 2721.37 | R25: =IFERROR(VLOOKUP(L25,Pesquisa!$D:$L,8,0),"") -> 2948.64 | S25: =IFERROR(VLOOKUP(L25,Pesquisa!$D:$L,9,0),"") -> 3175.91 | T25: =IFS('Painel Geral'!$B$5="Mediana",IFERROR(IF(OR(M25="",Q25=0,Q25=""),"",($M25/$Q25)),""),'Painel Geral'!$B$5="Menor Salário",IFERROR(IF(OR(M25="",Q25=0,Q25=""),"",($M25/$N25)),""),'Painel Geral'!$B$5="1º Quartil",IFERROR(IF(OR(M25="",Q25=0,Q25=""),"",($M25/$O25)),""),'Painel Geral'!$B$5="Média",IFERROR(IF(OR(M25="",Q25=0,Q25=""),"",($M25/$P25)),""),'Painel Geral'!$B$5="3º Quartil",IFERROR(IF(OR(M25="",Q25=0,Q25=""),"",($M25/$R25)),""),'Painel Geral'!$B$5="Maior Salário",IFERROR(IF(OR(M25="",Q25=0,Q25=""),"",($M25/$S25)),"")) -> 0.94070266 | U25: =IFS(OR(N25="",N25=0,M25="", M25=0),"",T25<=80%,"Muito Defasado",T25<=90%,"Defasado",T25<=100%,"Na Média",T25<=110%,"Na Média",T25<=120%,"Muito Competitivo",T25>120%,"Agressivo") -> Na Média | V25: =VLOOKUP(A25,'Cálculos Comparativos'!$A:$E,4,0) -> 10
A26: 17 | B26: 189 | C26: =VLOOKUP(A26,Jobmatch!A:F,2,0) -> ASSISTENTE DE RECURSOS HUMANOS | D26: =VLOOKUP(B26,'Folha de Pagamento'!B:G,6,0) -> DHO | E26: =VLOOKUP(A26,Jobmatch!A:F,4,0) -> 24 - ADM PROJETOS | F26: =VLOOKUP(A26,Jobmatch!A:F,5,0) -> Operacional | G26: =VLOOKUP(B26,'Folha de Pagamento'!B:O,13,0) -> Feminino | H26: =(TODAY()-G26)/365 -> #VALUE! | I26: =VLOOKUP(A26,Jobmatch!A:G,6,0) -> 77 | J26: =VLOOKUP(A26,Jobmatch!A:H,7,0) -> Assistente de Recursos Humanos | K26: =VLOOKUP(A26,Jobmatch!A:I,8,0) -> Indiferente | L26: =I26&K26 -> 77Indiferente | M26: =IFERROR(VLOOKUP(B26,'Folha de Pagamento'!B:K,10,0),"") -> 2919 | N26: =IFERROR(VLOOKUP(L26,Pesquisa!$D:$L,4,0),"") -> 2259.75 | O26: =IFERROR(VLOOKUP(L26,Pesquisa!$D:$L,5,0),"") -> 2625.37 | P26: =IFERROR(VLOOKUP(L26,Pesquisa!$D:$L,6,0),"") -> 3105.32 | Q26: =IFERROR(VLOOKUP(L26,Pesquisa!$D:$L,7,0),"") -> 3087.62 | R26: =IFERROR(VLOOKUP(L26,Pesquisa!$D:$L,8,0),"") -> 3499.72 | S26: =IFERROR(VLOOKUP(L26,Pesquisa!$D:$L,9,0),"") -> 4088.57 | T26: =IFS('Painel Geral'!$B$5="Mediana",IFERROR(IF(OR(M26="",Q26=0,Q26=""),"",($M26/$Q26)),""),'Painel Geral'!$B$5="Menor Salário",IFERROR(IF(OR(M26="",Q26=0,Q26=""),"",($M26/$N26)),""),'Painel Geral'!$B$5="1º Quartil",IFERROR(IF(OR(M26="",Q26=0,Q26=""),"",($M26/$O26)),""),'Painel Geral'!$B$5="Média",IFERROR(IF(OR(M26="",Q26=0,Q26=""),"",($M26/$P26)),""),'Painel Geral'!$B$5="3º Quartil",IFERROR(IF(OR(M26="",Q26=0,Q26=""),"",($M26/$R26)),""),'Painel Geral'!$B$5="Maior Salário",IFERROR(IF(OR(M26="",Q26=0,Q26=""),"",($M26/$S26)),"")) -> 0.94538836 | U26: =IFS(OR(N26="",N26=0,M26="", M26=0),"",T26<=80%,"Muito Defasado",T26<=90%,"Defasado",T26<=100%,"Na Média",T26<=110%,"Na Média",T26<=120%,"Muito Competitivo",T26>120%,"Agressivo") -> Na Média | V26: =VLOOKUP(A26,'Cálculos Comparativos'!$A:$E,4,0) -> 4
A27: 37 | B27: PJ9 | C27: =VLOOKUP(A27,Jobmatch!A:F,2,0) -> ENGENHEIRO SÊNIOR | D27: =VLOOKUP(B27,'Folha de Pagamento'!B:G,6,0) -> Edificação | E27: =VLOOKUP(A27,Jobmatch!A:F,4,0) -> 44 - ADM PROJETOS | F27: =VLOOKUP(A27,Jobmatch!A:F,5,0) -> Tático | G27: =VLOOKUP(B27,'Folha de Pagamento'!B:O,13,0) -> Feminino | H27: =(TODAY()-G27)/365 -> #VALUE! | I27: =VLOOKUP(A27,Jobmatch!A:G,6,0) -> 212 | J27: =VLOOKUP(A27,Jobmatch!A:H,7,0) -> Engenheiro de Urbanismo | K27: =VLOOKUP(A27,Jobmatch!A:I,8,0) -> Indiferente | L27: =I27&K27 -> 212Indiferente | M27: =IFERROR(VLOOKUP(B27,'Folha de Pagamento'!B:K,10,0),"") -> 14393.939 | N27: =IFERROR(VLOOKUP(L27,Pesquisa!$D:$L,4,0),"") -> 13744.09 | O27: =IFERROR(VLOOKUP(L27,Pesquisa!$D:$L,5,0),"") -> 14781.36 | P27: =IFERROR(VLOOKUP(L27,Pesquisa!$D:$L,6,0),"") -> 15210.85 | Q27: =IFERROR(VLOOKUP(L27,Pesquisa!$D:$L,7,0),"") -> 15118.5 | R27: =IFERROR(VLOOKUP(L27,Pesquisa!$D:$L,8,0),"") -> 16203.19 | S27: =IFERROR(VLOOKUP(L27,Pesquisa!$D:$L,9,0),"") -> 16203.19 | T27: =IFS('Painel Geral'!$B$5="Mediana",IFERROR(IF(OR(M27="",Q27=0,Q27=""),"",($M27/$Q27)),""),'Painel Geral'!$B$5="Menor Salário",IFERROR(IF(OR(M27="",Q27=0,Q27=""),"",($M27/$N27)),""),'Painel Geral'!$B$5="1º Quartil",IFERROR(IF(OR(M27="",Q27=0,Q27=""),"",($M27/$O27)),""),'Painel Geral'!$B$5="Média",IFERROR(IF(OR(M27="",Q27=0,Q27=""),"",($M27/$P27)),""),'Painel Geral'!$B$5="3º Quartil",IFERROR(IF(OR(M27="",Q27=0,Q27=""),"",($M27/$R27)),""),'Painel Geral'!$B$5="Maior Salário",IFERROR(IF(OR(M27="",Q27=0,Q27=""),"",($M27/$S27)),"")) -> 0.95207457 | U27: =IFS(OR(N27="",N27=0,M27="", M27=0),"",T27<=80%,"Muito Defasado",T27<=90%,"Defasado",T27<=100%,"Na Média",T27<=110%,"Na Média",T27<=120%,"Muito Competitivo",T27>120%,"Agressivo") -> Na Média | V27: =VLOOKUP(A27,'Cálculos Comparativos'!$A:$E,4,0) -> 5
A28: 53 | B28: PJ22 | C28: =VLOOKUP(A28,Jobmatch!A:F,2,0) -> TECNICO ANALISTA DE CUSTOS | D28: =VLOOKUP(B28,'Folha de Pagamento'!B:G,6,0) -> Edificação | E28: =VLOOKUP(A28,Jobmatch!A:F,4,0) -> 60 - ADM PROJETOS | F28: =VLOOKUP(A28,Jobmatch!A:F,5,0) -> Operacional | G28: =VLOOKUP(B28,'Folha de Pagamento'!B:O,13,0) -> Masculino | H28: =(TODAY()-G28)/365 -> #VALUE! | I28: =VLOOKUP(A28,Jobmatch!A:G,6,0) -> 876 | J28: =VLOOKUP(A28,Jobmatch!A:H,7,0) -> Analista de Custos | K28: =VLOOKUP(A28,Jobmatch!A:I,8,0) -> Indiferente | L28: =I28&K28 -> 876Indiferente | M28: =IFERROR(VLOOKUP(B28,'Folha de Pagamento'!B:K,10,0),"") -> 7000 | N28: =IFERROR(VLOOKUP(L28,Pesquisa!$D:$L,4,0),"") -> 6769.16 | O28: =IFERROR(VLOOKUP(L28,Pesquisa!$D:$L,5,0),"") -> 6884.72 | P28: =IFERROR(VLOOKUP(L28,Pesquisa!$D:$L,6,0),"") -> 7629.52 | Q28: =IFERROR(VLOOKUP(L28,Pesquisa!$D:$L,7,0),"") -> 7338.33 | R28: =IFERROR(VLOOKUP(L28,Pesquisa!$D:$L,8,0),"") -> 8173.29 | S28: =IFERROR(VLOOKUP(L28,Pesquisa!$D:$L,9,0),"") -> 9183.14 | T28: =IFS('Painel Geral'!$B$5="Mediana",IFERROR(IF(OR(M28="",Q28=0,Q28=""),"",($M28/$Q28)),""),'Painel Geral'!$B$5="Menor Salário",IFERROR(IF(OR(M28="",Q28=0,Q28=""),"",($M28/$N28)),""),'Painel Geral'!$B$5="1º Quartil",IFERROR(IF(OR(M28="",Q28=0,Q28=""),"",($M28/$O28)),""),'Painel Geral'!$B$5="Média",IFERROR(IF(OR(M28="",Q28=0,Q28=""),"",($M28/$P28)),""),'Painel Geral'!$B$5="3º Quartil",IFERROR(IF(OR(M28="",Q28=0,Q28=""),"",($M28/$R28)),""),'Painel Geral'!$B$5="Maior Salário",IFERROR(IF(OR(M28="",Q28=0,Q28=""),"",($M28/$S28)),"")) -> 0.9538955 | U28: =IFS(OR(N28="",N28=0,M28="", M28=0),"",T28<=80%,"Muito Defasado",T28<=90%,"Defasado",T28<=100%,"Na Média",T28<=110%,"Na Média",T28<=120%,"Muito Competitivo",T28>120%,"Agressivo") -> Na Média | V28: =VLOOKUP(A28,'Cálculos Comparativos'!$A:$E,4,0) -> 5
A29: 27 | B29: 1959 | C29: =VLOOKUP(A29,Jobmatch!A:F,2,0) -> COORDENADOR DE DHO | D29: =VLOOKUP(B29,'Folha de Pagamento'!B:G,6,0) -> DHO | E29: =VLOOKUP(A29,Jobmatch!A:F,4,0) -> 34 - ADM PROJETOS | F29: =VLOOKUP(A29,Jobmatch!A:F,5,0) -> Tático | G29: =VLOOKUP(B29,'Folha de Pagamento'!B:O,13,0) -> Feminino | H29: =(TODAY()-G29)/365 -> #VALUE! | I29: =VLOOKUP(A29,Jobmatch!A:G,6,0) -> 121 | J29: =VLOOKUP(A29,Jobmatch!A:H,7,0) -> Coordenador de Recursos Humanos | K29: =VLOOKUP(A29,Jobmatch!A:I,8,0) -> Indiferente | L29: =I29&K29 -> 121Indiferente | M29: =IFERROR(VLOOKUP(B29,'Folha de Pagamento'!B:K,10,0),"") -> 7420 | N29: =IFERROR(VLOOKUP(L29,Pesquisa!$D:$L,4,0),"") -> 4599.27 | O29: =IFERROR(VLOOKUP(L29,Pesquisa!$D:$L,5,0),"") -> 6690.07 | P29: =IFERROR(VLOOKUP(L29,Pesquisa!$D:$L,6,0),"") -> 8176.91 | Q29: =IFERROR(VLOOKUP(L29,Pesquisa!$D:$L,7,0),"") -> 7778.54 | R29: =IFERROR(VLOOKUP(L29,Pesquisa!$D:$L,8,0),"") -> 9253.45 | S29: =IFERROR(VLOOKUP(L29,Pesquisa!$D:$L,9,0),"") -> 17073.05 | T29: =IFS('Painel Geral'!$B$5="Mediana",IFERROR(IF(OR(M29="",Q29=0,Q29=""),"",($M29/$Q29)),""),'Painel Geral'!$B$5="Menor Salário",IFERROR(IF(OR(M29="",Q29=0,Q29=""),"",($M29/$N29)),""),'Painel Geral'!$B$5="1º Quartil",IFERROR(IF(OR(M29="",Q29=0,Q29=""),"",($M29/$O29)),""),'Painel Geral'!$B$5="Média",IFERROR(IF(OR(M29="",Q29=0,Q29=""),"",($M29/$P29)),""),'Painel Geral'!$B$5="3º Quartil",IFERROR(IF(OR(M29="",Q29=0,Q29=""),"",($M29/$R29)),""),'Painel Geral'!$B$5="Maior Salário",IFERROR(IF(OR(M29="",Q29=0,Q29=""),"",($M29/$S29)),"")) -> 0.95390652 | U29: =IFS(OR(N29="",N29=0,M29="", M29=0),"",T29<=80%,"Muito Defasado",T29<=90%,"Defasado",T29<=100%,"Na Média",T29<=110%,"Na Média",T29<=120%,"Muito Competitivo",T29>120%,"Agressivo") -> Na Média | V29: =VLOOKUP(A29,'Cálculos Comparativos'!$A:$E,4,0) -> 4
A30: 52 | B30: 186 | C30: =VLOOKUP(A30,Jobmatch!A:F,2,0) -> SUPERVISOR(A) FINANCEIRO I | D30: =VLOOKUP(B30,'Folha de Pagamento'!B:G,6,0) -> Financeiro | E30: =VLOOKUP(A30,Jobmatch!A:F,4,0) -> 59 - ADM PROJETOS | F30: =VLOOKUP(A30,Jobmatch!A:F,5,0) -> Operacional | G30: =VLOOKUP(B30,'Folha de Pagamento'!B:O,13,0) -> Feminino | H30: =(TODAY()-G30)/365 -> #VALUE! | I30: =VLOOKUP(A30,Jobmatch!A:G,6,0) -> 469 | J30: =VLOOKUP(A30,Jobmatch!A:H,7,0) -> Supervisor Financeiro | K30: =VLOOKUP(A30,Jobmatch!A:I,8,0) -> Indiferente | L30: =I30&K30 -> 469Indiferente | M30: =IFERROR(VLOOKUP(B30,'Folha de Pagamento'!B:K,10,0),"") -> 5955.08 | N30: =IFERROR(VLOOKUP(L30,Pesquisa!$D:$L,4,0),"") -> 4254.14 | O30: =IFERROR(VLOOKUP(L30,Pesquisa!$D:$L,5,0),"") -> 5291.84 | P30: =IFERROR(VLOOKUP(L30,Pesquisa!$D:$L,6,0),"") -> 6690.95 | Q30: =IFERROR(VLOOKUP(L30,Pesquisa!$D:$L,7,0),"") -> 6196.82 | R30: =IFERROR(VLOOKUP(L30,Pesquisa!$D:$L,8,0),"") -> 8126.61 | S30: =IFERROR(VLOOKUP(L30,Pesquisa!$D:$L,9,0),"") -> 9844.29 | T30: =IFS('Painel Geral'!$B$5="Mediana",IFERROR(IF(OR(M30="",Q30=0,Q30=""),"",($M30/$Q30)),""),'Painel Geral'!$B$5="Menor Salário",IFERROR(IF(OR(M30="",Q30=0,Q30=""),"",($M30/$N30)),""),'Painel Geral'!$B$5="1º Quartil",IFERROR(IF(OR(M30="",Q30=0,Q30=""),"",($M30/$O30)),""),'Painel Geral'!$B$5="Média",IFERROR(IF(OR(M30="",Q30=0,Q30=""),"",($M30/$P30)),""),'Painel Geral'!$B$5="3º Quartil",IFERROR(IF(OR(M30="",Q30=0,Q30=""),"",($M30/$R30)),""),'Painel Geral'!$B$5="Maior Salário",IFERROR(IF(OR(M30="",Q30=0,Q30=""),"",($M30/$S30)),"")) -> 0.96098967 | U30: =IFS(OR(N30="",N30=0,M30="", M30=0),"",T30<=80%,"Muito Defasado",T30<=90%,"Defasado",T30<=100%,"Na Média",T30<=110%,"Na Média",T30<=120%,"Muito Competitivo",T30>120%,"Agressivo") -> Na Média | V30: =VLOOKUP(A30,'Cálculos Comparativos'!$A:$E,4,0) -> 6
A31: 28 | B31: 151 | C31: =VLOOKUP(A31,Jobmatch!A:F,2,0) -> COORDENADOR DE LEGAIZAÇÃO ll | D31: =VLOOKUP(B31,'Folha de Pagamento'!B:G,6,0) -> Legalização | E31: =VLOOKUP(A31,Jobmatch!A:F,4,0) -> 35 - ADM PROJETOS | F31: =VLOOKUP(A31,Jobmatch!A:F,5,0) -> Tático | G31: =VLOOKUP(B31,'Folha de Pagamento'!B:O,13,0) -> Masculino | H31: =(TODAY()-G31)/365 -> #VALUE! | I31: =VLOOKUP(A31,Jobmatch!A:G,6,0) -> 1203 | J31: =VLOOKUP(A31,Jobmatch!A:H,7,0) -> Coordenador de Legalização | K31: =VLOOKUP(A31,Jobmatch!A:I,8,0) -> Indiferente | L31: =I31&K31 -> 1203Indiferente | M31: =IFERROR(VLOOKUP(B31,'Folha de Pagamento'!B:K,10,0),"") -> 8647 | N31: =IFERROR(VLOOKUP(L31,Pesquisa!$D:$L,4,0),"") -> 8694.57 | O31: =IFERROR(VLOOKUP(L31,Pesquisa!$D:$L,5,0),"") -> 8783.31 | P31: =IFERROR(VLOOKUP(L31,Pesquisa!$D:$L,6,0),"") -> 8872.04 | Q31: =IFERROR(VLOOKUP(L31,Pesquisa!$D:$L,7,0),"") -> 8872.04 | R31: =IFERROR(VLOOKUP(L31,Pesquisa!$D:$L,8,0),"") -> 8960.78 | S31: =IFERROR(VLOOKUP(L31,Pesquisa!$D:$L,9,0),"") -> 9049.51 | T31: =IFS('Painel Geral'!$B$5="Mediana",IFERROR(IF(OR(M31="",Q31=0,Q31=""),"",($M31/$Q31)),""),'Painel Geral'!$B$5="Menor Salário",IFERROR(IF(OR(M31="",Q31=0,Q31=""),"",($M31/$N31)),""),'Painel Geral'!$B$5="1º Quartil",IFERROR(IF(OR(M31="",Q31=0,Q31=""),"",($M31/$O31)),""),'Painel Geral'!$B$5="Média",IFERROR(IF(OR(M31="",Q31=0,Q31=""),"",($M31/$P31)),""),'Painel Geral'!$B$5="3º Quartil",IFERROR(IF(OR(M31="",Q31=0,Q31=""),"",($M31/$R31)),""),'Painel Geral'!$B$5="Maior Salário",IFERROR(IF(OR(M31="",Q31=0,Q31=""),"",($M31/$S31)),"")) -> 0.97463492 | U31: =IFS(OR(N31="",N31=0,M31="", M31=0),"",T31<=80%,"Muito Defasado",T31<=90%,"Defasado",T31<=100%,"Na Média",T31<=110%,"Na Média",T31<=120%,"Muito Competitivo",T31>120%,"Agressivo") -> Na Média | V31: =VLOOKUP(A31,'Cálculos Comparativos'!$A:$E,4,0) -> 7
A32: 20 | B32: 1961 | C32: =VLOOKUP(A32,Jobmatch!A:F,2,0) -> AUXILIAR ADMINISTRATIVO | D32: =VLOOKUP(B32,'Folha de Pagamento'!B:G,6,0) -> Administrativo | E32: =VLOOKUP(A32,Jobmatch!A:F,4,0) -> 27 - ADM PROJETOS | F32: =VLOOKUP(A32,Jobmatch!A:F,5,0) -> Operacional | G32: =VLOOKUP(B32,'Folha de Pagamento'!B:O,13,0) -> Feminino | H32: =(TODAY()-G32)/365 -> #VALUE! | I32: =VLOOKUP(A32,Jobmatch!A:G,6,0) -> 83 | J32: =VLOOKUP(A32,Jobmatch!A:H,7,0) -> Auxiliar Administrativo | K32: =VLOOKUP(A32,Jobmatch!A:I,8,0) -> Indiferente | L32: =I32&K32 -> 83Indiferente | M32: =IFERROR(VLOOKUP(B32,'Folha de Pagamento'!B:K,10,0),"") -> 2254 | N32: =IFERROR(VLOOKUP(L32,Pesquisa!$D:$L,4,0),"") -> 1771.74 | O32: =IFERROR(VLOOKUP(L32,Pesquisa!$D:$L,5,0),"") -> 2128.74 | P32: =IFERROR(VLOOKUP(L32,Pesquisa!$D:$L,6,0),"") -> 2292.87 | Q32: =IFERROR(VLOOKUP(L32,Pesquisa!$D:$L,7,0),"") -> 2309.71 | R32: =IFERROR(VLOOKUP(L32,Pesquisa!$D:$L,8,0),"") -> 2375.14 | S32: =IFERROR(VLOOKUP(L32,Pesquisa!$D:$L,9,0),"") -> 3073.32 | T32: =IFS('Painel Geral'!$B$5="Mediana",IFERROR(IF(OR(M32="",Q32=0,Q32=""),"",($M32/$Q32)),""),'Painel Geral'!$B$5="Menor Salário",IFERROR(IF(OR(M32="",Q32=0,Q32=""),"",($M32/$N32)),""),'Painel Geral'!$B$5="1º Quartil",IFERROR(IF(OR(M32="",Q32=0,Q32=""),"",($M32/$O32)),""),'Painel Geral'!$B$5="Média",IFERROR(IF(OR(M32="",Q32=0,Q32=""),"",($M32/$P32)),""),'Painel Geral'!$B$5="3º Quartil",IFERROR(IF(OR(M32="",Q32=0,Q32=""),"",($M32/$R32)),""),'Painel Geral'!$B$5="Maior Salário",IFERROR(IF(OR(M32="",Q32=0,Q32=""),"",($M32/$S32)),"")) -> 0.97588009 | U32: =IFS(OR(N32="",N32=0,M32="", M32=0),"",T32<=80%,"Muito Defasado",T32<=90%,"Defasado",T32<=100%,"Na Média",T32<=110%,"Na Média",T32<=120%,"Muito Competitivo",T32>120%,"Agressivo") -> Na Média | V32: =VLOOKUP(A32,'Cálculos Comparativos'!$A:$E,4,0) -> 1
A33: 32 | B33: PJ6 | C33: =VLOOKUP(A33,Jobmatch!A:F,2,0) -> COORDENADOR FINANCEIRO | D33: =VLOOKUP(B33,'Folha de Pagamento'!B:G,6,0) -> Financeiro | E33: =VLOOKUP(A33,Jobmatch!A:F,4,0) -> 39 - ADM PROJETOS | F33: =VLOOKUP(A33,Jobmatch!A:F,5,0) -> Tático | G33: =VLOOKUP(B33,'Folha de Pagamento'!B:O,13,0) -> Masculino | H33: =(TODAY()-G33)/365 -> #VALUE! | I33: =VLOOKUP(A33,Jobmatch!A:G,6,0) -> 122 | J33: =VLOOKUP(A33,Jobmatch!A:H,7,0) -> Coordenador Financeiro | K33: =VLOOKUP(A33,Jobmatch!A:I,8,0) -> Indiferente | L33: =I33&K33 -> 122Indiferente | M33: =IFERROR(VLOOKUP(B33,'Folha de Pagamento'!B:K,10,0),"") -> 7947.0199 | N33: =IFERROR(VLOOKUP(L33,Pesquisa!$D:$L,4,0),"") -> 6551.35 | O33: =IFERROR(VLOOKUP(L33,Pesquisa!$D:$L,5,0),"") -> 7801.2127 | P33: =IFERROR(VLOOKUP(L33,Pesquisa!$D:$L,6,0),"") -> 9247.2529 | Q33: =IFERROR(VLOOKUP(L33,Pesquisa!$D:$L,7,0),"") -> 8009.8013 | R33: =IFERROR(VLOOKUP(L33,Pesquisa!$D:$L,8,0),"") -> 10012.252 | S33: =IFERROR(VLOOKUP(L33,Pesquisa!$D:$L,9,0),"") -> 13861.649 | T33: =IFS('Painel Geral'!$B$5="Mediana",IFERROR(IF(OR(M33="",Q33=0,Q33=""),"",($M33/$Q33)),""),'Painel Geral'!$B$5="Menor Salário",IFERROR(IF(OR(M33="",Q33=0,Q33=""),"",($M33/$N33)),""),'Painel Geral'!$B$5="1º Quartil",IFERROR(IF(OR(M33="",Q33=0,Q33=""),"",($M33/$O33)),""),'Painel Geral'!$B$5="Média",IFERROR(IF(OR(M33="",Q33=0,Q33=""),"",($M33/$P33)),""),'Painel Geral'!$B$5="3º Quartil",IFERROR(IF(OR(M33="",Q33=0,Q33=""),"",($M33/$R33)),""),'Painel Geral'!$B$5="Maior Salário",IFERROR(IF(OR(M33="",Q33=0,Q33=""),"",($M33/$S33)),"")) -> 0.99216192 | U33: =IFS(OR(N33="",N33=0,M33="", M33=0),"",T33<=80%,"Muito Defasado",T33<=90%,"Defasado",T33<=100%,"Na Média",T33<=110%,"Na Média",T33<=120%,"Muito Competitivo",T33>120%,"Agressivo") -> Na Média | V33: =VLOOKUP(A33,'Cálculos Comparativos'!$A:$E,4,0) -> 6
A34: 43 | B34: PJ11 | C34: =VLOOKUP(A34,Jobmatch!A:F,2,0) -> GERENTE COMERCIAL | D34: =VLOOKUP(B34,'Folha de Pagamento'!B:G,6,0) -> Comercial | E34: =VLOOKUP(A34,Jobmatch!A:F,4,0) -> 50 - ADM PROJETOS | F34: =VLOOKUP(A34,Jobmatch!A:F,5,0) -> Tático | G34: =VLOOKUP(B34,'Folha de Pagamento'!B:O,13,0) -> Masculino | H34: =(TODAY()-G34)/365 -> #VALUE! | I34: =VLOOKUP(A34,Jobmatch!A:G,6,0) -> 107 | J34: =VLOOKUP(A34,Jobmatch!A:H,7,0) -> Gerente Comercial | K34: =VLOOKUP(A34,Jobmatch!A:I,8,0) -> Indiferente | L34: =I34&K34 -> 107Indiferente | M34: =IFERROR(VLOOKUP(B34,'Folha de Pagamento'!B:K,10,0),"") -> 12090.909 | N34: =IFERROR(VLOOKUP(L34,Pesquisa!$D:$L,4,0),"") -> 5570.67 | O34: =IFERROR(VLOOKUP(L34,Pesquisa!$D:$L,5,0),"") -> 9778.91 | P34: =IFERROR(VLOOKUP(L34,Pesquisa!$D:$L,6,0),"") -> 12281.04 | Q34: =IFERROR(VLOOKUP(L34,Pesquisa!$D:$L,7,0),"") -> 12107.57 | R34: =IFERROR(VLOOKUP(L34,Pesquisa!$D:$L,8,0),"") -> 15321.87 | S34: =IFERROR(VLOOKUP(L34,Pesquisa!$D:$L,9,0),"") -> 19289.48 | T34: =IFS('Painel Geral'!$B$5="Mediana",IFERROR(IF(OR(M34="",Q34=0,Q34=""),"",($M34/$Q34)),""),'Painel Geral'!$B$5="Menor Salário",IFERROR(IF(OR(M34="",Q34=0,Q34=""),"",($M34/$N34)),""),'Painel Geral'!$B$5="1º Quartil",IFERROR(IF(OR(M34="",Q34=0,Q34=""),"",($M34/$O34)),""),'Painel Geral'!$B$5="Média",IFERROR(IF(OR(M34="",Q34=0,Q34=""),"",($M34/$P34)),""),'Painel Geral'!$B$5="3º Quartil",IFERROR(IF(OR(M34="",Q34=0,Q34=""),"",($M34/$R34)),""),'Painel Geral'!$B$5="Maior Salário",IFERROR(IF(OR(M34="",Q34=0,Q34=""),"",($M34/$S34)),"")) -> 0.99862393 | U34: =IFS(OR(N34="",N34=0,M34="", M34=0),"",T34<=80%,"Muito Defasado",T34<=90%,"Defasado",T34<=100%,"Na Média",T34<=110%,"Na Média",T34<=120%,"Muito Competitivo",T34>120%,"Agressivo") -> Na Média | V34: =VLOOKUP(A34,'Cálculos Comparativos'!$A:$E,4,0) -> 2
A35: 16 | B35: 190 | C35: =VLOOKUP(A35,Jobmatch!A:F,2,0) -> ASSISTENTE DE MARKETING | D35: =VLOOKUP(B35,'Folha de Pagamento'!B:G,6,0) -> Marketing | E35: =VLOOKUP(A35,Jobmatch!A:F,4,0) -> 23 - ADM PROJETOS | F35: =VLOOKUP(A35,Jobmatch!A:F,5,0) -> Operacional | G35: =VLOOKUP(B35,'Folha de Pagamento'!B:O,13,0) -> Feminino | H35: =(TODAY()-G35)/365 -> #VALUE! | I35: =VLOOKUP(A35,Jobmatch!A:G,6,0) -> 71 | J35: =VLOOKUP(A35,Jobmatch!A:H,7,0) -> Assistente de Marketing | K35: =VLOOKUP(A35,Jobmatch!A:I,8,0) -> Indiferente | L35: =I35&K35 -> 71Indiferente | M35: =IFERROR(VLOOKUP(B35,'Folha de Pagamento'!B:K,10,0),"") -> 2919 | N35: =IFERROR(VLOOKUP(L35,Pesquisa!$D:$L,4,0),"") -> 2353.58 | O35: =IFERROR(VLOOKUP(L35,Pesquisa!$D:$L,5,0),"") -> 2726.74 | P35: =IFERROR(VLOOKUP(L35,Pesquisa!$D:$L,6,0),"") -> 3023.98 | Q35: =IFERROR(VLOOKUP(L35,Pesquisa!$D:$L,7,0),"") -> 2889.19 | R35: =IFERROR(VLOOKUP(L35,Pesquisa!$D:$L,8,0),"") -> 3160.38 | S35: =IFERROR(VLOOKUP(L35,Pesquisa!$D:$L,9,0),"") -> 4088.57 | T35: =IFS('Painel Geral'!$B$5="Mediana",IFERROR(IF(OR(M35="",Q35=0,Q35=""),"",($M35/$Q35)),""),'Painel Geral'!$B$5="Menor Salário",IFERROR(IF(OR(M35="",Q35=0,Q35=""),"",($M35/$N35)),""),'Painel Geral'!$B$5="1º Quartil",IFERROR(IF(OR(M35="",Q35=0,Q35=""),"",($M35/$O35)),""),'Painel Geral'!$B$5="Média",IFERROR(IF(OR(M35="",Q35=0,Q35=""),"",($M35/$P35)),""),'Painel Geral'!$B$5="3º Quartil",IFERROR(IF(OR(M35="",Q35=0,Q35=""),"",($M35/$R35)),""),'Painel Geral'!$B$5="Maior Salário",IFERROR(IF(OR(M35="",Q35=0,Q35=""),"",($M35/$S35)),"")) -> 1.0103178 | U35: =IFS(OR(N35="",N35=0,M35="", M35=0),"",T35<=80%,"Muito Defasado",T35<=90%,"Defasado",T35<=100%,"Na Média",T35<=110%,"Na Média",T35<=120%,"Muito Competitivo",T35>120%,"Agressivo") -> Na Média | V35: =VLOOKUP(A35,'Cálculos Comparativos'!$A:$E,4,0) -> 8
A36: 4 | B36: PJ1 | C36: =VLOOKUP(A36,Jobmatch!A:F,2,0) -> ANALISTA DE INOVAÇÃO | D36: =VLOOKUP(B36,'Folha de Pagamento'!B:G,6,0) -> Inovação | E36: =VLOOKUP(A36,Jobmatch!A:F,4,0) -> 11 - ADM PROJETOS | F36: =VLOOKUP(A36,Jobmatch!A:F,5,0) -> Tático | G36: =VLOOKUP(B36,'Folha de Pagamento'!B:O,13,0) -> Masculino | H36: =(TODAY()-G36)/365 -> #VALUE! | I36: =VLOOKUP(A36,Jobmatch!A:G,6,0) -> 437 | J36: =VLOOKUP(A36,Jobmatch!A:H,7,0) -> Analista de Inovação | K36: =VLOOKUP(A36,Jobmatch!A:I,8,0) -> Indiferente | L36: =I36&K36 -> 437Indiferente | M36: =IFERROR(VLOOKUP(B36,'Folha de Pagamento'!B:K,10,0),"") -> 7299.2701 | N36: =IFERROR(VLOOKUP(L36,Pesquisa!$D:$L,4,0),"") -> 5039.5 | O36: =IFERROR(VLOOKUP(L36,Pesquisa!$D:$L,5,0),"") -> 5955.7727 | P36: =IFERROR(VLOOKUP(L36,Pesquisa!$D:$L,6,0),"") -> 6515.7172 | Q36: =IFERROR(VLOOKUP(L36,Pesquisa!$D:$L,7,0),"") -> 6872.0455 | R36: =IFERROR(VLOOKUP(L36,Pesquisa!$D:$L,8,0),"") -> 7253.8258 | S36: =IFERROR(VLOOKUP(L36,Pesquisa!$D:$L,9,0),"") -> 7635.6061 | T36: =IFS('Painel Geral'!$B$5="Mediana",IFERROR(IF(OR(M36="",Q36=0,Q36=""),"",($M36/$Q36)),""),'Painel Geral'!$B$5="Menor Salário",IFERROR(IF(OR(M36="",Q36=0,Q36=""),"",($M36/$N36)),""),'Painel Geral'!$B$5="1º Quartil",IFERROR(IF(OR(M36="",Q36=0,Q36=""),"",($M36/$O36)),""),'Painel Geral'!$B$5="Média",IFERROR(IF(OR(M36="",Q36=0,Q36=""),"",($M36/$P36)),""),'Painel Geral'!$B$5="3º Quartil",IFERROR(IF(OR(M36="",Q36=0,Q36=""),"",($M36/$R36)),""),'Painel Geral'!$B$5="Maior Salário",IFERROR(IF(OR(M36="",Q36=0,Q36=""),"",($M36/$S36)),"")) -> 1.0621685 | U36: =IFS(OR(N36="",N36=0,M36="", M36=0),"",T36<=80%,"Muito Defasado",T36<=90%,"Defasado",T36<=100%,"Na Média",T36<=110%,"Na Média",T36<=120%,"Muito Competitivo",T36>120%,"Agressivo") -> Na Média | V36: =VLOOKUP(A36,'Cálculos Comparativos'!$A:$E,4,0) -> 7
A37: 29 | B37: 1911 | C37: =VLOOKUP(A37,Jobmatch!A:F,2,0) -> COORDENADOR DE MARKETING II | D37: =VLOOKUP(B37,'Folha de Pagamento'!B:G,6,0) -> Marketing | E37: =VLOOKUP(A37,Jobmatch!A:F,4,0) -> 36 - ADM PROJETOS | F37: =VLOOKUP(A37,Jobmatch!A:F,5,0) -> Tático | G37: =VLOOKUP(B37,'Folha de Pagamento'!B:O,13,0) -> Feminino | H37: =(TODAY()-G37)/365 -> #VALUE! | I37: =VLOOKUP(A37,Jobmatch!A:G,6,0) -> 56 | J37: =VLOOKUP(A37,Jobmatch!A:H,7,0) -> Coordenador de Marketing | K37: =VLOOKUP(A37,Jobmatch!A:I,8,0) -> Indiferente | L37: =I37&K37 -> 56Indiferente | M37: =IFERROR(VLOOKUP(B37,'Folha de Pagamento'!B:K,10,0),"") -> 8647 | N37: =IFERROR(VLOOKUP(L37,Pesquisa!$D:$L,4,0),"") -> 5322.81 | O37: =IFERROR(VLOOKUP(L37,Pesquisa!$D:$L,5,0),"") -> 7141.59 | P37: =IFERROR(VLOOKUP(L37,Pesquisa!$D:$L,6,0),"") -> 7927.07 | Q37: =IFERROR(VLOOKUP(L37,Pesquisa!$D:$L,7,0),"") -> 7958.59 | R37: =IFERROR(VLOOKUP(L37,Pesquisa!$D:$L,8,0),"") -> 8825.19 | S37: =IFERROR(VLOOKUP(L37,Pesquisa!$D:$L,9,0),"") -> 10531.61 | T37: =IFS('Painel Geral'!$B$5="Mediana",IFERROR(IF(OR(M37="",Q37=0,Q37=""),"",($M37/$Q37)),""),'Painel Geral'!$B$5="Menor Salário",IFERROR(IF(OR(M37="",Q37=0,Q37=""),"",($M37/$N37)),""),'Painel Geral'!$B$5="1º Quartil",IFERROR(IF(OR(M37="",Q37=0,Q37=""),"",($M37/$O37)),""),'Painel Geral'!$B$5="Média",IFERROR(IF(OR(M37="",Q37=0,Q37=""),"",($M37/$P37)),""),'Painel Geral'!$B$5="3º Quartil",IFERROR(IF(OR(M37="",Q37=0,Q37=""),"",($M37/$R37)),""),'Painel Geral'!$B$5="Maior Salário",IFERROR(IF(OR(M37="",Q37=0,Q37=""),"",($M37/$S37)),"")) -> 1.086499 | U37: =IFS(OR(N37="",N37=0,M37="", M37=0),"",T37<=80%,"Muito Defasado",T37<=90%,"Defasado",T37<=100%,"Na Média",T37<=110%,"Na Média",T37<=120%,"Muito Competitivo",T37>120%,"Agressivo") -> Na Média | V37: =VLOOKUP(A37,'Cálculos Comparativos'!$A:$E,4,0) -> 8
A38: 19 | B38: 192 | C38: =VLOOKUP(A38,Jobmatch!A:F,2,0) -> ASSISTENTE FINANCEIRO CONTAS A PAGAR | D38: =VLOOKUP(B38,'Folha de Pagamento'!B:G,6,0) -> Financeiro | E38: =VLOOKUP(A38,Jobmatch!A:F,4,0) -> 26 - ADM PROJETOS | F38: =VLOOKUP(A38,Jobmatch!A:F,5,0) -> Operacional | G38: =VLOOKUP(B38,'Folha de Pagamento'!B:O,13,0) -> Masculino | H38: =(TODAY()-G38)/365 -> #VALUE! | I38: =VLOOKUP(A38,Jobmatch!A:G,6,0) -> 79 | J38: =VLOOKUP(A38,Jobmatch!A:H,7,0) -> Assistente Financeiro | K38: =VLOOKUP(A38,Jobmatch!A:I,8,0) -> Indiferente | L38: =I38&K38 -> 79Indiferente | M38: =IFERROR(VLOOKUP(B38,'Folha de Pagamento'!B:K,10,0),"") -> 2919 | N38: =IFERROR(VLOOKUP(L38,Pesquisa!$D:$L,4,0),"") -> 2471.26 | O38: =IFERROR(VLOOKUP(L38,Pesquisa!$D:$L,5,0),"") -> 2566.19 | P38: =IFERROR(VLOOKUP(L38,Pesquisa!$D:$L,6,0),"") -> 2805.74 | Q38: =IFERROR(VLOOKUP(L38,Pesquisa!$D:$L,7,0),"") -> 2665.28 | R38: =IFERROR(VLOOKUP(L38,Pesquisa!$D:$L,8,0),"") -> 2942.11 | S38: =IFERROR(VLOOKUP(L38,Pesquisa!$D:$L,9,0),"") -> 3639.58 | T38: =IFS('Painel Geral'!$B$5="Mediana",IFERROR(IF(OR(M38="",Q38=0,Q38=""),"",($M38/$Q38)),""),'Painel Geral'!$B$5="Menor Salário",IFERROR(IF(OR(M38="",Q38=0,Q38=""),"",($M38/$N38)),""),'Painel Geral'!$B$5="1º Quartil",IFERROR(IF(OR(M38="",Q38=0,Q38=""),"",($M38/$O38)),""),'Painel Geral'!$B$5="Média",IFERROR(IF(OR(M38="",Q38=0,Q38=""),"",($M38/$P38)),""),'Painel Geral'!$B$5="3º Quartil",IFERROR(IF(OR(M38="",Q38=0,Q38=""),"",($M38/$R38)),""),'Painel Geral'!$B$5="Maior Salário",IFERROR(IF(OR(M38="",Q38=0,Q38=""),"",($M38/$S38)),"")) -> 1.0951945 | U38: =IFS(OR(N38="",N38=0,M38="", M38=0),"",T38<=80%,"Muito Defasado",T38<=90%,"Defasado",T38<=100%,"Na Média",T38<=110%,"Na Média",T38<=120%,"Muito Competitivo",T38>120%,"Agressivo") -> Na Média | V38: =VLOOKUP(A38,'Cálculos Comparativos'!$A:$E,4,0) -> 6
A39: 19 | B39: 193 | C39: =VLOOKUP(A39,Jobmatch!A:F,2,0) -> ASSISTENTE FINANCEIRO CONTAS A PAGAR | D39: =VLOOKUP(B39,'Folha de Pagamento'!B:G,6,0) -> Financeiro | E39: =VLOOKUP(A39,Jobmatch!A:F,4,0) -> 26 - ADM PROJETOS | F39: =VLOOKUP(A39,Jobmatch!A:F,5,0) -> Operacional | G39: =VLOOKUP(B39,'Folha de Pagamento'!B:O,13,0) -> Masculino | H39: =(TODAY()-G39)/365 -> #VALUE! | I39: =VLOOKUP(A39,Jobmatch!A:G,6,0) -> 79 | J39: =VLOOKUP(A39,Jobmatch!A:H,7,0) -> Assistente Financeiro | K39: =VLOOKUP(A39,Jobmatch!A:I,8,0) -> Indiferente | L39: =I39&K39 -> 79Indiferente | M39: =IFERROR(VLOOKUP(B39,'Folha de Pagamento'!B:K,10,0),"") -> 2919 | N39: =IFERROR(VLOOKUP(L39,Pesquisa!$D:$L,4,0),"") -> 2471.26 | O39: =IFERROR(VLOOKUP(L39,Pesquisa!$D:$L,5,0),"") -> 2566.19 | P39: =IFERROR(VLOOKUP(L39,Pesquisa!$D:$L,6,0),"") -> 2805.74 | Q39: =IFERROR(VLOOKUP(L39,Pesquisa!$D:$L,7,0),"") -> 2665.28 | R39: =IFERROR(VLOOKUP(L39,Pesquisa!$D:$L,8,0),"") -> 2942.11 | S39: =IFERROR(VLOOKUP(L39,Pesquisa!$D:$L,9,0),"") -> 3639.58 | T39: =IFS('Painel Geral'!$B$5="Mediana",IFERROR(IF(OR(M39="",Q39=0,Q39=""),"",($M39/$Q39)),""),'Painel Geral'!$B$5="Menor Salário",IFERROR(IF(OR(M39="",Q39=0,Q39=""),"",($M39/$N39)),""),'Painel Geral'!$B$5="1º Quartil",IFERROR(IF(OR(M39="",Q39=0,Q39=""),"",($M39/$O39)),""),'Painel Geral'!$B$5="Média",IFERROR(IF(OR(M39="",Q39=0,Q39=""),"",($M39/$P39)),""),'Painel Geral'!$B$5="3º Quartil",IFERROR(IF(OR(M39="",Q39=0,Q39=""),"",($M39/$R39)),""),'Painel Geral'!$B$5="Maior Salário",IFERROR(IF(OR(M39="",Q39=0,Q39=""),"",($M39/$S39)),"")) -> 1.0951945 | U39: =IFS(OR(N39="",N39=0,M39="", M39=0),"",T39<=80%,"Muito Defasado",T39<=90%,"Defasado",T39<=100%,"Na Média",T39<=110%,"Na Média",T39<=120%,"Muito Competitivo",T39>120%,"Agressivo") -> Na Média | V39: =VLOOKUP(A39,'Cálculos Comparativos'!$A:$E,4,0) -> 6
A40: 34 | B40: 132 | C40: =VLOOKUP(A40,Jobmatch!A:F,2,0) -> ENCARREGADO DE OBRAS | D40: =VLOOKUP(B40,'Folha de Pagamento'!B:G,6,0) -> Urbanismo | E40: =VLOOKUP(A40,Jobmatch!A:F,4,0) -> 41 - ADM PROJETOS | F40: =VLOOKUP(A40,Jobmatch!A:F,5,0) -> Operacional | G40: =VLOOKUP(B40,'Folha de Pagamento'!B:O,13,0) -> Masculino | H40: =(TODAY()-G40)/365 -> #VALUE! | I40: =VLOOKUP(A40,Jobmatch!A:G,6,0) -> 470 | J40: =VLOOKUP(A40,Jobmatch!A:H,7,0) -> Mestre de Obras | K40: =VLOOKUP(A40,Jobmatch!A:I,8,0) -> Indiferente | L40: =I40&K40 -> 470Indiferente | M40: =IFERROR(VLOOKUP(B40,'Folha de Pagamento'!B:K,10,0),"") -> 8461 | N40: =IFERROR(VLOOKUP(L40,Pesquisa!$D:$L,4,0),"") -> 5543.53 | O40: =IFERROR(VLOOKUP(L40,Pesquisa!$D:$L,5,0),"") -> 5543.53 | P40: =IFERROR(VLOOKUP(L40,Pesquisa!$D:$L,6,0),"") -> 7707.59 | Q40: =IFERROR(VLOOKUP(L40,Pesquisa!$D:$L,7,0),"") -> 7478.73 | R40: =IFERROR(VLOOKUP(L40,Pesquisa!$D:$L,8,0),"") -> 9809.03 | S40: =IFERROR(VLOOKUP(L40,Pesquisa!$D:$L,9,0),"") -> 11165.69 | T40: =IFS('Painel Geral'!$B$5="Mediana",IFERROR(IF(OR(M40="",Q40=0,Q40=""),"",($M40/$Q40)),""),'Painel Geral'!$B$5="Menor Salário",IFERROR(IF(OR(M40="",Q40=0,Q40=""),"",($M40/$N40)),""),'Painel Geral'!$B$5="1º Quartil",IFERROR(IF(OR(M40="",Q40=0,Q40=""),"",($M40/$O40)),""),'Painel Geral'!$B$5="Média",IFERROR(IF(OR(M40="",Q40=0,Q40=""),"",($M40/$P40)),""),'Painel Geral'!$B$5="3º Quartil",IFERROR(IF(OR(M40="",Q40=0,Q40=""),"",($M40/$R40)),""),'Painel Geral'!$B$5="Maior Salário",IFERROR(IF(OR(M40="",Q40=0,Q40=""),"",($M40/$S40)),"")) -> 1.1313418 | U40: =IFS(OR(N40="",N40=0,M40="", M40=0),"",T40<=80%,"Muito Defasado",T40<=90%,"Defasado",T40<=100%,"Na Média",T40<=110%,"Na Média",T40<=120%,"Muito Competitivo",T40>120%,"Agressivo") -> Muito Competitivo | V40: =VLOOKUP(A40,'Cálculos Comparativos'!$A:$E,4,0) -> 10
A41: 11 | B41: 1927 | C41: =VLOOKUP(A41,Jobmatch!A:F,2,0) -> ANALISTA FINANCEIRO I | D41: =VLOOKUP(B41,'Folha de Pagamento'!B:G,6,0) -> Financeiro | E41: =VLOOKUP(A41,Jobmatch!A:F,4,0) -> 18 - ADM PROJETOS | F41: =VLOOKUP(A41,Jobmatch!A:F,5,0) -> Operacional | G41: =VLOOKUP(B41,'Folha de Pagamento'!B:O,13,0) -> Feminino | H41: =(TODAY()-G41)/365 -> #VALUE! | I41: =VLOOKUP(A41,Jobmatch!A:G,6,0) -> 16 | J41: =VLOOKUP(A41,Jobmatch!A:H,7,0) -> Analista Financeiro | K41: =VLOOKUP(A41,Jobmatch!A:I,8,0) -> Júnior | L41: =I41&K41 -> 16Júnior | M41: =IFERROR(VLOOKUP(B41,'Folha de Pagamento'!B:K,10,0),"") -> 3993 | N41: =IFERROR(VLOOKUP(L41,Pesquisa!$D:$L,4,0),"") -> 2937.55 | O41: =IFERROR(VLOOKUP(L41,Pesquisa!$D:$L,5,0),"") -> 3176.35 | P41: =IFERROR(VLOOKUP(L41,Pesquisa!$D:$L,6,0),"") -> 3539.11 | Q41: =IFERROR(VLOOKUP(L41,Pesquisa!$D:$L,7,0),"") -> 3493.97 | R41: =IFERROR(VLOOKUP(L41,Pesquisa!$D:$L,8,0),"") -> 3798.49 | S41: =IFERROR(VLOOKUP(L41,Pesquisa!$D:$L,9,0),"") -> 4392.23 | T41: =IFS('Painel Geral'!$B$5="Mediana",IFERROR(IF(OR(M41="",Q41=0,Q41=""),"",($M41/$Q41)),""),'Painel Geral'!$B$5="Menor Salário",IFERROR(IF(OR(M41="",Q41=0,Q41=""),"",($M41/$N41)),""),'Painel Geral'!$B$5="1º Quartil",IFERROR(IF(OR(M41="",Q41=0,Q41=""),"",($M41/$O41)),""),'Painel Geral'!$B$5="Média",IFERROR(IF(OR(M41="",Q41=0,Q41=""),"",($M41/$P41)),""),'Painel Geral'!$B$5="3º Quartil",IFERROR(IF(OR(M41="",Q41=0,Q41=""),"",($M41/$R41)),""),'Painel Geral'!$B$5="Maior Salário",IFERROR(IF(OR(M41="",Q41=0,Q41=""),"",($M41/$S41)),"")) -> 1.1428261 | U41: =IFS(OR(N41="",N41=0,M41="", M41=0),"",T41<=80%,"Muito Defasado",T41<=90%,"Defasado",T41<=100%,"Na Média",T41<=110%,"Na Média",T41<=120%,"Muito Competitivo",T41>120%,"Agressivo") -> Muito Competitivo | V41: =VLOOKUP(A41,'Cálculos Comparativos'!$A:$E,4,0) -> 6
A42: 35 | B42: 1351 | C42: =VLOOKUP(A42,Jobmatch!A:F,2,0) -> ENCARREGADO OBRAS/MANUTENCAO | D42: =VLOOKUP(B42,'Folha de Pagamento'!B:G,6,0) -> Edificação | E42: =VLOOKUP(A42,Jobmatch!A:F,4,0) -> 42 - ADM PROJETOS | F42: =VLOOKUP(A42,Jobmatch!A:F,5,0) -> Operacional | G42: =VLOOKUP(B42,'Folha de Pagamento'!B:O,13,0) -> Masculino | H42: =(TODAY()-G42)/365 -> #VALUE! | I42: =VLOOKUP(A42,Jobmatch!A:G,6,0) -> 470 | J42: =VLOOKUP(A42,Jobmatch!A:H,7,0) -> Mestre de Obras | K42: =VLOOKUP(A42,Jobmatch!A:I,8,0) -> Indiferente | L42: =I42&K42 -> 470Indiferente | M42: =IFERROR(VLOOKUP(B42,'Folha de Pagamento'!B:K,10,0),"") -> 8714 | N42: =IFERROR(VLOOKUP(L42,Pesquisa!$D:$L,4,0),"") -> 5543.53 | O42: =IFERROR(VLOOKUP(L42,Pesquisa!$D:$L,5,0),"") -> 5543.53 | P42: =IFERROR(VLOOKUP(L42,Pesquisa!$D:$L,6,0),"") -> 7707.59 | Q42: =IFERROR(VLOOKUP(L42,Pesquisa!$D:$L,7,0),"") -> 7478.73 | R42: =IFERROR(VLOOKUP(L42,Pesquisa!$D:$L,8,0),"") -> 9809.03 | S42: =IFERROR(VLOOKUP(L42,Pesquisa!$D:$L,9,0),"") -> 11165.69 | T42: =IFS('Painel Geral'!$B$5="Mediana",IFERROR(IF(OR(M42="",Q42=0,Q42=""),"",($M42/$Q42)),""),'Painel Geral'!$B$5="Menor Salário",IFERROR(IF(OR(M42="",Q42=0,Q42=""),"",($M42/$N42)),""),'Painel Geral'!$B$5="1º Quartil",IFERROR(IF(OR(M42="",Q42=0,Q42=""),"",($M42/$O42)),""),'Painel Geral'!$B$5="Média",IFERROR(IF(OR(M42="",Q42=0,Q42=""),"",($M42/$P42)),""),'Painel Geral'!$B$5="3º Quartil",IFERROR(IF(OR(M42="",Q42=0,Q42=""),"",($M42/$R42)),""),'Painel Geral'!$B$5="Maior Salário",IFERROR(IF(OR(M42="",Q42=0,Q42=""),"",($M42/$S42)),"")) -> 1.1651711 | U42: =IFS(OR(N42="",N42=0,M42="", M42=0),"",T42<=80%,"Muito Defasado",T42<=90%,"Defasado",T42<=100%,"Na Média",T42<=110%,"Na Média",T42<=120%,"Muito Competitivo",T42>120%,"Agressivo") -> Muito Competitivo | V42: =VLOOKUP(A42,'Cálculos Comparativos'!$A:$E,4,0) -> 5
A43: 12 | B43: 164 | C43: =VLOOKUP(A43,Jobmatch!A:F,2,0) -> ASSISTENTE ADM DE LEGALIZAÇÃO III | D43: =VLOOKUP(B43,'Folha de Pagamento'!B:G,6,0) -> Legalização | E43: =VLOOKUP(A43,Jobmatch!A:F,4,0) -> 19 - ADM PROJETOS | F43: =VLOOKUP(A43,Jobmatch!A:F,5,0) -> Operacional | G43: =VLOOKUP(B43,'Folha de Pagamento'!B:O,13,0) -> Feminino | H43: =(TODAY()-G43)/365 -> #VALUE! | I43: =VLOOKUP(A43,Jobmatch!A:G,6,0) -> 1201 | J43: =VLOOKUP(A43,Jobmatch!A:H,7,0) -> Assistente de Legalização | K43: =VLOOKUP(A43,Jobmatch!A:I,8,0) -> Indiferente | L43: =I43&K43 -> 1201Indiferente | M43: =IFERROR(VLOOKUP(B43,'Folha de Pagamento'!B:K,10,0),"") -> 3652 | N43: =IFERROR(VLOOKUP(L43,Pesquisa!$D:$L,4,0),"") -> 2513.75 | O43: =IFERROR(VLOOKUP(L43,Pesquisa!$D:$L,5,0),"") -> 2803.34 | P43: =IFERROR(VLOOKUP(L43,Pesquisa!$D:$L,6,0),"") -> 3092.92 | Q43: =IFERROR(VLOOKUP(L43,Pesquisa!$D:$L,7,0),"") -> 3092.92 | R43: =IFERROR(VLOOKUP(L43,Pesquisa!$D:$L,8,0),"") -> 3382.51 | S43: =IFERROR(VLOOKUP(L43,Pesquisa!$D:$L,9,0),"") -> 3672.09 | T43: =IFS('Painel Geral'!$B$5="Mediana",IFERROR(IF(OR(M43="",Q43=0,Q43=""),"",($M43/$Q43)),""),'Painel Geral'!$B$5="Menor Salário",IFERROR(IF(OR(M43="",Q43=0,Q43=""),"",($M43/$N43)),""),'Painel Geral'!$B$5="1º Quartil",IFERROR(IF(OR(M43="",Q43=0,Q43=""),"",($M43/$O43)),""),'Painel Geral'!$B$5="Média",IFERROR(IF(OR(M43="",Q43=0,Q43=""),"",($M43/$P43)),""),'Painel Geral'!$B$5="3º Quartil",IFERROR(IF(OR(M43="",Q43=0,Q43=""),"",($M43/$R43)),""),'Painel Geral'!$B$5="Maior Salário",IFERROR(IF(OR(M43="",Q43=0,Q43=""),"",($M43/$S43)),"")) -> 1.1807612 | U43: =IFS(OR(N43="",N43=0,M43="", M43=0),"",T43<=80%,"Muito Defasado",T43<=90%,"Defasado",T43<=100%,"Na Média",T43<=110%,"Na Média",T43<=120%,"Muito Competitivo",T43>120%,"Agressivo") -> Muito Competitivo | V43: =VLOOKUP(A43,'Cálculos Comparativos'!$A:$E,4,0) -> 7
A44: 20 | B44: 184 | C44: =VLOOKUP(A44,Jobmatch!A:F,2,0) -> AUXILIAR ADMINISTRATIVO | D44: =VLOOKUP(B44,'Folha de Pagamento'!B:G,6,0) -> Administrativo | E44: =VLOOKUP(A44,Jobmatch!A:F,4,0) -> 27 - ADM PROJETOS | F44: =VLOOKUP(A44,Jobmatch!A:F,5,0) -> Operacional | G44: =VLOOKUP(B44,'Folha de Pagamento'!B:O,13,0) -> Feminino | H44: =(TODAY()-G44)/365 -> #VALUE! | I44: =VLOOKUP(A44,Jobmatch!A:G,6,0) -> 83 | J44: =VLOOKUP(A44,Jobmatch!A:H,7,0) -> Auxiliar Administrativo | K44: =VLOOKUP(A44,Jobmatch!A:I,8,0) -> Indiferente | L44: =I44&K44 -> 83Indiferente | M44: =IFERROR(VLOOKUP(B44,'Folha de Pagamento'!B:K,10,0),"") -> 2739.04 | N44: =IFERROR(VLOOKUP(L44,Pesquisa!$D:$L,4,0),"") -> 1771.74 | O44: =IFERROR(VLOOKUP(L44,Pesquisa!$D:$L,5,0),"") -> 2128.74 | P44: =IFERROR(VLOOKUP(L44,Pesquisa!$D:$L,6,0),"") -> 2292.87 | Q44: =IFERROR(VLOOKUP(L44,Pesquisa!$D:$L,7,0),"") -> 2309.71 | R44: =IFERROR(VLOOKUP(L44,Pesquisa!$D:$L,8,0),"") -> 2375.14 | S44: =IFERROR(VLOOKUP(L44,Pesquisa!$D:$L,9,0),"") -> 3073.32 | T44: =IFS('Painel Geral'!$B$5="Mediana",IFERROR(IF(OR(M44="",Q44=0,Q44=""),"",($M44/$Q44)),""),'Painel Geral'!$B$5="Menor Salário",IFERROR(IF(OR(M44="",Q44=0,Q44=""),"",($M44/$N44)),""),'Painel Geral'!$B$5="1º Quartil",IFERROR(IF(OR(M44="",Q44=0,Q44=""),"",($M44/$O44)),""),'Painel Geral'!$B$5="Média",IFERROR(IF(OR(M44="",Q44=0,Q44=""),"",($M44/$P44)),""),'Painel Geral'!$B$5="3º Quartil",IFERROR(IF(OR(M44="",Q44=0,Q44=""),"",($M44/$R44)),""),'Painel Geral'!$B$5="Maior Salário",IFERROR(IF(OR(M44="",Q44=0,Q44=""),"",($M44/$S44)),"")) -> 1.1858805 | U44: =IFS(OR(N44="",N44=0,M44="", M44=0),"",T44<=80%,"Muito Defasado",T44<=90%,"Defasado",T44<=100%,"Na Média",T44<=110%,"Na Média",T44<=120%,"Muito Competitivo",T44>120%,"Agressivo") -> Muito Competitivo | V44: =VLOOKUP(A44,'Cálculos Comparativos'!$A:$E,4,0) -> 1
A45: 7 | B45: 1962 | C45: =VLOOKUP(A45,Jobmatch!A:F,2,0) -> ANALISTA DE PÓS VENDAS II | D45: =VLOOKUP(B45,'Folha de Pagamento'!B:G,6,0) -> Pós Vendas | E45: =VLOOKUP(A45,Jobmatch!A:F,4,0) -> 14 - ADM PROJETOS | F45: =VLOOKUP(A45,Jobmatch!A:F,5,0) -> Operacional | G45: =VLOOKUP(B45,'Folha de Pagamento'!B:O,13,0) -> Masculino | H45: =(TODAY()-G45)/365 -> #VALUE! | I45: =VLOOKUP(A45,Jobmatch!A:G,6,0) -> 376 | J45: =VLOOKUP(A45,Jobmatch!A:H,7,0) -> Analista de Relacionamento | K45: =VLOOKUP(A45,Jobmatch!A:I,8,0) -> Indiferente | L45: =I45&K45 -> 376Indiferente | M45: =IFERROR(VLOOKUP(B45,'Folha de Pagamento'!B:K,10,0),"") -> 4550 | N45: =IFERROR(VLOOKUP(L45,Pesquisa!$D:$L,4,0),"") -> 2872.56 | O45: =IFERROR(VLOOKUP(L45,Pesquisa!$D:$L,5,0),"") -> 3241.46 | P45: =IFERROR(VLOOKUP(L45,Pesquisa!$D:$L,6,0),"") -> 3918.59 | Q45: =IFERROR(VLOOKUP(L45,Pesquisa!$D:$L,7,0),"") -> 3830.08 | R45: =IFERROR(VLOOKUP(L45,Pesquisa!$D:$L,8,0),"") -> 4233.24 | S45: =IFERROR(VLOOKUP(L45,Pesquisa!$D:$L,9,0),"") -> 5820.01 | T45: =IFS('Painel Geral'!$B$5="Mediana",IFERROR(IF(OR(M45="",Q45=0,Q45=""),"",($M45/$Q45)),""),'Painel Geral'!$B$5="Menor Salário",IFERROR(IF(OR(M45="",Q45=0,Q45=""),"",($M45/$N45)),""),'Painel Geral'!$B$5="1º Quartil",IFERROR(IF(OR(M45="",Q45=0,Q45=""),"",($M45/$O45)),""),'Painel Geral'!$B$5="Média",IFERROR(IF(OR(M45="",Q45=0,Q45=""),"",($M45/$P45)),""),'Painel Geral'!$B$5="3º Quartil",IFERROR(IF(OR(M45="",Q45=0,Q45=""),"",($M45/$R45)),""),'Painel Geral'!$B$5="Maior Salário",IFERROR(IF(OR(M45="",Q45=0,Q45=""),"",($M45/$S45)),"")) -> 1.1879647 | U45: =IFS(OR(N45="",N45=0,M45="", M45=0),"",T45<=80%,"Muito Defasado",T45<=90%,"Defasado",T45<=100%,"Na Média",T45<=110%,"Na Média",T45<=120%,"Muito Competitivo",T45>120%,"Agressivo") -> Muito Competitivo | V45: =VLOOKUP(A45,'Cálculos Comparativos'!$A:$E,4,0) -> 9
A46: 1 | B46: 1362 | C46: =VLOOKUP(A46,Jobmatch!A:F,2,0) -> ALMOXARIFE | D46: =VLOOKUP(B46,'Folha de Pagamento'!B:G,6,0) -> Edificação | E46: =VLOOKUP(A46,Jobmatch!A:F,4,0) -> 8 - ADM PROJETOS | F46: =VLOOKUP(A46,Jobmatch!A:F,5,0) -> Operacional | G46: =VLOOKUP(B46,'Folha de Pagamento'!B:O,13,0) -> Masculino | H46: =(TODAY()-G46)/365 -> #VALUE! | I46: =VLOOKUP(A46,Jobmatch!A:G,6,0) -> 203 | J46: =VLOOKUP(A46,Jobmatch!A:H,7,0) -> Almoxarife | K46: =VLOOKUP(A46,Jobmatch!A:I,8,0) -> Indiferente | L46: =I46&K46 -> 203Indiferente | M46: =IFERROR(VLOOKUP(B46,'Folha de Pagamento'!B:K,10,0),"") -> 3683 | N46: =IFERROR(VLOOKUP(L46,Pesquisa!$D:$L,4,0),"") -> 2973.35 | O46: =IFERROR(VLOOKUP(L46,Pesquisa!$D:$L,5,0),"") -> 3096.32 | P46: =IFERROR(VLOOKUP(L46,Pesquisa!$D:$L,6,0),"") -> 3405.54 | Q46: =IFERROR(VLOOKUP(L46,Pesquisa!$D:$L,7,0),"") -> 3096.32 | R46: =IFERROR(VLOOKUP(L46,Pesquisa!$D:$L,8,0),"") -> 3712.15 | S46: =IFERROR(VLOOKUP(L46,Pesquisa!$D:$L,9,0),"") -> 4435.84 | T46: =IFS('Painel Geral'!$B$5="Mediana",IFERROR(IF(OR(M46="",Q46=0,Q46=""),"",($M46/$Q46)),""),'Painel Geral'!$B$5="Menor Salário",IFERROR(IF(OR(M46="",Q46=0,Q46=""),"",($M46/$N46)),""),'Painel Geral'!$B$5="1º Quartil",IFERROR(IF(OR(M46="",Q46=0,Q46=""),"",($M46/$O46)),""),'Painel Geral'!$B$5="Média",IFERROR(IF(OR(M46="",Q46=0,Q46=""),"",($M46/$P46)),""),'Painel Geral'!$B$5="3º Quartil",IFERROR(IF(OR(M46="",Q46=0,Q46=""),"",($M46/$R46)),""),'Painel Geral'!$B$5="Maior Salário",IFERROR(IF(OR(M46="",Q46=0,Q46=""),"",($M46/$S46)),"")) -> 1.1894765 | U46: =IFS(OR(N46="",N46=0,M46="", M46=0),"",T46<=80%,"Muito Defasado",T46<=90%,"Defasado",T46<=100%,"Na Média",T46<=110%,"Na Média",T46<=120%,"Muito Competitivo",T46>120%,"Agressivo") -> Muito Competitivo | V46: =VLOOKUP(A46,'Cálculos Comparativos'!$A:$E,4,0) -> 5
A47: 1 | B47: 1957 | C47: =VLOOKUP(A47,Jobmatch!A:F,2,0) -> ALMOXARIFE | D47: =VLOOKUP(B47,'Folha de Pagamento'!B:G,6,0) -> Edificação | E47: =VLOOKUP(A47,Jobmatch!A:F,4,0) -> 8 - ADM PROJETOS | F47: =VLOOKUP(A47,Jobmatch!A:F,5,0) -> Operacional | G47: =VLOOKUP(B47,'Folha de Pagamento'!B:O,13,0) -> Feminino | H47: =(TODAY()-G47)/365 -> #VALUE! | I47: =VLOOKUP(A47,Jobmatch!A:G,6,0) -> 203 | J47: =VLOOKUP(A47,Jobmatch!A:H,7,0) -> Almoxarife | K47: =VLOOKUP(A47,Jobmatch!A:I,8,0) -> Indiferente | L47: =I47&K47 -> 203Indiferente | M47: =IFERROR(VLOOKUP(B47,'Folha de Pagamento'!B:K,10,0),"") -> 3683 | N47: =IFERROR(VLOOKUP(L47,Pesquisa!$D:$L,4,0),"") -> 2973.35 | O47: =IFERROR(VLOOKUP(L47,Pesquisa!$D:$L,5,0),"") -> 3096.32 | P47: =IFERROR(VLOOKUP(L47,Pesquisa!$D:$L,6,0),"") -> 3405.54 | Q47: =IFERROR(VLOOKUP(L47,Pesquisa!$D:$L,7,0),"") -> 3096.32 | R47: =IFERROR(VLOOKUP(L47,Pesquisa!$D:$L,8,0),"") -> 3712.15 | S47: =IFERROR(VLOOKUP(L47,Pesquisa!$D:$L,9,0),"") -> 4435.84 | T47: =IFS('Painel Geral'!$B$5="Mediana",IFERROR(IF(OR(M47="",Q47=0,Q47=""),"",($M47/$Q47)),""),'Painel Geral'!$B$5="Menor Salário",IFERROR(IF(OR(M47="",Q47=0,Q47=""),"",($M47/$N47)),""),'Painel Geral'!$B$5="1º Quartil",IFERROR(IF(OR(M47="",Q47=0,Q47=""),"",($M47/$O47)),""),'Painel Geral'!$B$5="Média",IFERROR(IF(OR(M47="",Q47=0,Q47=""),"",($M47/$P47)),""),'Painel Geral'!$B$5="3º Quartil",IFERROR(IF(OR(M47="",Q47=0,Q47=""),"",($M47/$R47)),""),'Painel Geral'!$B$5="Maior Salário",IFERROR(IF(OR(M47="",Q47=0,Q47=""),"",($M47/$S47)),"")) -> 1.1894765 | U47: =IFS(OR(N47="",N47=0,M47="", M47=0),"",T47<=80%,"Muito Defasado",T47<=90%,"Defasado",T47<=100%,"Na Média",T47<=110%,"Na Média",T47<=120%,"Muito Competitivo",T47>120%,"Agressivo") -> Muito Competitivo | V47: =VLOOKUP(A47,'Cálculos Comparativos'!$A:$E,4,0) -> 5
A48: 18 | B48: 1656 | C48: =VLOOKUP(A48,Jobmatch!A:F,2,0) -> ASSISTENTE DE TI | D48: =VLOOKUP(B48,'Folha de Pagamento'!B:G,6,0) -> Tecnologia da Informação | E48: =VLOOKUP(A48,Jobmatch!A:F,4,0) -> 25 - ADM PROJETOS | F48: =VLOOKUP(A48,Jobmatch!A:F,5,0) -> Operacional | G48: =VLOOKUP(B48,'Folha de Pagamento'!B:O,13,0) -> Masculino | H48: =(TODAY()-G48)/365 -> #VALUE! | I48: =VLOOKUP(A48,Jobmatch!A:G,6,0) -> 31 | J48: =VLOOKUP(A48,Jobmatch!A:H,7,0) -> Assistente de Tecnologia da Informação | K48: =VLOOKUP(A48,Jobmatch!A:I,8,0) -> Indiferente | L48: =I48&K48 -> 31Indiferente | M48: =IFERROR(VLOOKUP(B48,'Folha de Pagamento'!B:K,10,0),"") -> 2919 | N48: =IFERROR(VLOOKUP(L48,Pesquisa!$D:$L,4,0),"") -> 2010.58 | O48: =IFERROR(VLOOKUP(L48,Pesquisa!$D:$L,5,0),"") -> 2066.4 | P48: =IFERROR(VLOOKUP(L48,Pesquisa!$D:$L,6,0),"") -> 2589.89 | Q48: =IFERROR(VLOOKUP(L48,Pesquisa!$D:$L,7,0),"") -> 2413.7 | R48: =IFERROR(VLOOKUP(L48,Pesquisa!$D:$L,8,0),"") -> 3121.21 | S48: =IFERROR(VLOOKUP(L48,Pesquisa!$D:$L,9,0),"") -> 3521.6 | T48: =IFS('Painel Geral'!$B$5="Mediana",IFERROR(IF(OR(M48="",Q48=0,Q48=""),"",($M48/$Q48)),""),'Painel Geral'!$B$5="Menor Salário",IFERROR(IF(OR(M48="",Q48=0,Q48=""),"",($M48/$N48)),""),'Painel Geral'!$B$5="1º Quartil",IFERROR(IF(OR(M48="",Q48=0,Q48=""),"",($M48/$O48)),""),'Painel Geral'!$B$5="Média",IFERROR(IF(OR(M48="",Q48=0,Q48=""),"",($M48/$P48)),""),'Painel Geral'!$B$5="3º Quartil",IFERROR(IF(OR(M48="",Q48=0,Q48=""),"",($M48/$R48)),""),'Painel Geral'!$B$5="Maior Salário",IFERROR(IF(OR(M48="",Q48=0,Q48=""),"",($M48/$S48)),"")) -> 1.2093466 | U48: =IFS(OR(N48="",N48=0,M48="", M48=0),"",T48<=80%,"Muito Defasado",T48<=90%,"Defasado",T48<=100%,"Na Média",T48<=110%,"Na Média",T48<=120%,"Muito Competitivo",T48>120%,"Agressivo") -> Agressivo | V48: =VLOOKUP(A48,'Cálculos Comparativos'!$A:$E,4,0) -> 1
... A54: 19 | B54: 1941 | C54: =VLOOKUP(A54,Jobmatch!A:F,2,0) -> ASSISTENTE FINANCEIRO CONTAS A PAGAR | D54: =VLOOKUP(B54,'Folha de Pagamento'!B:G,6,0) -> Financeiro | E54: =VLOOKUP(A54,Jobmatch!A:F,4,0) -> 26 - ADM PROJETOS | F54: =VLOOKUP(A54,Jobmatch!A:F,5,0) -> Operacional | G54: =VLOOKUP(B54,'Folha de Pagamento'!B:O,13,0) -> Masculino | H54: =(TODAY()-G54)/365 -> #VALUE! | I54: =VLOOKUP(A54,Jobmatch!A:G,6,0) -> 79 | J54: =VLOOKUP(A54,Jobmatch!A:H,7,0) -> Assistente Financeiro | K54: =VLOOKUP(A54,Jobmatch!A:I,8,0) -> Indiferente | L54: =I54&K54 -> 79Indiferente | M54: =IFERROR(VLOOKUP(B54,'Folha de Pagamento'!B:K,10,0),"") -> 3652 | N54: =IFERROR(VLOOKUP(L54,Pesquisa!$D:$L,4,0),"") -> 2471.26 | O54: =IFERROR(VLOOKUP(L54,Pesquisa!$D:$L,5,0),"") -> 2566.19 | P54: =IFERROR(VLOOKUP(L54,Pesquisa!$D:$L,6,0),"") -> 2805.74 | Q54: =IFERROR(VLOOKUP(L54,Pesquisa!$D:$L,7,0),"") -> 2665.28 | R54: =IFERROR(VLOOKUP(L54,Pesquisa!$D:$L,8,0),"") -> 2942.11 | S54: =IFERROR(VLOOKUP(L54,Pesquisa!$D:$L,9,0),"") -> 3639.58 | T54: =IFS('Painel Geral'!$B$5="Mediana",IFERROR(IF(OR(M54="",Q54=0,Q54=""),"",($M54/$Q54)),""),'Painel Geral'!$B$5="Menor Salário",IFERROR(IF(OR(M54="",Q54=0,Q54=""),"",($M54/$N54)),""),'Painel Geral'!$B$5="1º Quartil",IFERROR(IF(OR(M54="",Q54=0,Q54=""),"",($M54/$O54)),""),'Painel Geral'!$B$5="Média",IFERROR(IF(OR(M54="",Q54=0,Q54=""),"",($M54/$P54)),""),'Painel Geral'!$B$5="3º Quartil",IFERROR(IF(OR(M54="",Q54=0,Q54=""),"",($M54/$R54)),""),'Painel Geral'!$B$5="Maior Salário",IFERROR(IF(OR(M54="",Q54=0,Q54=""),"",($M54/$S54)),"")) -> 1.3702125 | U54: =IFS(OR(N54="",N54=0,M54="", M54=0),"",T54<=80%,"Muito Defasado",T54<=90%,"Defasado",T54<=100%,"Na Média",T54<=110%,"Na Média",T54<=120%,"Muito Competitivo",T54>120%,"Agressivo") -> Agressivo | V54: =VLOOKUP(A54,'Cálculos Comparativos'!$A:$E,4,0) -> 6
